Workbook

Sheet README
A1: COB Calculator (Excel)
A2: A formula-driven Excel port of the COB segmented mortgage / cost-of-borrowing engine.
A5: COLOR LEGEND
A6: Blue text, yellow-tinted cells = INPUT -- edit these.
A7: Black text = COMPUTED formula -- do not edit; it will recalculate automatically.
A9: SHEETS
A10: Segments, LumpSums, Overrides, PMI_Costs -- inputs for the segmented mortgage engine.
A11: Schedule, Summary, YearlySummary -- computed output of the segmented engine (do not edit).
A12: PaymentFrequency, ExtraPayment -- standalone single-loan calculators (own inputs).
A13: Points, Refinance, CompareTerms, LTV_DSCR, ARM_Reset, Fees_APR, DTI_Affordability -- standalone calculators.
A15: KEY ASSUMPTIONS (see docs/new-req/ in the source repo for full specs)
A16: - Segmented Schedule is bounded to 360 rows (30 years monthly). Extend by selecting the
... A33: for details. Recalculated with LibreOffice via the xlsx skill's recalc.py: 0 formula errors.

Sheet Segments
A1: Segments (input)
A2: Blue cells = edit these. One row per segment, chronological. Segment 1's Starting Balance is required; later segments inherit their starting balance from the prior segment's computed ending balance (do not fill in Starting Balance for row 2+).
A4: Seg # | B4: Start Date | C4: Annual Rate % | D4: Payment Amount (blank = compute) | E4: Amortization Months Remaining (blank if Payment Amount given) | F4: Term Months (blank = final/runs to payoff) | G4: Starting Balance (segment 1 only) | H4: Balloon? (Y/N) | I4: Interest Only? (Y/N) | J4: Start Payment # | K4: End Payment # | L4: Monthly Payment (computed) | M4: Segment Starting Balance (computed) | N4: Segment Ending Balance (computed)
A5: 1 | B5: 2024-01-01 | C5: 5 | E5: 300 | F5: 60 | G5: 200000 | H5: N | I5: N | J5: =1 | K5: =IF(OR($F5="",$J5=""),"",J5+F5-1) | L5: =IF($B5="","",IF(I5="Y",ROUND(M5*(C5/100/12),2),IF(D5<>"",ROUND(D5,2),ROUND(-PMT(C5/100/12,E5,M5),2)))) | M5: =G5 | N5: =IF($B5="","",IF(K5<>"",IFERROR(INDEX(Schedule!$AA:$AA,MATCH(K5,Schedule!$A:$A,0)),""),IFERROR(INDEX(Schedule!$AA:$AA,MATCH(SUMPRODUCT(MAX((Schedule!$B$5:$B$364=$A5)*Schedule!$A$5:$A$364)),Schedule!$A:$A,0)),"")))
A6: 2 | B6: 2029-01-01 | C6: 6 | E6: 240 | H6: N | I6: N | J6: =IF($F5="","",K5+1) | K6: =IF(OR($F6="",$J6=""),"",J6+F6-1) | L6: =IF($B6="","",IF(I6="Y",ROUND(M6*(C6/100/12),2),IF(D6<>"",ROUND(D6,2),ROUND(-PMT(C6/100/12,E6,M6),2)))) | M6: =IF($B6="","",IFERROR(INDEX(Schedule!$AA:$AA,MATCH(K5,Schedule!$A:$A,0)),"")) | N6: =IF($B6="","",IF(K6<>"",IFERROR(INDEX(Schedule!$AA:$AA,MATCH(K6,Schedule!$A:$A,0)),""),IFERROR(INDEX(Schedule!$AA:$AA,MATCH(SUMPRODUCT(MAX((Schedule!$B$5:$B$364=$A6)*Schedule!$A$5:$A$364)),Schedule!$A:$A,0)),"")))
A7: 3 | J7: =IF($F6="","",K6+1) | K7: =IF(OR($F7="",$J7=""),"",J7+F7-1) | L7: =IF($B7="","",IF(I7="Y",ROUND(M7*(C7/100/12),2),IF(D7<>"",ROUND(D7,2),ROUND(-PMT(C7/100/12,E7,M7),2)))) | M7: =IF($B7="","",IFERROR(INDEX(Schedule!$AA:$AA,MATCH(K6,Schedule!$A:$A,0)),"")) | N7: =IF($B7="","",IF(K7<>"",IFERROR(INDEX(Schedule!$AA:$AA,MATCH(K7,Schedule!$A:$A,0)),""),IFERROR(INDEX(Schedule!$AA:$AA,MATCH(SUMPRODUCT(MAX((Schedule!$B$5:$B$364=$A7)*Schedule!$A$5:$A$364)),Schedule!$A:$A,0)),"")))
A8: 4 | J8: =IF($F7="","",K7+1) | K8: =IF(OR($F8="",$J8=""),"",J8+F8-1) | L8: =IF($B8="","",IF(I8="Y",ROUND(M8*(C8/100/12),2),IF(D8<>"",ROUND(D8,2),ROUND(-PMT(C8/100/12,E8,M8),2)))) | M8: =IF($B8="","",IFERROR(INDEX(Schedule!$AA:$AA,MATCH(K7,Schedule!$A:$A,0)),"")) | N8: =IF($B8="","",IF(K8<>"",IFERROR(INDEX(Schedule!$AA:$AA,MATCH(K8,Schedule!$A:$A,0)),""),IFERROR(INDEX(Schedule!$AA:$AA,MATCH(SUMPRODUCT(MAX((Schedule!$B$5:$B$364=$A8)*Schedule!$A$5:$A$364)),Schedule!$A:$A,0)),"")))
A9: 5 | J9: =IF($F8="","",K8+1) | K9: =IF(OR($F9="",$J9=""),"",J9+F9-1) | L9: =IF($B9="","",IF(I9="Y",ROUND(M9*(C9/100/12),2),IF(D9<>"",ROUND(D9,2),ROUND(-PMT(C9/100/12,E9,M9),2)))) | M9: =IF($B9="","",IFERROR(INDEX(Schedule!$AA:$AA,MATCH(K8,Schedule!$A:$A,0)),"")) | N9: =IF($B9="","",IF(K9<>"",IFERROR(INDEX(Schedule!$AA:$AA,MATCH(K9,Schedule!$A:$A,0)),""),IFERROR(INDEX(Schedule!$AA:$AA,MATCH(SUMPRODUCT(MAX((Schedule!$B$5:$B$364=$A9)*Schedule!$A$5:$A$364)),Schedule!$A:$A,0)),"")))
A10: 6 | J10: =IF($F9="","",K9+1) | K10: =IF(OR($F10="",$J10=""),"",J10+F10-1) | L10: =IF($B10="","",IF(I10="Y",ROUND(M10*(C10/100/12),2),IF(D10<>"",ROUND(D10,2),ROUND(-PMT(C10/100/12,E10,M10),2)))) | M10: =IF($B10="","",IFERROR(INDEX(Schedule!$AA:$AA,MATCH(K9,Schedule!$A:$A,0)),"")) | N10: =IF($B10="","",IF(K10<>"",IFERROR(INDEX(Schedule!$AA:$AA,MATCH(K10,Schedule!$A:$A,0)),""),IFERROR(INDEX(Schedule!$AA:$AA,MATCH(SUMPRODUCT(MAX((Schedule!$B$5:$B$364=$A10)*Schedule!$A$5:$A$364)),Schedule!$A:$A,0)),"")))
A11: 7 | J11: =IF($F10="","",K10+1) | K11: =IF(OR($F11="",$J11=""),"",J11+F11-1) | L11: =IF($B11="","",IF(I11="Y",ROUND(M11*(C11/100/12),2),IF(D11<>"",ROUND(D11,2),ROUND(-PMT(C11/100/12,E11,M11),2)))) | M11: =IF($B11="","",IFERROR(INDEX(Schedule!$AA:$AA,MATCH(K10,Schedule!$A:$A,0)),"")) | N11: =IF($B11="","",IF(K11<>"",IFERROR(INDEX(Schedule!$AA:$AA,MATCH(K11,Schedule!$A:$A,0)),""),IFERROR(INDEX(Schedule!$AA:$AA,MATCH(SUMPRODUCT(MAX((Schedule!$B$5:$B$364=$A11)*Schedule!$A$5:$A$364)),Schedule!$A:$A,0)),"")))
A12: 8 | J12: =IF($F11="","",K11+1) | K12: =IF(OR($F12="",$J12=""),"",J12+F12-1) | L12: =IF($B12="","",IF(I12="Y",ROUND(M12*(C12/100/12),2),IF(D12<>"",ROUND(D12,2),ROUND(-PMT(C12/100/12,E12,M12),2)))) | M12: =IF($B12="","",IFERROR(INDEX(Schedule!$AA:$AA,MATCH(K11,Schedule!$A:$A,0)),"")) | N12: =IF($B12="","",IF(K12<>"",IFERROR(INDEX(Schedule!$AA:$AA,MATCH(K12,Schedule!$A:$A,0)),""),IFERROR(INDEX(Schedule!$AA:$AA,MATCH(SUMPRODUCT(MAX((Schedule!$B$5:$B$364=$A12)*Schedule!$A$5:$A$364)),Schedule!$A:$A,0)),"")))

Sheet LumpSums
A1: Lump Sum Payments (input)
A2: Applied at a segment/renewal boundary only -- After Payment # must equal one of Segments!K (End Payment #) for a non-final segment. Leave rows blank if unused.
A4: After Payment # | B4: Amount
A5: 60 | B5: 20000

Sheet Overrides
A1: Manual Payment Overrides (input)
A2: Bank-statement reconciliation rows. Leave a field blank to use the computed value; Payment # is required, all other fields optional per row.
A4: Payment # | B4: Payment Amount | C4: Interest Portion | D4: Principal Portion | E4: Remaining Balance | F4: Reason
A5: 10 | C5: 700 | F5: example: bank fee adjustment

Sheet PMI_Costs
A1: PMI & Recurring Costs (input)
A2: Leave PMI/cost annual amounts blank (0) to disable that cost.
A4: PMI annual rate (%) | B4: 0.6
A5: Property value ($) | B5: 220000
A6: PMI drop-at LTV (%) | B6: 80
A8: Property tax annual amount ($) | B8: 4800
A9: Property tax annual increase (%) | B9: 0
A10: Home insurance annual amount ($) | B10: 1200
A11: Home insurance annual increase (%) | B11: 0
A12: HOA annual amount ($) | B12: 0
A13: HOA annual increase (%) | B13: 0

Sheet Schedule
A1: Schedule (computed) -- do not edit
A2: One row per global payment number, 1..360 (30 years). Rows past the loan's actual payoff show as blank. Extend by selecting the last row and copying its formulas down if you need a longer schedule.
A4: Payment # | B4: Seg Idx | C4: Seg Start Date | D4: Seg Start Pay# | E4: Payment Date | F4: Monthly Rate | G4: Seg Monthly Pmt | H4: Seg IO? | I4: Seg Final? | J4: Seg End Pay# | K4: Seg Known Len | L4: Beginning Balance | M4: Ovr: Interest | N4: Ovr: Rem Bal | O4: Ovr: Principal | P4: Ovr: Payment | Q4: Ovr: Reason | R4: Has Override? | S4: Payoff Row? | T4: Interest | U4: Principal (pre-lump) | V4: Payment (pre-lump) | W4: Ending Bal (pre-lump) | X4: Lump Sum Applied | Y4: Principal | Z4: Payment | AA4: Ending Balance | AB4: Active Row? | AC4: Tax | AD4: Insurance | AE4: HOA | AF4: Current LTV | AG4: PMI Active? | AH4: PMI | AI4: PMI Just Dropped?
A5: 1 | B5: =SUMPRODUCT((Segments!$J$5:$J$12<>"")*(Segments!$J$5:$J$12<=A5)) | C5: =INDEX(Segments!$B$5:$B$12,B5) | D5: =INDEX(Segments!$J$5:$J$12,B5) | E5: =DATE(YEAR(C5)+INT((MONTH(C5)-1+(A5-D5))/12),MOD(MONTH(C5)-1+(A5-D5),12)+1,1)+(DAY(C5)-1) | F5: =INDEX(Segments!$C$5:$C$12,B5)/100/12 | G5: =INDEX(Segments!$L$5:$L$12,B5) | H5: =INDEX(Segments!$I$5:$I$12,B5)="Y" | I5: =INDEX(Segments!$F$5:$F$12,B5)="" | J5: =INDEX(Segments!$K$5:$K$12,B5) | K5: =IF(INDEX(Segments!$F$5:$F$12,B5)<>"",INDEX(Segments!$F$5:$F$12,B5),IF(INDEX(Segments!$E$5:$E$12,B5)<>"",INDEX(Segments!$E$5:$E$12,B5),"")) | L5: =Segments!$G$5 | M5: =IFERROR(INDEX(Overrides!$C:$C,MATCH(A5,Overrides!$A:$A,0)),"") | N5: =IFERROR(INDEX(Overrides!$E:$E,MATCH(A5,Overrides!$A:$A,0)),"") | O5: =IFERROR(INDEX(Overrides!$D:$D,MATCH(A5,Overrides!$A:$A,0)),"") | P5: =IFERROR(INDEX(Overrides!$B:$B,MATCH(A5,Overrides!$A:$A,0)),"") | Q5: =IFERROR(INDEX(Overrides!$F:$F,MATCH(A5,Overrides!$A:$A,0)),"") | R5: =ISNUMBER(MATCH(A5,Overrides!$A:$A,0)) | S5: =OR(ROUND(L5-ROUND(G5-T5,2),2)<=0,AND(I5,K5<>"",(A5-D5+1)=K5)) | T5: =IF(M5<>"",M5,ROUND(L5*F5,2)) | U5: =IF(R5,IF(O5<>"",O5,IF(N5<>"",ROUND(L5-N5,2),ROUND((IF(P5<>"",P5,G5))-T5,2))),IF(H5,0,IF(S5,L5,ROUND(G5-T5,2)))) | V5: =IF(R5,IF(P5<>"",P5,ROUND(T5+U5,2)),IF(H5,T5,IF(S5,ROUND(T5+U5,2),G5))) | W5: =IF(R5,IF(N5<>"",N5,ROUND(L5-U5,2)),IF(H5,L5,IF(S5,0,ROUND(L5-U5,2)))) | X5: =IFERROR(MIN(INDEX(LumpSums!$B:$B,MATCH(A5,LumpSums!$A:$A,0)),W5),0) | Y5: =ROUND(U5+X5,2) | Z5: =ROUND(V5+X5,2) | AA5: =ROUND(W5-X5,2) | AB5: =TRUE | AC5: =IF(PMI_Costs!$B$8=0,0,ROUND(PMI_Costs!$B$8*(1+PMI_Costs!$B$9/100)^INT((A5-1)/12)/12,2)) | AD5: =IF(PMI_Costs!$B$10=0,0,ROUND(PMI_Costs!$B$10*(1+PMI_Costs!$B$11/100)^INT((A5-1)/12)/12,2)) | AE5: =IF(PMI_Costs!$B$12=0,0,ROUND(PMI_Costs!$B$12*(1+PMI_Costs!$B$13/100)^INT((A5-1)/12)/12,2)) | AF5: =IF(PMI_Costs!$B$5=0,0,AA5/PMI_Costs!$B$5) | AG5: =AND(PMI_Costs!$B$4>0,AF5>PMI_Costs!$B$6/100) | AH5: =IF(AG5,ROUND(Segments!$G$5*PMI_Costs!$B$4/100/12,2),0) | AI5: =FALSE
A6: 2 | B6: =SUMPRODUCT((Segments!$J$5:$J$12<>"")*(Segments!$J$5:$J$12<=A6)) | C6: =INDEX(Segments!$B$5:$B$12,B6) | D6: =INDEX(Segments!$J$5:$J$12,B6) | E6: =DATE(YEAR(C6)+INT((MONTH(C6)-1+(A6-D6))/12),MOD(MONTH(C6)-1+(A6-D6),12)+1,1)+(DAY(C6)-1) | F6: =INDEX(Segments!$C$5:$C$12,B6)/100/12 | G6: =INDEX(Segments!$L$5:$L$12,B6) | H6: =INDEX(Segments!$I$5:$I$12,B6)="Y" | I6: =INDEX(Segments!$F$5:$F$12,B6)="" | J6: =INDEX(Segments!$K$5:$K$12,B6) | K6: =IF(INDEX(Segments!$F$5:$F$12,B6)<>"",INDEX(Segments!$F$5:$F$12,B6),IF(INDEX(Segments!$E$5:$E$12,B6)<>"",INDEX(Segments!$E$5:$E$12,B6),"")) | L6: =AA5 | M6: =IFERROR(INDEX(Overrides!$C:$C,MATCH(A6,Overrides!$A:$A,0)),"") | N6: =IFERROR(INDEX(Overrides!$E:$E,MATCH(A6,Overrides!$A:$A,0)),"") | O6: =IFERROR(INDEX(Overrides!$D:$D,MATCH(A6,Overrides!$A:$A,0)),"") | P6: =IFERROR(INDEX(Overrides!$B:$B,MATCH(A6,Overrides!$A:$A,0)),"") | Q6: =IFERROR(INDEX(Overrides!$F:$F,MATCH(A6,Overrides!$A:$A,0)),"") | R6: =ISNUMBER(MATCH(A6,Overrides!$A:$A,0)) | S6: =OR(ROUND(L6-ROUND(G6-T6,2),2)<=0,AND(I6,K6<>"",(A6-D6+1)=K6)) | T6: =IF(M6<>"",M6,ROUND(L6*F6,2)) | U6: =IF(R6,IF(O6<>"",O6,IF(N6<>"",ROUND(L6-N6,2),ROUND((IF(P6<>"",P6,G6))-T6,2))),IF(H6,0,IF(S6,L6,ROUND(G6-T6,2)))) | V6: =IF(R6,IF(P6<>"",P6,ROUND(T6+U6,2)),IF(H6,T6,IF(S6,ROUND(T6+U6,2),G6))) | W6: =IF(R6,IF(N6<>"",N6,ROUND(L6-U6,2)),IF(H6,L6,IF(S6,0,ROUND(L6-U6,2)))) | X6: =IFERROR(MIN(INDEX(LumpSums!$B:$B,MATCH(A6,LumpSums!$A:$A,0)),W6),0) | Y6: =ROUND(U6+X6,2) | Z6: =ROUND(V6+X6,2) | AA6: =ROUND(W6-X6,2) | AB6: =AND(AB5,L6>0) | AC6: =IF(PMI_Costs!$B$8=0,0,ROUND(PMI_Costs!$B$8*(1+PMI_Costs!$B$9/100)^INT((A6-1)/12)/12,2)) | AD6: =IF(PMI_Costs!$B$10=0,0,ROUND(PMI_Costs!$B$10*(1+PMI_Costs!$B$11/100)^INT((A6-1)/12)/12,2)) | AE6: =IF(PMI_Costs!$B$12=0,0,ROUND(PMI_Costs!$B$12*(1+PMI_Costs!$B$13/100)^INT((A6-1)/12)/12,2)) | AF6: =IF(PMI_Costs!$B$5=0,0,AA6/PMI_Costs!$B$5) | AG6: =AND(PMI_Costs!$B$4>0,AF6>PMI_Costs!$B$6/100) | AH6: =IF(AG6,ROUND(Segments!$G$5*PMI_Costs!$B$4/100/12,2),0) | AI6: =AND(NOT(AG6),AG5)
A7: 3 | B7: =SUMPRODUCT((Segments!$J$5:$J$12<>"")*(Segments!$J$5:$J$12<=A7)) | C7: =INDEX(Segments!$B$5:$B$12,B7) | D7: =INDEX(Segments!$J$5:$J$12,B7) | E7: =DATE(YEAR(C7)+INT((MONTH(C7)-1+(A7-D7))/12),MOD(MONTH(C7)-1+(A7-D7),12)+1,1)+(DAY(C7)-1) | F7: =INDEX(Segments!$C$5:$C$12,B7)/100/12 | G7: =INDEX(Segments!$L$5:$L$12,B7) | H7: =INDEX(Segments!$I$5:$I$12,B7)="Y" | I7: =INDEX(Segments!$F$5:$F$12,B7)="" | J7: =INDEX(Segments!$K$5:$K$12,B7) | K7: =IF(INDEX(Segments!$F$5:$F$12,B7)<>"",INDEX(Segments!$F$5:$F$12,B7),IF(INDEX(Segments!$E$5:$E$12,B7)<>"",INDEX(Segments!$E$5:$E$12,B7),"")) | L7: =AA6 | M7: =IFERROR(INDEX(Overrides!$C:$C,MATCH(A7,Overrides!$A:$A,0)),"") | N7: =IFERROR(INDEX(Overrides!$E:$E,MATCH(A7,Overrides!$A:$A,0)),"") | O7: =IFERROR(INDEX(Overrides!$D:$D,MATCH(A7,Overrides!$A:$A,0)),"") | P7: =IFERROR(INDEX(Overrides!$B:$B,MATCH(A7,Overrides!$A:$A,0)),"") | Q7: =IFERROR(INDEX(Overrides!$F:$F,MATCH(A7,Overrides!$A:$A,0)),"") | R7: =ISNUMBER(MATCH(A7,Overrides!$A:$A,0)) | S7: =OR(ROUND(L7-ROUND(G7-T7,2),2)<=0,AND(I7,K7<>"",(A7-D7+1)=K7)) | T7: =IF(M7<>"",M7,ROUND(L7*F7,2)) | U7: =IF(R7,IF(O7<>"",O7,IF(N7<>"",ROUND(L7-N7,2),ROUND((IF(P7<>"",P7,G7))-T7,2))),IF(H7,0,IF(S7,L7,ROUND(G7-T7,2)))) | V7: =IF(R7,IF(P7<>"",P7,ROUND(T7+U7,2)),IF(H7,T7,IF(S7,ROUND(T7+U7,2),G7))) | W7: =IF(R7,IF(N7<>"",N7,ROUND(L7-U7,2)),IF(H7,L7,IF(S7,0,ROUND(L7-U7,2)))) | X7: =IFERROR(MIN(INDEX(LumpSums!$B:$B,MATCH(A7,LumpSums!$A:$A,0)),W7),0) | Y7: =ROUND(U7+X7,2) | Z7: =ROUND(V7+X7,2) | AA7: =ROUND(W7-X7,2) | AB7: =AND(AB6,L7>0) | AC7: =IF(PMI_Costs!$B$8=0,0,ROUND(PMI_Costs!$B$8*(1+PMI_Costs!$B$9/100)^INT((A7-1)/12)/12,2)) | AD7: =IF(PMI_Costs!$B$10=0,0,ROUND(PMI_Costs!$B$10*(1+PMI_Costs!$B$11/100)^INT((A7-1)/12)/12,2)) | AE7: =IF(PMI_Costs!$B$12=0,0,ROUND(PMI_Costs!$B$12*(1+PMI_Costs!$B$13/100)^INT((A7-1)/12)/12,2)) | AF7: =IF(PMI_Costs!$B$5=0,0,AA7/PMI_Costs!$B$5) | AG7: =AND(PMI_Costs!$B$4>0,AF7>PMI_Costs!$B$6/100) | AH7: =IF(AG7,ROUND(Segments!$G$5*PMI_Costs!$B$4/100/12,2),0) | AI7: =AND(NOT(AG7),AG6)
A8: 4 | B8: =SUMPRODUCT((Segments!$J$5:$J$12<>"")*(Segments!$J$5:$J$12<=A8)) | C8: =INDEX(Segments!$B$5:$B$12,B8) | D8: =INDEX(Segments!$J$5:$J$12,B8) | E8: =DATE(YEAR(C8)+INT((MONTH(C8)-1+(A8-D8))/12),MOD(MONTH(C8)-1+(A8-D8),12)+1,1)+(DAY(C8)-1) | F8: =INDEX(Segments!$C$5:$C$12,B8)/100/12 | G8: =INDEX(Segments!$L$5:$L$12,B8) | H8: =INDEX(Segments!$I$5:$I$12,B8)="Y" | I8: =INDEX(Segments!$F$5:$F$12,B8)="" | J8: =INDEX(Segments!$K$5:$K$12,B8) | K8: =IF(INDEX(Segments!$F$5:$F$12,B8)<>"",INDEX(Segments!$F$5:$F$12,B8),IF(INDEX(Segments!$E$5:$E$12,B8)<>"",INDEX(Segments!$E$5:$E$12,B8),"")) | L8: =AA7 | M8: =IFERROR(INDEX(Overrides!$C:$C,MATCH(A8,Overrides!$A:$A,0)),"") | N8: =IFERROR(INDEX(Overrides!$E:$E,MATCH(A8,Overrides!$A:$A,0)),"") | O8: =IFERROR(INDEX(Overrides!$D:$D,MATCH(A8,Overrides!$A:$A,0)),"") | P8: =IFERROR(INDEX(Overrides!$B:$B,MATCH(A8,Overrides!$A:$A,0)),"") | Q8: =IFERROR(INDEX(Overrides!$F:$F,MATCH(A8,Overrides!$A:$A,0)),"") | R8: =ISNUMBER(MATCH(A8,Overrides!$A:$A,0)) | S8: =OR(ROUND(L8-ROUND(G8-T8,2),2)<=0,AND(I8,K8<>"",(A8-D8+1)=K8)) | T8: =IF(M8<>"",M8,ROUND(L8*F8,2)) | U8: =IF(R8,IF(O8<>"",O8,IF(N8<>"",ROUND(L8-N8,2),ROUND((IF(P8<>"",P8,G8))-T8,2))),IF(H8,0,IF(S8,L8,ROUND(G8-T8,2)))) | V8: =IF(R8,IF(P8<>"",P8,ROUND(T8+U8,2)),IF(H8,T8,IF(S8,ROUND(T8+U8,2),G8))) | W8: =IF(R8,IF(N8<>"",N8,ROUND(L8-U8,2)),IF(H8,L8,IF(S8,0,ROUND(L8-U8,2)))) | X8: =IFERROR(MIN(INDEX(LumpSums!$B:$B,MATCH(A8,LumpSums!$A:$A,0)),W8),0) | Y8: =ROUND(U8+X8,2) | Z8: =ROUND(V8+X8,2) | AA8: =ROUND(W8-X8,2) | AB8: =AND(AB7,L8>0) | AC8: =IF(PMI_Costs!$B$8=0,0,ROUND(PMI_Costs!$B$8*(1+PMI_Costs!$B$9/100)^INT((A8-1)/12)/12,2)) | AD8: =IF(PMI_Costs!$B$10=0,0,ROUND(PMI_Costs!$B$10*(1+PMI_Costs!$B$11/100)^INT((A8-1)/12)/12,2)) | AE8: =IF(PMI_Costs!$B$12=0,0,ROUND(PMI_Costs!$B$12*(1+PMI_Costs!$B$13/100)^INT((A8-1)/12)/12,2)) | AF8: =IF(PMI_Costs!$B$5=0,0,AA8/PMI_Costs!$B$5) | AG8: =AND(PMI_Costs!$B$4>0,AF8>PMI_Costs!$B$6/100) | AH8: =IF(AG8,ROUND(Segments!$G$5*PMI_Costs!$B$4/100/12,2),0) | AI8: =AND(NOT(AG8),AG7)
A9: 5 | B9: =SUMPRODUCT((Segments!$J$5:$J$12<>"")*(Segments!$J$5:$J$12<=A9)) | C9: =INDEX(Segments!$B$5:$B$12,B9) | D9: =INDEX(Segments!$J$5:$J$12,B9) | E9: =DATE(YEAR(C9)+INT((MONTH(C9)-1+(A9-D9))/12),MOD(MONTH(C9)-1+(A9-D9),12)+1,1)+(DAY(C9)-1) | F9: =INDEX(Segments!$C$5:$C$12,B9)/100/12 | G9: =INDEX(Segments!$L$5:$L$12,B9) | H9: =INDEX(Segments!$I$5:$I$12,B9)="Y" | I9: =INDEX(Segments!$F$5:$F$12,B9)="" | J9: =INDEX(Segments!$K$5:$K$12,B9) | K9: =IF(INDEX(Segments!$F$5:$F$12,B9)<>"",INDEX(Segments!$F$5:$F$12,B9),IF(INDEX(Segments!$E$5:$E$12,B9)<>"",INDEX(Segments!$E$5:$E$12,B9),"")) | L9: =AA8 | M9: =IFERROR(INDEX(Overrides!$C:$C,MATCH(A9,Overrides!$A:$A,0)),"") | N9: =IFERROR(INDEX(Overrides!$E:$E,MATCH(A9,Overrides!$A:$A,0)),"") | O9: =IFERROR(INDEX(Overrides!$D:$D,MATCH(A9,Overrides!$A:$A,0)),"") | P9: =IFERROR(INDEX(Overrides!$B:$B,MATCH(A9,Overrides!$A:$A,0)),"") | Q9: =IFERROR(INDEX(Overrides!$F:$F,MATCH(A9,Overrides!$A:$A,0)),"") | R9: =ISNUMBER(MATCH(A9,Overrides!$A:$A,0)) | S9: =OR(ROUND(L9-ROUND(G9-T9,2),2)<=0,AND(I9,K9<>"",(A9-D9+1)=K9)) | T9: =IF(M9<>"",M9,ROUND(L9*F9,2)) | U9: =IF(R9,IF(O9<>"",O9,IF(N9<>"",ROUND(L9-N9,2),ROUND((IF(P9<>"",P9,G9))-T9,2))),IF(H9,0,IF(S9,L9,ROUND(G9-T9,2)))) | V9: =IF(R9,IF(P9<>"",P9,ROUND(T9+U9,2)),IF(H9,T9,IF(S9,ROUND(T9+U9,2),G9))) | W9: =IF(R9,IF(N9<>"",N9,ROUND(L9-U9,2)),IF(H9,L9,IF(S9,0,ROUND(L9-U9,2)))) | X9: =IFERROR(MIN(INDEX(LumpSums!$B:$B,MATCH(A9,LumpSums!$A:$A,0)),W9),0) | Y9: =ROUND(U9+X9,2) | Z9: =ROUND(V9+X9,2) | AA9: =ROUND(W9-X9,2) | AB9: =AND(AB8,L9>0) | AC9: =IF(PMI_Costs!$B$8=0,0,ROUND(PMI_Costs!$B$8*(1+PMI_Costs!$B$9/100)^INT((A9-1)/12)/12,2)) | AD9: =IF(PMI_Costs!$B$10=0,0,ROUND(PMI_Costs!$B$10*(1+PMI_Costs!$B$11/100)^INT((A9-1)/12)/12,2)) | AE9: =IF(PMI_Costs!$B$12=0,0,ROUND(PMI_Costs!$B$12*(1+PMI_Costs!$B$13/100)^INT((A9-1)/12)/12,2)) | AF9: =IF(PMI_Costs!$B$5=0,0,AA9/PMI_Costs!$B$5) | AG9: =AND(PMI_Costs!$B$4>0,AF9>PMI_Costs!$B$6/100) | AH9: =IF(AG9,ROUND(Segments!$G$5*PMI_Costs!$B$4/100/12,2),0) | AI9: =AND(NOT(AG9),AG8)
A10: 6 | B10: =SUMPRODUCT((Segments!$J$5:$J$12<>"")*(Segments!$J$5:$J$12<=A10)) | C10: =INDEX(Segments!$B$5:$B$12,B10) | D10: =INDEX(Segments!$J$5:$J$12,B10) | E10: =DATE(YEAR(C10)+INT((MONTH(C10)-1+(A10-D10))/12),MOD(MONTH(C10)-1+(A10-D10),12)+1,1)+(DAY(C10)-1) | F10: =INDEX(Segments!$C$5:$C$12,B10)/100/12 | G10: =INDEX(Segments!$L$5:$L$12,B10) | H10: =INDEX(Segments!$I$5:$I$12,B10)="Y" | I10: =INDEX(Segments!$F$5:$F$12,B10)="" | J10: =INDEX(Segments!$K$5:$K$12,B10) | K10: =IF(INDEX(Segments!$F$5:$F$12,B10)<>"",INDEX(Segments!$F$5:$F$12,B10),IF(INDEX(Segments!$E$5:$E$12,B10)<>"",INDEX(Segments!$E$5:$E$12,B10),"")) | L10: =AA9 | M10: =IFERROR(INDEX(Overrides!$C:$C,MATCH(A10,Overrides!$A:$A,0)),"") | N10: =IFERROR(INDEX(Overrides!$E:$E,MATCH(A10,Overrides!$A:$A,0)),"") | O10: =IFERROR(INDEX(Overrides!$D:$D,MATCH(A10,Overrides!$A:$A,0)),"") | P10: =IFERROR(INDEX(Overrides!$B:$B,MATCH(A10,Overrides!$A:$A,0)),"") | Q10: =IFERROR(INDEX(Overrides!$F:$F,MATCH(A10,Overrides!$A:$A,0)),"") | R10: =ISNUMBER(MATCH(A10,Overrides!$A:$A,0)) | S10: =OR(ROUND(L10-ROUND(G10-T10,2),2)<=0,AND(I10,K10<>"",(A10-D10+1)=K10)) | T10: =IF(M10<>"",M10,ROUND(L10*F10,2)) | U10: =IF(R10,IF(O10<>"",O10,IF(N10<>"",ROUND(L10-N10,2),ROUND((IF(P10<>"",P10,G10))-T10,2))),IF(H10,0,IF(S10,L10,ROUND(G10-T10,2)))) | V10: =IF(R10,IF(P10<>"",P10,ROUND(T10+U10,2)),IF(H10,T10,IF(S10,ROUND(T10+U10,2),G10))) | W10: =IF(R10,IF(N10<>"",N10,ROUND(L10-U10,2)),IF(H10,L10,IF(S10,0,ROUND(L10-U10,2)))) | X10: =IFERROR(MIN(INDEX(LumpSums!$B:$B,MATCH(A10,LumpSums!$A:$A,0)),W10),0) | Y10: =ROUND(U10+X10,2) | Z10: =ROUND(V10+X10,2) | AA10: =ROUND(W10-X10,2) | AB10: =AND(AB9,L10>0) | AC10: =IF(PMI_Costs!$B$8=0,0,ROUND(PMI_Costs!$B$8*(1+PMI_Costs!$B$9/100)^INT((A10-1)/12)/12,2)) | AD10: =IF(PMI_Costs!$B$10=0,0,ROUND(PMI_Costs!$B$10*(1+PMI_Costs!$B$11/100)^INT((A10-1)/12)/12,2)) | AE10: =IF(PMI_Costs!$B$12=0,0,ROUND(PMI_Costs!$B$12*(1+PMI_Costs!$B$13/100)^INT((A10-1)/12)/12,2)) | AF10: =IF(PMI_Costs!$B$5=0,0,AA10/PMI_Costs!$B$5) | AG10: =AND(PMI_Costs!$B$4>0,AF10>PMI_Costs!$B$6/100) | AH10: =IF(AG10,ROUND(Segments!$G$5*PMI_Costs!$B$4/100/12,2),0) | AI10: =AND(NOT(AG10),AG9)
A11: 7 | B11: =SUMPRODUCT((Segments!$J$5:$J$12<>"")*(Segments!$J$5:$J$12<=A11)) | C11: =INDEX(Segments!$B$5:$B$12,B11) | D11: =INDEX(Segments!$J$5:$J$12,B11) | E11: =DATE(YEAR(C11)+INT((MONTH(C11)-1+(A11-D11))/12),MOD(MONTH(C11)-1+(A11-D11),12)+1,1)+(DAY(C11)-1) | F11: =INDEX(Segments!$C$5:$C$12,B11)/100/12 | G11: =INDEX(Segments!$L$5:$L$12,B11) | H11: =INDEX(Segments!$I$5:$I$12,B11)="Y" | I11: =INDEX(Segments!$F$5:$F$12,B11)="" | J11: =INDEX(Segments!$K$5:$K$12,B11) | K11: =IF(INDEX(Segments!$F$5:$F$12,B11)<>"",INDEX(Segments!$F$5:$F$12,B11),IF(INDEX(Segments!$E$5:$E$12,B11)<>"",INDEX(Segments!$E$5:$E$12,B11),"")) | L11: =AA10 | M11: =IFERROR(INDEX(Overrides!$C:$C,MATCH(A11,Overrides!$A:$A,0)),"") | N11: =IFERROR(INDEX(Overrides!$E:$E,MATCH(A11,Overrides!$A:$A,0)),"") | O11: =IFERROR(INDEX(Overrides!$D:$D,MATCH(A11,Overrides!$A:$A,0)),"") | P11: =IFERROR(INDEX(Overrides!$B:$B,MATCH(A11,Overrides!$A:$A,0)),"") | Q11: =IFERROR(INDEX(Overrides!$F:$F,MATCH(A11,Overrides!$A:$A,0)),"") | R11: =ISNUMBER(MATCH(A11,Overrides!$A:$A,0)) | S11: =OR(ROUND(L11-ROUND(G11-T11,2),2)<=0,AND(I11,K11<>"",(A11-D11+1)=K11)) | T11: =IF(M11<>"",M11,ROUND(L11*F11,2)) | U11: =IF(R11,IF(O11<>"",O11,IF(N11<>"",ROUND(L11-N11,2),ROUND((IF(P11<>"",P11,G11))-T11,2))),IF(H11,0,IF(S11,L11,ROUND(G11-T11,2)))) | V11: =IF(R11,IF(P11<>"",P11,ROUND(T11+U11,2)),IF(H11,T11,IF(S11,ROUND(T11+U11,2),G11))) | W11: =IF(R11,IF(N11<>"",N11,ROUND(L11-U11,2)),IF(H11,L11,IF(S11,0,ROUND(L11-U11,2)))) | X11: =IFERROR(MIN(INDEX(LumpSums!$B:$B,MATCH(A11,LumpSums!$A:$A,0)),W11),0) | Y11: =ROUND(U11+X11,2) | Z11: =ROUND(V11+X11,2) | AA11: =ROUND(W11-X11,2) | AB11: =AND(AB10,L11>0) | AC11: =IF(PMI_Costs!$B$8=0,0,ROUND(PMI_Costs!$B$8*(1+PMI_Costs!$B$9/100)^INT((A11-1)/12)/12,2)) | AD11: =IF(PMI_Costs!$B$10=0,0,ROUND(PMI_Costs!$B$10*(1+PMI_Costs!$B$11/100)^INT((A11-1)/12)/12,2)) | AE11: =IF(PMI_Costs!$B$12=0,0,ROUND(PMI_Costs!$B$12*(1+PMI_Costs!$B$13/100)^INT((A11-1)/12)/12,2)) | AF11: =IF(PMI_Costs!$B$5=0,0,AA11/PMI_Costs!$B$5) | AG11: =AND(PMI_Costs!$B$4>0,AF11>PMI_Costs!$B$6/100) | AH11: =IF(AG11,ROUND(Segments!$G$5*PMI_Costs!$B$4/100/12,2),0) | AI11: =AND(NOT(AG11),AG10)
A12: 8 | B12: =SUMPRODUCT((Segments!$J$5:$J$12<>"")*(Segments!$J$5:$J$12<=A12)) | C12: =INDEX(Segments!$B$5:$B$12,B12) | D12: =INDEX(Segments!$J$5:$J$12,B12) | E12: =DATE(YEAR(C12)+INT((MONTH(C12)-1+(A12-D12))/12),MOD(MONTH(C12)-1+(A12-D12),12)+1,1)+(DAY(C12)-1) | F12: =INDEX(Segments!$C$5:$C$12,B12)/100/12 | G12: =INDEX(Segments!$L$5:$L$12,B12) | H12: =INDEX(Segments!$I$5:$I$12,B12)="Y" | I12: =INDEX(Segments!$F$5:$F$12,B12)="" | J12: =INDEX(Segments!$K$5:$K$12,B12) | K12: =IF(INDEX(Segments!$F$5:$F$12,B12)<>"",INDEX(Segments!$F$5:$F$12,B12),IF(INDEX(Segments!$E$5:$E$12,B12)<>"",INDEX(Segments!$E$5:$E$12,B12),"")) | L12: =AA11 | M12: =IFERROR(INDEX(Overrides!$C:$C,MATCH(A12,Overrides!$A:$A,0)),"") | N12: =IFERROR(INDEX(Overrides!$E:$E,MATCH(A12,Overrides!$A:$A,0)),"") | O12: =IFERROR(INDEX(Overrides!$D:$D,MATCH(A12,Overrides!$A:$A,0)),"") | P12: =IFERROR(INDEX(Overrides!$B:$B,MATCH(A12,Overrides!$A:$A,0)),"") | Q12: =IFERROR(INDEX(Overrides!$F:$F,MATCH(A12,Overrides!$A:$A,0)),"") | R12: =ISNUMBER(MATCH(A12,Overrides!$A:$A,0)) | S12: =OR(ROUND(L12-ROUND(G12-T12,2),2)<=0,AND(I12,K12<>"",(A12-D12+1)=K12)) | T12: =IF(M12<>"",M12,ROUND(L12*F12,2)) | U12: =IF(R12,IF(O12<>"",O12,IF(N12<>"",ROUND(L12-N12,2),ROUND((IF(P12<>"",P12,G12))-T12,2))),IF(H12,0,IF(S12,L12,ROUND(G12-T12,2)))) | V12: =IF(R12,IF(P12<>"",P12,ROUND(T12+U12,2)),IF(H12,T12,IF(S12,ROUND(T12+U12,2),G12))) | W12: =IF(R12,IF(N12<>"",N12,ROUND(L12-U12,2)),IF(H12,L12,IF(S12,0,ROUND(L12-U12,2)))) | X12: =IFERROR(MIN(INDEX(LumpSums!$B:$B,MATCH(A12,LumpSums!$A:$A,0)),W12),0) | Y12: =ROUND(U12+X12,2) | Z12: =ROUND(V12+X12,2) | AA12: =ROUND(W12-X12,2) | AB12: =AND(AB11,L12>0) | AC12: =IF(PMI_Costs!$B$8=0,0,ROUND(PMI_Costs!$B$8*(1+PMI_Costs!$B$9/100)^INT((A12-1)/12)/12,2)) | AD12: =IF(PMI_Costs!$B$10=0,0,ROUND(PMI_Costs!$B$10*(1+PMI_Costs!$B$11/100)^INT((A12-1)/12)/12,2)) | AE12: =IF(PMI_Costs!$B$12=0,0,ROUND(PMI_Costs!$B$12*(1+PMI_Costs!$B$13/100)^INT((A12-1)/12)/12,2)) | AF12: =IF(PMI_Costs!$B$5=0,0,AA12/PMI_Costs!$B$5) | AG12: =AND(PMI_Costs!$B$4>0,AF12>PMI_Costs!$B$6/100) | AH12: =IF(AG12,ROUND(Segments!$G$5*PMI_Costs!$B$4/100/12,2),0) | AI12: =AND(NOT(AG12),AG11)
A13: 9 | B13: =SUMPRODUCT((Segments!$J$5:$J$12<>"")*(Segments!$J$5:$J$12<=A13)) | C13: =INDEX(Segments!$B$5:$B$12,B13) | D13: =INDEX(Segments!$J$5:$J$12,B13) | E13: =DATE(YEAR(C13)+INT((MONTH(C13)-1+(A13-D13))/12),MOD(MONTH(C13)-1+(A13-D13),12)+1,1)+(DAY(C13)-1) | F13: =INDEX(Segments!$C$5:$C$12,B13)/100/12 | G13: =INDEX(Segments!$L$5:$L$12,B13) | H13: =INDEX(Segments!$I$5:$I$12,B13)="Y" | I13: =INDEX(Segments!$F$5:$F$12,B13)="" | J13: =INDEX(Segments!$K$5:$K$12,B13) | K13: =IF(INDEX(Segments!$F$5:$F$12,B13)<>"",INDEX(Segments!$F$5:$F$12,B13),IF(INDEX(Segments!$E$5:$E$12,B13)<>"",INDEX(Segments!$E$5:$E$12,B13),"")) | L13: =AA12 | M13: =IFERROR(INDEX(Overrides!$C:$C,MATCH(A13,Overrides!$A:$A,0)),"") | N13: =IFERROR(INDEX(Overrides!$E:$E,MATCH(A13,Overrides!$A:$A,0)),"") | O13: =IFERROR(INDEX(Overrides!$D:$D,MATCH(A13,Overrides!$A:$A,0)),"") | P13: =IFERROR(INDEX(Overrides!$B:$B,MATCH(A13,Overrides!$A:$A,0)),"") | Q13: =IFERROR(INDEX(Overrides!$F:$F,MATCH(A13,Overrides!$A:$A,0)),"") | R13: =ISNUMBER(MATCH(A13,Overrides!$A:$A,0)) | S13: =OR(ROUND(L13-ROUND(G13-T13,2),2)<=0,AND(I13,K13<>"",(A13-D13+1)=K13)) | T13: =IF(M13<>"",M13,ROUND(L13*F13,2)) | U13: =IF(R13,IF(O13<>"",O13,IF(N13<>"",ROUND(L13-N13,2),ROUND((IF(P13<>"",P13,G13))-T13,2))),IF(H13,0,IF(S13,L13,ROUND(G13-T13,2)))) | V13: =IF(R13,IF(P13<>"",P13,ROUND(T13+U13,2)),IF(H13,T13,IF(S13,ROUND(T13+U13,2),G13))) | W13: =IF(R13,IF(N13<>"",N13,ROUND(L13-U13,2)),IF(H13,L13,IF(S13,0,ROUND(L13-U13,2)))) | X13: =IFERROR(MIN(INDEX(LumpSums!$B:$B,MATCH(A13,LumpSums!$A:$A,0)),W13),0) | Y13: =ROUND(U13+X13,2) | Z13: =ROUND(V13+X13,2) | AA13: =ROUND(W13-X13,2) | AB13: =AND(AB12,L13>0) | AC13: =IF(PMI_Costs!$B$8=0,0,ROUND(PMI_Costs!$B$8*(1+PMI_Costs!$B$9/100)^INT((A13-1)/12)/12,2)) | AD13: =IF(PMI_Costs!$B$10=0,0,ROUND(PMI_Costs!$B$10*(1+PMI_Costs!$B$11/100)^INT((A13-1)/12)/12,2)) | AE13: =IF(PMI_Costs!$B$12=0,0,ROUND(PMI_Costs!$B$12*(1+PMI_Costs!$B$13/100)^INT((A13-1)/12)/12,2)) | AF13: =IF(PMI_Costs!$B$5=0,0,AA13/PMI_Costs!$B$5) | AG13: =AND(PMI_Costs!$B$4>0,AF13>PMI_Costs!$B$6/100) | AH13: =IF(AG13,ROUND(Segments!$G$5*PMI_Costs!$B$4/100/12,2),0) | AI13: =AND(NOT(AG13),AG12)
A14: 10 | B14: =SUMPRODUCT((Segments!$J$5:$J$12<>"")*(Segments!$J$5:$J$12<=A14)) | C14: =INDEX(Segments!$B$5:$B$12,B14) | D14: =INDEX(Segments!$J$5:$J$12,B14) | E14: =DATE(YEAR(C14)+INT((MONTH(C14)-1+(A14-D14))/12),MOD(MONTH(C14)-1+(A14-D14),12)+1,1)+(DAY(C14)-1) | F14: =INDEX(Segments!$C$5:$C$12,B14)/100/12 | G14: =INDEX(Segments!$L$5:$L$12,B14) | H14: =INDEX(Segments!$I$5:$I$12,B14)="Y" | I14: =INDEX(Segments!$F$5:$F$12,B14)="" | J14: =INDEX(Segments!$K$5:$K$12,B14) | K14: =IF(INDEX(Segments!$F$5:$F$12,B14)<>"",INDEX(Segments!$F$5:$F$12,B14),IF(INDEX(Segments!$E$5:$E$12,B14)<>"",INDEX(Segments!$E$5:$E$12,B14),"")) | L14: =AA13 | M14: =IFERROR(INDEX(Overrides!$C:$C,MATCH(A14,Overrides!$A:$A,0)),"") | N14: =IFERROR(INDEX(Overrides!$E:$E,MATCH(A14,Overrides!$A:$A,0)),"") | O14: =IFERROR(INDEX(Overrides!$D:$D,MATCH(A14,Overrides!$A:$A,0)),"") | P14: =IFERROR(INDEX(Overrides!$B:$B,MATCH(A14,Overrides!$A:$A,0)),"") | Q14: =IFERROR(INDEX(Overrides!$F:$F,MATCH(A14,Overrides!$A:$A,0)),"") | R14: =ISNUMBER(MATCH(A14,Overrides!$A:$A,0)) | S14: =OR(ROUND(L14-ROUND(G14-T14,2),2)<=0,AND(I14,K14<>"",(A14-D14+1)=K14)) | T14: =IF(M14<>"",M14,ROUND(L14*F14,2)) | U14: =IF(R14,IF(O14<>"",O14,IF(N14<>"",ROUND(L14-N14,2),ROUND((IF(P14<>"",P14,G14))-T14,2))),IF(H14,0,IF(S14,L14,ROUND(G14-T14,2)))) | V14: =IF(R14,IF(P14<>"",P14,ROUND(T14+U14,2)),IF(H14,T14,IF(S14,ROUND(T14+U14,2),G14))) | W14: =IF(R14,IF(N14<>"",N14,ROUND(L14-U14,2)),IF(H14,L14,IF(S14,0,ROUND(L14-U14,2)))) | X14: =IFERROR(MIN(INDEX(LumpSums!$B:$B,MATCH(A14,LumpSums!$A:$A,0)),W14),0) | Y14: =ROUND(U14+X14,2) | Z14: =ROUND(V14+X14,2) | AA14: =ROUND(W14-X14,2) | AB14: =AND(AB13,L14>0) | AC14: =IF(PMI_Costs!$B$8=0,0,ROUND(PMI_Costs!$B$8*(1+PMI_Costs!$B$9/100)^INT((A14-1)/12)/12,2)) | AD14: =IF(PMI_Costs!$B$10=0,0,ROUND(PMI_Costs!$B$10*(1+PMI_Costs!$B$11/100)^INT((A14-1)/12)/12,2)) | AE14: =IF(PMI_Costs!$B$12=0,0,ROUND(PMI_Costs!$B$12*(1+PMI_Costs!$B$13/100)^INT((A14-1)/12)/12,2)) | AF14: =IF(PMI_Costs!$B$5=0,0,AA14/PMI_Costs!$B$5) | AG14: =AND(PMI_Costs!$B$4>0,AF14>PMI_Costs!$B$6/100) | AH14: =IF(AG14,ROUND(Segments!$G$5*PMI_Costs!$B$4/100/12,2),0) | AI14: =AND(NOT(AG14),AG13)
A15: 11 | B15: =SUMPRODUCT((Segments!$J$5:$J$12<>"")*(Segments!$J$5:$J$12<=A15)) | C15: =INDEX(Segments!$B$5:$B$12,B15) | D15: =INDEX(Segments!$J$5:$J$12,B15) | E15: =DATE(YEAR(C15)+INT((MONTH(C15)-1+(A15-D15))/12),MOD(MONTH(C15)-1+(A15-D15),12)+1,1)+(DAY(C15)-1) | F15: =INDEX(Segments!$C$5:$C$12,B15)/100/12 | G15: =INDEX(Segments!$L$5:$L$12,B15) | H15: =INDEX(Segments!$I$5:$I$12,B15)="Y" | I15: =INDEX(Segments!$F$5:$F$12,B15)="" | J15: =INDEX(Segments!$K$5:$K$12,B15) | K15: =IF(INDEX(Segments!$F$5:$F$12,B15)<>"",INDEX(Segments!$F$5:$F$12,B15),IF(INDEX(Segments!$E$5:$E$12,B15)<>"",INDEX(Segments!$E$5:$E$12,B15),"")) | L15: =AA14 | M15: =IFERROR(INDEX(Overrides!$C:$C,MATCH(A15,Overrides!$A:$A,0)),"") | N15: =IFERROR(INDEX(Overrides!$E:$E,MATCH(A15,Overrides!$A:$A,0)),"") | O15: =IFERROR(INDEX(Overrides!$D:$D,MATCH(A15,Overrides!$A:$A,0)),"") | P15: =IFERROR(INDEX(Overrides!$B:$B,MATCH(A15,Overrides!$A:$A,0)),"") | Q15: =IFERROR(INDEX(Overrides!$F:$F,MATCH(A15,Overrides!$A:$A,0)),"") | R15: =ISNUMBER(MATCH(A15,Overrides!$A:$A,0)) | S15: =OR(ROUND(L15-ROUND(G15-T15,2),2)<=0,AND(I15,K15<>"",(A15-D15+1)=K15)) | T15: =IF(M15<>"",M15,ROUND(L15*F15,2)) | U15: =IF(R15,IF(O15<>"",O15,IF(N15<>"",ROUND(L15-N15,2),ROUND((IF(P15<>"",P15,G15))-T15,2))),IF(H15,0,IF(S15,L15,ROUND(G15-T15,2)))) | V15: =IF(R15,IF(P15<>"",P15,ROUND(T15+U15,2)),IF(H15,T15,IF(S15,ROUND(T15+U15,2),G15))) | W15: =IF(R15,IF(N15<>"",N15,ROUND(L15-U15,2)),IF(H15,L15,IF(S15,0,ROUND(L15-U15,2)))) | X15: =IFERROR(MIN(INDEX(LumpSums!$B:$B,MATCH(A15,LumpSums!$A:$A,0)),W15),0) | Y15: =ROUND(U15+X15,2) | Z15: =ROUND(V15+X15,2) | AA15: =ROUND(W15-X15,2) | AB15: =AND(AB14,L15>0) | AC15: =IF(PMI_Costs!$B$8=0,0,ROUND(PMI_Costs!$B$8*(1+PMI_Costs!$B$9/100)^INT((A15-1)/12)/12,2)) | AD15: =IF(PMI_Costs!$B$10=0,0,ROUND(PMI_Costs!$B$10*(1+PMI_Costs!$B$11/100)^INT((A15-1)/12)/12,2)) | AE15: =IF(PMI_Costs!$B$12=0,0,ROUND(PMI_Costs!$B$12*(1+PMI_Costs!$B$13/100)^INT((A15-1)/12)/12,2)) | AF15: =IF(PMI_Costs!$B$5=0,0,AA15/PMI_Costs!$B$5) | AG15: =AND(PMI_Costs!$B$4>0,AF15>PMI_Costs!$B$6/100) | AH15: =IF(AG15,ROUND(Segments!$G$5*PMI_Costs!$B$4/100/12,2),0) | AI15: =AND(NOT(AG15),AG14)
A16: 12 | B16: =SUMPRODUCT((Segments!$J$5:$J$12<>"")*(Segments!$J$5:$J$12<=A16)) | C16: =INDEX(Segments!$B$5:$B$12,B16) | D16: =INDEX(Segments!$J$5:$J$12,B16) | E16: =DATE(YEAR(C16)+INT((MONTH(C16)-1+(A16-D16))/12),MOD(MONTH(C16)-1+(A16-D16),12)+1,1)+(DAY(C16)-1) | F16: =INDEX(Segments!$C$5:$C$12,B16)/100/12 | G16: =INDEX(Segments!$L$5:$L$12,B16) | H16: =INDEX(Segments!$I$5:$I$12,B16)="Y" | I16: =INDEX(Segments!$F$5:$F$12,B16)="" | J16: =INDEX(Segments!$K$5:$K$12,B16) | K16: =IF(INDEX(Segments!$F$5:$F$12,B16)<>"",INDEX(Segments!$F$5:$F$12,B16),IF(INDEX(Segments!$E$5:$E$12,B16)<>"",INDEX(Segments!$E$5:$E$12,B16),"")) | L16: =AA15 | M16: =IFERROR(INDEX(Overrides!$C:$C,MATCH(A16,Overrides!$A:$A,0)),"") | N16: =IFERROR(INDEX(Overrides!$E:$E,MATCH(A16,Overrides!$A:$A,0)),"") | O16: =IFERROR(INDEX(Overrides!$D:$D,MATCH(A16,Overrides!$A:$A,0)),"") | P16: =IFERROR(INDEX(Overrides!$B:$B,MATCH(A16,Overrides!$A:$A,0)),"") | Q16: =IFERROR(INDEX(Overrides!$F:$F,MATCH(A16,Overrides!$A:$A,0)),"") | R16: =ISNUMBER(MATCH(A16,Overrides!$A:$A,0)) | S16: =OR(ROUND(L16-ROUND(G16-T16,2),2)<=0,AND(I16,K16<>"",(A16-D16+1)=K16)) | T16: =IF(M16<>"",M16,ROUND(L16*F16,2)) | U16: =IF(R16,IF(O16<>"",O16,IF(N16<>"",ROUND(L16-N16,2),ROUND((IF(P16<>"",P16,G16))-T16,2))),IF(H16,0,IF(S16,L16,ROUND(G16-T16,2)))) | V16: =IF(R16,IF(P16<>"",P16,ROUND(T16+U16,2)),IF(H16,T16,IF(S16,ROUND(T16+U16,2),G16))) | W16: =IF(R16,IF(N16<>"",N16,ROUND(L16-U16,2)),IF(H16,L16,IF(S16,0,ROUND(L16-U16,2)))) | X16: =IFERROR(MIN(INDEX(LumpSums!$B:$B,MATCH(A16,LumpSums!$A:$A,0)),W16),0) | Y16: =ROUND(U16+X16,2) | Z16: =ROUND(V16+X16,2) | AA16: =ROUND(W16-X16,2) | AB16: =AND(AB15,L16>0) | AC16: =IF(PMI_Costs!$B$8=0,0,ROUND(PMI_Costs!$B$8*(1+PMI_Costs!$B$9/100)^INT((A16-1)/12)/12,2)) | AD16: =IF(PMI_Costs!$B$10=0,0,ROUND(PMI_Costs!$B$10*(1+PMI_Costs!$B$11/100)^INT((A16-1)/12)/12,2)) | AE16: =IF(PMI_Costs!$B$12=0,0,ROUND(PMI_Costs!$B$12*(1+PMI_Costs!$B$13/100)^INT((A16-1)/12)/12,2)) | AF16: =IF(PMI_Costs!$B$5=0,0,AA16/PMI_Costs!$B$5) | AG16: =AND(PMI_Costs!$B$4>0,AF16>PMI_Costs!$B$6/100) | AH16: =IF(AG16,ROUND(Segments!$G$5*PMI_Costs!$B$4/100/12,2),0) | AI16: =AND(NOT(AG16),AG15)
A17: 13 | B17: =SUMPRODUCT((Segments!$J$5:$J$12<>"")*(Segments!$J$5:$J$12<=A17)) | C17: =INDEX(Segments!$B$5:$B$12,B17) | D17: =INDEX(Segments!$J$5:$J$12,B17) | E17: =DATE(YEAR(C17)+INT((MONTH(C17)-1+(A17-D17))/12),MOD(MONTH(C17)-1+(A17-D17),12)+1,1)+(DAY(C17)-1) | F17: =INDEX(Segments!$C$5:$C$12,B17)/100/12 | G17: =INDEX(Segments!$L$5:$L$12,B17) | H17: =INDEX(Segments!$I$5:$I$12,B17)="Y" | I17: =INDEX(Segments!$F$5:$F$12,B17)="" | J17: =INDEX(Segments!$K$5:$K$12,B17) | K17: =IF(INDEX(Segments!$F$5:$F$12,B17)<>"",INDEX(Segments!$F$5:$F$12,B17),IF(INDEX(Segments!$E$5:$E$12,B17)<>"",INDEX(Segments!$E$5:$E$12,B17),"")) | L17: =AA16 | M17: =IFERROR(INDEX(Overrides!$C:$C,MATCH(A17,Overrides!$A:$A,0)),"") | N17: =IFERROR(INDEX(Overrides!$E:$E,MATCH(A17,Overrides!$A:$A,0)),"") | O17: =IFERROR(INDEX(Overrides!$D:$D,MATCH(A17,Overrides!$A:$A,0)),"") | P17: =IFERROR(INDEX(Overrides!$B:$B,MATCH(A17,Overrides!$A:$A,0)),"") | Q17: =IFERROR(INDEX(Overrides!$F:$F,MATCH(A17,Overrides!$A:$A,0)),"") | R17: =ISNUMBER(MATCH(A17,Overrides!$A:$A,0)) | S17: =OR(ROUND(L17-ROUND(G17-T17,2),2)<=0,AND(I17,K17<>"",(A17-D17+1)=K17)) | T17: =IF(M17<>"",M17,ROUND(L17*F17,2)) | U17: =IF(R17,IF(O17<>"",O17,IF(N17<>"",ROUND(L17-N17,2),ROUND((IF(P17<>"",P17,G17))-T17,2))),IF(H17,0,IF(S17,L17,ROUND(G17-T17,2)))) | V17: =IF(R17,IF(P17<>"",P17,ROUND(T17+U17,2)),IF(H17,T17,IF(S17,ROUND(T17+U17,2),G17))) | W17: =IF(R17,IF(N17<>"",N17,ROUND(L17-U17,2)),IF(H17,L17,IF(S17,0,ROUND(L17-U17,2)))) | X17: =IFERROR(MIN(INDEX(LumpSums!$B:$B,MATCH(A17,LumpSums!$A:$A,0)),W17),0) | Y17: =ROUND(U17+X17,2) | Z17: =ROUND(V17+X17,2) | AA17: =ROUND(W17-X17,2) | AB17: =AND(AB16,L17>0) | AC17: =IF(PMI_Costs!$B$8=0,0,ROUND(PMI_Costs!$B$8*(1+PMI_Costs!$B$9/100)^INT((A17-1)/12)/12,2)) | AD17: =IF(PMI_Costs!$B$10=0,0,ROUND(PMI_Costs!$B$10*(1+PMI_Costs!$B$11/100)^INT((A17-1)/12)/12,2)) | AE17: =IF(PMI_Costs!$B$12=0,0,ROUND(PMI_Costs!$B$12*(1+PMI_Costs!$B$13/100)^INT((A17-1)/12)/12,2)) | AF17: =IF(PMI_Costs!$B$5=0,0,AA17/PMI_Costs!$B$5) | AG17: =AND(PMI_Costs!$B$4>0,AF17>PMI_Costs!$B$6/100) | AH17: =IF(AG17,ROUND(Segments!$G$5*PMI_Costs!$B$4/100/12,2),0) | AI17: =AND(NOT(AG17),AG16)
... A364: 360 | B364: =SUMPRODUCT((Segments!$J$5:$J$12<>"")*(Segments!$J$5:$J$12<=A364)) | C364: =INDEX(Segments!$B$5:$B$12,B364) | D364: =INDEX(Segments!$J$5:$J$12,B364) | E364: =DATE(YEAR(C364)+INT((MONTH(C364)-1+(A364-D364))/12),MOD(MONTH(C364)-1+(A364-D364),12)+1,1)+(DAY(C364)-1) | F364: =INDEX(Segments!$C$5:$C$12,B364)/100/12 | G364: =INDEX(Segments!$L$5:$L$12,B364) | H364: =INDEX(Segments!$I$5:$I$12,B364)="Y" | I364: =INDEX(Segments!$F$5:$F$12,B364)="" | J364: =INDEX(Segments!$K$5:$K$12,B364) | K364: =IF(INDEX(Segments!$F$5:$F$12,B364)<>"",INDEX(Segments!$F$5:$F$12,B364),IF(INDEX(Segments!$E$5:$E$12,B364)<>"",INDEX(Segments!$E$5:$E$12,B364),"")) | L364: =AA363 | M364: =IFERROR(INDEX(Overrides!$C:$C,MATCH(A364,Overrides!$A:$A,0)),"") | N364: =IFERROR(INDEX(Overrides!$E:$E,MATCH(A364,Overrides!$A:$A,0)),"") | O364: =IFERROR(INDEX(Overrides!$D:$D,MATCH(A364,Overrides!$A:$A,0)),"") | P364: =IFERROR(INDEX(Overrides!$B:$B,MATCH(A364,Overrides!$A:$A,0)),"") | Q364: =IFERROR(INDEX(Overrides!$F:$F,MATCH(A364,Overrides!$A:$A,0)),"") | R364: =ISNUMBER(MATCH(A364,Overrides!$A:$A,0)) | S364: =OR(ROUND(L364-ROUND(G364-T364,2),2)<=0,AND(I364,K364<>"",(A364-D364+1)=K364)) | T364: =IF(M364<>"",M364,ROUND(L364*F364,2)) | U364: =IF(R364,IF(O364<>"",O364,IF(N364<>"",ROUND(L364-N364,2),ROUND((IF(P364<>"",P364,G364))-T364,2))),IF(H364,0,IF(S364,L364,ROUND(G364-T364,2)))) | V364: =IF(R364,IF(P364<>"",P364,ROUND(T364+U364,2)),IF(H364,T364,IF(S364,ROUND(T364+U364,2),G364))) | W364: =IF(R364,IF(N364<>"",N364,ROUND(L364-U364,2)),IF(H364,L364,IF(S364,0,ROUND(L364-U364,2)))) | X364: =IFERROR(MIN(INDEX(LumpSums!$B:$B,MATCH(A364,LumpSums!$A:$A,0)),W364),0) | Y364: =ROUND(U364+X364,2) | Z364: =ROUND(V364+X364,2) | AA364: =ROUND(W364-X364,2) | AB364: =AND(AB363,L364>0) | AC364: =IF(PMI_Costs!$B$8=0,0,ROUND(PMI_Costs!$B$8*(1+PMI_Costs!$B$9/100)^INT((A364-1)/12)/12,2)) | AD364: =IF(PMI_Costs!$B$10=0,0,ROUND(PMI_Costs!$B$10*(1+PMI_Costs!$B$11/100)^INT((A364-1)/12)/12,2)) | AE364: =IF(PMI_Costs!$B$12=0,0,ROUND(PMI_Costs!$B$12*(1+PMI_Costs!$B$13/100)^INT((A364-1)/12)/12,2)) | AF364: =IF(PMI_Costs!$B$5=0,0,AA364/PMI_Costs!$B$5) | AG364: =AND(PMI_Costs!$B$4>0,AF364>PMI_Costs!$B$6/100) | AH364: =IF(AG364,ROUND(Segments!$G$5*PMI_Costs!$B$4/100/12,2),0) | AI364: =AND(NOT(AG364),AG363)

Sheet Summary
A1: Summary (computed)
A2: Totals over the Schedule sheet's active rows only.
A4: Number of payments | B4: =COUNTIF(Schedule!$AB$5:$AB$364,TRUE)
A5: Total interest paid | B5: =SUMIFS(Schedule!$T$5:$T$364,Schedule!$AB$5:$AB$364,TRUE)
A6: Total principal paid (P&I only) | B6: =SUMIFS(Schedule!$Y$5:$Y$364,Schedule!$AB$5:$AB$364,TRUE)
A7: Total of payments (P&I) | B7: =SUMIFS(Schedule!$Z$5:$Z$364,Schedule!$AB$5:$AB$364,TRUE)
A8: Payoff date | B8: =SUMPRODUCT(MAX((Schedule!$AB$5:$AB$364)*(Schedule!$E$5:$E$364)))
A10: Total tax paid | B10: =SUMIFS(Schedule!$AC$5:$AC$364,Schedule!$AB$5:$AB$364,TRUE)
A11: Total insurance paid | B11: =SUMIFS(Schedule!$AD$5:$AD$364,Schedule!$AB$5:$AB$364,TRUE)
A12: Total HOA paid | B12: =SUMIFS(Schedule!$AE$5:$AE$364,Schedule!$AB$5:$AB$364,TRUE)
A13: Total PMI paid | B13: =SUMIFS(Schedule!$AH$5:$AH$364,Schedule!$AB$5:$AB$364,TRUE)
A14: Total cost of ownership | B14: =B7+B10+B11+B12+B13
A15: PMI dropped at payment # | B15: =IFERROR(INDEX(Schedule!$A$5:$A$364,MATCH(TRUE,Schedule!$AI$5:$AI$364,0)),IF(SUMPRODUCT((Schedule!$AB$5:$AB$364)*(Schedule!$AG$5:$AG$364))>0,"active through payoff","never"))
A17: Balloon segment index (last active row's segment) | B17: =SUMPRODUCT(MAX((Schedule!$AB$5:$AB$364)*(Schedule!$B$5:$B$364)))
A18: Balloon payment due? | B18: =IF(INDEX(Segments!$H:$H,B17+4)="Y","Yes","No")
A19: Balloon amount (if due) | B19: =IF(INDEX(Segments!$H:$H,B17+4)="Y",SUMPRODUCT(MAX((Schedule!$AB$5:$AB$364)*(Schedule!$W$5:$W$364))),"n/a")
A20: Balloon due date (if due) | B20: =IF(INDEX(Segments!$H:$H,B17+4)="Y",SUMPRODUCT(MAX((Schedule!$AB$5:$AB$364)*(Schedule!$E$5:$E$364))),"n/a")

Sheet YearlySummary
A1: Yearly Summary / Report Window
A2: Set 'Show through year' below (blue cell) to see cumulative totals for just the first N years -- e.g. enter 5 to answer 'how much interest will I pay in the first 5 years?' without scrolling the full Schedule.
A4: Show through year: | B4: 5
A6: Year | B6: Payments in Year | C6: Starting Balance | D6: Ending Balance | E6: Interest Paid | F6: Principal Paid
A7: 1 | B7: =SUMPRODUCT(((INT((Schedule!$A$5:$A$364-1)/12)+1=1))*(Schedule!$AB$5:$AB$364)) | C7: =IFERROR(INDEX(Schedule!$L$5:$L$364,MATCH(1,((INT((Schedule!$A$5:$A$364-1)/12)+1=1))*(Schedule!$AB$5:$AB$364),0)),"") | D7: =IFERROR(INDEX(Schedule!$AA$5:$AA$364,MATCH(SUMPRODUCT(MAX(((INT((Schedule!$A$5:$A$364-1)/12)+1=1))*(Schedule!$AB$5:$AB$364)*(Schedule!$A$5:$A$364))),Schedule!$A$5:$A$364,0)),"") | E7: =SUMPRODUCT(((INT((Schedule!$A$5:$A$364-1)/12)+1=1))*(Schedule!$AB$5:$AB$364)*(Schedule!$T$5:$T$364)) | F7: =SUMPRODUCT(((INT((Schedule!$A$5:$A$364-1)/12)+1=1))*(Schedule!$AB$5:$AB$364)*(Schedule!$Y$5:$Y$364))
A8: 2 | B8: =SUMPRODUCT(((INT((Schedule!$A$5:$A$364-1)/12)+1=2))*(Schedule!$AB$5:$AB$364)) | C8: =IFERROR(INDEX(Schedule!$L$5:$L$364,MATCH(1,((INT((Schedule!$A$5:$A$364-1)/12)+1=2))*(Schedule!$AB$5:$AB$364),0)),"") | D8: =IFERROR(INDEX(Schedule!$AA$5:$AA$364,MATCH(SUMPRODUCT(MAX(((INT((Schedule!$A$5:$A$364-1)/12)+1=2))*(Schedule!$AB$5:$AB$364)*(Schedule!$A$5:$A$364))),Schedule!$A$5:$A$364,0)),"") | E8: =SUMPRODUCT(((INT((Schedule!$A$5:$A$364-1)/12)+1=2))*(Schedule!$AB$5:$AB$364)*(Schedule!$T$5:$T$364)) | F8: =SUMPRODUCT(((INT((Schedule!$A$5:$A$364-1)/12)+1=2))*(Schedule!$AB$5:$AB$364)*(Schedule!$Y$5:$Y$364))
A9: 3 | B9: =SUMPRODUCT(((INT((Schedule!$A$5:$A$364-1)/12)+1=3))*(Schedule!$AB$5:$AB$364)) | C9: =IFERROR(INDEX(Schedule!$L$5:$L$364,MATCH(1,((INT((Schedule!$A$5:$A$364-1)/12)+1=3))*(Schedule!$AB$5:$AB$364),0)),"") | D9: =IFERROR(INDEX(Schedule!$AA$5:$AA$364,MATCH(SUMPRODUCT(MAX(((INT((Schedule!$A$5:$A$364-1)/12)+1=3))*(Schedule!$AB$5:$AB$364)*(Schedule!$A$5:$A$364))),Schedule!$A$5:$A$364,0)),"") | E9: =SUMPRODUCT(((INT((Schedule!$A$5:$A$364-1)/12)+1=3))*(Schedule!$AB$5:$AB$364)*(Schedule!$T$5:$T$364)) | F9: =SUMPRODUCT(((INT((Schedule!$A$5:$A$364-1)/12)+1=3))*(Schedule!$AB$5:$AB$364)*(Schedule!$Y$5:$Y$364))
A10: 4 | B10: =SUMPRODUCT(((INT((Schedule!$A$5:$A$364-1)/12)+1=4))*(Schedule!$AB$5:$AB$364)) | C10: =IFERROR(INDEX(Schedule!$L$5:$L$364,MATCH(1,((INT((Schedule!$A$5:$A$364-1)/12)+1=4))*(Schedule!$AB$5:$AB$364),0)),"") | D10: =IFERROR(INDEX(Schedule!$AA$5:$AA$364,MATCH(SUMPRODUCT(MAX(((INT((Schedule!$A$5:$A$364-1)/12)+1=4))*(Schedule!$AB$5:$AB$364)*(Schedule!$A$5:$A$364))),Schedule!$A$5:$A$364,0)),"") | E10: =SUMPRODUCT(((INT((Schedule!$A$5:$A$364-1)/12)+1=4))*(Schedule!$AB$5:$AB$364)*(Schedule!$T$5:$T$364)) | F10: =SUMPRODUCT(((INT((Schedule!$A$5:$A$364-1)/12)+1=4))*(Schedule!$AB$5:$AB$364)*(Schedule!$Y$5:$Y$364))
A11: 5 | B11: =SUMPRODUCT(((INT((Schedule!$A$5:$A$364-1)/12)+1=5))*(Schedule!$AB$5:$AB$364)) | C11: =IFERROR(INDEX(Schedule!$L$5:$L$364,MATCH(1,((INT((Schedule!$A$5:$A$364-1)/12)+1=5))*(Schedule!$AB$5:$AB$364),0)),"") | D11: =IFERROR(INDEX(Schedule!$AA$5:$AA$364,MATCH(SUMPRODUCT(MAX(((INT((Schedule!$A$5:$A$364-1)/12)+1=5))*(Schedule!$AB$5:$AB$364)*(Schedule!$A$5:$A$364))),Schedule!$A$5:$A$364,0)),"") | E11: =SUMPRODUCT(((INT((Schedule!$A$5:$A$364-1)/12)+1=5))*(Schedule!$AB$5:$AB$364)*(Schedule!$T$5:$T$364)) | F11: =SUMPRODUCT(((INT((Schedule!$A$5:$A$364-1)/12)+1=5))*(Schedule!$AB$5:$AB$364)*(Schedule!$Y$5:$Y$364))
A12: 6 | B12: =SUMPRODUCT(((INT((Schedule!$A$5:$A$364-1)/12)+1=6))*(Schedule!$AB$5:$AB$364)) | C12: =IFERROR(INDEX(Schedule!$L$5:$L$364,MATCH(1,((INT((Schedule!$A$5:$A$364-1)/12)+1=6))*(Schedule!$AB$5:$AB$364),0)),"") | D12: =IFERROR(INDEX(Schedule!$AA$5:$AA$364,MATCH(SUMPRODUCT(MAX(((INT((Schedule!$A$5:$A$364-1)/12)+1=6))*(Schedule!$AB$5:$AB$364)*(Schedule!$A$5:$A$364))),Schedule!$A$5:$A$364,0)),"") | E12: =SUMPRODUCT(((INT((Schedule!$A$5:$A$364-1)/12)+1=6))*(Schedule!$AB$5:$AB$364)*(Schedule!$T$5:$T$364)) | F12: =SUMPRODUCT(((INT((Schedule!$A$5:$A$364-1)/12)+1=6))*(Schedule!$AB$5:$AB$364)*(Schedule!$Y$5:$Y$364))
A13: 7 | B13: =SUMPRODUCT(((INT((Schedule!$A$5:$A$364-1)/12)+1=7))*(Schedule!$AB$5:$AB$364)) | C13: =IFERROR(INDEX(Schedule!$L$5:$L$364,MATCH(1,((INT((Schedule!$A$5:$A$364-1)/12)+1=7))*(Schedule!$AB$5:$AB$364),0)),"") | D13: =IFERROR(INDEX(Schedule!$AA$5:$AA$364,MATCH(SUMPRODUCT(MAX(((INT((Schedule!$A$5:$A$364-1)/12)+1=7))*(Schedule!$AB$5:$AB$364)*(Schedule!$A$5:$A$364))),Schedule!$A$5:$A$364,0)),"") | E13: =SUMPRODUCT(((INT((Schedule!$A$5:$A$364-1)/12)+1=7))*(Schedule!$AB$5:$AB$364)*(Schedule!$T$5:$T$364)) | F13: =SUMPRODUCT(((INT((Schedule!$A$5:$A$364-1)/12)+1=7))*(Schedule!$AB$5:$AB$364)*(Schedule!$Y$5:$Y$364))
A14: 8 | B14: =SUMPRODUCT(((INT((Schedule!$A$5:$A$364-1)/12)+1=8))*(Schedule!$AB$5:$AB$364)) | C14: =IFERROR(INDEX(Schedule!$L$5:$L$364,MATCH(1,((INT((Schedule!$A$5:$A$364-1)/12)+1=8))*(Schedule!$AB$5:$AB$364),0)),"") | D14: =IFERROR(INDEX(Schedule!$AA$5:$AA$364,MATCH(SUMPRODUCT(MAX(((INT((Schedule!$A$5:$A$364-1)/12)+1=8))*(Schedule!$AB$5:$AB$364)*(Schedule!$A$5:$A$364))),Schedule!$A$5:$A$364,0)),"") | E14: =SUMPRODUCT(((INT((Schedule!$A$5:$A$364-1)/12)+1=8))*(Schedule!$AB$5:$AB$364)*(Schedule!$T$5:$T$364)) | F14: =SUMPRODUCT(((INT((Schedule!$A$5:$A$364-1)/12)+1=8))*(Schedule!$AB$5:$AB$364)*(Schedule!$Y$5:$Y$364))
A15: 9 | B15: =SUMPRODUCT(((INT((Schedule!$A$5:$A$364-1)/12)+1=9))*(Schedule!$AB$5:$AB$364)) | C15: =IFERROR(INDEX(Schedule!$L$5:$L$364,MATCH(1,((INT((Schedule!$A$5:$A$364-1)/12)+1=9))*(Schedule!$AB$5:$AB$364),0)),"") | D15: =IFERROR(INDEX(Schedule!$AA$5:$AA$364,MATCH(SUMPRODUCT(MAX(((INT((Schedule!$A$5:$A$364-1)/12)+1=9))*(Schedule!$AB$5:$AB$364)*(Schedule!$A$5:$A$364))),Schedule!$A$5:$A$364,0)),"") | E15: =SUMPRODUCT(((INT((Schedule!$A$5:$A$364-1)/12)+1=9))*(Schedule!$AB$5:$AB$364)*(Schedule!$T$5:$T$364)) | F15: =SUMPRODUCT(((INT((Schedule!$A$5:$A$364-1)/12)+1=9))*(Schedule!$AB$5:$AB$364)*(Schedule!$Y$5:$Y$364))
A16: 10 | B16: =SUMPRODUCT(((INT((Schedule!$A$5:$A$364-1)/12)+1=10))*(Schedule!$AB$5:$AB$364)) | C16: =IFERROR(INDEX(Schedule!$L$5:$L$364,MATCH(1,((INT((Schedule!$A$5:$A$364-1)/12)+1=10))*(Schedule!$AB$5:$AB$364),0)),"") | D16: =IFERROR(INDEX(Schedule!$AA$5:$AA$364,MATCH(SUMPRODUCT(MAX(((INT((Schedule!$A$5:$A$364-1)/12)+1=10))*(Schedule!$AB$5:$AB$364)*(Schedule!$A$5:$A$364))),Schedule!$A$5:$A$364,0)),"") | E16: =SUMPRODUCT(((INT((Schedule!$A$5:$A$364-1)/12)+1=10))*(Schedule!$AB$5:$AB$364)*(Schedule!$T$5:$T$364)) | F16: =SUMPRODUCT(((INT((Schedule!$A$5:$A$364-1)/12)+1=10))*(Schedule!$AB$5:$AB$364)*(Schedule!$Y$5:$Y$364))
A17: 11 | B17: =SUMPRODUCT(((INT((Schedule!$A$5:$A$364-1)/12)+1=11))*(Schedule!$AB$5:$AB$364)) | C17: =IFERROR(INDEX(Schedule!$L$5:$L$364,MATCH(1,((INT((Schedule!$A$5:$A$364-1)/12)+1=11))*(Schedule!$AB$5:$AB$364),0)),"") | D17: =IFERROR(INDEX(Schedule!$AA$5:$AA$364,MATCH(SUMPRODUCT(MAX(((INT((Schedule!$A$5:$A$364-1)/12)+1=11))*(Schedule!$AB$5:$AB$364)*(Schedule!$A$5:$A$364))),Schedule!$A$5:$A$364,0)),"") | E17: =SUMPRODUCT(((INT((Schedule!$A$5:$A$364-1)/12)+1=11))*(Schedule!$AB$5:$AB$364)*(Schedule!$T$5:$T$364)) | F17: =SUMPRODUCT(((INT((Schedule!$A$5:$A$364-1)/12)+1=11))*(Schedule!$AB$5:$AB$364)*(Schedule!$Y$5:$Y$364))
A18: 12 | B18: =SUMPRODUCT(((INT((Schedule!$A$5:$A$364-1)/12)+1=12))*(Schedule!$AB$5:$AB$364)) | C18: =IFERROR(INDEX(Schedule!$L$5:$L$364,MATCH(1,((INT((Schedule!$A$5:$A$364-1)/12)+1=12))*(Schedule!$AB$5:$AB$364),0)),"") | D18: =IFERROR(INDEX(Schedule!$AA$5:$AA$364,MATCH(SUMPRODUCT(MAX(((INT((Schedule!$A$5:$A$364-1)/12)+1=12))*(Schedule!$AB$5:$AB$364)*(Schedule!$A$5:$A$364))),Schedule!$A$5:$A$364,0)),"") | E18: =SUMPRODUCT(((INT((Schedule!$A$5:$A$364-1)/12)+1=12))*(Schedule!$AB$5:$AB$364)*(Schedule!$T$5:$T$364)) | F18: =SUMPRODUCT(((INT((Schedule!$A$5:$A$364-1)/12)+1=12))*(Schedule!$AB$5:$AB$364)*(Schedule!$Y$5:$Y$364))
A19: 13 | B19: =SUMPRODUCT(((INT((Schedule!$A$5:$A$364-1)/12)+1=13))*(Schedule!$AB$5:$AB$364)) | C19: =IFERROR(INDEX(Schedule!$L$5:$L$364,MATCH(1,((INT((Schedule!$A$5:$A$364-1)/12)+1=13))*(Schedule!$AB$5:$AB$364),0)),"") | D19: =IFERROR(INDEX(Schedule!$AA$5:$AA$364,MATCH(SUMPRODUCT(MAX(((INT((Schedule!$A$5:$A$364-1)/12)+1=13))*(Schedule!$AB$5:$AB$364)*(Schedule!$A$5:$A$364))),Schedule!$A$5:$A$364,0)),"") | E19: =SUMPRODUCT(((INT((Schedule!$A$5:$A$364-1)/12)+1=13))*(Schedule!$AB$5:$AB$364)*(Schedule!$T$5:$T$364)) | F19: =SUMPRODUCT(((INT((Schedule!$A$5:$A$364-1)/12)+1=13))*(Schedule!$AB$5:$AB$364)*(Schedule!$Y$5:$Y$364))
A20: 14 | B20: =SUMPRODUCT(((INT((Schedule!$A$5:$A$364-1)/12)+1=14))*(Schedule!$AB$5:$AB$364)) | C20: =IFERROR(INDEX(Schedule!$L$5:$L$364,MATCH(1,((INT((Schedule!$A$5:$A$364-1)/12)+1=14))*(Schedule!$AB$5:$AB$364),0)),"") | D20: =IFERROR(INDEX(Schedule!$AA$5:$AA$364,MATCH(SUMPRODUCT(MAX(((INT((Schedule!$A$5:$A$364-1)/12)+1=14))*(Schedule!$AB$5:$AB$364)*(Schedule!$A$5:$A$364))),Schedule!$A$5:$A$364,0)),"") | E20: =SUMPRODUCT(((INT((Schedule!$A$5:$A$364-1)/12)+1=14))*(Schedule!$AB$5:$AB$364)*(Schedule!$T$5:$T$364)) | F20: =SUMPRODUCT(((INT((Schedule!$A$5:$A$364-1)/12)+1=14))*(Schedule!$AB$5:$AB$364)*(Schedule!$Y$5:$Y$364))
A21: 15 | B21: =SUMPRODUCT(((INT((Schedule!$A$5:$A$364-1)/12)+1=15))*(Schedule!$AB$5:$AB$364)) | C21: =IFERROR(INDEX(Schedule!$L$5:$L$364,MATCH(1,((INT((Schedule!$A$5:$A$364-1)/12)+1=15))*(Schedule!$AB$5:$AB$364),0)),"") | D21: =IFERROR(INDEX(Schedule!$AA$5:$AA$364,MATCH(SUMPRODUCT(MAX(((INT((Schedule!$A$5:$A$364-1)/12)+1=15))*(Schedule!$AB$5:$AB$364)*(Schedule!$A$5:$A$364))),Schedule!$A$5:$A$364,0)),"") | E21: =SUMPRODUCT(((INT((Schedule!$A$5:$A$364-1)/12)+1=15))*(Schedule!$AB$5:$AB$364)*(Schedule!$T$5:$T$364)) | F21: =SUMPRODUCT(((INT((Schedule!$A$5:$A$364-1)/12)+1=15))*(Schedule!$AB$5:$AB$364)*(Schedule!$Y$5:$Y$364))
A22: 16 | B22: =SUMPRODUCT(((INT((Schedule!$A$5:$A$364-1)/12)+1=16))*(Schedule!$AB$5:$AB$364)) | C22: =IFERROR(INDEX(Schedule!$L$5:$L$364,MATCH(1,((INT((Schedule!$A$5:$A$364-1)/12)+1=16))*(Schedule!$AB$5:$AB$364),0)),"") | D22: =IFERROR(INDEX(Schedule!$AA$5:$AA$364,MATCH(SUMPRODUCT(MAX(((INT((Schedule!$A$5:$A$364-1)/12)+1=16))*(Schedule!$AB$5:$AB$364)*(Schedule!$A$5:$A$364))),Schedule!$A$5:$A$364,0)),"") | E22: =SUMPRODUCT(((INT((Schedule!$A$5:$A$364-1)/12)+1=16))*(Schedule!$AB$5:$AB$364)*(Schedule!$T$5:$T$364)) | F22: =SUMPRODUCT(((INT((Schedule!$A$5:$A$364-1)/12)+1=16))*(Schedule!$AB$5:$AB$364)*(Schedule!$Y$5:$Y$364))
A23: 17 | B23: =SUMPRODUCT(((INT((Schedule!$A$5:$A$364-1)/12)+1=17))*(Schedule!$AB$5:$AB$364)) | C23: =IFERROR(INDEX(Schedule!$L$5:$L$364,MATCH(1,((INT((Schedule!$A$5:$A$364-1)/12)+1=17))*(Schedule!$AB$5:$AB$364),0)),"") | D23: =IFERROR(INDEX(Schedule!$AA$5:$AA$364,MATCH(SUMPRODUCT(MAX(((INT((Schedule!$A$5:$A$364-1)/12)+1=17))*(Schedule!$AB$5:$AB$364)*(Schedule!$A$5:$A$364))),Schedule!$A$5:$A$364,0)),"") | E23: =SUMPRODUCT(((INT((Schedule!$A$5:$A$364-1)/12)+1=17))*(Schedule!$AB$5:$AB$364)*(Schedule!$T$5:$T$364)) | F23: =SUMPRODUCT(((INT((Schedule!$A$5:$A$364-1)/12)+1=17))*(Schedule!$AB$5:$AB$364)*(Schedule!$Y$5:$Y$364))
A24: 18 | B24: =SUMPRODUCT(((INT((Schedule!$A$5:$A$364-1)/12)+1=18))*(Schedule!$AB$5:$AB$364)) | C24: =IFERROR(INDEX(Schedule!$L$5:$L$364,MATCH(1,((INT((Schedule!$A$5:$A$364-1)/12)+1=18))*(Schedule!$AB$5:$AB$364),0)),"") | D24: =IFERROR(INDEX(Schedule!$AA$5:$AA$364,MATCH(SUMPRODUCT(MAX(((INT((Schedule!$A$5:$A$364-1)/12)+1=18))*(Schedule!$AB$5:$AB$364)*(Schedule!$A$5:$A$364))),Schedule!$A$5:$A$364,0)),"") | E24: =SUMPRODUCT(((INT((Schedule!$A$5:$A$364-1)/12)+1=18))*(Schedule!$AB$5:$AB$364)*(Schedule!$T$5:$T$364)) | F24: =SUMPRODUCT(((INT((Schedule!$A$5:$A$364-1)/12)+1=18))*(Schedule!$AB$5:$AB$364)*(Schedule!$Y$5:$Y$364))
A25: 19 | B25: =SUMPRODUCT(((INT((Schedule!$A$5:$A$364-1)/12)+1=19))*(Schedule!$AB$5:$AB$364)) | C25: =IFERROR(INDEX(Schedule!$L$5:$L$364,MATCH(1,((INT((Schedule!$A$5:$A$364-1)/12)+1=19))*(Schedule!$AB$5:$AB$364),0)),"") | D25: =IFERROR(INDEX(Schedule!$AA$5:$AA$364,MATCH(SUMPRODUCT(MAX(((INT((Schedule!$A$5:$A$364-1)/12)+1=19))*(Schedule!$AB$5:$AB$364)*(Schedule!$A$5:$A$364))),Schedule!$A$5:$A$364,0)),"") | E25: =SUMPRODUCT(((INT((Schedule!$A$5:$A$364-1)/12)+1=19))*(Schedule!$AB$5:$AB$364)*(Schedule!$T$5:$T$364)) | F25: =SUMPRODUCT(((INT((Schedule!$A$5:$A$364-1)/12)+1=19))*(Schedule!$AB$5:$AB$364)*(Schedule!$Y$5:$Y$364))
A26: 20 | B26: =SUMPRODUCT(((INT((Schedule!$A$5:$A$364-1)/12)+1=20))*(Schedule!$AB$5:$AB$364)) | C26: =IFERROR(INDEX(Schedule!$L$5:$L$364,MATCH(1,((INT((Schedule!$A$5:$A$364-1)/12)+1=20))*(Schedule!$AB$5:$AB$364),0)),"") | D26: =IFERROR(INDEX(Schedule!$AA$5:$AA$364,MATCH(SUMPRODUCT(MAX(((INT((Schedule!$A$5:$A$364-1)/12)+1=20))*(Schedule!$AB$5:$AB$364)*(Schedule!$A$5:$A$364))),Schedule!$A$5:$A$364,0)),"") | E26: =SUMPRODUCT(((INT((Schedule!$A$5:$A$364-1)/12)+1=20))*(Schedule!$AB$5:$AB$364)*(Schedule!$T$5:$T$364)) | F26: =SUMPRODUCT(((INT((Schedule!$A$5:$A$364-1)/12)+1=20))*(Schedule!$AB$5:$AB$364)*(Schedule!$Y$5:$Y$364))
A27: 21 | B27: =SUMPRODUCT(((INT((Schedule!$A$5:$A$364-1)/12)+1=21))*(Schedule!$AB$5:$AB$364)) | C27: =IFERROR(INDEX(Schedule!$L$5:$L$364,MATCH(1,((INT((Schedule!$A$5:$A$364-1)/12)+1=21))*(Schedule!$AB$5:$AB$364),0)),"") | D27: =IFERROR(INDEX(Schedule!$AA$5:$AA$364,MATCH(SUMPRODUCT(MAX(((INT((Schedule!$A$5:$A$364-1)/12)+1=21))*(Schedule!$AB$5:$AB$364)*(Schedule!$A$5:$A$364))),Schedule!$A$5:$A$364,0)),"") | E27: =SUMPRODUCT(((INT((Schedule!$A$5:$A$364-1)/12)+1=21))*(Schedule!$AB$5:$AB$364)*(Schedule!$T$5:$T$364)) | F27: =SUMPRODUCT(((INT((Schedule!$A$5:$A$364-1)/12)+1=21))*(Schedule!$AB$5:$AB$364)*(Schedule!$Y$5:$Y$364))
A28: 22 | B28: =SUMPRODUCT(((INT((Schedule!$A$5:$A$364-1)/12)+1=22))*(Schedule!$AB$5:$AB$364)) | C28: =IFERROR(INDEX(Schedule!$L$5:$L$364,MATCH(1,((INT((Schedule!$A$5:$A$364-1)/12)+1=22))*(Schedule!$AB$5:$AB$364),0)),"") | D28: =IFERROR(INDEX(Schedule!$AA$5:$AA$364,MATCH(SUMPRODUCT(MAX(((INT((Schedule!$A$5:$A$364-1)/12)+1=22))*(Schedule!$AB$5:$AB$364)*(Schedule!$A$5:$A$364))),Schedule!$A$5:$A$364,0)),"") | E28: =SUMPRODUCT(((INT((Schedule!$A$5:$A$364-1)/12)+1=22))*(Schedule!$AB$5:$AB$364)*(Schedule!$T$5:$T$364)) | F28: =SUMPRODUCT(((INT((Schedule!$A$5:$A$364-1)/12)+1=22))*(Schedule!$AB$5:$AB$364)*(Schedule!$Y$5:$Y$364))
A29: 23 | B29: =SUMPRODUCT(((INT((Schedule!$A$5:$A$364-1)/12)+1=23))*(Schedule!$AB$5:$AB$364)) | C29: =IFERROR(INDEX(Schedule!$L$5:$L$364,MATCH(1,((INT((Schedule!$A$5:$A$364-1)/12)+1=23))*(Schedule!$AB$5:$AB$364),0)),"") | D29: =IFERROR(INDEX(Schedule!$AA$5:$AA$364,MATCH(SUMPRODUCT(MAX(((INT((Schedule!$A$5:$A$364-1)/12)+1=23))*(Schedule!$AB$5:$AB$364)*(Schedule!$A$5:$A$364))),Schedule!$A$5:$A$364,0)),"") | E29: =SUMPRODUCT(((INT((Schedule!$A$5:$A$364-1)/12)+1=23))*(Schedule!$AB$5:$AB$364)*(Schedule!$T$5:$T$364)) | F29: =SUMPRODUCT(((INT((Schedule!$A$5:$A$364-1)/12)+1=23))*(Schedule!$AB$5:$AB$364)*(Schedule!$Y$5:$Y$364))
A30: 24 | B30: =SUMPRODUCT(((INT((Schedule!$A$5:$A$364-1)/12)+1=24))*(Schedule!$AB$5:$AB$364)) | C30: =IFERROR(INDEX(Schedule!$L$5:$L$364,MATCH(1,((INT((Schedule!$A$5:$A$364-1)/12)+1=24))*(Schedule!$AB$5:$AB$364),0)),"") | D30: =IFERROR(INDEX(Schedule!$AA$5:$AA$364,MATCH(SUMPRODUCT(MAX(((INT((Schedule!$A$5:$A$364-1)/12)+1=24))*(Schedule!$AB$5:$AB$364)*(Schedule!$A$5:$A$364))),Schedule!$A$5:$A$364,0)),"") | E30: =SUMPRODUCT(((INT((Schedule!$A$5:$A$364-1)/12)+1=24))*(Schedule!$AB$5:$AB$364)*(Schedule!$T$5:$T$364)) | F30: =SUMPRODUCT(((INT((Schedule!$A$5:$A$364-1)/12)+1=24))*(Schedule!$AB$5:$AB$364)*(Schedule!$Y$5:$Y$364))
A31: 25 | B31: =SUMPRODUCT(((INT((Schedule!$A$5:$A$364-1)/12)+1=25))*(Schedule!$AB$5:$AB$364)) | C31: =IFERROR(INDEX(Schedule!$L$5:$L$364,MATCH(1,((INT((Schedule!$A$5:$A$364-1)/12)+1=25))*(Schedule!$AB$5:$AB$364),0)),"") | D31: =IFERROR(INDEX(Schedule!$AA$5:$AA$364,MATCH(SUMPRODUCT(MAX(((INT((Schedule!$A$5:$A$364-1)/12)+1=25))*(Schedule!$AB$5:$AB$364)*(Schedule!$A$5:$A$364))),Schedule!$A$5:$A$364,0)),"") | E31: =SUMPRODUCT(((INT((Schedule!$A$5:$A$364-1)/12)+1=25))*(Schedule!$AB$5:$AB$364)*(Schedule!$T$5:$T$364)) | F31: =SUMPRODUCT(((INT((Schedule!$A$5:$A$364-1)/12)+1=25))*(Schedule!$AB$5:$AB$364)*(Schedule!$Y$5:$Y$364))
A32: 26 | B32: =SUMPRODUCT(((INT((Schedule!$A$5:$A$364-1)/12)+1=26))*(Schedule!$AB$5:$AB$364)) | C32: =IFERROR(INDEX(Schedule!$L$5:$L$364,MATCH(1,((INT((Schedule!$A$5:$A$364-1)/12)+1=26))*(Schedule!$AB$5:$AB$364),0)),"") | D32: =IFERROR(INDEX(Schedule!$AA$5:$AA$364,MATCH(SUMPRODUCT(MAX(((INT((Schedule!$A$5:$A$364-1)/12)+1=26))*(Schedule!$AB$5:$AB$364)*(Schedule!$A$5:$A$364))),Schedule!$A$5:$A$364,0)),"") | E32: =SUMPRODUCT(((INT((Schedule!$A$5:$A$364-1)/12)+1=26))*(Schedule!$AB$5:$AB$364)*(Schedule!$T$5:$T$364)) | F32: =SUMPRODUCT(((INT((Schedule!$A$5:$A$364-1)/12)+1=26))*(Schedule!$AB$5:$AB$364)*(Schedule!$Y$5:$Y$364))
A33: 27 | B33: =SUMPRODUCT(((INT((Schedule!$A$5:$A$364-1)/12)+1=27))*(Schedule!$AB$5:$AB$364)) | C33: =IFERROR(INDEX(Schedule!$L$5:$L$364,MATCH(1,((INT((Schedule!$A$5:$A$364-1)/12)+1=27))*(Schedule!$AB$5:$AB$364),0)),"") | D33: =IFERROR(INDEX(Schedule!$AA$5:$AA$364,MATCH(SUMPRODUCT(MAX(((INT((Schedule!$A$5:$A$364-1)/12)+1=27))*(Schedule!$AB$5:$AB$364)*(Schedule!$A$5:$A$364))),Schedule!$A$5:$A$364,0)),"") | E33: =SUMPRODUCT(((INT((Schedule!$A$5:$A$364-1)/12)+1=27))*(Schedule!$AB$5:$AB$364)*(Schedule!$T$5:$T$364)) | F33: =SUMPRODUCT(((INT((Schedule!$A$5:$A$364-1)/12)+1=27))*(Schedule!$AB$5:$AB$364)*(Schedule!$Y$5:$Y$364))
A34: 28 | B34: =SUMPRODUCT(((INT((Schedule!$A$5:$A$364-1)/12)+1=28))*(Schedule!$AB$5:$AB$364)) | C34: =IFERROR(INDEX(Schedule!$L$5:$L$364,MATCH(1,((INT((Schedule!$A$5:$A$364-1)/12)+1=28))*(Schedule!$AB$5:$AB$364),0)),"") | D34: =IFERROR(INDEX(Schedule!$AA$5:$AA$364,MATCH(SUMPRODUCT(MAX(((INT((Schedule!$A$5:$A$364-1)/12)+1=28))*(Schedule!$AB$5:$AB$364)*(Schedule!$A$5:$A$364))),Schedule!$A$5:$A$364,0)),"") | E34: =SUMPRODUCT(((INT((Schedule!$A$5:$A$364-1)/12)+1=28))*(Schedule!$AB$5:$AB$364)*(Schedule!$T$5:$T$364)) | F34: =SUMPRODUCT(((INT((Schedule!$A$5:$A$364-1)/12)+1=28))*(Schedule!$AB$5:$AB$364)*(Schedule!$Y$5:$Y$364))
A35: 29 | B35: =SUMPRODUCT(((INT((Schedule!$A$5:$A$364-1)/12)+1=29))*(Schedule!$AB$5:$AB$364)) | C35: =IFERROR(INDEX(Schedule!$L$5:$L$364,MATCH(1,((INT((Schedule!$A$5:$A$364-1)/12)+1=29))*(Schedule!$AB$5:$AB$364),0)),"") | D35: =IFERROR(INDEX(Schedule!$AA$5:$AA$364,MATCH(SUMPRODUCT(MAX(((INT((Schedule!$A$5:$A$364-1)/12)+1=29))*(Schedule!$AB$5:$AB$364)*(Schedule!$A$5:$A$364))),Schedule!$A$5:$A$364,0)),"") | E35: =SUMPRODUCT(((INT((Schedule!$A$5:$A$364-1)/12)+1=29))*(Schedule!$AB$5:$AB$364)*(Schedule!$T$5:$T$364)) | F35: =SUMPRODUCT(((INT((Schedule!$A$5:$A$364-1)/12)+1=29))*(Schedule!$AB$5:$AB$364)*(Schedule!$Y$5:$Y$364))
A36: 30 | B36: =SUMPRODUCT(((INT((Schedule!$A$5:$A$364-1)/12)+1=30))*(Schedule!$AB$5:$AB$364)) | C36: =IFERROR(INDEX(Schedule!$L$5:$L$364,MATCH(1,((INT((Schedule!$A$5:$A$364-1)/12)+1=30))*(Schedule!$AB$5:$AB$364),0)),"") | D36: =IFERROR(INDEX(Schedule!$AA$5:$AA$364,MATCH(SUMPRODUCT(MAX(((INT((Schedule!$A$5:$A$364-1)/12)+1=30))*(Schedule!$AB$5:$AB$364)*(Schedule!$A$5:$A$364))),Schedule!$A$5:$A$364,0)),"") | E36: =SUMPRODUCT(((INT((Schedule!$A$5:$A$364-1)/12)+1=30))*(Schedule!$AB$5:$AB$364)*(Schedule!$T$5:$T$364)) | F36: =SUMPRODUCT(((INT((Schedule!$A$5:$A$364-1)/12)+1=30))*(Schedule!$AB$5:$AB$364)*(Schedule!$Y$5:$Y$364))
A38: Totals through year (see B4) | B38: =SUMIFS($E$7:$E$36,$A$7:$A$36,"<="&B4) | C38: =SUMIFS($F$7:$F$36,$A$7:$A$36,"<="&B4) | D38: =INDEX($D$7:$D$36,MATCH(MIN(B4,COUNT($A$7:$A$36)),$A$7:$A$36,0))
A39: (Interest / Principal / Ending balance)

Sheet PaymentFrequency
A1: Payment Frequency (monthly / semi-monthly / biweekly / weekly)
A2: Standalone single-loan calculator (not part of the segmented engine). Genuine per-period amortization at the chosen cadence. Bounded to 1560 periods (30 years at weekly, the densest cadence).
A4: Loan amount ($) | B4: 300000 | D4: Frequency | E4: Payments/Yr | F4: Payment Fraction
A5: Annual interest rate (%) | B5: 6.5 | D5: monthly | E5: 12 | F5: 1
A6: Term (months) | B6: 360 | D6: semiMonthly | E6: 24 | F6: 0.5
A7: Start date | B7: 2024-01-01 | D7: biweekly | E7: 26 | F7: 0.5
A8: Frequency (monthly/semiMonthly/biweekly/weekly) | B8: biweekly | D8: weekly | E8: 52 | F8: 0.25
A10: Payments per year (looked up) | B10: =INDEX($E$5:$E$8,MATCH(B8,$D$5:$D$8,0))
A11: Payment fraction (looked up) | B11: =INDEX($F$5:$F$8,MATCH(B8,$D$5:$D$8,0))
A12: Monthly-equivalent payment | B12: =ROUND(-PMT(B5/100/12,B6,B4),2)
A13: Period payment amount | B13: =ROUND(B12*B11,2)
A14: Number of periods to payoff | B14: =IFERROR(MATCH(0,$F$17:$F$1576,0),"loan does not pay off within 1560 periods -- extend the table")
A15: Total interest (this frequency) | B15: =SUM($D$17:$D$1576)
A16: Period # | B16: Period Date | C16: Payment | D16: Interest | E16: Principal | F16: Remaining Balance
A17: 1 | B17: =IF(B8="monthly",DATE(YEAR(B7)+INT((MONTH(B7)-1+0)/12),MOD(MONTH(B7)-1+0,12)+1,1)+(DAY(B7)-1),IF(B8="weekly",B7+0,IF(B8="biweekly",B7+0,B7+ROUND((0*365.25)/24,0)))) | C17: =IF((ROUND(B4-ROUND($B$13-D17,2),2)<=0),ROUND(D17+E17,2),$B$13) | D17: =ROUND(B4*B5/100/B10,2) | E17: =IF((ROUND(B4-ROUND($B$13-D17,2),2)<=0),B4,ROUND($B$13-D17,2)) | F17: =IF((ROUND(B4-ROUND($B$13-D17,2),2)<=0),0,ROUND(B4-E17,2))
A18: 2 | B18: =IF(B8="monthly",DATE(YEAR(B7)+INT((MONTH(B7)-1+1)/12),MOD(MONTH(B7)-1+1,12)+1,1)+(DAY(B7)-1),IF(B8="weekly",B7+7,IF(B8="biweekly",B7+14,B7+ROUND((1*365.25)/24,0)))) | C18: =IF((ROUND(F17-ROUND($B$13-D18,2),2)<=0),ROUND(D18+E18,2),$B$13) | D18: =ROUND(F17*B5/100/B10,2) | E18: =IF((ROUND(F17-ROUND($B$13-D18,2),2)<=0),F17,ROUND($B$13-D18,2)) | F18: =IF((ROUND(F17-ROUND($B$13-D18,2),2)<=0),0,ROUND(F17-E18,2))
A19: 3 | B19: =IF(B8="monthly",DATE(YEAR(B7)+INT((MONTH(B7)-1+2)/12),MOD(MONTH(B7)-1+2,12)+1,1)+(DAY(B7)-1),IF(B8="weekly",B7+14,IF(B8="biweekly",B7+28,B7+ROUND((2*365.25)/24,0)))) | C19: =IF((ROUND(F18-ROUND($B$13-D19,2),2)<=0),ROUND(D19+E19,2),$B$13) | D19: =ROUND(F18*B5/100/B10,2) | E19: =IF((ROUND(F18-ROUND($B$13-D19,2),2)<=0),F18,ROUND($B$13-D19,2)) | F19: =IF((ROUND(F18-ROUND($B$13-D19,2),2)<=0),0,ROUND(F18-E19,2))
A20: 4 | B20: =IF(B8="monthly",DATE(YEAR(B7)+INT((MONTH(B7)-1+3)/12),MOD(MONTH(B7)-1+3,12)+1,1)+(DAY(B7)-1),IF(B8="weekly",B7+21,IF(B8="biweekly",B7+42,B7+ROUND((3*365.25)/24,0)))) | C20: =IF((ROUND(F19-ROUND($B$13-D20,2),2)<=0),ROUND(D20+E20,2),$B$13) | D20: =ROUND(F19*B5/100/B10,2) | E20: =IF((ROUND(F19-ROUND($B$13-D20,2),2)<=0),F19,ROUND($B$13-D20,2)) | F20: =IF((ROUND(F19-ROUND($B$13-D20,2),2)<=0),0,ROUND(F19-E20,2))
A21: 5 | B21: =IF(B8="monthly",DATE(YEAR(B7)+INT((MONTH(B7)-1+4)/12),MOD(MONTH(B7)-1+4,12)+1,1)+(DAY(B7)-1),IF(B8="weekly",B7+28,IF(B8="biweekly",B7+56,B7+ROUND((4*365.25)/24,0)))) | C21: =IF((ROUND(F20-ROUND($B$13-D21,2),2)<=0),ROUND(D21+E21,2),$B$13) | D21: =ROUND(F20*B5/100/B10,2) | E21: =IF((ROUND(F20-ROUND($B$13-D21,2),2)<=0),F20,ROUND($B$13-D21,2)) | F21: =IF((ROUND(F20-ROUND($B$13-D21,2),2)<=0),0,ROUND(F20-E21,2))
A22: 6 | B22: =IF(B8="monthly",DATE(YEAR(B7)+INT((MONTH(B7)-1+5)/12),MOD(MONTH(B7)-1+5,12)+1,1)+(DAY(B7)-1),IF(B8="weekly",B7+35,IF(B8="biweekly",B7+70,B7+ROUND((5*365.25)/24,0)))) | C22: =IF((ROUND(F21-ROUND($B$13-D22,2),2)<=0),ROUND(D22+E22,2),$B$13) | D22: =ROUND(F21*B5/100/B10,2) | E22: =IF((ROUND(F21-ROUND($B$13-D22,2),2)<=0),F21,ROUND($B$13-D22,2)) | F22: =IF((ROUND(F21-ROUND($B$13-D22,2),2)<=0),0,ROUND(F21-E22,2))
A23: 7 | B23: =IF(B8="monthly",DATE(YEAR(B7)+INT((MONTH(B7)-1+6)/12),MOD(MONTH(B7)-1+6,12)+1,1)+(DAY(B7)-1),IF(B8="weekly",B7+42,IF(B8="biweekly",B7+84,B7+ROUND((6*365.25)/24,0)))) | C23: =IF((ROUND(F22-ROUND($B$13-D23,2),2)<=0),ROUND(D23+E23,2),$B$13) | D23: =ROUND(F22*B5/100/B10,2) | E23: =IF((ROUND(F22-ROUND($B$13-D23,2),2)<=0),F22,ROUND($B$13-D23,2)) | F23: =IF((ROUND(F22-ROUND($B$13-D23,2),2)<=0),0,ROUND(F22-E23,2))
A24: 8 | B24: =IF(B8="monthly",DATE(YEAR(B7)+INT((MONTH(B7)-1+7)/12),MOD(MONTH(B7)-1+7,12)+1,1)+(DAY(B7)-1),IF(B8="weekly",B7+49,IF(B8="biweekly",B7+98,B7+ROUND((7*365.25)/24,0)))) | C24: =IF((ROUND(F23-ROUND($B$13-D24,2),2)<=0),ROUND(D24+E24,2),$B$13) | D24: =ROUND(F23*B5/100/B10,2) | E24: =IF((ROUND(F23-ROUND($B$13-D24,2),2)<=0),F23,ROUND($B$13-D24,2)) | F24: =IF((ROUND(F23-ROUND($B$13-D24,2),2)<=0),0,ROUND(F23-E24,2))
A25: 9 | B25: =IF(B8="monthly",DATE(YEAR(B7)+INT((MONTH(B7)-1+8)/12),MOD(MONTH(B7)-1+8,12)+1,1)+(DAY(B7)-1),IF(B8="weekly",B7+56,IF(B8="biweekly",B7+112,B7+ROUND((8*365.25)/24,0)))) | C25: =IF((ROUND(F24-ROUND($B$13-D25,2),2)<=0),ROUND(D25+E25,2),$B$13) | D25: =ROUND(F24*B5/100/B10,2) | E25: =IF((ROUND(F24-ROUND($B$13-D25,2),2)<=0),F24,ROUND($B$13-D25,2)) | F25: =IF((ROUND(F24-ROUND($B$13-D25,2),2)<=0),0,ROUND(F24-E25,2))
A26: 10 | B26: =IF(B8="monthly",DATE(YEAR(B7)+INT((MONTH(B7)-1+9)/12),MOD(MONTH(B7)-1+9,12)+1,1)+(DAY(B7)-1),IF(B8="weekly",B7+63,IF(B8="biweekly",B7+126,B7+ROUND((9*365.25)/24,0)))) | C26: =IF((ROUND(F25-ROUND($B$13-D26,2),2)<=0),ROUND(D26+E26,2),$B$13) | D26: =ROUND(F25*B5/100/B10,2) | E26: =IF((ROUND(F25-ROUND($B$13-D26,2),2)<=0),F25,ROUND($B$13-D26,2)) | F26: =IF((ROUND(F25-ROUND($B$13-D26,2),2)<=0),0,ROUND(F25-E26,2))
A27: 11 | B27: =IF(B8="monthly",DATE(YEAR(B7)+INT((MONTH(B7)-1+10)/12),MOD(MONTH(B7)-1+10,12)+1,1)+(DAY(B7)-1),IF(B8="weekly",B7+70,IF(B8="biweekly",B7+140,B7+ROUND((10*365.25)/24,0)))) | C27: =IF((ROUND(F26-ROUND($B$13-D27,2),2)<=0),ROUND(D27+E27,2),$B$13) | D27: =ROUND(F26*B5/100/B10,2) | E27: =IF((ROUND(F26-ROUND($B$13-D27,2),2)<=0),F26,ROUND($B$13-D27,2)) | F27: =IF((ROUND(F26-ROUND($B$13-D27,2),2)<=0),0,ROUND(F26-E27,2))
A28: 12 | B28: =IF(B8="monthly",DATE(YEAR(B7)+INT((MONTH(B7)-1+11)/12),MOD(MONTH(B7)-1+11,12)+1,1)+(DAY(B7)-1),IF(B8="weekly",B7+77,IF(B8="biweekly",B7+154,B7+ROUND((11*365.25)/24,0)))) | C28: =IF((ROUND(F27-ROUND($B$13-D28,2),2)<=0),ROUND(D28+E28,2),$B$13) | D28: =ROUND(F27*B5/100/B10,2) | E28: =IF((ROUND(F27-ROUND($B$13-D28,2),2)<=0),F27,ROUND($B$13-D28,2)) | F28: =IF((ROUND(F27-ROUND($B$13-D28,2),2)<=0),0,ROUND(F27-E28,2))
A29: 13 | B29: =IF(B8="monthly",DATE(YEAR(B7)+INT((MONTH(B7)-1+12)/12),MOD(MONTH(B7)-1+12,12)+1,1)+(DAY(B7)-1),IF(B8="weekly",B7+84,IF(B8="biweekly",B7+168,B7+ROUND((12*365.25)/24,0)))) | C29: =IF((ROUND(F28-ROUND($B$13-D29,2),2)<=0),ROUND(D29+E29,2),$B$13) | D29: =ROUND(F28*B5/100/B10,2) | E29: =IF((ROUND(F28-ROUND($B$13-D29,2),2)<=0),F28,ROUND($B$13-D29,2)) | F29: =IF((ROUND(F28-ROUND($B$13-D29,2),2)<=0),0,ROUND(F28-E29,2))
A30: 14 | B30: =IF(B8="monthly",DATE(YEAR(B7)+INT((MONTH(B7)-1+13)/12),MOD(MONTH(B7)-1+13,12)+1,1)+(DAY(B7)-1),IF(B8="weekly",B7+91,IF(B8="biweekly",B7+182,B7+ROUND((13*365.25)/24,0)))) | C30: =IF((ROUND(F29-ROUND($B$13-D30,2),2)<=0),ROUND(D30+E30,2),$B$13) | D30: =ROUND(F29*B5/100/B10,2) | E30: =IF((ROUND(F29-ROUND($B$13-D30,2),2)<=0),F29,ROUND($B$13-D30,2)) | F30: =IF((ROUND(F29-ROUND($B$13-D30,2),2)<=0),0,ROUND(F29-E30,2))
A31: 15 | B31: =IF(B8="monthly",DATE(YEAR(B7)+INT((MONTH(B7)-1+14)/12),MOD(MONTH(B7)-1+14,12)+1,1)+(DAY(B7)-1),IF(B8="weekly",B7+98,IF(B8="biweekly",B7+196,B7+ROUND((14*365.25)/24,0)))) | C31: =IF((ROUND(F30-ROUND($B$13-D31,2),2)<=0),ROUND(D31+E31,2),$B$13) | D31: =ROUND(F30*B5/100/B10,2) | E31: =IF((ROUND(F30-ROUND($B$13-D31,2),2)<=0),F30,ROUND($B$13-D31,2)) | F31: =IF((ROUND(F30-ROUND($B$13-D31,2),2)<=0),0,ROUND(F30-E31,2))
A32: 16 | B32: =IF(B8="monthly",DATE(YEAR(B7)+INT((MONTH(B7)-1+15)/12),MOD(MONTH(B7)-1+15,12)+1,1)+(DAY(B7)-1),IF(B8="weekly",B7+105,IF(B8="biweekly",B7+210,B7+ROUND((15*365.25)/24,0)))) | C32: =IF((ROUND(F31-ROUND($B$13-D32,2),2)<=0),ROUND(D32+E32,2),$B$13) | D32: =ROUND(F31*B5/100/B10,2) | E32: =IF((ROUND(F31-ROUND($B$13-D32,2),2)<=0),F31,ROUND($B$13-D32,2)) | F32: =IF((ROUND(F31-ROUND($B$13-D32,2),2)<=0),0,ROUND(F31-E32,2))
A33: 17 | B33: =IF(B8="monthly",DATE(YEAR(B7)+INT((MONTH(B7)-1+16)/12),MOD(MONTH(B7)-1+16,12)+1,1)+(DAY(B7)-1),IF(B8="weekly",B7+112,IF(B8="biweekly",B7+224,B7+ROUND((16*365.25)/24,0)))) | C33: =IF((ROUND(F32-ROUND($B$13-D33,2),2)<=0),ROUND(D33+E33,2),$B$13) | D33: =ROUND(F32*B5/100/B10,2) | E33: =IF((ROUND(F32-ROUND($B$13-D33,2),2)<=0),F32,ROUND($B$13-D33,2)) | F33: =IF((ROUND(F32-ROUND($B$13-D33,2),2)<=0),0,ROUND(F32-E33,2))
A34: 18 | B34: =IF(B8="monthly",DATE(YEAR(B7)+INT((MONTH(B7)-1+17)/12),MOD(MONTH(B7)-1+17,12)+1,1)+(DAY(B7)-1),IF(B8="weekly",B7+119,IF(B8="biweekly",B7+238,B7+ROUND((17*365.25)/24,0)))) | C34: =IF((ROUND(F33-ROUND($B$13-D34,2),2)<=0),ROUND(D34+E34,2),$B$13) | D34: =ROUND(F33*B5/100/B10,2) | E34: =IF((ROUND(F33-ROUND($B$13-D34,2),2)<=0),F33,ROUND($B$13-D34,2)) | F34: =IF((ROUND(F33-ROUND($B$13-D34,2),2)<=0),0,ROUND(F33-E34,2))
A35: 19 | B35: =IF(B8="monthly",DATE(YEAR(B7)+INT((MONTH(B7)-1+18)/12),MOD(MONTH(B7)-1+18,12)+1,1)+(DAY(B7)-1),IF(B8="weekly",B7+126,IF(B8="biweekly",B7+252,B7+ROUND((18*365.25)/24,0)))) | C35: =IF((ROUND(F34-ROUND($B$13-D35,2),2)<=0),ROUND(D35+E35,2),$B$13) | D35: =ROUND(F34*B5/100/B10,2) | E35: =IF((ROUND(F34-ROUND($B$13-D35,2),2)<=0),F34,ROUND($B$13-D35,2)) | F35: =IF((ROUND(F34-ROUND($B$13-D35,2),2)<=0),0,ROUND(F34-E35,2))
A36: 20 | B36: =IF(B8="monthly",DATE(YEAR(B7)+INT((MONTH(B7)-1+19)/12),MOD(MONTH(B7)-1+19,12)+1,1)+(DAY(B7)-1),IF(B8="weekly",B7+133,IF(B8="biweekly",B7+266,B7+ROUND((19*365.25)/24,0)))) | C36: =IF((ROUND(F35-ROUND($B$13-D36,2),2)<=0),ROUND(D36+E36,2),$B$13) | D36: =ROUND(F35*B5/100/B10,2) | E36: =IF((ROUND(F35-ROUND($B$13-D36,2),2)<=0),F35,ROUND($B$13-D36,2)) | F36: =IF((ROUND(F35-ROUND($B$13-D36,2),2)<=0),0,ROUND(F35-E36,2))
A37: 21 | B37: =IF(B8="monthly",DATE(YEAR(B7)+INT((MONTH(B7)-1+20)/12),MOD(MONTH(B7)-1+20,12)+1,1)+(DAY(B7)-1),IF(B8="weekly",B7+140,IF(B8="biweekly",B7+280,B7+ROUND((20*365.25)/24,0)))) | C37: =IF((ROUND(F36-ROUND($B$13-D37,2),2)<=0),ROUND(D37+E37,2),$B$13) | D37: =ROUND(F36*B5/100/B10,2) | E37: =IF((ROUND(F36-ROUND($B$13-D37,2),2)<=0),F36,ROUND($B$13-D37,2)) | F37: =IF((ROUND(F36-ROUND($B$13-D37,2),2)<=0),0,ROUND(F36-E37,2))
A38: 22 | B38: =IF(B8="monthly",DATE(YEAR(B7)+INT((MONTH(B7)-1+21)/12),MOD(MONTH(B7)-1+21,12)+1,1)+(DAY(B7)-1),IF(B8="weekly",B7+147,IF(B8="biweekly",B7+294,B7+ROUND((21*365.25)/24,0)))) | C38: =IF((ROUND(F37-ROUND($B$13-D38,2),2)<=0),ROUND(D38+E38,2),$B$13) | D38: =ROUND(F37*B5/100/B10,2) | E38: =IF((ROUND(F37-ROUND($B$13-D38,2),2)<=0),F37,ROUND($B$13-D38,2)) | F38: =IF((ROUND(F37-ROUND($B$13-D38,2),2)<=0),0,ROUND(F37-E38,2))
A39: 23 | B39: =IF(B8="monthly",DATE(YEAR(B7)+INT((MONTH(B7)-1+22)/12),MOD(MONTH(B7)-1+22,12)+1,1)+(DAY(B7)-1),IF(B8="weekly",B7+154,IF(B8="biweekly",B7+308,B7+ROUND((22*365.25)/24,0)))) | C39: =IF((ROUND(F38-ROUND($B$13-D39,2),2)<=0),ROUND(D39+E39,2),$B$13) | D39: =ROUND(F38*B5/100/B10,2) | E39: =IF((ROUND(F38-ROUND($B$13-D39,2),2)<=0),F38,ROUND($B$13-D39,2)) | F39: =IF((ROUND(F38-ROUND($B$13-D39,2),2)<=0),0,ROUND(F38-E39,2))
A40: 24 | B40: =IF(B8="monthly",DATE(YEAR(B7)+INT((MONTH(B7)-1+23)/12),MOD(MONTH(B7)-1+23,12)+1,1)+(DAY(B7)-1),IF(B8="weekly",B7+161,IF(B8="biweekly",B7+322,B7+ROUND((23*365.25)/24,0)))) | C40: =IF((ROUND(F39-ROUND($B$13-D40,2),2)<=0),ROUND(D40+E40,2),$B$13) | D40: =ROUND(F39*B5/100/B10,2) | E40: =IF((ROUND(F39-ROUND($B$13-D40,2),2)<=0),F39,ROUND($B$13-D40,2)) | F40: =IF((ROUND(F39-ROUND($B$13-D40,2),2)<=0),0,ROUND(F39-E40,2))
A41: 25 | B41: =IF(B8="monthly",DATE(YEAR(B7)+INT((MONTH(B7)-1+24)/12),MOD(MONTH(B7)-1+24,12)+1,1)+(DAY(B7)-1),IF(B8="weekly",B7+168,IF(B8="biweekly",B7+336,B7+ROUND((24*365.25)/24,0)))) | C41: =IF((ROUND(F40-ROUND($B$13-D41,2),2)<=0),ROUND(D41+E41,2),$B$13) | D41: =ROUND(F40*B5/100/B10,2) | E41: =IF((ROUND(F40-ROUND($B$13-D41,2),2)<=0),F40,ROUND($B$13-D41,2)) | F41: =IF((ROUND(F40-ROUND($B$13-D41,2),2)<=0),0,ROUND(F40-E41,2))
A42: 26 | B42: =IF(B8="monthly",DATE(YEAR(B7)+INT((MONTH(B7)-1+25)/12),MOD(MONTH(B7)-1+25,12)+1,1)+(DAY(B7)-1),IF(B8="weekly",B7+175,IF(B8="biweekly",B7+350,B7+ROUND((25*365.25)/24,0)))) | C42: =IF((ROUND(F41-ROUND($B$13-D42,2),2)<=0),ROUND(D42+E42,2),$B$13) | D42: =ROUND(F41*B5/100/B10,2) | E42: =IF((ROUND(F41-ROUND($B$13-D42,2),2)<=0),F41,ROUND($B$13-D42,2)) | F42: =IF((ROUND(F41-ROUND($B$13-D42,2),2)<=0),0,ROUND(F41-E42,2))
A43: 27 | B43: =IF(B8="monthly",DATE(YEAR(B7)+INT((MONTH(B7)-1+26)/12),MOD(MONTH(B7)-1+26,12)+1,1)+(DAY(B7)-1),IF(B8="weekly",B7+182,IF(B8="biweekly",B7+364,B7+ROUND((26*365.25)/24,0)))) | C43: =IF((ROUND(F42-ROUND($B$13-D43,2),2)<=0),ROUND(D43+E43,2),$B$13) | D43: =ROUND(F42*B5/100/B10,2) | E43: =IF((ROUND(F42-ROUND($B$13-D43,2),2)<=0),F42,ROUND($B$13-D43,2)) | F43: =IF((ROUND(F42-ROUND($B$13-D43,2),2)<=0),0,ROUND(F42-E43,2))
A44: 28 | B44: =IF(B8="monthly",DATE(YEAR(B7)+INT((MONTH(B7)-1+27)/12),MOD(MONTH(B7)-1+27,12)+1,1)+(DAY(B7)-1),IF(B8="weekly",B7+189,IF(B8="biweekly",B7+378,B7+ROUND((27*365.25)/24,0)))) | C44: =IF((ROUND(F43-ROUND($B$13-D44,2),2)<=0),ROUND(D44+E44,2),$B$13) | D44: =ROUND(F43*B5/100/B10,2) | E44: =IF((ROUND(F43-ROUND($B$13-D44,2),2)<=0),F43,ROUND($B$13-D44,2)) | F44: =IF((ROUND(F43-ROUND($B$13-D44,2),2)<=0),0,ROUND(F43-E44,2))
A45: 29 | B45: =IF(B8="monthly",DATE(YEAR(B7)+INT((MONTH(B7)-1+28)/12),MOD(MONTH(B7)-1+28,12)+1,1)+(DAY(B7)-1),IF(B8="weekly",B7+196,IF(B8="biweekly",B7+392,B7+ROUND((28*365.25)/24,0)))) | C45: =IF((ROUND(F44-ROUND($B$13-D45,2),2)<=0),ROUND(D45+E45,2),$B$13) | D45: =ROUND(F44*B5/100/B10,2) | E45: =IF((ROUND(F44-ROUND($B$13-D45,2),2)<=0),F44,ROUND($B$13-D45,2)) | F45: =IF((ROUND(F44-ROUND($B$13-D45,2),2)<=0),0,ROUND(F44-E45,2))
A46: 30 | B46: =IF(B8="monthly",DATE(YEAR(B7)+INT((MONTH(B7)-1+29)/12),MOD(MONTH(B7)-1+29,12)+1,1)+(DAY(B7)-1),IF(B8="weekly",B7+203,IF(B8="biweekly",B7+406,B7+ROUND((29*365.25)/24,0)))) | C46: =IF((ROUND(F45-ROUND($B$13-D46,2),2)<=0),ROUND(D46+E46,2),$B$13) | D46: =ROUND(F45*B5/100/B10,2) | E46: =IF((ROUND(F45-ROUND($B$13-D46,2),2)<=0),F45,ROUND($B$13-D46,2)) | F46: =IF((ROUND(F45-ROUND($B$13-D46,2),2)<=0),0,ROUND(F45-E46,2))
A47: 31 | B47: =IF(B8="monthly",DATE(YEAR(B7)+INT((MONTH(B7)-1+30)/12),MOD(MONTH(B7)-1+30,12)+1,1)+(DAY(B7)-1),IF(B8="weekly",B7+210,IF(B8="biweekly",B7+420,B7+ROUND((30*365.25)/24,0)))) | C47: =IF((ROUND(F46-ROUND($B$13-D47,2),2)<=0),ROUND(D47+E47,2),$B$13) | D47: =ROUND(F46*B5/100/B10,2) | E47: =IF((ROUND(F46-ROUND($B$13-D47,2),2)<=0),F46,ROUND($B$13-D47,2)) | F47: =IF((ROUND(F46-ROUND($B$13-D47,2),2)<=0),0,ROUND(F46-E47,2))
A48: 32 | B48: =IF(B8="monthly",DATE(YEAR(B7)+INT((MONTH(B7)-1+31)/12),MOD(MONTH(B7)-1+31,12)+1,1)+(DAY(B7)-1),IF(B8="weekly",B7+217,IF(B8="biweekly",B7+434,B7+ROUND((31*365.25)/24,0)))) | C48: =IF((ROUND(F47-ROUND($B$13-D48,2),2)<=0),ROUND(D48+E48,2),$B$13) | D48: =ROUND(F47*B5/100/B10,2) | E48: =IF((ROUND(F47-ROUND($B$13-D48,2),2)<=0),F47,ROUND($B$13-D48,2)) | F48: =IF((ROUND(F47-ROUND($B$13-D48,2),2)<=0),0,ROUND(F47-E48,2))
A49: 33 | B49: =IF(B8="monthly",DATE(YEAR(B7)+INT((MONTH(B7)-1+32)/12),MOD(MONTH(B7)-1+32,12)+1,1)+(DAY(B7)-1),IF(B8="weekly",B7+224,IF(B8="biweekly",B7+448,B7+ROUND((32*365.25)/24,0)))) | C49: =IF((ROUND(F48-ROUND($B$13-D49,2),2)<=0),ROUND(D49+E49,2),$B$13) | D49: =ROUND(F48*B5/100/B10,2) | E49: =IF((ROUND(F48-ROUND($B$13-D49,2),2)<=0),F48,ROUND($B$13-D49,2)) | F49: =IF((ROUND(F48-ROUND($B$13-D49,2),2)<=0),0,ROUND(F48-E49,2))
A50: 34 | B50: =IF(B8="monthly",DATE(YEAR(B7)+INT((MONTH(B7)-1+33)/12),MOD(MONTH(B7)-1+33,12)+1,1)+(DAY(B7)-1),IF(B8="weekly",B7+231,IF(B8="biweekly",B7+462,B7+ROUND((33*365.25)/24,0)))) | C50: =IF((ROUND(F49-ROUND($B$13-D50,2),2)<=0),ROUND(D50+E50,2),$B$13) | D50: =ROUND(F49*B5/100/B10,2) | E50: =IF((ROUND(F49-ROUND($B$13-D50,2),2)<=0),F49,ROUND($B$13-D50,2)) | F50: =IF((ROUND(F49-ROUND($B$13-D50,2),2)<=0),0,ROUND(F49-E50,2))
A51: 35 | B51: =IF(B8="monthly",DATE(YEAR(B7)+INT((MONTH(B7)-1+34)/12),MOD(MONTH(B7)-1+34,12)+1,1)+(DAY(B7)-1),IF(B8="weekly",B7+238,IF(B8="biweekly",B7+476,B7+ROUND((34*365.25)/24,0)))) | C51: =IF((ROUND(F50-ROUND($B$13-D51,2),2)<=0),ROUND(D51+E51,2),$B$13) | D51: =ROUND(F50*B5/100/B10,2) | E51: =IF((ROUND(F50-ROUND($B$13-D51,2),2)<=0),F50,ROUND($B$13-D51,2)) | F51: =IF((ROUND(F50-ROUND($B$13-D51,2),2)<=0),0,ROUND(F50-E51,2))
A52: 36 | B52: =IF(B8="monthly",DATE(YEAR(B7)+INT((MONTH(B7)-1+35)/12),MOD(MONTH(B7)-1+35,12)+1,1)+(DAY(B7)-1),IF(B8="weekly",B7+245,IF(B8="biweekly",B7+490,B7+ROUND((35*365.25)/24,0)))) | C52: =IF((ROUND(F51-ROUND($B$13-D52,2),2)<=0),ROUND(D52+E52,2),$B$13) | D52: =ROUND(F51*B5/100/B10,2) | E52: =IF((ROUND(F51-ROUND($B$13-D52,2),2)<=0),F51,ROUND($B$13-D52,2)) | F52: =IF((ROUND(F51-ROUND($B$13-D52,2),2)<=0),0,ROUND(F51-E52,2))
A53: 37 | B53: =IF(B8="monthly",DATE(YEAR(B7)+INT((MONTH(B7)-1+36)/12),MOD(MONTH(B7)-1+36,12)+1,1)+(DAY(B7)-1),IF(B8="weekly",B7+252,IF(B8="biweekly",B7+504,B7+ROUND((36*365.25)/24,0)))) | C53: =IF((ROUND(F52-ROUND($B$13-D53,2),2)<=0),ROUND(D53+E53,2),$B$13) | D53: =ROUND(F52*B5/100/B10,2) | E53: =IF((ROUND(F52-ROUND($B$13-D53,2),2)<=0),F52,ROUND($B$13-D53,2)) | F53: =IF((ROUND(F52-ROUND($B$13-D53,2),2)<=0),0,ROUND(F52-E53,2))
A54: 38 | B54: =IF(B8="monthly",DATE(YEAR(B7)+INT((MONTH(B7)-1+37)/12),MOD(MONTH(B7)-1+37,12)+1,1)+(DAY(B7)-1),IF(B8="weekly",B7+259,IF(B8="biweekly",B7+518,B7+ROUND((37*365.25)/24,0)))) | C54: =IF((ROUND(F53-ROUND($B$13-D54,2),2)<=0),ROUND(D54+E54,2),$B$13) | D54: =ROUND(F53*B5/100/B10,2) | E54: =IF((ROUND(F53-ROUND($B$13-D54,2),2)<=0),F53,ROUND($B$13-D54,2)) | F54: =IF((ROUND(F53-ROUND($B$13-D54,2),2)<=0),0,ROUND(F53-E54,2))
A55: 39 | B55: =IF(B8="monthly",DATE(YEAR(B7)+INT((MONTH(B7)-1+38)/12),MOD(MONTH(B7)-1+38,12)+1,1)+(DAY(B7)-1),IF(B8="weekly",B7+266,IF(B8="biweekly",B7+532,B7+ROUND((38*365.25)/24,0)))) | C55: =IF((ROUND(F54-ROUND($B$13-D55,2),2)<=0),ROUND(D55+E55,2),$B$13) | D55: =ROUND(F54*B5/100/B10,2) | E55: =IF((ROUND(F54-ROUND($B$13-D55,2),2)<=0),F54,ROUND($B$13-D55,2)) | F55: =IF((ROUND(F54-ROUND($B$13-D55,2),2)<=0),0,ROUND(F54-E55,2))
A56: 40 | B56: =IF(B8="monthly",DATE(YEAR(B7)+INT((MONTH(B7)-1+39)/12),MOD(MONTH(B7)-1+39,12)+1,1)+(DAY(B7)-1),IF(B8="weekly",B7+273,IF(B8="biweekly",B7+546,B7+ROUND((39*365.25)/24,0)))) | C56: =IF((ROUND(F55-ROUND($B$13-D56,2),2)<=0),ROUND(D56+E56,2),$B$13) | D56: =ROUND(F55*B5/100/B10,2) | E56: =IF((ROUND(F55-ROUND($B$13-D56,2),2)<=0),F55,ROUND($B$13-D56,2)) | F56: =IF((ROUND(F55-ROUND($B$13-D56,2),2)<=0),0,ROUND(F55-E56,2))
A57: 41 | B57: =IF(B8="monthly",DATE(YEAR(B7)+INT((MONTH(B7)-1+40)/12),MOD(MONTH(B7)-1+40,12)+1,1)+(DAY(B7)-1),IF(B8="weekly",B7+280,IF(B8="biweekly",B7+560,B7+ROUND((40*365.25)/24,0)))) | C57: =IF((ROUND(F56-ROUND($B$13-D57,2),2)<=0),ROUND(D57+E57,2),$B$13) | D57: =ROUND(F56*B5/100/B10,2) | E57: =IF((ROUND(F56-ROUND($B$13-D57,2),2)<=0),F56,ROUND($B$13-D57,2)) | F57: =IF((ROUND(F56-ROUND($B$13-D57,2),2)<=0),0,ROUND(F56-E57,2))
A58: 42 | B58: =IF(B8="monthly",DATE(YEAR(B7)+INT((MONTH(B7)-1+41)/12),MOD(MONTH(B7)-1+41,12)+1,1)+(DAY(B7)-1),IF(B8="weekly",B7+287,IF(B8="biweekly",B7+574,B7+ROUND((41*365.25)/24,0)))) | C58: =IF((ROUND(F57-ROUND($B$13-D58,2),2)<=0),ROUND(D58+E58,2),$B$13) | D58: =ROUND(F57*B5/100/B10,2) | E58: =IF((ROUND(F57-ROUND($B$13-D58,2),2)<=0),F57,ROUND($B$13-D58,2)) | F58: =IF((ROUND(F57-ROUND($B$13-D58,2),2)<=0),0,ROUND(F57-E58,2))
A59: 43 | B59: =IF(B8="monthly",DATE(YEAR(B7)+INT((MONTH(B7)-1+42)/12),MOD(MONTH(B7)-1+42,12)+1,1)+(DAY(B7)-1),IF(B8="weekly",B7+294,IF(B8="biweekly",B7+588,B7+ROUND((42*365.25)/24,0)))) | C59: =IF((ROUND(F58-ROUND($B$13-D59,2),2)<=0),ROUND(D59+E59,2),$B$13) | D59: =ROUND(F58*B5/100/B10,2) | E59: =IF((ROUND(F58-ROUND($B$13-D59,2),2)<=0),F58,ROUND($B$13-D59,2)) | F59: =IF((ROUND(F58-ROUND($B$13-D59,2),2)<=0),0,ROUND(F58-E59,2))
A60: 44 | B60: =IF(B8="monthly",DATE(YEAR(B7)+INT((MONTH(B7)-1+43)/12),MOD(MONTH(B7)-1+43,12)+1,1)+(DAY(B7)-1),IF(B8="weekly",B7+301,IF(B8="biweekly",B7+602,B7+ROUND((43*365.25)/24,0)))) | C60: =IF((ROUND(F59-ROUND($B$13-D60,2),2)<=0),ROUND(D60+E60,2),$B$13) | D60: =ROUND(F59*B5/100/B10,2) | E60: =IF((ROUND(F59-ROUND($B$13-D60,2),2)<=0),F59,ROUND($B$13-D60,2)) | F60: =IF((ROUND(F59-ROUND($B$13-D60,2),2)<=0),0,ROUND(F59-E60,2))
A61: 45 | B61: =IF(B8="monthly",DATE(YEAR(B7)+INT((MONTH(B7)-1+44)/12),MOD(MONTH(B7)-1+44,12)+1,1)+(DAY(B7)-1),IF(B8="weekly",B7+308,IF(B8="biweekly",B7+616,B7+ROUND((44*365.25)/24,0)))) | C61: =IF((ROUND(F60-ROUND($B$13-D61,2),2)<=0),ROUND(D61+E61,2),$B$13) | D61: =ROUND(F60*B5/100/B10,2) | E61: =IF((ROUND(F60-ROUND($B$13-D61,2),2)<=0),F60,ROUND($B$13-D61,2)) | F61: =IF((ROUND(F60-ROUND($B$13-D61,2),2)<=0),0,ROUND(F60-E61,2))
A62: 46 | B62: =IF(B8="monthly",DATE(YEAR(B7)+INT((MONTH(B7)-1+45)/12),MOD(MONTH(B7)-1+45,12)+1,1)+(DAY(B7)-1),IF(B8="weekly",B7+315,IF(B8="biweekly",B7+630,B7+ROUND((45*365.25)/24,0)))) | C62: =IF((ROUND(F61-ROUND($B$13-D62,2),2)<=0),ROUND(D62+E62,2),$B$13) | D62: =ROUND(F61*B5/100/B10,2) | E62: =IF((ROUND(F61-ROUND($B$13-D62,2),2)<=0),F61,ROUND($B$13-D62,2)) | F62: =IF((ROUND(F61-ROUND($B$13-D62,2),2)<=0),0,ROUND(F61-E62,2))
A63: 47 | B63: =IF(B8="monthly",DATE(YEAR(B7)+INT((MONTH(B7)-1+46)/12),MOD(MONTH(B7)-1+46,12)+1,1)+(DAY(B7)-1),IF(B8="weekly",B7+322,IF(B8="biweekly",B7+644,B7+ROUND((46*365.25)/24,0)))) | C63: =IF((ROUND(F62-ROUND($B$13-D63,2),2)<=0),ROUND(D63+E63,2),$B$13) | D63: =ROUND(F62*B5/100/B10,2) | E63: =IF((ROUND(F62-ROUND($B$13-D63,2),2)<=0),F62,ROUND($B$13-D63,2)) | F63: =IF((ROUND(F62-ROUND($B$13-D63,2),2)<=0),0,ROUND(F62-E63,2))
A64: 48 | B64: =IF(B8="monthly",DATE(YEAR(B7)+INT((MONTH(B7)-1+47)/12),MOD(MONTH(B7)-1+47,12)+1,1)+(DAY(B7)-1),IF(B8="weekly",B7+329,IF(B8="biweekly",B7+658,B7+ROUND((47*365.25)/24,0)))) | C64: =IF((ROUND(F63-ROUND($B$13-D64,2),2)<=0),ROUND(D64+E64,2),$B$13) | D64: =ROUND(F63*B5/100/B10,2) | E64: =IF((ROUND(F63-ROUND($B$13-D64,2),2)<=0),F63,ROUND($B$13-D64,2)) | F64: =IF((ROUND(F63-ROUND($B$13-D64,2),2)<=0),0,ROUND(F63-E64,2))
A65: 49 | B65: =IF(B8="monthly",DATE(YEAR(B7)+INT((MONTH(B7)-1+48)/12),MOD(MONTH(B7)-1+48,12)+1,1)+(DAY(B7)-1),IF(B8="weekly",B7+336,IF(B8="biweekly",B7+672,B7+ROUND((48*365.25)/24,0)))) | C65: =IF((ROUND(F64-ROUND($B$13-D65,2),2)<=0),ROUND(D65+E65,2),$B$13) | D65: =ROUND(F64*B5/100/B10,2) | E65: =IF((ROUND(F64-ROUND($B$13-D65,2),2)<=0),F64,ROUND($B$13-D65,2)) | F65: =IF((ROUND(F64-ROUND($B$13-D65,2),2)<=0),0,ROUND(F64-E65,2))
A66: 50 | B66: =IF(B8="monthly",DATE(YEAR(B7)+INT((MONTH(B7)-1+49)/12),MOD(MONTH(B7)-1+49,12)+1,1)+(DAY(B7)-1),IF(B8="weekly",B7+343,IF(B8="biweekly",B7+686,B7+ROUND((49*365.25)/24,0)))) | C66: =IF((ROUND(F65-ROUND($B$13-D66,2),2)<=0),ROUND(D66+E66,2),$B$13) | D66: =ROUND(F65*B5/100/B10,2) | E66: =IF((ROUND(F65-ROUND($B$13-D66,2),2)<=0),F65,ROUND($B$13-D66,2)) | F66: =IF((ROUND(F65-ROUND($B$13-D66,2),2)<=0),0,ROUND(F65-E66,2))
A67: 51 | B67: =IF(B8="monthly",DATE(YEAR(B7)+INT((MONTH(B7)-1+50)/12),MOD(MONTH(B7)-1+50,12)+1,1)+(DAY(B7)-1),IF(B8="weekly",B7+350,IF(B8="biweekly",B7+700,B7+ROUND((50*365.25)/24,0)))) | C67: =IF((ROUND(F66-ROUND($B$13-D67,2),2)<=0),ROUND(D67+E67,2),$B$13) | D67: =ROUND(F66*B5/100/B10,2) | E67: =IF((ROUND(F66-ROUND($B$13-D67,2),2)<=0),F66,ROUND($B$13-D67,2)) | F67: =IF((ROUND(F66-ROUND($B$13-D67,2),2)<=0),0,ROUND(F66-E67,2))
A68: 52 | B68: =IF(B8="monthly",DATE(YEAR(B7)+INT((MONTH(B7)-1+51)/12),MOD(MONTH(B7)-1+51,12)+1,1)+(DAY(B7)-1),IF(B8="weekly",B7+357,IF(B8="biweekly",B7+714,B7+ROUND((51*365.25)/24,0)))) | C68: =IF((ROUND(F67-ROUND($B$13-D68,2),2)<=0),ROUND(D68+E68,2),$B$13) | D68: =ROUND(F67*B5/100/B10,2) | E68: =IF((ROUND(F67-ROUND($B$13-D68,2),2)<=0),F67,ROUND($B$13-D68,2)) | F68: =IF((ROUND(F67-ROUND($B$13-D68,2),2)<=0),0,ROUND(F67-E68,2))
A69: 53 | B69: =IF(B8="monthly",DATE(YEAR(B7)+INT((MONTH(B7)-1+52)/12),MOD(MONTH(B7)-1+52,12)+1,1)+(DAY(B7)-1),IF(B8="weekly",B7+364,IF(B8="biweekly",B7+728,B7+ROUND((52*365.25)/24,0)))) | C69: =IF((ROUND(F68-ROUND($B$13-D69,2),2)<=0),ROUND(D69+E69,2),$B$13) | D69: =ROUND(F68*B5/100/B10,2) | E69: =IF((ROUND(F68-ROUND($B$13-D69,2),2)<=0),F68,ROUND($B$13-D69,2)) | F69: =IF((ROUND(F68-ROUND($B$13-D69,2),2)<=0),0,ROUND(F68-E69,2))
A70: 54 | B70: =IF(B8="monthly",DATE(YEAR(B7)+INT((MONTH(B7)-1+53)/12),MOD(MONTH(B7)-1+53,12)+1,1)+(DAY(B7)-1),IF(B8="weekly",B7+371,IF(B8="biweekly",B7+742,B7+ROUND((53*365.25)/24,0)))) | C70: =IF((ROUND(F69-ROUND($B$13-D70,2),2)<=0),ROUND(D70+E70,2),$B$13) | D70: =ROUND(F69*B5/100/B10,2) | E70: =IF((ROUND(F69-ROUND($B$13-D70,2),2)<=0),F69,ROUND($B$13-D70,2)) | F70: =IF((ROUND(F69-ROUND($B$13-D70,2),2)<=0),0,ROUND(F69-E70,2))
A71: 55 | B71: =IF(B8="monthly",DATE(YEAR(B7)+INT((MONTH(B7)-1+54)/12),MOD(MONTH(B7)-1+54,12)+1,1)+(DAY(B7)-1),IF(B8="weekly",B7+378,IF(B8="biweekly",B7+756,B7+ROUND((54*365.25)/24,0)))) | C71: =IF((ROUND(F70-ROUND($B$13-D71,2),2)<=0),ROUND(D71+E71,2),$B$13) | D71: =ROUND(F70*B5/100/B10,2) | E71: =IF((ROUND(F70-ROUND($B$13-D71,2),2)<=0),F70,ROUND($B$13-D71,2)) | F71: =IF((ROUND(F70-ROUND($B$13-D71,2),2)<=0),0,ROUND(F70-E71,2))
A72: 56 | B72: =IF(B8="monthly",DATE(YEAR(B7)+INT((MONTH(B7)-1+55)/12),MOD(MONTH(B7)-1+55,12)+1,1)+(DAY(B7)-1),IF(B8="weekly",B7+385,IF(B8="biweekly",B7+770,B7+ROUND((55*365.25)/24,0)))) | C72: =IF((ROUND(F71-ROUND($B$13-D72,2),2)<=0),ROUND(D72+E72,2),$B$13) | D72: =ROUND(F71*B5/100/B10,2) | E72: =IF((ROUND(F71-ROUND($B$13-D72,2),2)<=0),F71,ROUND($B$13-D72,2)) | F72: =IF((ROUND(F71-ROUND($B$13-D72,2),2)<=0),0,ROUND(F71-E72,2))
A73: 57 | B73: =IF(B8="monthly",DATE(YEAR(B7)+INT((MONTH(B7)-1+56)/12),MOD(MONTH(B7)-1+56,12)+1,1)+(DAY(B7)-1),IF(B8="weekly",B7+392,IF(B8="biweekly",B7+784,B7+ROUND((56*365.25)/24,0)))) | C73: =IF((ROUND(F72-ROUND($B$13-D73,2),2)<=0),ROUND(D73+E73,2),$B$13) | D73: =ROUND(F72*B5/100/B10,2) | E73: =IF((ROUND(F72-ROUND($B$13-D73,2),2)<=0),F72,ROUND($B$13-D73,2)) | F73: =IF((ROUND(F72-ROUND($B$13-D73,2),2)<=0),0,ROUND(F72-E73,2))
A74: 58 | B74: =IF(B8="monthly",DATE(YEAR(B7)+INT((MONTH(B7)-1+57)/12),MOD(MONTH(B7)-1+57,12)+1,1)+(DAY(B7)-1),IF(B8="weekly",B7+399,IF(B8="biweekly",B7+798,B7+ROUND((57*365.25)/24,0)))) | C74: =IF((ROUND(F73-ROUND($B$13-D74,2),2)<=0),ROUND(D74+E74,2),$B$13) | D74: =ROUND(F73*B5/100/B10,2) | E74: =IF((ROUND(F73-ROUND($B$13-D74,2),2)<=0),F73,ROUND($B$13-D74,2)) | F74: =IF((ROUND(F73-ROUND($B$13-D74,2),2)<=0),0,ROUND(F73-E74,2))
A75: 59 | B75: =IF(B8="monthly",DATE(YEAR(B7)+INT((MONTH(B7)-1+58)/12),MOD(MONTH(B7)-1+58,12)+1,1)+(DAY(B7)-1),IF(B8="weekly",B7+406,IF(B8="biweekly",B7+812,B7+ROUND((58*365.25)/24,0)))) | C75: =IF((ROUND(F74-ROUND($B$13-D75,2),2)<=0),ROUND(D75+E75,2),$B$13) | D75: =ROUND(F74*B5/100/B10,2) | E75: =IF((ROUND(F74-ROUND($B$13-D75,2),2)<=0),F74,ROUND($B$13-D75,2)) | F75: =IF((ROUND(F74-ROUND($B$13-D75,2),2)<=0),0,ROUND(F74-E75,2))
A76: 60 | B76: =IF(B8="monthly",DATE(YEAR(B7)+INT((MONTH(B7)-1+59)/12),MOD(MONTH(B7)-1+59,12)+1,1)+(DAY(B7)-1),IF(B8="weekly",B7+413,IF(B8="biweekly",B7+826,B7+ROUND((59*365.25)/24,0)))) | C76: =IF((ROUND(F75-ROUND($B$13-D76,2),2)<=0),ROUND(D76+E76,2),$B$13) | D76: =ROUND(F75*B5/100/B10,2) | E76: =IF((ROUND(F75-ROUND($B$13-D76,2),2)<=0),F75,ROUND($B$13-D76,2)) | F76: =IF((ROUND(F75-ROUND($B$13-D76,2),2)<=0),0,ROUND(F75-E76,2))
A77: 61 | B77: =IF(B8="monthly",DATE(YEAR(B7)+INT((MONTH(B7)-1+60)/12),MOD(MONTH(B7)-1+60,12)+1,1)+(DAY(B7)-1),IF(B8="weekly",B7+420,IF(B8="biweekly",B7+840,B7+ROUND((60*365.25)/24,0)))) | C77: =IF((ROUND(F76-ROUND($B$13-D77,2),2)<=0),ROUND(D77+E77,2),$B$13) | D77: =ROUND(F76*B5/100/B10,2) | E77: =IF((ROUND(F76-ROUND($B$13-D77,2),2)<=0),F76,ROUND($B$13-D77,2)) | F77: =IF((ROUND(F76-ROUND($B$13-D77,2),2)<=0),0,ROUND(F76-E77,2))
A78: 62 | B78: =IF(B8="monthly",DATE(YEAR(B7)+INT((MONTH(B7)-1+61)/12),MOD(MONTH(B7)-1+61,12)+1,1)+(DAY(B7)-1),IF(B8="weekly",B7+427,IF(B8="biweekly",B7+854,B7+ROUND((61*365.25)/24,0)))) | C78: =IF((ROUND(F77-ROUND($B$13-D78,2),2)<=0),ROUND(D78+E78,2),$B$13) | D78: =ROUND(F77*B5/100/B10,2) | E78: =IF((ROUND(F77-ROUND($B$13-D78,2),2)<=0),F77,ROUND($B$13-D78,2)) | F78: =IF((ROUND(F77-ROUND($B$13-D78,2),2)<=0),0,ROUND(F77-E78,2))
A79: 63 | B79: =IF(B8="monthly",DATE(YEAR(B7)+INT((MONTH(B7)-1+62)/12),MOD(MONTH(B7)-1+62,12)+1,1)+(DAY(B7)-1),IF(B8="weekly",B7+434,IF(B8="biweekly",B7+868,B7+ROUND((62*365.25)/24,0)))) | C79: =IF((ROUND(F78-ROUND($B$13-D79,2),2)<=0),ROUND(D79+E79,2),$B$13) | D79: =ROUND(F78*B5/100/B10,2) | E79: =IF((ROUND(F78-ROUND($B$13-D79,2),2)<=0),F78,ROUND($B$13-D79,2)) | F79: =IF((ROUND(F78-ROUND($B$13-D79,2),2)<=0),0,ROUND(F78-E79,2))
A80: 64 | B80: =IF(B8="monthly",DATE(YEAR(B7)+INT((MONTH(B7)-1+63)/12),MOD(MONTH(B7)-1+63,12)+1,1)+(DAY(B7)-1),IF(B8="weekly",B7+441,IF(B8="biweekly",B7+882,B7+ROUND((63*365.25)/24,0)))) | C80: =IF((ROUND(F79-ROUND($B$13-D80,2),2)<=0),ROUND(D80+E80,2),$B$13) | D80: =ROUND(F79*B5/100/B10,2) | E80: =IF((ROUND(F79-ROUND($B$13-D80,2),2)<=0),F79,ROUND($B$13-D80,2)) | F80: =IF((ROUND(F79-ROUND($B$13-D80,2),2)<=0),0,ROUND(F79-E80,2))
A81: 65 | B81: =IF(B8="monthly",DATE(YEAR(B7)+INT((MONTH(B7)-1+64)/12),MOD(MONTH(B7)-1+64,12)+1,1)+(DAY(B7)-1),IF(B8="weekly",B7+448,IF(B8="biweekly",B7+896,B7+ROUND((64*365.25)/24,0)))) | C81: =IF((ROUND(F80-ROUND($B$13-D81,2),2)<=0),ROUND(D81+E81,2),$B$13) | D81: =ROUND(F80*B5/100/B10,2) | E81: =IF((ROUND(F80-ROUND($B$13-D81,2),2)<=0),F80,ROUND($B$13-D81,2)) | F81: =IF((ROUND(F80-ROUND($B$13-D81,2),2)<=0),0,ROUND(F80-E81,2))
A82: 66 | B82: =IF(B8="monthly",DATE(YEAR(B7)+INT((MONTH(B7)-1+65)/12),MOD(MONTH(B7)-1+65,12)+1,1)+(DAY(B7)-1),IF(B8="weekly",B7+455,IF(B8="biweekly",B7+910,B7+ROUND((65*365.25)/24,0)))) | C82: =IF((ROUND(F81-ROUND($B$13-D82,2),2)<=0),ROUND(D82+E82,2),$B$13) | D82: =ROUND(F81*B5/100/B10,2) | E82: =IF((ROUND(F81-ROUND($B$13-D82,2),2)<=0),F81,ROUND($B$13-D82,2)) | F82: =IF((ROUND(F81-ROUND($B$13-D82,2),2)<=0),0,ROUND(F81-E82,2))
A83: 67 | B83: =IF(B8="monthly",DATE(YEAR(B7)+INT((MONTH(B7)-1+66)/12),MOD(MONTH(B7)-1+66,12)+1,1)+(DAY(B7)-1),IF(B8="weekly",B7+462,IF(B8="biweekly",B7+924,B7+ROUND((66*365.25)/24,0)))) | C83: =IF((ROUND(F82-ROUND($B$13-D83,2),2)<=0),ROUND(D83+E83,2),$B$13) | D83: =ROUND(F82*B5/100/B10,2) | E83: =IF((ROUND(F82-ROUND($B$13-D83,2),2)<=0),F82,ROUND($B$13-D83,2)) | F83: =IF((ROUND(F82-ROUND($B$13-D83,2),2)<=0),0,ROUND(F82-E83,2))
A84: 68 | B84: =IF(B8="monthly",DATE(YEAR(B7)+INT((MONTH(B7)-1+67)/12),MOD(MONTH(B7)-1+67,12)+1,1)+(DAY(B7)-1),IF(B8="weekly",B7+469,IF(B8="biweekly",B7+938,B7+ROUND((67*365.25)/24,0)))) | C84: =IF((ROUND(F83-ROUND($B$13-D84,2),2)<=0),ROUND(D84+E84,2),$B$13) | D84: =ROUND(F83*B5/100/B10,2) | E84: =IF((ROUND(F83-ROUND($B$13-D84,2),2)<=0),F83,ROUND($B$13-D84,2)) | F84: =IF((ROUND(F83-ROUND($B$13-D84,2),2)<=0),0,ROUND(F83-E84,2))
A85: 69 | B85: =IF(B8="monthly",DATE(YEAR(B7)+INT((MONTH(B7)-1+68)/12),MOD(MONTH(B7)-1+68,12)+1,1)+(DAY(B7)-1),IF(B8="weekly",B7+476,IF(B8="biweekly",B7+952,B7+ROUND((68*365.25)/24,0)))) | C85: =IF((ROUND(F84-ROUND($B$13-D85,2),2)<=0),ROUND(D85+E85,2),$B$13) | D85: =ROUND(F84*B5/100/B10,2) | E85: =IF((ROUND(F84-ROUND($B$13-D85,2),2)<=0),F84,ROUND($B$13-D85,2)) | F85: =IF((ROUND(F84-ROUND($B$13-D85,2),2)<=0),0,ROUND(F84-E85,2))
A86: 70 | B86: =IF(B8="monthly",DATE(YEAR(B7)+INT((MONTH(B7)-1+69)/12),MOD(MONTH(B7)-1+69,12)+1,1)+(DAY(B7)-1),IF(B8="weekly",B7+483,IF(B8="biweekly",B7+966,B7+ROUND((69*365.25)/24,0)))) | C86: =IF((ROUND(F85-ROUND($B$13-D86,2),2)<=0),ROUND(D86+E86,2),$B$13) | D86: =ROUND(F85*B5/100/B10,2) | E86: =IF((ROUND(F85-ROUND($B$13-D86,2),2)<=0),F85,ROUND($B$13-D86,2)) | F86: =IF((ROUND(F85-ROUND($B$13-D86,2),2)<=0),0,ROUND(F85-E86,2))
A87: 71 | B87: =IF(B8="monthly",DATE(YEAR(B7)+INT((MONTH(B7)-1+70)/12),MOD(MONTH(B7)-1+70,12)+1,1)+(DAY(B7)-1),IF(B8="weekly",B7+490,IF(B8="biweekly",B7+980,B7+ROUND((70*365.25)/24,0)))) | C87: =IF((ROUND(F86-ROUND($B$13-D87,2),2)<=0),ROUND(D87+E87,2),$B$13) | D87: =ROUND(F86*B5/100/B10,2) | E87: =IF((ROUND(F86-ROUND($B$13-D87,2),2)<=0),F86,ROUND($B$13-D87,2)) | F87: =IF((ROUND(F86-ROUND($B$13-D87,2),2)<=0),0,ROUND(F86-E87,2))
A88: 72 | B88: =IF(B8="monthly",DATE(YEAR(B7)+INT((MONTH(B7)-1+71)/12),MOD(MONTH(B7)-1+71,12)+1,1)+(DAY(B7)-1),IF(B8="weekly",B7+497,IF(B8="biweekly",B7+994,B7+ROUND((71*365.25)/24,0)))) | C88: =IF((ROUND(F87-ROUND($B$13-D88,2),2)<=0),ROUND(D88+E88,2),$B$13) | D88: =ROUND(F87*B5/100/B10,2) | E88: =IF((ROUND(F87-ROUND($B$13-D88,2),2)<=0),F87,ROUND($B$13-D88,2)) | F88: =IF((ROUND(F87-ROUND($B$13-D88,2),2)<=0),0,ROUND(F87-E88,2))
A89: 73 | B89: =IF(B8="monthly",DATE(YEAR(B7)+INT((MONTH(B7)-1+72)/12),MOD(MONTH(B7)-1+72,12)+1,1)+(DAY(B7)-1),IF(B8="weekly",B7+504,IF(B8="biweekly",B7+1008,B7+ROUND((72*365.25)/24,0)))) | C89: =IF((ROUND(F88-ROUND($B$13-D89,2),2)<=0),ROUND(D89+E89,2),$B$13) | D89: =ROUND(F88*B5/100/B10,2) | E89: =IF((ROUND(F88-ROUND($B$13-D89,2),2)<=0),F88,ROUND($B$13-D89,2)) | F89: =IF((ROUND(F88-ROUND($B$13-D89,2),2)<=0),0,ROUND(F88-E89,2))
A90: 74 | B90: =IF(B8="monthly",DATE(YEAR(B7)+INT((MONTH(B7)-1+73)/12),MOD(MONTH(B7)-1+73,12)+1,1)+(DAY(B7)-1),IF(B8="weekly",B7+511,IF(B8="biweekly",B7+1022,B7+ROUND((73*365.25)/24,0)))) | C90: =IF((ROUND(F89-ROUND($B$13-D90,2),2)<=0),ROUND(D90+E90,2),$B$13) | D90: =ROUND(F89*B5/100/B10,2) | E90: =IF((ROUND(F89-ROUND($B$13-D90,2),2)<=0),F89,ROUND($B$13-D90,2)) | F90: =IF((ROUND(F89-ROUND($B$13-D90,2),2)<=0),0,ROUND(F89-E90,2))
A91: 75 | B91: =IF(B8="monthly",DATE(YEAR(B7)+INT((MONTH(B7)-1+74)/12),MOD(MONTH(B7)-1+74,12)+1,1)+(DAY(B7)-1),IF(B8="weekly",B7+518,IF(B8="biweekly",B7+1036,B7+ROUND((74*365.25)/24,0)))) | C91: =IF((ROUND(F90-ROUND($B$13-D91,2),2)<=0),ROUND(D91+E91,2),$B$13) | D91: =ROUND(F90*B5/100/B10,2) | E91: =IF((ROUND(F90-ROUND($B$13-D91,2),2)<=0),F90,ROUND($B$13-D91,2)) | F91: =IF((ROUND(F90-ROUND($B$13-D91,2),2)<=0),0,ROUND(F90-E91,2))
A92: 76 | B92: =IF(B8="monthly",DATE(YEAR(B7)+INT((MONTH(B7)-1+75)/12),MOD(MONTH(B7)-1+75,12)+1,1)+(DAY(B7)-1),IF(B8="weekly",B7+525,IF(B8="biweekly",B7+1050,B7+ROUND((75*365.25)/24,0)))) | C92: =IF((ROUND(F91-ROUND($B$13-D92,2),2)<=0),ROUND(D92+E92,2),$B$13) | D92: =ROUND(F91*B5/100/B10,2) | E92: =IF((ROUND(F91-ROUND($B$13-D92,2),2)<=0),F91,ROUND($B$13-D92,2)) | F92: =IF((ROUND(F91-ROUND($B$13-D92,2),2)<=0),0,ROUND(F91-E92,2))
A93: 77 | B93: =IF(B8="monthly",DATE(YEAR(B7)+INT((MONTH(B7)-1+76)/12),MOD(MONTH(B7)-1+76,12)+1,1)+(DAY(B7)-1),IF(B8="weekly",B7+532,IF(B8="biweekly",B7+1064,B7+ROUND((76*365.25)/24,0)))) | C93: =IF((ROUND(F92-ROUND($B$13-D93,2),2)<=0),ROUND(D93+E93,2),$B$13) | D93: =ROUND(F92*B5/100/B10,2) | E93: =IF((ROUND(F92-ROUND($B$13-D93,2),2)<=0),F92,ROUND($B$13-D93,2)) | F93: =IF((ROUND(F92-ROUND($B$13-D93,2),2)<=0),0,ROUND(F92-E93,2))
A94: 78 | B94: =IF(B8="monthly",DATE(YEAR(B7)+INT((MONTH(B7)-1+77)/12),MOD(MONTH(B7)-1+77,12)+1,1)+(DAY(B7)-1),IF(B8="weekly",B7+539,IF(B8="biweekly",B7+1078,B7+ROUND((77*365.25)/24,0)))) | C94: =IF((ROUND(F93-ROUND($B$13-D94,2),2)<=0),ROUND(D94+E94,2),$B$13) | D94: =ROUND(F93*B5/100/B10,2) | E94: =IF((ROUND(F93-ROUND($B$13-D94,2),2)<=0),F93,ROUND($B$13-D94,2)) | F94: =IF((ROUND(F93-ROUND($B$13-D94,2),2)<=0),0,ROUND(F93-E94,2))
A95: 79 | B95: =IF(B8="monthly",DATE(YEAR(B7)+INT((MONTH(B7)-1+78)/12),MOD(MONTH(B7)-1+78,12)+1,1)+(DAY(B7)-1),IF(B8="weekly",B7+546,IF(B8="biweekly",B7+1092,B7+ROUND((78*365.25)/24,0)))) | C95: =IF((ROUND(F94-ROUND($B$13-D95,2),2)<=0),ROUND(D95+E95,2),$B$13) | D95: =ROUND(F94*B5/100/B10,2) | E95: =IF((ROUND(F94-ROUND($B$13-D95,2),2)<=0),F94,ROUND($B$13-D95,2)) | F95: =IF((ROUND(F94-ROUND($B$13-D95,2),2)<=0),0,ROUND(F94-E95,2))
A96: 80 | B96: =IF(B8="monthly",DATE(YEAR(B7)+INT((MONTH(B7)-1+79)/12),MOD(MONTH(B7)-1+79,12)+1,1)+(DAY(B7)-1),IF(B8="weekly",B7+553,IF(B8="biweekly",B7+1106,B7+ROUND((79*365.25)/24,0)))) | C96: =IF((ROUND(F95-ROUND($B$13-D96,2),2)<=0),ROUND(D96+E96,2),$B$13) | D96: =ROUND(F95*B5/100/B10,2) | E96: =IF((ROUND(F95-ROUND($B$13-D96,2),2)<=0),F95,ROUND($B$13-D96,2)) | F96: =IF((ROUND(F95-ROUND($B$13-D96,2),2)<=0),0,ROUND(F95-E96,2))
A97: 81 | B97: =IF(B8="monthly",DATE(YEAR(B7)+INT((MONTH(B7)-1+80)/12),MOD(MONTH(B7)-1+80,12)+1,1)+(DAY(B7)-1),IF(B8="weekly",B7+560,IF(B8="biweekly",B7+1120,B7+ROUND((80*365.25)/24,0)))) | C97: =IF((ROUND(F96-ROUND($B$13-D97,2),2)<=0),ROUND(D97+E97,2),$B$13) | D97: =ROUND(F96*B5/100/B10,2) | E97: =IF((ROUND(F96-ROUND($B$13-D97,2),2)<=0),F96,ROUND($B$13-D97,2)) | F97: =IF((ROUND(F96-ROUND($B$13-D97,2),2)<=0),0,ROUND(F96-E97,2))
A98: 82 | B98: =IF(B8="monthly",DATE(YEAR(B7)+INT((MONTH(B7)-1+81)/12),MOD(MONTH(B7)-1+81,12)+1,1)+(DAY(B7)-1),IF(B8="weekly",B7+567,IF(B8="biweekly",B7+1134,B7+ROUND((81*365.25)/24,0)))) | C98: =IF((ROUND(F97-ROUND($B$13-D98,2),2)<=0),ROUND(D98+E98,2),$B$13) | D98: =ROUND(F97*B5/100/B10,2) | E98: =IF((ROUND(F97-ROUND($B$13-D98,2),2)<=0),F97,ROUND($B$13-D98,2)) | F98: =IF((ROUND(F97-ROUND($B$13-D98,2),2)<=0),0,ROUND(F97-E98,2))
A99: 83 | B99: =IF(B8="monthly",DATE(YEAR(B7)+INT((MONTH(B7)-1+82)/12),MOD(MONTH(B7)-1+82,12)+1,1)+(DAY(B7)-1),IF(B8="weekly",B7+574,IF(B8="biweekly",B7+1148,B7+ROUND((82*365.25)/24,0)))) | C99: =IF((ROUND(F98-ROUND($B$13-D99,2),2)<=0),ROUND(D99+E99,2),$B$13) | D99: =ROUND(F98*B5/100/B10,2) | E99: =IF((ROUND(F98-ROUND($B$13-D99,2),2)<=0),F98,ROUND($B$13-D99,2)) | F99: =IF((ROUND(F98-ROUND($B$13-D99,2),2)<=0),0,ROUND(F98-E99,2))
A100: 84 | B100: =IF(B8="monthly",DATE(YEAR(B7)+INT((MONTH(B7)-1+83)/12),MOD(MONTH(B7)-1+83,12)+1,1)+(DAY(B7)-1),IF(B8="weekly",B7+581,IF(B8="biweekly",B7+1162,B7+ROUND((83*365.25)/24,0)))) | C100: =IF((ROUND(F99-ROUND($B$13-D100,2),2)<=0),ROUND(D100+E100,2),$B$13) | D100: =ROUND(F99*B5/100/B10,2) | E100: =IF((ROUND(F99-ROUND($B$13-D100,2),2)<=0),F99,ROUND($B$13-D100,2)) | F100: =IF((ROUND(F99-ROUND($B$13-D100,2),2)<=0),0,ROUND(F99-E100,2))
A101: 85 | B101: =IF(B8="monthly",DATE(YEAR(B7)+INT((MONTH(B7)-1+84)/12),MOD(MONTH(B7)-1+84,12)+1,1)+(DAY(B7)-1),IF(B8="weekly",B7+588,IF(B8="biweekly",B7+1176,B7+ROUND((84*365.25)/24,0)))) | C101: =IF((ROUND(F100-ROUND($B$13-D101,2),2)<=0),ROUND(D101+E101,2),$B$13) | D101: =ROUND(F100*B5/100/B10,2) | E101: =IF((ROUND(F100-ROUND($B$13-D101,2),2)<=0),F100,ROUND($B$13-D101,2)) | F101: =IF((ROUND(F100-ROUND($B$13-D101,2),2)<=0),0,ROUND(F100-E101,2))
A102: 86 | B102: =IF(B8="monthly",DATE(YEAR(B7)+INT((MONTH(B7)-1+85)/12),MOD(MONTH(B7)-1+85,12)+1,1)+(DAY(B7)-1),IF(B8="weekly",B7+595,IF(B8="biweekly",B7+1190,B7+ROUND((85*365.25)/24,0)))) | C102: =IF((ROUND(F101-ROUND($B$13-D102,2),2)<=0),ROUND(D102+E102,2),$B$13) | D102: =ROUND(F101*B5/100/B10,2) | E102: =IF((ROUND(F101-ROUND($B$13-D102,2),2)<=0),F101,ROUND($B$13-D102,2)) | F102: =IF((ROUND(F101-ROUND($B$13-D102,2),2)<=0),0,ROUND(F101-E102,2))
...

Sheet ExtraPayment
A1: Extra Monthly Payment Savings
A2: Standalone single-loan calculator: baseline (fixed 360-row-bounded term) vs. the same loan with an extra monthly principal payment (runs until payoff, self-stabilizing at $0 once paid off -- see PaymentFrequency sheet for the same pattern).
A4: Loan amount ($) | B4: 300000
A5: Annual interest rate (%) | B5: 6.5
A6: Term (months) | B6: 360
A7: Extra monthly payment ($) | B7: 200
A8: Start date | B8: 2024-01-01
A10: Base monthly payment | B10: =ROUND(-PMT(B5/100/12,B6,B4),2)
A11: Payment with extra | B11: =ROUND(B10+B7,2)
A14: Month | B14: Date | C14: Baseline: Interest | D14: Baseline: Principal | E14: Baseline: Balance | F14: With Extra: Interest | G14: With Extra: Principal | H14: With Extra: Balance
A15: 1 | B15: =DATE(YEAR(B8)+INT((MONTH(B8)-1+0)/12),MOD(MONTH(B8)-1+0,12)+1,1)+(DAY(B8)-1) | C15: =ROUND(B4*B5/100/12,2) | D15: =IF((OR(ROUND(B4-ROUND($B$10-C15,2),2)<=0,1=B6)),B4,ROUND($B$10-C15,2)) | E15: =IF((OR(ROUND(B4-ROUND($B$10-C15,2),2)<=0,1=B6)),0,ROUND(B4-D15,2)) | F15: =ROUND(B4*B5/100/12,2) | G15: =IF((ROUND(B4-ROUND($B$11-F15,2),2)<=0),B4,ROUND($B$11-F15,2)) | H15: =IF((ROUND(B4-ROUND($B$11-F15,2),2)<=0),0,ROUND(B4-G15,2))
A16: 2 | B16: =DATE(YEAR(B8)+INT((MONTH(B8)-1+1)/12),MOD(MONTH(B8)-1+1,12)+1,1)+(DAY(B8)-1) | C16: =ROUND(E15*B5/100/12,2) | D16: =IF((OR(ROUND(E15-ROUND($B$10-C16,2),2)<=0,2=B6)),E15,ROUND($B$10-C16,2)) | E16: =IF((OR(ROUND(E15-ROUND($B$10-C16,2),2)<=0,2=B6)),0,ROUND(E15-D16,2)) | F16: =ROUND(H15*B5/100/12,2) | G16: =IF((ROUND(H15-ROUND($B$11-F16,2),2)<=0),H15,ROUND($B$11-F16,2)) | H16: =IF((ROUND(H15-ROUND($B$11-F16,2),2)<=0),0,ROUND(H15-G16,2))
A17: 3 | B17: =DATE(YEAR(B8)+INT((MONTH(B8)-1+2)/12),MOD(MONTH(B8)-1+2,12)+1,1)+(DAY(B8)-1) | C17: =ROUND(E16*B5/100/12,2) | D17: =IF((OR(ROUND(E16-ROUND($B$10-C17,2),2)<=0,3=B6)),E16,ROUND($B$10-C17,2)) | E17: =IF((OR(ROUND(E16-ROUND($B$10-C17,2),2)<=0,3=B6)),0,ROUND(E16-D17,2)) | F17: =ROUND(H16*B5/100/12,2) | G17: =IF((ROUND(H16-ROUND($B$11-F17,2),2)<=0),H16,ROUND($B$11-F17,2)) | H17: =IF((ROUND(H16-ROUND($B$11-F17,2),2)<=0),0,ROUND(H16-G17,2))
A18: 4 | B18: =DATE(YEAR(B8)+INT((MONTH(B8)-1+3)/12),MOD(MONTH(B8)-1+3,12)+1,1)+(DAY(B8)-1) | C18: =ROUND(E17*B5/100/12,2) | D18: =IF((OR(ROUND(E17-ROUND($B$10-C18,2),2)<=0,4=B6)),E17,ROUND($B$10-C18,2)) | E18: =IF((OR(ROUND(E17-ROUND($B$10-C18,2),2)<=0,4=B6)),0,ROUND(E17-D18,2)) | F18: =ROUND(H17*B5/100/12,2) | G18: =IF((ROUND(H17-ROUND($B$11-F18,2),2)<=0),H17,ROUND($B$11-F18,2)) | H18: =IF((ROUND(H17-ROUND($B$11-F18,2),2)<=0),0,ROUND(H17-G18,2))
A19: 5 | B19: =DATE(YEAR(B8)+INT((MONTH(B8)-1+4)/12),MOD(MONTH(B8)-1+4,12)+1,1)+(DAY(B8)-1) | C19: =ROUND(E18*B5/100/12,2) | D19: =IF((OR(ROUND(E18-ROUND($B$10-C19,2),2)<=0,5=B6)),E18,ROUND($B$10-C19,2)) | E19: =IF((OR(ROUND(E18-ROUND($B$10-C19,2),2)<=0,5=B6)),0,ROUND(E18-D19,2)) | F19: =ROUND(H18*B5/100/12,2) | G19: =IF((ROUND(H18-ROUND($B$11-F19,2),2)<=0),H18,ROUND($B$11-F19,2)) | H19: =IF((ROUND(H18-ROUND($B$11-F19,2),2)<=0),0,ROUND(H18-G19,2))
A20: 6 | B20: =DATE(YEAR(B8)+INT((MONTH(B8)-1+5)/12),MOD(MONTH(B8)-1+5,12)+1,1)+(DAY(B8)-1) | C20: =ROUND(E19*B5/100/12,2) | D20: =IF((OR(ROUND(E19-ROUND($B$10-C20,2),2)<=0,6=B6)),E19,ROUND($B$10-C20,2)) | E20: =IF((OR(ROUND(E19-ROUND($B$10-C20,2),2)<=0,6=B6)),0,ROUND(E19-D20,2)) | F20: =ROUND(H19*B5/100/12,2) | G20: =IF((ROUND(H19-ROUND($B$11-F20,2),2)<=0),H19,ROUND($B$11-F20,2)) | H20: =IF((ROUND(H19-ROUND($B$11-F20,2),2)<=0),0,ROUND(H19-G20,2))
A21: 7 | B21: =DATE(YEAR(B8)+INT((MONTH(B8)-1+6)/12),MOD(MONTH(B8)-1+6,12)+1,1)+(DAY(B8)-1) | C21: =ROUND(E20*B5/100/12,2) | D21: =IF((OR(ROUND(E20-ROUND($B$10-C21,2),2)<=0,7=B6)),E20,ROUND($B$10-C21,2)) | E21: =IF((OR(ROUND(E20-ROUND($B$10-C21,2),2)<=0,7=B6)),0,ROUND(E20-D21,2)) | F21: =ROUND(H20*B5/100/12,2) | G21: =IF((ROUND(H20-ROUND($B$11-F21,2),2)<=0),H20,ROUND($B$11-F21,2)) | H21: =IF((ROUND(H20-ROUND($B$11-F21,2),2)<=0),0,ROUND(H20-G21,2))
A22: 8 | B22: =DATE(YEAR(B8)+INT((MONTH(B8)-1+7)/12),MOD(MONTH(B8)-1+7,12)+1,1)+(DAY(B8)-1) | C22: =ROUND(E21*B5/100/12,2) | D22: =IF((OR(ROUND(E21-ROUND($B$10-C22,2),2)<=0,8=B6)),E21,ROUND($B$10-C22,2)) | E22: =IF((OR(ROUND(E21-ROUND($B$10-C22,2),2)<=0,8=B6)),0,ROUND(E21-D22,2)) | F22: =ROUND(H21*B5/100/12,2) | G22: =IF((ROUND(H21-ROUND($B$11-F22,2),2)<=0),H21,ROUND($B$11-F22,2)) | H22: =IF((ROUND(H21-ROUND($B$11-F22,2),2)<=0),0,ROUND(H21-G22,2))
A23: 9 | B23: =DATE(YEAR(B8)+INT((MONTH(B8)-1+8)/12),MOD(MONTH(B8)-1+8,12)+1,1)+(DAY(B8)-1) | C23: =ROUND(E22*B5/100/12,2) | D23: =IF((OR(ROUND(E22-ROUND($B$10-C23,2),2)<=0,9=B6)),E22,ROUND($B$10-C23,2)) | E23: =IF((OR(ROUND(E22-ROUND($B$10-C23,2),2)<=0,9=B6)),0,ROUND(E22-D23,2)) | F23: =ROUND(H22*B5/100/12,2) | G23: =IF((ROUND(H22-ROUND($B$11-F23,2),2)<=0),H22,ROUND($B$11-F23,2)) | H23: =IF((ROUND(H22-ROUND($B$11-F23,2),2)<=0),0,ROUND(H22-G23,2))
A24: 10 | B24: =DATE(YEAR(B8)+INT((MONTH(B8)-1+9)/12),MOD(MONTH(B8)-1+9,12)+1,1)+(DAY(B8)-1) | C24: =ROUND(E23*B5/100/12,2) | D24: =IF((OR(ROUND(E23-ROUND($B$10-C24,2),2)<=0,10=B6)),E23,ROUND($B$10-C24,2)) | E24: =IF((OR(ROUND(E23-ROUND($B$10-C24,2),2)<=0,10=B6)),0,ROUND(E23-D24,2)) | F24: =ROUND(H23*B5/100/12,2) | G24: =IF((ROUND(H23-ROUND($B$11-F24,2),2)<=0),H23,ROUND($B$11-F24,2)) | H24: =IF((ROUND(H23-ROUND($B$11-F24,2),2)<=0),0,ROUND(H23-G24,2))
A25: 11 | B25: =DATE(YEAR(B8)+INT((MONTH(B8)-1+10)/12),MOD(MONTH(B8)-1+10,12)+1,1)+(DAY(B8)-1) | C25: =ROUND(E24*B5/100/12,2) | D25: =IF((OR(ROUND(E24-ROUND($B$10-C25,2),2)<=0,11=B6)),E24,ROUND($B$10-C25,2)) | E25: =IF((OR(ROUND(E24-ROUND($B$10-C25,2),2)<=0,11=B6)),0,ROUND(E24-D25,2)) | F25: =ROUND(H24*B5/100/12,2) | G25: =IF((ROUND(H24-ROUND($B$11-F25,2),2)<=0),H24,ROUND($B$11-F25,2)) | H25: =IF((ROUND(H24-ROUND($B$11-F25,2),2)<=0),0,ROUND(H24-G25,2))
A26: 12 | B26: =DATE(YEAR(B8)+INT((MONTH(B8)-1+11)/12),MOD(MONTH(B8)-1+11,12)+1,1)+(DAY(B8)-1) | C26: =ROUND(E25*B5/100/12,2) | D26: =IF((OR(ROUND(E25-ROUND($B$10-C26,2),2)<=0,12=B6)),E25,ROUND($B$10-C26,2)) | E26: =IF((OR(ROUND(E25-ROUND($B$10-C26,2),2)<=0,12=B6)),0,ROUND(E25-D26,2)) | F26: =ROUND(H25*B5/100/12,2) | G26: =IF((ROUND(H25-ROUND($B$11-F26,2),2)<=0),H25,ROUND($B$11-F26,2)) | H26: =IF((ROUND(H25-ROUND($B$11-F26,2),2)<=0),0,ROUND(H25-G26,2))
A27: 13 | B27: =DATE(YEAR(B8)+INT((MONTH(B8)-1+12)/12),MOD(MONTH(B8)-1+12,12)+1,1)+(DAY(B8)-1) | C27: =ROUND(E26*B5/100/12,2) | D27: =IF((OR(ROUND(E26-ROUND($B$10-C27,2),2)<=0,13=B6)),E26,ROUND($B$10-C27,2)) | E27: =IF((OR(ROUND(E26-ROUND($B$10-C27,2),2)<=0,13=B6)),0,ROUND(E26-D27,2)) | F27: =ROUND(H26*B5/100/12,2) | G27: =IF((ROUND(H26-ROUND($B$11-F27,2),2)<=0),H26,ROUND($B$11-F27,2)) | H27: =IF((ROUND(H26-ROUND($B$11-F27,2),2)<=0),0,ROUND(H26-G27,2))
A28: 14 | B28: =DATE(YEAR(B8)+INT((MONTH(B8)-1+13)/12),MOD(MONTH(B8)-1+13,12)+1,1)+(DAY(B8)-1) | C28: =ROUND(E27*B5/100/12,2) | D28: =IF((OR(ROUND(E27-ROUND($B$10-C28,2),2)<=0,14=B6)),E27,ROUND($B$10-C28,2)) | E28: =IF((OR(ROUND(E27-ROUND($B$10-C28,2),2)<=0,14=B6)),0,ROUND(E27-D28,2)) | F28: =ROUND(H27*B5/100/12,2) | G28: =IF((ROUND(H27-ROUND($B$11-F28,2),2)<=0),H27,ROUND($B$11-F28,2)) | H28: =IF((ROUND(H27-ROUND($B$11-F28,2),2)<=0),0,ROUND(H27-G28,2))
A29: 15 | B29: =DATE(YEAR(B8)+INT((MONTH(B8)-1+14)/12),MOD(MONTH(B8)-1+14,12)+1,1)+(DAY(B8)-1) | C29: =ROUND(E28*B5/100/12,2) | D29: =IF((OR(ROUND(E28-ROUND($B$10-C29,2),2)<=0,15=B6)),E28,ROUND($B$10-C29,2)) | E29: =IF((OR(ROUND(E28-ROUND($B$10-C29,2),2)<=0,15=B6)),0,ROUND(E28-D29,2)) | F29: =ROUND(H28*B5/100/12,2) | G29: =IF((ROUND(H28-ROUND($B$11-F29,2),2)<=0),H28,ROUND($B$11-F29,2)) | H29: =IF((ROUND(H28-ROUND($B$11-F29,2),2)<=0),0,ROUND(H28-G29,2))
A30: 16 | B30: =DATE(YEAR(B8)+INT((MONTH(B8)-1+15)/12),MOD(MONTH(B8)-1+15,12)+1,1)+(DAY(B8)-1) | C30: =ROUND(E29*B5/100/12,2) | D30: =IF((OR(ROUND(E29-ROUND($B$10-C30,2),2)<=0,16=B6)),E29,ROUND($B$10-C30,2)) | E30: =IF((OR(ROUND(E29-ROUND($B$10-C30,2),2)<=0,16=B6)),0,ROUND(E29-D30,2)) | F30: =ROUND(H29*B5/100/12,2) | G30: =IF((ROUND(H29-ROUND($B$11-F30,2),2)<=0),H29,ROUND($B$11-F30,2)) | H30: =IF((ROUND(H29-ROUND($B$11-F30,2),2)<=0),0,ROUND(H29-G30,2))
A31: 17 | B31: =DATE(YEAR(B8)+INT((MONTH(B8)-1+16)/12),MOD(MONTH(B8)-1+16,12)+1,1)+(DAY(B8)-1) | C31: =ROUND(E30*B5/100/12,2) | D31: =IF((OR(ROUND(E30-ROUND($B$10-C31,2),2)<=0,17=B6)),E30,ROUND($B$10-C31,2)) | E31: =IF((OR(ROUND(E30-ROUND($B$10-C31,2),2)<=0,17=B6)),0,ROUND(E30-D31,2)) | F31: =ROUND(H30*B5/100/12,2) | G31: =IF((ROUND(H30-ROUND($B$11-F31,2),2)<=0),H30,ROUND($B$11-F31,2)) | H31: =IF((ROUND(H30-ROUND($B$11-F31,2),2)<=0),0,ROUND(H30-G31,2))
A32: 18 | B32: =DATE(YEAR(B8)+INT((MONTH(B8)-1+17)/12),MOD(MONTH(B8)-1+17,12)+1,1)+(DAY(B8)-1) | C32: =ROUND(E31*B5/100/12,2) | D32: =IF((OR(ROUND(E31-ROUND($B$10-C32,2),2)<=0,18=B6)),E31,ROUND($B$10-C32,2)) | E32: =IF((OR(ROUND(E31-ROUND($B$10-C32,2),2)<=0,18=B6)),0,ROUND(E31-D32,2)) | F32: =ROUND(H31*B5/100/12,2) | G32: =IF((ROUND(H31-ROUND($B$11-F32,2),2)<=0),H31,ROUND($B$11-F32,2)) | H32: =IF((ROUND(H31-ROUND($B$11-F32,2),2)<=0),0,ROUND(H31-G32,2))
A33: 19 | B33: =DATE(YEAR(B8)+INT((MONTH(B8)-1+18)/12),MOD(MONTH(B8)-1+18,12)+1,1)+(DAY(B8)-1) | C33: =ROUND(E32*B5/100/12,2) | D33: =IF((OR(ROUND(E32-ROUND($B$10-C33,2),2)<=0,19=B6)),E32,ROUND($B$10-C33,2)) | E33: =IF((OR(ROUND(E32-ROUND($B$10-C33,2),2)<=0,19=B6)),0,ROUND(E32-D33,2)) | F33: =ROUND(H32*B5/100/12,2) | G33: =IF((ROUND(H32-ROUND($B$11-F33,2),2)<=0),H32,ROUND($B$11-F33,2)) | H33: =IF((ROUND(H32-ROUND($B$11-F33,2),2)<=0),0,ROUND(H32-G33,2))
A34: 20 | B34: =DATE(YEAR(B8)+INT((MONTH(B8)-1+19)/12),MOD(MONTH(B8)-1+19,12)+1,1)+(DAY(B8)-1) | C34: =ROUND(E33*B5/100/12,2) | D34: =IF((OR(ROUND(E33-ROUND($B$10-C34,2),2)<=0,20=B6)),E33,ROUND($B$10-C34,2)) | E34: =IF((OR(ROUND(E33-ROUND($B$10-C34,2),2)<=0,20=B6)),0,ROUND(E33-D34,2)) | F34: =ROUND(H33*B5/100/12,2) | G34: =IF((ROUND(H33-ROUND($B$11-F34,2),2)<=0),H33,ROUND($B$11-F34,2)) | H34: =IF((ROUND(H33-ROUND($B$11-F34,2),2)<=0),0,ROUND(H33-G34,2))
A35: 21 | B35: =DATE(YEAR(B8)+INT((MONTH(B8)-1+20)/12),MOD(MONTH(B8)-1+20,12)+1,1)+(DAY(B8)-1) | C35: =ROUND(E34*B5/100/12,2) | D35: =IF((OR(ROUND(E34-ROUND($B$10-C35,2),2)<=0,21=B6)),E34,ROUND($B$10-C35,2)) | E35: =IF((OR(ROUND(E34-ROUND($B$10-C35,2),2)<=0,21=B6)),0,ROUND(E34-D35,2)) | F35: =ROUND(H34*B5/100/12,2) | G35: =IF((ROUND(H34-ROUND($B$11-F35,2),2)<=0),H34,ROUND($B$11-F35,2)) | H35: =IF((ROUND(H34-ROUND($B$11-F35,2),2)<=0),0,ROUND(H34-G35,2))
A36: 22 | B36: =DATE(YEAR(B8)+INT((MONTH(B8)-1+21)/12),MOD(MONTH(B8)-1+21,12)+1,1)+(DAY(B8)-1) | C36: =ROUND(E35*B5/100/12,2) | D36: =IF((OR(ROUND(E35-ROUND($B$10-C36,2),2)<=0,22=B6)),E35,ROUND($B$10-C36,2)) | E36: =IF((OR(ROUND(E35-ROUND($B$10-C36,2),2)<=0,22=B6)),0,ROUND(E35-D36,2)) | F36: =ROUND(H35*B5/100/12,2) | G36: =IF((ROUND(H35-ROUND($B$11-F36,2),2)<=0),H35,ROUND($B$11-F36,2)) | H36: =IF((ROUND(H35-ROUND($B$11-F36,2),2)<=0),0,ROUND(H35-G36,2))
A37: 23 | B37: =DATE(YEAR(B8)+INT((MONTH(B8)-1+22)/12),MOD(MONTH(B8)-1+22,12)+1,1)+(DAY(B8)-1) | C37: =ROUND(E36*B5/100/12,2) | D37: =IF((OR(ROUND(E36-ROUND($B$10-C37,2),2)<=0,23=B6)),E36,ROUND($B$10-C37,2)) | E37: =IF((OR(ROUND(E36-ROUND($B$10-C37,2),2)<=0,23=B6)),0,ROUND(E36-D37,2)) | F37: =ROUND(H36*B5/100/12,2) | G37: =IF((ROUND(H36-ROUND($B$11-F37,2),2)<=0),H36,ROUND($B$11-F37,2)) | H37: =IF((ROUND(H36-ROUND($B$11-F37,2),2)<=0),0,ROUND(H36-G37,2))
A38: 24 | B38: =DATE(YEAR(B8)+INT((MONTH(B8)-1+23)/12),MOD(MONTH(B8)-1+23,12)+1,1)+(DAY(B8)-1) | C38: =ROUND(E37*B5/100/12,2) | D38: =IF((OR(ROUND(E37-ROUND($B$10-C38,2),2)<=0,24=B6)),E37,ROUND($B$10-C38,2)) | E38: =IF((OR(ROUND(E37-ROUND($B$10-C38,2),2)<=0,24=B6)),0,ROUND(E37-D38,2)) | F38: =ROUND(H37*B5/100/12,2) | G38: =IF((ROUND(H37-ROUND($B$11-F38,2),2)<=0),H37,ROUND($B$11-F38,2)) | H38: =IF((ROUND(H37-ROUND($B$11-F38,2),2)<=0),0,ROUND(H37-G38,2))
A39: 25 | B39: =DATE(YEAR(B8)+INT((MONTH(B8)-1+24)/12),MOD(MONTH(B8)-1+24,12)+1,1)+(DAY(B8)-1) | C39: =ROUND(E38*B5/100/12,2) | D39: =IF((OR(ROUND(E38-ROUND($B$10-C39,2),2)<=0,25=B6)),E38,ROUND($B$10-C39,2)) | E39: =IF((OR(ROUND(E38-ROUND($B$10-C39,2),2)<=0,25=B6)),0,ROUND(E38-D39,2)) | F39: =ROUND(H38*B5/100/12,2) | G39: =IF((ROUND(H38-ROUND($B$11-F39,2),2)<=0),H38,ROUND($B$11-F39,2)) | H39: =IF((ROUND(H38-ROUND($B$11-F39,2),2)<=0),0,ROUND(H38-G39,2))
A40: 26 | B40: =DATE(YEAR(B8)+INT((MONTH(B8)-1+25)/12),MOD(MONTH(B8)-1+25,12)+1,1)+(DAY(B8)-1) | C40: =ROUND(E39*B5/100/12,2) | D40: =IF((OR(ROUND(E39-ROUND($B$10-C40,2),2)<=0,26=B6)),E39,ROUND($B$10-C40,2)) | E40: =IF((OR(ROUND(E39-ROUND($B$10-C40,2),2)<=0,26=B6)),0,ROUND(E39-D40,2)) | F40: =ROUND(H39*B5/100/12,2) | G40: =IF((ROUND(H39-ROUND($B$11-F40,2),2)<=0),H39,ROUND($B$11-F40,2)) | H40: =IF((ROUND(H39-ROUND($B$11-F40,2),2)<=0),0,ROUND(H39-G40,2))
A41: 27 | B41: =DATE(YEAR(B8)+INT((MONTH(B8)-1+26)/12),MOD(MONTH(B8)-1+26,12)+1,1)+(DAY(B8)-1) | C41: =ROUND(E40*B5/100/12,2) | D41: =IF((OR(ROUND(E40-ROUND($B$10-C41,2),2)<=0,27=B6)),E40,ROUND($B$10-C41,2)) | E41: =IF((OR(ROUND(E40-ROUND($B$10-C41,2),2)<=0,27=B6)),0,ROUND(E40-D41,2)) | F41: =ROUND(H40*B5/100/12,2) | G41: =IF((ROUND(H40-ROUND($B$11-F41,2),2)<=0),H40,ROUND($B$11-F41,2)) | H41: =IF((ROUND(H40-ROUND($B$11-F41,2),2)<=0),0,ROUND(H40-G41,2))
A42: 28 | B42: =DATE(YEAR(B8)+INT((MONTH(B8)-1+27)/12),MOD(MONTH(B8)-1+27,12)+1,1)+(DAY(B8)-1) | C42: =ROUND(E41*B5/100/12,2) | D42: =IF((OR(ROUND(E41-ROUND($B$10-C42,2),2)<=0,28=B6)),E41,ROUND($B$10-C42,2)) | E42: =IF((OR(ROUND(E41-ROUND($B$10-C42,2),2)<=0,28=B6)),0,ROUND(E41-D42,2)) | F42: =ROUND(H41*B5/100/12,2) | G42: =IF((ROUND(H41-ROUND($B$11-F42,2),2)<=0),H41,ROUND($B$11-F42,2)) | H42: =IF((ROUND(H41-ROUND($B$11-F42,2),2)<=0),0,ROUND(H41-G42,2))
A43: 29 | B43: =DATE(YEAR(B8)+INT((MONTH(B8)-1+28)/12),MOD(MONTH(B8)-1+28,12)+1,1)+(DAY(B8)-1) | C43: =ROUND(E42*B5/100/12,2) | D43: =IF((OR(ROUND(E42-ROUND($B$10-C43,2),2)<=0,29=B6)),E42,ROUND($B$10-C43,2)) | E43: =IF((OR(ROUND(E42-ROUND($B$10-C43,2),2)<=0,29=B6)),0,ROUND(E42-D43,2)) | F43: =ROUND(H42*B5/100/12,2) | G43: =IF((ROUND(H42-ROUND($B$11-F43,2),2)<=0),H42,ROUND($B$11-F43,2)) | H43: =IF((ROUND(H42-ROUND($B$11-F43,2),2)<=0),0,ROUND(H42-G43,2))
A44: 30 | B44: =DATE(YEAR(B8)+INT((MONTH(B8)-1+29)/12),MOD(MONTH(B8)-1+29,12)+1,1)+(DAY(B8)-1) | C44: =ROUND(E43*B5/100/12,2) | D44: =IF((OR(ROUND(E43-ROUND($B$10-C44,2),2)<=0,30=B6)),E43,ROUND($B$10-C44,2)) | E44: =IF((OR(ROUND(E43-ROUND($B$10-C44,2),2)<=0,30=B6)),0,ROUND(E43-D44,2)) | F44: =ROUND(H43*B5/100/12,2) | G44: =IF((ROUND(H43-ROUND($B$11-F44,2),2)<=0),H43,ROUND($B$11-F44,2)) | H44: =IF((ROUND(H43-ROUND($B$11-F44,2),2)<=0),0,ROUND(H43-G44,2))
A45: 31 | B45: =DATE(YEAR(B8)+INT((MONTH(B8)-1+30)/12),MOD(MONTH(B8)-1+30,12)+1,1)+(DAY(B8)-1) | C45: =ROUND(E44*B5/100/12,2) | D45: =IF((OR(ROUND(E44-ROUND($B$10-C45,2),2)<=0,31=B6)),E44,ROUND($B$10-C45,2)) | E45: =IF((OR(ROUND(E44-ROUND($B$10-C45,2),2)<=0,31=B6)),0,ROUND(E44-D45,2)) | F45: =ROUND(H44*B5/100/12,2) | G45: =IF((ROUND(H44-ROUND($B$11-F45,2),2)<=0),H44,ROUND($B$11-F45,2)) | H45: =IF((ROUND(H44-ROUND($B$11-F45,2),2)<=0),0,ROUND(H44-G45,2))
A46: 32 | B46: =DATE(YEAR(B8)+INT((MONTH(B8)-1+31)/12),MOD(MONTH(B8)-1+31,12)+1,1)+(DAY(B8)-1) | C46: =ROUND(E45*B5/100/12,2) | D46: =IF((OR(ROUND(E45-ROUND($B$10-C46,2),2)<=0,32=B6)),E45,ROUND($B$10-C46,2)) | E46: =IF((OR(ROUND(E45-ROUND($B$10-C46,2),2)<=0,32=B6)),0,ROUND(E45-D46,2)) | F46: =ROUND(H45*B5/100/12,2) | G46: =IF((ROUND(H45-ROUND($B$11-F46,2),2)<=0),H45,ROUND($B$11-F46,2)) | H46: =IF((ROUND(H45-ROUND($B$11-F46,2),2)<=0),0,ROUND(H45-G46,2))
A47: 33 | B47: =DATE(YEAR(B8)+INT((MONTH(B8)-1+32)/12),MOD(MONTH(B8)-1+32,12)+1,1)+(DAY(B8)-1) | C47: =ROUND(E46*B5/100/12,2) | D47: =IF((OR(ROUND(E46-ROUND($B$10-C47,2),2)<=0,33=B6)),E46,ROUND($B$10-C47,2)) | E47: =IF((OR(ROUND(E46-ROUND($B$10-C47,2),2)<=0,33=B6)),0,ROUND(E46-D47,2)) | F47: =ROUND(H46*B5/100/12,2) | G47: =IF((ROUND(H46-ROUND($B$11-F47,2),2)<=0),H46,ROUND($B$11-F47,2)) | H47: =IF((ROUND(H46-ROUND($B$11-F47,2),2)<=0),0,ROUND(H46-G47,2))
A48: 34 | B48: =DATE(YEAR(B8)+INT((MONTH(B8)-1+33)/12),MOD(MONTH(B8)-1+33,12)+1,1)+(DAY(B8)-1) | C48: =ROUND(E47*B5/100/12,2) | D48: =IF((OR(ROUND(E47-ROUND($B$10-C48,2),2)<=0,34=B6)),E47,ROUND($B$10-C48,2)) | E48: =IF((OR(ROUND(E47-ROUND($B$10-C48,2),2)<=0,34=B6)),0,ROUND(E47-D48,2)) | F48: =ROUND(H47*B5/100/12,2) | G48: =IF((ROUND(H47-ROUND($B$11-F48,2),2)<=0),H47,ROUND($B$11-F48,2)) | H48: =IF((ROUND(H47-ROUND($B$11-F48,2),2)<=0),0,ROUND(H47-G48,2))
A49: 35 | B49: =DATE(YEAR(B8)+INT((MONTH(B8)-1+34)/12),MOD(MONTH(B8)-1+34,12)+1,1)+(DAY(B8)-1) | C49: =ROUND(E48*B5/100/12,2) | D49: =IF((OR(ROUND(E48-ROUND($B$10-C49,2),2)<=0,35=B6)),E48,ROUND($B$10-C49,2)) | E49: =IF((OR(ROUND(E48-ROUND($B$10-C49,2),2)<=0,35=B6)),0,ROUND(E48-D49,2)) | F49: =ROUND(H48*B5/100/12,2) | G49: =IF((ROUND(H48-ROUND($B$11-F49,2),2)<=0),H48,ROUND($B$11-F49,2)) | H49: =IF((ROUND(H48-ROUND($B$11-F49,2),2)<=0),0,ROUND(H48-G49,2))
A50: 36 | B50: =DATE(YEAR(B8)+INT((MONTH(B8)-1+35)/12),MOD(MONTH(B8)-1+35,12)+1,1)+(DAY(B8)-1) | C50: =ROUND(E49*B5/100/12,2) | D50: =IF((OR(ROUND(E49-ROUND($B$10-C50,2),2)<=0,36=B6)),E49,ROUND($B$10-C50,2)) | E50: =IF((OR(ROUND(E49-ROUND($B$10-C50,2),2)<=0,36=B6)),0,ROUND(E49-D50,2)) | F50: =ROUND(H49*B5/100/12,2) | G50: =IF((ROUND(H49-ROUND($B$11-F50,2),2)<=0),H49,ROUND($B$11-F50,2)) | H50: =IF((ROUND(H49-ROUND($B$11-F50,2),2)<=0),0,ROUND(H49-G50,2))
A51: 37 | B51: =DATE(YEAR(B8)+INT((MONTH(B8)-1+36)/12),MOD(MONTH(B8)-1+36,12)+1,1)+(DAY(B8)-1) | C51: =ROUND(E50*B5/100/12,2) | D51: =IF((OR(ROUND(E50-ROUND($B$10-C51,2),2)<=0,37=B6)),E50,ROUND($B$10-C51,2)) | E51: =IF((OR(ROUND(E50-ROUND($B$10-C51,2),2)<=0,37=B6)),0,ROUND(E50-D51,2)) | F51: =ROUND(H50*B5/100/12,2) | G51: =IF((ROUND(H50-ROUND($B$11-F51,2),2)<=0),H50,ROUND($B$11-F51,2)) | H51: =IF((ROUND(H50-ROUND($B$11-F51,2),2)<=0),0,ROUND(H50-G51,2))
A52: 38 | B52: =DATE(YEAR(B8)+INT((MONTH(B8)-1+37)/12),MOD(MONTH(B8)-1+37,12)+1,1)+(DAY(B8)-1) | C52: =ROUND(E51*B5/100/12,2) | D52: =IF((OR(ROUND(E51-ROUND($B$10-C52,2),2)<=0,38=B6)),E51,ROUND($B$10-C52,2)) | E52: =IF((OR(ROUND(E51-ROUND($B$10-C52,2),2)<=0,38=B6)),0,ROUND(E51-D52,2)) | F52: =ROUND(H51*B5/100/12,2) | G52: =IF((ROUND(H51-ROUND($B$11-F52,2),2)<=0),H51,ROUND($B$11-F52,2)) | H52: =IF((ROUND(H51-ROUND($B$11-F52,2),2)<=0),0,ROUND(H51-G52,2))
A53: 39 | B53: =DATE(YEAR(B8)+INT((MONTH(B8)-1+38)/12),MOD(MONTH(B8)-1+38,12)+1,1)+(DAY(B8)-1) | C53: =ROUND(E52*B5/100/12,2) | D53: =IF((OR(ROUND(E52-ROUND($B$10-C53,2),2)<=0,39=B6)),E52,ROUND($B$10-C53,2)) | E53: =IF((OR(ROUND(E52-ROUND($B$10-C53,2),2)<=0,39=B6)),0,ROUND(E52-D53,2)) | F53: =ROUND(H52*B5/100/12,2) | G53: =IF((ROUND(H52-ROUND($B$11-F53,2),2)<=0),H52,ROUND($B$11-F53,2)) | H53: =IF((ROUND(H52-ROUND($B$11-F53,2),2)<=0),0,ROUND(H52-G53,2))
A54: 40 | B54: =DATE(YEAR(B8)+INT((MONTH(B8)-1+39)/12),MOD(MONTH(B8)-1+39,12)+1,1)+(DAY(B8)-1) | C54: =ROUND(E53*B5/100/12,2) | D54: =IF((OR(ROUND(E53-ROUND($B$10-C54,2),2)<=0,40=B6)),E53,ROUND($B$10-C54,2)) | E54: =IF((OR(ROUND(E53-ROUND($B$10-C54,2),2)<=0,40=B6)),0,ROUND(E53-D54,2)) | F54: =ROUND(H53*B5/100/12,2) | G54: =IF((ROUND(H53-ROUND($B$11-F54,2),2)<=0),H53,ROUND($B$11-F54,2)) | H54: =IF((ROUND(H53-ROUND($B$11-F54,2),2)<=0),0,ROUND(H53-G54,2))
A55: 41 | B55: =DATE(YEAR(B8)+INT((MONTH(B8)-1+40)/12),MOD(MONTH(B8)-1+40,12)+1,1)+(DAY(B8)-1) | C55: =ROUND(E54*B5/100/12,2) | D55: =IF((OR(ROUND(E54-ROUND($B$10-C55,2),2)<=0,41=B6)),E54,ROUND($B$10-C55,2)) | E55: =IF((OR(ROUND(E54-ROUND($B$10-C55,2),2)<=0,41=B6)),0,ROUND(E54-D55,2)) | F55: =ROUND(H54*B5/100/12,2) | G55: =IF((ROUND(H54-ROUND($B$11-F55,2),2)<=0),H54,ROUND($B$11-F55,2)) | H55: =IF((ROUND(H54-ROUND($B$11-F55,2),2)<=0),0,ROUND(H54-G55,2))
A56: 42 | B56: =DATE(YEAR(B8)+INT((MONTH(B8)-1+41)/12),MOD(MONTH(B8)-1+41,12)+1,1)+(DAY(B8)-1) | C56: =ROUND(E55*B5/100/12,2) | D56: =IF((OR(ROUND(E55-ROUND($B$10-C56,2),2)<=0,42=B6)),E55,ROUND($B$10-C56,2)) | E56: =IF((OR(ROUND(E55-ROUND($B$10-C56,2),2)<=0,42=B6)),0,ROUND(E55-D56,2)) | F56: =ROUND(H55*B5/100/12,2) | G56: =IF((ROUND(H55-ROUND($B$11-F56,2),2)<=0),H55,ROUND($B$11-F56,2)) | H56: =IF((ROUND(H55-ROUND($B$11-F56,2),2)<=0),0,ROUND(H55-G56,2))
A57: 43 | B57: =DATE(YEAR(B8)+INT((MONTH(B8)-1+42)/12),MOD(MONTH(B8)-1+42,12)+1,1)+(DAY(B8)-1) | C57: =ROUND(E56*B5/100/12,2) | D57: =IF((OR(ROUND(E56-ROUND($B$10-C57,2),2)<=0,43=B6)),E56,ROUND($B$10-C57,2)) | E57: =IF((OR(ROUND(E56-ROUND($B$10-C57,2),2)<=0,43=B6)),0,ROUND(E56-D57,2)) | F57: =ROUND(H56*B5/100/12,2) | G57: =IF((ROUND(H56-ROUND($B$11-F57,2),2)<=0),H56,ROUND($B$11-F57,2)) | H57: =IF((ROUND(H56-ROUND($B$11-F57,2),2)<=0),0,ROUND(H56-G57,2))
A58: 44 | B58: =DATE(YEAR(B8)+INT((MONTH(B8)-1+43)/12),MOD(MONTH(B8)-1+43,12)+1,1)+(DAY(B8)-1) | C58: =ROUND(E57*B5/100/12,2) | D58: =IF((OR(ROUND(E57-ROUND($B$10-C58,2),2)<=0,44=B6)),E57,ROUND($B$10-C58,2)) | E58: =IF((OR(ROUND(E57-ROUND($B$10-C58,2),2)<=0,44=B6)),0,ROUND(E57-D58,2)) | F58: =ROUND(H57*B5/100/12,2) | G58: =IF((ROUND(H57-ROUND($B$11-F58,2),2)<=0),H57,ROUND($B$11-F58,2)) | H58: =IF((ROUND(H57-ROUND($B$11-F58,2),2)<=0),0,ROUND(H57-G58,2))
A59: 45 | B59: =DATE(YEAR(B8)+INT((MONTH(B8)-1+44)/12),MOD(MONTH(B8)-1+44,12)+1,1)+(DAY(B8)-1) | C59: =ROUND(E58*B5/100/12,2) | D59: =IF((OR(ROUND(E58-ROUND($B$10-C59,2),2)<=0,45=B6)),E58,ROUND($B$10-C59,2)) | E59: =IF((OR(ROUND(E58-ROUND($B$10-C59,2),2)<=0,45=B6)),0,ROUND(E58-D59,2)) | F59: =ROUND(H58*B5/100/12,2) | G59: =IF((ROUND(H58-ROUND($B$11-F59,2),2)<=0),H58,ROUND($B$11-F59,2)) | H59: =IF((ROUND(H58-ROUND($B$11-F59,2),2)<=0),0,ROUND(H58-G59,2))
A60: 46 | B60: =DATE(YEAR(B8)+INT((MONTH(B8)-1+45)/12),MOD(MONTH(B8)-1+45,12)+1,1)+(DAY(B8)-1) | C60: =ROUND(E59*B5/100/12,2) | D60: =IF((OR(ROUND(E59-ROUND($B$10-C60,2),2)<=0,46=B6)),E59,ROUND($B$10-C60,2)) | E60: =IF((OR(ROUND(E59-ROUND($B$10-C60,2),2)<=0,46=B6)),0,ROUND(E59-D60,2)) | F60: =ROUND(H59*B5/100/12,2) | G60: =IF((ROUND(H59-ROUND($B$11-F60,2),2)<=0),H59,ROUND($B$11-F60,2)) | H60: =IF((ROUND(H59-ROUND($B$11-F60,2),2)<=0),0,ROUND(H59-G60,2))
A61: 47 | B61: =DATE(YEAR(B8)+INT((MONTH(B8)-1+46)/12),MOD(MONTH(B8)-1+46,12)+1,1)+(DAY(B8)-1) | C61: =ROUND(E60*B5/100/12,2) | D61: =IF((OR(ROUND(E60-ROUND($B$10-C61,2),2)<=0,47=B6)),E60,ROUND($B$10-C61,2)) | E61: =IF((OR(ROUND(E60-ROUND($B$10-C61,2),2)<=0,47=B6)),0,ROUND(E60-D61,2)) | F61: =ROUND(H60*B5/100/12,2) | G61: =IF((ROUND(H60-ROUND($B$11-F61,2),2)<=0),H60,ROUND($B$11-F61,2)) | H61: =IF((ROUND(H60-ROUND($B$11-F61,2),2)<=0),0,ROUND(H60-G61,2))
A62: 48 | B62: =DATE(YEAR(B8)+INT((MONTH(B8)-1+47)/12),MOD(MONTH(B8)-1+47,12)+1,1)+(DAY(B8)-1) | C62: =ROUND(E61*B5/100/12,2) | D62: =IF((OR(ROUND(E61-ROUND($B$10-C62,2),2)<=0,48=B6)),E61,ROUND($B$10-C62,2)) | E62: =IF((OR(ROUND(E61-ROUND($B$10-C62,2),2)<=0,48=B6)),0,ROUND(E61-D62,2)) | F62: =ROUND(H61*B5/100/12,2) | G62: =IF((ROUND(H61-ROUND($B$11-F62,2),2)<=0),H61,ROUND($B$11-F62,2)) | H62: =IF((ROUND(H61-ROUND($B$11-F62,2),2)<=0),0,ROUND(H61-G62,2))
A63: 49 | B63: =DATE(YEAR(B8)+INT((MONTH(B8)-1+48)/12),MOD(MONTH(B8)-1+48,12)+1,1)+(DAY(B8)-1) | C63: =ROUND(E62*B5/100/12,2) | D63: =IF((OR(ROUND(E62-ROUND($B$10-C63,2),2)<=0,49=B6)),E62,ROUND($B$10-C63,2)) | E63: =IF((OR(ROUND(E62-ROUND($B$10-C63,2),2)<=0,49=B6)),0,ROUND(E62-D63,2)) | F63: =ROUND(H62*B5/100/12,2) | G63: =IF((ROUND(H62-ROUND($B$11-F63,2),2)<=0),H62,ROUND($B$11-F63,2)) | H63: =IF((ROUND(H62-ROUND($B$11-F63,2),2)<=0),0,ROUND(H62-G63,2))
A64: 50 | B64: =DATE(YEAR(B8)+INT((MONTH(B8)-1+49)/12),MOD(MONTH(B8)-1+49,12)+1,1)+(DAY(B8)-1) | C64: =ROUND(E63*B5/100/12,2) | D64: =IF((OR(ROUND(E63-ROUND($B$10-C64,2),2)<=0,50=B6)),E63,ROUND($B$10-C64,2)) | E64: =IF((OR(ROUND(E63-ROUND($B$10-C64,2),2)<=0,50=B6)),0,ROUND(E63-D64,2)) | F64: =ROUND(H63*B5/100/12,2) | G64: =IF((ROUND(H63-ROUND($B$11-F64,2),2)<=0),H63,ROUND($B$11-F64,2)) | H64: =IF((ROUND(H63-ROUND($B$11-F64,2),2)<=0),0,ROUND(H63-G64,2))
A65: 51 | B65: =DATE(YEAR(B8)+INT((MONTH(B8)-1+50)/12),MOD(MONTH(B8)-1+50,12)+1,1)+(DAY(B8)-1) | C65: =ROUND(E64*B5/100/12,2) | D65: =IF((OR(ROUND(E64-ROUND($B$10-C65,2),2)<=0,51=B6)),E64,ROUND($B$10-C65,2)) | E65: =IF((OR(ROUND(E64-ROUND($B$10-C65,2),2)<=0,51=B6)),0,ROUND(E64-D65,2)) | F65: =ROUND(H64*B5/100/12,2) | G65: =IF((ROUND(H64-ROUND($B$11-F65,2),2)<=0),H64,ROUND($B$11-F65,2)) | H65: =IF((ROUND(H64-ROUND($B$11-F65,2),2)<=0),0,ROUND(H64-G65,2))
A66: 52 | B66: =DATE(YEAR(B8)+INT((MONTH(B8)-1+51)/12),MOD(MONTH(B8)-1+51,12)+1,1)+(DAY(B8)-1) | C66: =ROUND(E65*B5/100/12,2) | D66: =IF((OR(ROUND(E65-ROUND($B$10-C66,2),2)<=0,52=B6)),E65,ROUND($B$10-C66,2)) | E66: =IF((OR(ROUND(E65-ROUND($B$10-C66,2),2)<=0,52=B6)),0,ROUND(E65-D66,2)) | F66: =ROUND(H65*B5/100/12,2) | G66: =IF((ROUND(H65-ROUND($B$11-F66,2),2)<=0),H65,ROUND($B$11-F66,2)) | H66: =IF((ROUND(H65-ROUND($B$11-F66,2),2)<=0),0,ROUND(H65-G66,2))
A67: 53 | B67: =DATE(YEAR(B8)+INT((MONTH(B8)-1+52)/12),MOD(MONTH(B8)-1+52,12)+1,1)+(DAY(B8)-1) | C67: =ROUND(E66*B5/100/12,2) | D67: =IF((OR(ROUND(E66-ROUND($B$10-C67,2),2)<=0,53=B6)),E66,ROUND($B$10-C67,2)) | E67: =IF((OR(ROUND(E66-ROUND($B$10-C67,2),2)<=0,53=B6)),0,ROUND(E66-D67,2)) | F67: =ROUND(H66*B5/100/12,2) | G67: =IF((ROUND(H66-ROUND($B$11-F67,2),2)<=0),H66,ROUND($B$11-F67,2)) | H67: =IF((ROUND(H66-ROUND($B$11-F67,2),2)<=0),0,ROUND(H66-G67,2))
A68: 54 | B68: =DATE(YEAR(B8)+INT((MONTH(B8)-1+53)/12),MOD(MONTH(B8)-1+53,12)+1,1)+(DAY(B8)-1) | C68: =ROUND(E67*B5/100/12,2) | D68: =IF((OR(ROUND(E67-ROUND($B$10-C68,2),2)<=0,54=B6)),E67,ROUND($B$10-C68,2)) | E68: =IF((OR(ROUND(E67-ROUND($B$10-C68,2),2)<=0,54=B6)),0,ROUND(E67-D68,2)) | F68: =ROUND(H67*B5/100/12,2) | G68: =IF((ROUND(H67-ROUND($B$11-F68,2),2)<=0),H67,ROUND($B$11-F68,2)) | H68: =IF((ROUND(H67-ROUND($B$11-F68,2),2)<=0),0,ROUND(H67-G68,2))
A69: 55 | B69: =DATE(YEAR(B8)+INT((MONTH(B8)-1+54)/12),MOD(MONTH(B8)-1+54,12)+1,1)+(DAY(B8)-1) | C69: =ROUND(E68*B5/100/12,2) | D69: =IF((OR(ROUND(E68-ROUND($B$10-C69,2),2)<=0,55=B6)),E68,ROUND($B$10-C69,2)) | E69: =IF((OR(ROUND(E68-ROUND($B$10-C69,2),2)<=0,55=B6)),0,ROUND(E68-D69,2)) | F69: =ROUND(H68*B5/100/12,2) | G69: =IF((ROUND(H68-ROUND($B$11-F69,2),2)<=0),H68,ROUND($B$11-F69,2)) | H69: =IF((ROUND(H68-ROUND($B$11-F69,2),2)<=0),0,ROUND(H68-G69,2))
A70: 56 | B70: =DATE(YEAR(B8)+INT((MONTH(B8)-1+55)/12),MOD(MONTH(B8)-1+55,12)+1,1)+(DAY(B8)-1) | C70: =ROUND(E69*B5/100/12,2) | D70: =IF((OR(ROUND(E69-ROUND($B$10-C70,2),2)<=0,56=B6)),E69,ROUND($B$10-C70,2)) | E70: =IF((OR(ROUND(E69-ROUND($B$10-C70,2),2)<=0,56=B6)),0,ROUND(E69-D70,2)) | F70: =ROUND(H69*B5/100/12,2) | G70: =IF((ROUND(H69-ROUND($B$11-F70,2),2)<=0),H69,ROUND($B$11-F70,2)) | H70: =IF((ROUND(H69-ROUND($B$11-F70,2),2)<=0),0,ROUND(H69-G70,2))
A71: 57 | B71: =DATE(YEAR(B8)+INT((MONTH(B8)-1+56)/12),MOD(MONTH(B8)-1+56,12)+1,1)+(DAY(B8)-1) | C71: =ROUND(E70*B5/100/12,2) | D71: =IF((OR(ROUND(E70-ROUND($B$10-C71,2),2)<=0,57=B6)),E70,ROUND($B$10-C71,2)) | E71: =IF((OR(ROUND(E70-ROUND($B$10-C71,2),2)<=0,57=B6)),0,ROUND(E70-D71,2)) | F71: =ROUND(H70*B5/100/12,2) | G71: =IF((ROUND(H70-ROUND($B$11-F71,2),2)<=0),H70,ROUND($B$11-F71,2)) | H71: =IF((ROUND(H70-ROUND($B$11-F71,2),2)<=0),0,ROUND(H70-G71,2))
A72: 58 | B72: =DATE(YEAR(B8)+INT((MONTH(B8)-1+57)/12),MOD(MONTH(B8)-1+57,12)+1,1)+(DAY(B8)-1) | C72: =ROUND(E71*B5/100/12,2) | D72: =IF((OR(ROUND(E71-ROUND($B$10-C72,2),2)<=0,58=B6)),E71,ROUND($B$10-C72,2)) | E72: =IF((OR(ROUND(E71-ROUND($B$10-C72,2),2)<=0,58=B6)),0,ROUND(E71-D72,2)) | F72: =ROUND(H71*B5/100/12,2) | G72: =IF((ROUND(H71-ROUND($B$11-F72,2),2)<=0),H71,ROUND($B$11-F72,2)) | H72: =IF((ROUND(H71-ROUND($B$11-F72,2),2)<=0),0,ROUND(H71-G72,2))
A73: 59 | B73: =DATE(YEAR(B8)+INT((MONTH(B8)-1+58)/12),MOD(MONTH(B8)-1+58,12)+1,1)+(DAY(B8)-1) | C73: =ROUND(E72*B5/100/12,2) | D73: =IF((OR(ROUND(E72-ROUND($B$10-C73,2),2)<=0,59=B6)),E72,ROUND($B$10-C73,2)) | E73: =IF((OR(ROUND(E72-ROUND($B$10-C73,2),2)<=0,59=B6)),0,ROUND(E72-D73,2)) | F73: =ROUND(H72*B5/100/12,2) | G73: =IF((ROUND(H72-ROUND($B$11-F73,2),2)<=0),H72,ROUND($B$11-F73,2)) | H73: =IF((ROUND(H72-ROUND($B$11-F73,2),2)<=0),0,ROUND(H72-G73,2))
A74: 60 | B74: =DATE(YEAR(B8)+INT((MONTH(B8)-1+59)/12),MOD(MONTH(B8)-1+59,12)+1,1)+(DAY(B8)-1) | C74: =ROUND(E73*B5/100/12,2) | D74: =IF((OR(ROUND(E73-ROUND($B$10-C74,2),2)<=0,60=B6)),E73,ROUND($B$10-C74,2)) | E74: =IF((OR(ROUND(E73-ROUND($B$10-C74,2),2)<=0,60=B6)),0,ROUND(E73-D74,2)) | F74: =ROUND(H73*B5/100/12,2) | G74: =IF((ROUND(H73-ROUND($B$11-F74,2),2)<=0),H73,ROUND($B$11-F74,2)) | H74: =IF((ROUND(H73-ROUND($B$11-F74,2),2)<=0),0,ROUND(H73-G74,2))
A75: 61 | B75: =DATE(YEAR(B8)+INT((MONTH(B8)-1+60)/12),MOD(MONTH(B8)-1+60,12)+1,1)+(DAY(B8)-1) | C75: =ROUND(E74*B5/100/12,2) | D75: =IF((OR(ROUND(E74-ROUND($B$10-C75,2),2)<=0,61=B6)),E74,ROUND($B$10-C75,2)) | E75: =IF((OR(ROUND(E74-ROUND($B$10-C75,2),2)<=0,61=B6)),0,ROUND(E74-D75,2)) | F75: =ROUND(H74*B5/100/12,2) | G75: =IF((ROUND(H74-ROUND($B$11-F75,2),2)<=0),H74,ROUND($B$11-F75,2)) | H75: =IF((ROUND(H74-ROUND($B$11-F75,2),2)<=0),0,ROUND(H74-G75,2))
A76: 62 | B76: =DATE(YEAR(B8)+INT((MONTH(B8)-1+61)/12),MOD(MONTH(B8)-1+61,12)+1,1)+(DAY(B8)-1) | C76: =ROUND(E75*B5/100/12,2) | D76: =IF((OR(ROUND(E75-ROUND($B$10-C76,2),2)<=0,62=B6)),E75,ROUND($B$10-C76,2)) | E76: =IF((OR(ROUND(E75-ROUND($B$10-C76,2),2)<=0,62=B6)),0,ROUND(E75-D76,2)) | F76: =ROUND(H75*B5/100/12,2) | G76: =IF((ROUND(H75-ROUND($B$11-F76,2),2)<=0),H75,ROUND($B$11-F76,2)) | H76: =IF((ROUND(H75-ROUND($B$11-F76,2),2)<=0),0,ROUND(H75-G76,2))
A77: 63 | B77: =DATE(YEAR(B8)+INT((MONTH(B8)-1+62)/12),MOD(MONTH(B8)-1+62,12)+1,1)+(DAY(B8)-1) | C77: =ROUND(E76*B5/100/12,2) | D77: =IF((OR(ROUND(E76-ROUND($B$10-C77,2),2)<=0,63=B6)),E76,ROUND($B$10-C77,2)) | E77: =IF((OR(ROUND(E76-ROUND($B$10-C77,2),2)<=0,63=B6)),0,ROUND(E76-D77,2)) | F77: =ROUND(H76*B5/100/12,2) | G77: =IF((ROUND(H76-ROUND($B$11-F77,2),2)<=0),H76,ROUND($B$11-F77,2)) | H77: =IF((ROUND(H76-ROUND($B$11-F77,2),2)<=0),0,ROUND(H76-G77,2))
A78: 64 | B78: =DATE(YEAR(B8)+INT((MONTH(B8)-1+63)/12),MOD(MONTH(B8)-1+63,12)+1,1)+(DAY(B8)-1) | C78: =ROUND(E77*B5/100/12,2) | D78: =IF((OR(ROUND(E77-ROUND($B$10-C78,2),2)<=0,64=B6)),E77,ROUND($B$10-C78,2)) | E78: =IF((OR(ROUND(E77-ROUND($B$10-C78,2),2)<=0,64=B6)),0,ROUND(E77-D78,2)) | F78: =ROUND(H77*B5/100/12,2) | G78: =IF((ROUND(H77-ROUND($B$11-F78,2),2)<=0),H77,ROUND($B$11-F78,2)) | H78: =IF((ROUND(H77-ROUND($B$11-F78,2),2)<=0),0,ROUND(H77-G78,2))
A79: 65 | B79: =DATE(YEAR(B8)+INT((MONTH(B8)-1+64)/12),MOD(MONTH(B8)-1+64,12)+1,1)+(DAY(B8)-1) | C79: =ROUND(E78*B5/100/12,2) | D79: =IF((OR(ROUND(E78-ROUND($B$10-C79,2),2)<=0,65=B6)),E78,ROUND($B$10-C79,2)) | E79: =IF((OR(ROUND(E78-ROUND($B$10-C79,2),2)<=0,65=B6)),0,ROUND(E78-D79,2)) | F79: =ROUND(H78*B5/100/12,2) | G79: =IF((ROUND(H78-ROUND($B$11-F79,2),2)<=0),H78,ROUND($B$11-F79,2)) | H79: =IF((ROUND(H78-ROUND($B$11-F79,2),2)<=0),0,ROUND(H78-G79,2))
A80: 66 | B80: =DATE(YEAR(B8)+INT((MONTH(B8)-1+65)/12),MOD(MONTH(B8)-1+65,12)+1,1)+(DAY(B8)-1) | C80: =ROUND(E79*B5/100/12,2) | D80: =IF((OR(ROUND(E79-ROUND($B$10-C80,2),2)<=0,66=B6)),E79,ROUND($B$10-C80,2)) | E80: =IF((OR(ROUND(E79-ROUND($B$10-C80,2),2)<=0,66=B6)),0,ROUND(E79-D80,2)) | F80: =ROUND(H79*B5/100/12,2) | G80: =IF((ROUND(H79-ROUND($B$11-F80,2),2)<=0),H79,ROUND($B$11-F80,2)) | H80: =IF((ROUND(H79-ROUND($B$11-F80,2),2)<=0),0,ROUND(H79-G80,2))
A81: 67 | B81: =DATE(YEAR(B8)+INT((MONTH(B8)-1+66)/12),MOD(MONTH(B8)-1+66,12)+1,1)+(DAY(B8)-1) | C81: =ROUND(E80*B5/100/12,2) | D81: =IF((OR(ROUND(E80-ROUND($B$10-C81,2),2)<=0,67=B6)),E80,ROUND($B$10-C81,2)) | E81: =IF((OR(ROUND(E80-ROUND($B$10-C81,2),2)<=0,67=B6)),0,ROUND(E80-D81,2)) | F81: =ROUND(H80*B5/100/12,2) | G81: =IF((ROUND(H80-ROUND($B$11-F81,2),2)<=0),H80,ROUND($B$11-F81,2)) | H81: =IF((ROUND(H80-ROUND($B$11-F81,2),2)<=0),0,ROUND(H80-G81,2))
A82: 68 | B82: =DATE(YEAR(B8)+INT((MONTH(B8)-1+67)/12),MOD(MONTH(B8)-1+67,12)+1,1)+(DAY(B8)-1) | C82: =ROUND(E81*B5/100/12,2) | D82: =IF((OR(ROUND(E81-ROUND($B$10-C82,2),2)<=0,68=B6)),E81,ROUND($B$10-C82,2)) | E82: =IF((OR(ROUND(E81-ROUND($B$10-C82,2),2)<=0,68=B6)),0,ROUND(E81-D82,2)) | F82: =ROUND(H81*B5/100/12,2) | G82: =IF((ROUND(H81-ROUND($B$11-F82,2),2)<=0),H81,ROUND($B$11-F82,2)) | H82: =IF((ROUND(H81-ROUND($B$11-F82,2),2)<=0),0,ROUND(H81-G82,2))
A83: 69 | B83: =DATE(YEAR(B8)+INT((MONTH(B8)-1+68)/12),MOD(MONTH(B8)-1+68,12)+1,1)+(DAY(B8)-1) | C83: =ROUND(E82*B5/100/12,2) | D83: =IF((OR(ROUND(E82-ROUND($B$10-C83,2),2)<=0,69=B6)),E82,ROUND($B$10-C83,2)) | E83: =IF((OR(ROUND(E82-ROUND($B$10-C83,2),2)<=0,69=B6)),0,ROUND(E82-D83,2)) | F83: =ROUND(H82*B5/100/12,2) | G83: =IF((ROUND(H82-ROUND($B$11-F83,2),2)<=0),H82,ROUND($B$11-F83,2)) | H83: =IF((ROUND(H82-ROUND($B$11-F83,2),2)<=0),0,ROUND(H82-G83,2))
A84: 70 | B84: =DATE(YEAR(B8)+INT((MONTH(B8)-1+69)/12),MOD(MONTH(B8)-1+69,12)+1,1)+(DAY(B8)-1) | C84: =ROUND(E83*B5/100/12,2) | D84: =IF((OR(ROUND(E83-ROUND($B$10-C84,2),2)<=0,70=B6)),E83,ROUND($B$10-C84,2)) | E84: =IF((OR(ROUND(E83-ROUND($B$10-C84,2),2)<=0,70=B6)),0,ROUND(E83-D84,2)) | F84: =ROUND(H83*B5/100/12,2) | G84: =IF((ROUND(H83-ROUND($B$11-F84,2),2)<=0),H83,ROUND($B$11-F84,2)) | H84: =IF((ROUND(H83-ROUND($B$11-F84,2),2)<=0),0,ROUND(H83-G84,2))
A85: 71 | B85: =DATE(YEAR(B8)+INT((MONTH(B8)-1+70)/12),MOD(MONTH(B8)-1+70,12)+1,1)+(DAY(B8)-1) | C85: =ROUND(E84*B5/100/12,2) | D85: =IF((OR(ROUND(E84-ROUND($B$10-C85,2),2)<=0,71=B6)),E84,ROUND($B$10-C85,2)) | E85: =IF((OR(ROUND(E84-ROUND($B$10-C85,2),2)<=0,71=B6)),0,ROUND(E84-D85,2)) | F85: =ROUND(H84*B5/100/12,2) | G85: =IF((ROUND(H84-ROUND($B$11-F85,2),2)<=0),H84,ROUND($B$11-F85,2)) | H85: =IF((ROUND(H84-ROUND($B$11-F85,2),2)<=0),0,ROUND(H84-G85,2))
A86: 72 | B86: =DATE(YEAR(B8)+INT((MONTH(B8)-1+71)/12),MOD(MONTH(B8)-1+71,12)+1,1)+(DAY(B8)-1) | C86: =ROUND(E85*B5/100/12,2) | D86: =IF((OR(ROUND(E85-ROUND($B$10-C86,2),2)<=0,72=B6)),E85,ROUND($B$10-C86,2)) | E86: =IF((OR(ROUND(E85-ROUND($B$10-C86,2),2)<=0,72=B6)),0,ROUND(E85-D86,2)) | F86: =ROUND(H85*B5/100/12,2) | G86: =IF((ROUND(H85-ROUND($B$11-F86,2),2)<=0),H85,ROUND($B$11-F86,2)) | H86: =IF((ROUND(H85-ROUND($B$11-F86,2),2)<=0),0,ROUND(H85-G86,2))
A87: 73 | B87: =DATE(YEAR(B8)+INT((MONTH(B8)-1+72)/12),MOD(MONTH(B8)-1+72,12)+1,1)+(DAY(B8)-1) | C87: =ROUND(E86*B5/100/12,2) | D87: =IF((OR(ROUND(E86-ROUND($B$10-C87,2),2)<=0,73=B6)),E86,ROUND($B$10-C87,2)) | E87: =IF((OR(ROUND(E86-ROUND($B$10-C87,2),2)<=0,73=B6)),0,ROUND(E86-D87,2)) | F87: =ROUND(H86*B5/100/12,2) | G87: =IF((ROUND(H86-ROUND($B$11-F87,2),2)<=0),H86,ROUND($B$11-F87,2)) | H87: =IF((ROUND(H86-ROUND($B$11-F87,2),2)<=0),0,ROUND(H86-G87,2))
A88: 74 | B88: =DATE(YEAR(B8)+INT((MONTH(B8)-1+73)/12),MOD(MONTH(B8)-1+73,12)+1,1)+(DAY(B8)-1) | C88: =ROUND(E87*B5/100/12,2) | D88: =IF((OR(ROUND(E87-ROUND($B$10-C88,2),2)<=0,74=B6)),E87,ROUND($B$10-C88,2)) | E88: =IF((OR(ROUND(E87-ROUND($B$10-C88,2),2)<=0,74=B6)),0,ROUND(E87-D88,2)) | F88: =ROUND(H87*B5/100/12,2) | G88: =IF((ROUND(H87-ROUND($B$11-F88,2),2)<=0),H87,ROUND($B$11-F88,2)) | H88: =IF((ROUND(H87-ROUND($B$11-F88,2),2)<=0),0,ROUND(H87-G88,2))
A89: 75 | B89: =DATE(YEAR(B8)+INT((MONTH(B8)-1+74)/12),MOD(MONTH(B8)-1+74,12)+1,1)+(DAY(B8)-1) | C89: =ROUND(E88*B5/100/12,2) | D89: =IF((OR(ROUND(E88-ROUND($B$10-C89,2),2)<=0,75=B6)),E88,ROUND($B$10-C89,2)) | E89: =IF((OR(ROUND(E88-ROUND($B$10-C89,2),2)<=0,75=B6)),0,ROUND(E88-D89,2)) | F89: =ROUND(H88*B5/100/12,2) | G89: =IF((ROUND(H88-ROUND($B$11-F89,2),2)<=0),H88,ROUND($B$11-F89,2)) | H89: =IF((ROUND(H88-ROUND($B$11-F89,2),2)<=0),0,ROUND(H88-G89,2))
A90: 76 | B90: =DATE(YEAR(B8)+INT((MONTH(B8)-1+75)/12),MOD(MONTH(B8)-1+75,12)+1,1)+(DAY(B8)-1) | C90: =ROUND(E89*B5/100/12,2) | D90: =IF((OR(ROUND(E89-ROUND($B$10-C90,2),2)<=0,76=B6)),E89,ROUND($B$10-C90,2)) | E90: =IF((OR(ROUND(E89-ROUND($B$10-C90,2),2)<=0,76=B6)),0,ROUND(E89-D90,2)) | F90: =ROUND(H89*B5/100/12,2) | G90: =IF((ROUND(H89-ROUND($B$11-F90,2),2)<=0),H89,ROUND($B$11-F90,2)) | H90: =IF((ROUND(H89-ROUND($B$11-F90,2),2)<=0),0,ROUND(H89-G90,2))
A91: 77 | B91: =DATE(YEAR(B8)+INT((MONTH(B8)-1+76)/12),MOD(MONTH(B8)-1+76,12)+1,1)+(DAY(B8)-1) | C91: =ROUND(E90*B5/100/12,2) | D91: =IF((OR(ROUND(E90-ROUND($B$10-C91,2),2)<=0,77=B6)),E90,ROUND($B$10-C91,2)) | E91: =IF((OR(ROUND(E90-ROUND($B$10-C91,2),2)<=0,77=B6)),0,ROUND(E90-D91,2)) | F91: =ROUND(H90*B5/100/12,2) | G91: =IF((ROUND(H90-ROUND($B$11-F91,2),2)<=0),H90,ROUND($B$11-F91,2)) | H91: =IF((ROUND(H90-ROUND($B$11-F91,2),2)<=0),0,ROUND(H90-G91,2))
A92: 78 | B92: =DATE(YEAR(B8)+INT((MONTH(B8)-1+77)/12),MOD(MONTH(B8)-1+77,12)+1,1)+(DAY(B8)-1) | C92: =ROUND(E91*B5/100/12,2) | D92: =IF((OR(ROUND(E91-ROUND($B$10-C92,2),2)<=0,78=B6)),E91,ROUND($B$10-C92,2)) | E92: =IF((OR(ROUND(E91-ROUND($B$10-C92,2),2)<=0,78=B6)),0,ROUND(E91-D92,2)) | F92: =ROUND(H91*B5/100/12,2) | G92: =IF((ROUND(H91-ROUND($B$11-F92,2),2)<=0),H91,ROUND($B$11-F92,2)) | H92: =IF((ROUND(H91-ROUND($B$11-F92,2),2)<=0),0,ROUND(H91-G92,2))
A93: 79 | B93: =DATE(YEAR(B8)+INT((MONTH(B8)-1+78)/12),MOD(MONTH(B8)-1+78,12)+1,1)+(DAY(B8)-1) | C93: =ROUND(E92*B5/100/12,2) | D93: =IF((OR(ROUND(E92-ROUND($B$10-C93,2),2)<=0,79=B6)),E92,ROUND($B$10-C93,2)) | E93: =IF((OR(ROUND(E92-ROUND($B$10-C93,2),2)<=0,79=B6)),0,ROUND(E92-D93,2)) | F93: =ROUND(H92*B5/100/12,2) | G93: =IF((ROUND(H92-ROUND($B$11-F93,2),2)<=0),H92,ROUND($B$11-F93,2)) | H93: =IF((ROUND(H92-ROUND($B$11-F93,2),2)<=0),0,ROUND(H92-G93,2))
A94: 80 | B94: =DATE(YEAR(B8)+INT((MONTH(B8)-1+79)/12),MOD(MONTH(B8)-1+79,12)+1,1)+(DAY(B8)-1) | C94: =ROUND(E93*B5/100/12,2) | D94: =IF((OR(ROUND(E93-ROUND($B$10-C94,2),2)<=0,80=B6)),E93,ROUND($B$10-C94,2)) | E94: =IF((OR(ROUND(E93-ROUND($B$10-C94,2),2)<=0,80=B6)),0,ROUND(E93-D94,2)) | F94: =ROUND(H93*B5/100/12,2) | G94: =IF((ROUND(H93-ROUND($B$11-F94,2),2)<=0),H93,ROUND($B$11-F94,2)) | H94: =IF((ROUND(H93-ROUND($B$11-F94,2),2)<=0),0,ROUND(H93-G94,2))
A95: 81 | B95: =DATE(YEAR(B8)+INT((MONTH(B8)-1+80)/12),MOD(MONTH(B8)-1+80,12)+1,1)+(DAY(B8)-1) | C95: =ROUND(E94*B5/100/12,2) | D95: =IF((OR(ROUND(E94-ROUND($B$10-C95,2),2)<=0,81=B6)),E94,ROUND($B$10-C95,2)) | E95: =IF((OR(ROUND(E94-ROUND($B$10-C95,2),2)<=0,81=B6)),0,ROUND(E94-D95,2)) | F95: =ROUND(H94*B5/100/12,2) | G95: =IF((ROUND(H94-ROUND($B$11-F95,2),2)<=0),H94,ROUND($B$11-F95,2)) | H95: =IF((ROUND(H94-ROUND($B$11-F95,2),2)<=0),0,ROUND(H94-G95,2))
A96: 82 | B96: =DATE(YEAR(B8)+INT((MONTH(B8)-1+81)/12),MOD(MONTH(B8)-1+81,12)+1,1)+(DAY(B8)-1) | C96: =ROUND(E95*B5/100/12,2) | D96: =IF((OR(ROUND(E95-ROUND($B$10-C96,2),2)<=0,82=B6)),E95,ROUND($B$10-C96,2)) | E96: =IF((OR(ROUND(E95-ROUND($B$10-C96,2),2)<=0,82=B6)),0,ROUND(E95-D96,2)) | F96: =ROUND(H95*B5/100/12,2) | G96: =IF((ROUND(H95-ROUND($B$11-F96,2),2)<=0),H95,ROUND($B$11-F96,2)) | H96: =IF((ROUND(H95-ROUND($B$11-F96,2),2)<=0),0,ROUND(H95-G96,2))
A97: 83 | B97: =DATE(YEAR(B8)+INT((MONTH(B8)-1+82)/12),MOD(MONTH(B8)-1+82,12)+1,1)+(DAY(B8)-1) | C97: =ROUND(E96*B5/100/12,2) | D97: =IF((OR(ROUND(E96-ROUND($B$10-C97,2),2)<=0,83=B6)),E96,ROUND($B$10-C97,2)) | E97: =IF((OR(ROUND(E96-ROUND($B$10-C97,2),2)<=0,83=B6)),0,ROUND(E96-D97,2)) | F97: =ROUND(H96*B5/100/12,2) | G97: =IF((ROUND(H96-ROUND($B$11-F97,2),2)<=0),H96,ROUND($B$11-F97,2)) | H97: =IF((ROUND(H96-ROUND($B$11-F97,2),2)<=0),0,ROUND(H96-G97,2))
A98: 84 | B98: =DATE(YEAR(B8)+INT((MONTH(B8)-1+83)/12),MOD(MONTH(B8)-1+83,12)+1,1)+(DAY(B8)-1) | C98: =ROUND(E97*B5/100/12,2) | D98: =IF((OR(ROUND(E97-ROUND($B$10-C98,2),2)<=0,84=B6)),E97,ROUND($B$10-C98,2)) | E98: =IF((OR(ROUND(E97-ROUND($B$10-C98,2),2)<=0,84=B6)),0,ROUND(E97-D98,2)) | F98: =ROUND(H97*B5/100/12,2) | G98: =IF((ROUND(H97-ROUND($B$11-F98,2),2)<=0),H97,ROUND($B$11-F98,2)) | H98: =IF((ROUND(H97-ROUND($B$11-F98,2),2)<=0),0,ROUND(H97-G98,2))
A99: 85 | B99: =DATE(YEAR(B8)+INT((MONTH(B8)-1+84)/12),MOD(MONTH(B8)-1+84,12)+1,1)+(DAY(B8)-1) | C99: =ROUND(E98*B5/100/12,2) | D99: =IF((OR(ROUND(E98-ROUND($B$10-C99,2),2)<=0,85=B6)),E98,ROUND($B$10-C99,2)) | E99: =IF((OR(ROUND(E98-ROUND($B$10-C99,2),2)<=0,85=B6)),0,ROUND(E98-D99,2)) | F99: =ROUND(H98*B5/100/12,2) | G99: =IF((ROUND(H98-ROUND($B$11-F99,2),2)<=0),H98,ROUND($B$11-F99,2)) | H99: =IF((ROUND(H98-ROUND($B$11-F99,2),2)<=0),0,ROUND(H98-G99,2))
A100: 86 | B100: =DATE(YEAR(B8)+INT((MONTH(B8)-1+85)/12),MOD(MONTH(B8)-1+85,12)+1,1)+(DAY(B8)-1) | C100: =ROUND(E99*B5/100/12,2) | D100: =IF((OR(ROUND(E99-ROUND($B$10-C100,2),2)<=0,86=B6)),E99,ROUND($B$10-C100,2)) | E100: =IF((OR(ROUND(E99-ROUND($B$10-C100,2),2)<=0,86=B6)),0,ROUND(E99-D100,2)) | F100: =ROUND(H99*B5/100/12,2) | G100: =IF((ROUND(H99-ROUND($B$11-F100,2),2)<=0),H99,ROUND($B$11-F100,2)) | H100: =IF((ROUND(H99-ROUND($B$11-F100,2),2)<=0),0,ROUND(H99-G100,2))
A101: 87 | B101: =DATE(YEAR(B8)+INT((MONTH(B8)-1+86)/12),MOD(MONTH(B8)-1+86,12)+1,1)+(DAY(B8)-1) | C101: =ROUND(E100*B5/100/12,2) | D101: =IF((OR(ROUND(E100-ROUND($B$10-C101,2),2)<=0,87=B6)),E100,ROUND($B$10-C101,2)) | E101: =IF((OR(ROUND(E100-ROUND($B$10-C101,2),2)<=0,87=B6)),0,ROUND(E100-D101,2)) | F101: =ROUND(H100*B5/100/12,2) | G101: =IF((ROUND(H100-ROUND($B$11-F101,2),2)<=0),H100,ROUND($B$11-F101,2)) | H101: =IF((ROUND(H100-ROUND($B$11-F101,2),2)<=0),0,ROUND(H100-G101,2))
A102: 88 | B102: =DATE(YEAR(B8)+INT((MONTH(B8)-1+87)/12),MOD(MONTH(B8)-1+87,12)+1,1)+(DAY(B8)-1) | C102: =ROUND(E101*B5/100/12,2) | D102: =IF((OR(ROUND(E101-ROUND($B$10-C102,2),2)<=0,88=B6)),E101,ROUND($B$10-C102,2)) | E102: =IF((OR(ROUND(E101-ROUND($B$10-C102,2),2)<=0,88=B6)),0,ROUND(E101-D102,2)) | F102: =ROUND(H101*B5/100/12,2) | G102: =IF((ROUND(H101-ROUND($B$11-F102,2),2)<=0),H101,ROUND($B$11-F102,2)) | H102: =IF((ROUND(H101-ROUND($B$11-F102,2),2)<=0),0,ROUND(H101-G102,2))
A103: 89 | B103: =DATE(YEAR(B8)+INT((MONTH(B8)-1+88)/12),MOD(MONTH(B8)-1+88,12)+1,1)+(DAY(B8)-1) | C103: =ROUND(E102*B5/100/12,2) | D103: =IF((OR(ROUND(E102-ROUND($B$10-C103,2),2)<=0,89=B6)),E102,ROUND($B$10-C103,2)) | E103: =IF((OR(ROUND(E102-ROUND($B$10-C103,2),2)<=0,89=B6)),0,ROUND(E102-D103,2)) | F103: =ROUND(H102*B5/100/12,2) | G103: =IF((ROUND(H102-ROUND($B$11-F103,2),2)<=0),H102,ROUND($B$11-F103,2)) | H103: =IF((ROUND(H102-ROUND($B$11-F103,2),2)<=0),0,ROUND(H102-G103,2))
A104: 90 | B104: =DATE(YEAR(B8)+INT((MONTH(B8)-1+89)/12),MOD(MONTH(B8)-1+89,12)+1,1)+(DAY(B8)-1) | C104: =ROUND(E103*B5/100/12,2) | D104: =IF((OR(ROUND(E103-ROUND($B$10-C104,2),2)<=0,90=B6)),E103,ROUND($B$10-C104,2)) | E104: =IF((OR(ROUND(E103-ROUND($B$10-C104,2),2)<=0,90=B6)),0,ROUND(E103-D104,2)) | F104: =ROUND(H103*B5/100/12,2) | G104: =IF((ROUND(H103-ROUND($B$11-F104,2),2)<=0),H103,ROUND($B$11-F104,2)) | H104: =IF((ROUND(H103-ROUND($B$11-F104,2),2)<=0),0,ROUND(H103-G104,2))
...

Sheet Points
A1: Discount Points Breakeven
A4: Loan amount ($) | B4: 400000
A5: Points purchased (1 = 1% of loan) | B5: 1
A6: Rate reduction from points (pts) | B6: 0.25
A7: Original rate (%) | B7: 6.5
A8: Term (months) | B8: 360
A10: Points cost | B10: =ROUND(B4*B5/100,2)
A11: Monthly payment (original rate) | B11: =ROUND(-PMT(B7/100/12,B8,B4),2)
A12: Monthly payment (with points) | B12: =ROUND(-PMT((B7-B6)/100/12,B8,B4),2)
A13: Monthly savings | B13: =B11-B12
A14: Breakeven (months) | B14: =IF(B13<=0,"never (no monthly savings)",B10/B13)

Sheet Refinance
A1: Refinance Comparison
A2: Total costs use n*payment over the full term, a quick-comparison simplification -- expect the same small rounding-drift deviation from a full cent-rounded schedule documented in docs/new-req/004-rounding-drift-accuracy-disclosure.md.
A4: Old: remaining balance ($) | B4: 280000
A5: Old: rate (%) | B5: 7
A6: Old: remaining term (years) | B6: 28
A7: New: loan amount ($) | B7: 280000
A8: New: rate (%) | B8: 6
A9: New: term (years) | B9: 30
A10: Closing costs ($) | B10: 6000
A12: Old monthly payment | B12: =ROUND(-PMT(B5/100/12,B6*12,B4),2)
A13: New monthly payment | B13: =ROUND(-PMT(B8/100/12,B9*12,B7),2)
A14: Old total cost (remaining term) | B14: =B12*B6*12
A15: New total cost (incl. closing costs) | B15: =B13*B9*12+B10
A16: Net savings | B16: =B14-B15
A17: Breakeven (months) | B17: =IF(B12-B13<=0,"never (no monthly savings)",B10/(B12-B13))

Sheet CompareTerms
A1: Compare Loan Offers
A2: Up to 4 offers, side by side.
B4: Offer 1 | C4: Offer 2 | D4: Offer 3 | E4: Offer 4
A5: Loan amount ($) | B5: 300000 | C5: 300000 | D5: 300000 | E5: 300000
A6: Rate (%) | B6: 6.5 | C6: 6 | D6: 6.5 | E6: 5.75
A7: Term (years) | B7: 30 | C7: 30 | D7: 15 | E7: 15
A8: Monthly payment | B8: =ROUND(-PMT(B6/100/12,B7*12,B5),2) | C8: =ROUND(-PMT(C6/100/12,C7*12,C5),2) | D8: =ROUND(-PMT(D6/100/12,D7*12,D5),2) | E8: =ROUND(-PMT(E6/100/12,E7*12,E5),2)
A9: Total interest | B9: =B8*B7*12-B5 | C9: =C8*C7*12-C5 | D9: =D8*D7*12-D5 | E9: =E8*E7*12-E5
A10: Total of payments | B10: =B8*B7*12 | C10: =C8*C7*12 | D10: =D8*D7*12 | E10: =E8*E7*12
A12: Lowest monthly payment | B12: =INDEX($B$4:$E$4,MATCH(MIN(B8:E8),B8:E8,0))
A13: Lowest total interest | B13: =INDEX($B$4:$E$4,MATCH(MIN(B9:E9),B9:E9,0))

Sheet LTV_DSCR
A1: LTV, CLTV & DSCR
A4: Loan-to-Value (LTV)
A5: Loan amount ($) | B5: 270000
A6: Property value ($) | B6: 300000
A7: LTV | B7: =IF(B6=0,"n/a",B5/B6)
A10: Combined LTV (CLTV)
A11: First lien balance ($) | B11: 200000
A12: Second lien / HELOC ($) | B12: 50000
A13: Property value ($) | B13: 300000
A14: CLTV | B14: =IF(B13=0,"n/a",(B11+B12)/B13)
A17: Debt Service Coverage Ratio (DSCR)
A18: Net operating income ($/yr) | B18: 120000
A19: Annual debt service ($/yr) | B19: 90000
A20: DSCR | B20: =IF(B19=0,"n/a",B18/B19)

Sheet ARM_Reset
A1: ARM Rate Reset
A2: Pure rate-cap calculator; plug the capped rate into a Segments row to model the resulting schedule.
A4: Is this the first reset? (Y/N) | B4: Y
A5: Previous rate (%) | B5: 5
A6: Initial (start) rate (%) | B6: 4
A7: Current index rate (%) | B7: 5.5
A8: Margin (%) | B8: 2.75
A9: Initial cap (pts, blank = none) | B9: 2
A10: Periodic cap (pts, blank = none) | B10: 2
A11: Lifetime cap (pts, blank = none) | B11: 5
A12: Remaining balance ($) | B12: 380000
A13: Remaining amortization (months) | B13: 300
A15: Fully-indexed rate (%) | B15: =B7+B8
A16: Capped rate (%) | B16: =MAX(0,MIN(IF(IF(B4="Y",B9,B10)="",B15,MIN(B15,B5+IF(B4="Y",B9,B10))),IF(B11="",B15,B6+B11)))
A17: New monthly payment | B17: =ROUND(-PMT(B16/100/12,B13,B12),2)

Sheet Fees_APR
A1: Fees & APR
A2: A simplified actuarial-method APR (via Excel's RATE function) -- not a certified TILA/Reg Z disclosure. See docs/new-req/002-fees-and-apr.md.
A4: Loan amount (note amount, $) | B4: 300000
A5: Annual interest rate / note rate (%) | B5: 6.5
A6: Term (months) | B6: 360
A9: Fee name | B9: Amount | C9: Financed? (Y/N)
A10: Origination fee | B10: 3000 | C10: N
A11: Application fee | B11: 500 | C11: N
A12: Appraisal | B12: 650 | C12: N
A18: Total fees | B18: =SUM($B$10:$B$16)
A19: Total financed fees | B19: =SUMIF($C$10:$C$16,"Y",$B$10:$B$16)
A20: Total cash fees | B20: =SUMIF($C$10:$C$16,"<>Y",$B$10:$B$16)-SUMIF($C$10:$C$16,"",$B$10:$B$16)
A21: Effective loan amount | B21: =B4+B19
A22: Monthly payment | B22: =ROUND(-PMT(B5/100/12,B6,B21),2)
A23: Amount financed | B23: =B21-B20
A24: APR (%) | B24: =IFERROR(RATE(B6,-B22,B23)*12*100,"n/a -- fees too large relative to loan")
A25: APR minus note rate (pts) | B25: =IFERROR(B24-B5,"n/a")

Sheet DTI_Affordability
A1: DTI & Affordability
A4: Check my DTI
A5: Gross monthly income ($) | B5: 9000
A6: Full housing payment ($/mo) | B6: 2200
A7: Other monthly debts ($) | B7: 500
A8: Front-end max (%) | B8: 28
A9: Back-end max (%) | B9: 36
A11: Front-end DTI | B11: =B6/B5
A12: Back-end DTI | B12: =(B6+B7)/B5
A13: Front-end OK? | B13: =B11<=B8/100
A14: Back-end OK? | B14: =B12<=B9/100
A15: Qualifies? | B15: =AND(B13,B14)
A18: How much can I afford
A19: Gross monthly income ($) | B19: 9000
A20: Other monthly debts ($) | B20: 500
A21: Annual interest rate (%) | B21: 6.5
A22: Term (months) | B22: 360
A23: Est. non-P&I housing costs ($/mo) | B23: 400
A24: Front-end max (%) | B24: 28
A25: Back-end max (%) | B25: 36
A26: Down payment ($) | B26: 60000
A28: Front-end allowance | B28: =B19*B24/100-B23
A29: Back-end allowance | B29: =B19*B25/100-B20-B23
A30: Max P&I payment | B30: =ROUND(MAX(0,MIN(B28,B29)),2)
A31: Binding constraint | B31: =IF(B28<=B29,"front_end","back_end")
A32: Max loan amount | B32: =IF(B30=0,0,ROUND(PV(B21/100/12,B22,-B30),2))
A33: Max home price | B33: =B32+B26
A34: Qualifies? | B34: =B30>0
