Workbook

Sheet COB_CA
A1: Canadian Cost of Borrowing (COB) Disclosure -- inputs & summary
A2: Borrower-facing COST-OF-BORROWING ESTIMATE, not a certified regulatory disclosure -- see docs/new-req/006-cost-of-borrowing-disclosure.md. Blue cells = edit; black = computed. Every input field stays visible for every Flow (no macros can hide/show fields) -- pick Flow/Product type/Rate type below, then read the four computed helper rows to see which date field, trigger-rate, compounding, and accrued-interest rules actually apply; unused fields for your Flow are simply ignored by the formulas.
A4: Flow / product / rate-type selection | D4: Frequency | E4: Payments/Yr
A5: Flow | B5: New mortgage | D5: monthly | E5: 12
A6: Product type | B6: mortgage | D6: semiMonthly | E6: 24
A7: Rate type | B7: variable | D7: biweekly | E7: 26
D8: weekly | E8: 52
A9: Date field used (per spec's Flow table) | B9: =IF(OR(B5="New mortgage",B5="New loan"),"Pre-approval date","Renewal date")
A10: Accrued-interest carry-forward applies? | B10: =IF(OR(B5="Existing mortgage",B5="Existing loan",B5="Payment change",B5="Variable rate payment change"),"Yes","No")
A11: Compounding convention (eq. 1 / eq. 2) | B11: =IF(AND(B6="mortgage",B7="fixed"),"Semi-annual (Interest Act s.6, CONFIRMED)","Monthly (best-available default, eq. 2)")
A12: Trigger rate computed? (mortgage + variable only) | B12: =IF(AND(B6="mortgage",B7="variable"),"Yes","No / N/A")
A14: Inputs -- common to every flow
A15: Loan amount ($) / current outstanding balance ($) | B15: 400000 | C15: New flows: the new loan/mortgage face amount. Existing/Payment-change flows: enter the CURRENT OUTSTANDING BALANCE here instead (same field, reused per spec).
A16: Contract rate, nominal annual (%) | B16: 5
A17: Payment frequency | B17: monthly
A18: Term years (CONTRACT TERM, not amortization) | B18: 5
A19: Term months (contract term, extra months) | B19: 0
A20: Remaining amortization years | B20: 25
A21: Remaining amortization months (extra) | B21: 0
A22: First payment date | B22: 2026-02-01
A23: End date (this term's maturity/renewal date) | B23: 2031-01-01
A25: Inputs -- flow-conditional
A26: Disbursal date (new flows only) | B26: 2026-01-15
A27: Pre-approval date (new mortgage / new loan only) | B27: 2025-12-01
A28: Renewal date (existing/payment-change flows only) | B28: 2026-01-01
A29: Accrued interest ($) -- existing/renewal flows only | B29: 0 | C29: Judgment call: capitalized into this term's opening balance when the carry-forward row above reads Yes -- see docs/new-req/006's Excel implementation notes.
A30: Semi-annual compounding reference date (fixed mortgages only) | B30: 2026-01-01 | C30: Display/reference only -- eq. 1's periodic-rate conversion does not depend on this date (see spec 006, equation 1). Not used in any formula below.
A32: Fees (equation 7's fee-inclusion list)
A33: Financed? and Included in COB? are INDEPENDENT flags (spec 006 eq. 7) -- e.g. a prepayment penalty or discharge fee is never included in cob_amount even if financed.
A35: Fee name | B35: Amount ($) | C35: Financed? (Y/N) | D35: Included in COB? (Y/N)
A36: Administrative charge | B36: 200 | C36: N | D36: Y
A37: Appraisal fee (lender-required) | B37: 400 | C37: N | D37: Y
A38: Broker fee (paid by lender to broker, included in amount borrowed) | B38: 500 | C38: Y | D38: Y
A39: Prepayment penalty | B39: 0 | C39: N | D39: N
A40: Discharge fee | B40: 0 | C40: N | D40: N
A41: Mortgage default insurance premium (high-ratio) | B41: 0 | C41: Y | D41: N
A43: Derived quantities
A44: Payments per year (n) | B44: =INDEX($E$5:$E$8,MATCH(B17,$D$5:$D$8,0))
A45: Periodic rate i_period (eq. 1 / eq. 2) | B45: =IF(AND(B6="mortgage",B7="fixed"),(1+B16/100/2)^(2/B44)-1,B16/100/B44)
A46: Total fees | B46: =SUM($B$36:$B$41)
A47: Total financed fees | B47: =SUMIF($C$36:$C$41,"Y",$B$36:$B$41)
A48: Total cash fees | B48: =B46-B47
A49: Total fees included in cob_amount (eq. 7 list) | B49: =SUMIF($D$36:$D$41,"Y",$B$36:$B$41)
A50: Disbursal amount (cash actually advanced) | B50: =B15+B47-B48 | C50: Per spec 006's resolved 'Financed fees' formulas (matching spec 002's effective_loan_amount/amount_financed exactly): financed fees layer ON TOP of loan_amount (never reduce disbursal); only cash fees reduce disbursal. See docs/new-req/006's Excel implementation notes.
A51: Accrued interest capitalized into this term's opening balance | B51: =IF(B10="Yes",B29,0)
A52: Amortized principal P0 (opening balance this term) | B52: =B15+B47+B51
A53: Term total months | B53: =(B18*12+B19)
A54: Term, years (T, eq. 6, 2dp) | B54: =ROUND(B53/12,2)
A55: Remaining amortization total months | B55: =(B20*12+B21)
A56: Remaining amortization total periods (n in eq. 3) | B56: =ROUND(B55/12*B44,0)
A57: Term length, periods (raw, before clamping to remaining amortization) | B57: =ROUND(B53/12*B44,0)
A58: Term length, periods (schedule bound, clamped) | B58: =MIN(B57,B56) | C58: Clamped so a term can never run longer than remaining amortization. Bounded to 520 schedule rows -- see COB_CA_Schedule.
A59: Payment amount (eq. 3 -- always an OUTPUT, never entered) | B59: =ROUND(-PMT(B45,B56,B52),2)
A60: Trigger rate % (eq. 4 -- mortgage + variable only) | B60: =IF(B12="Yes",ROUND(B59*B44/B52*100,4),"N/A") | C60: total_borrowed = current outstanding balance = P0 above (== loan_amount for a brand-new disbursal, == the current-balance input for existing/renewal/payment-change flows).
A61: (helper) first_payment_date + term_total_months, whole-month date | B61: =DATE(YEAR(B22)+INT((MONTH(B22)-1+B53)/12),MOD(MONTH(B22)-1+B53,12)+1,1)+(DAY(B22)-1) | C61: Explicit month-rollover arithmetic (not EDATE), matching this project's other date formulas -- see docs/new-req/005.
A62: term_days (eq. 8, DISPLAY ONLY -- never feeds any monetary formula) | B62: =B23-B61
A64: Outputs -- scoped to the current contract term only
A65: number_of_payments | B65: =COUNTIF(COB_CA_Schedule!$H$5:$H$524,TRUE)
A66: total_payment | B66: =SUMIFS(COB_CA_Schedule!$F$5:$F$524,COB_CA_Schedule!$H$5:$H$524,TRUE)
A67: total_interest | B67: =SUMIFS(COB_CA_Schedule!$D$5:$D$524,COB_CA_Schedule!$H$5:$H$524,TRUE)
A68: principal_payment (== total_payment - total_interest, eq. 5) | B68: =B66-B67
A69: Ending balance at term maturity (next renewal's opening balance) | B69: =IFERROR(INDEX(COB_CA_Schedule!$G$5:$G$524,MATCH(B58,COB_CA_Schedule!$A$5:$A$524,0)),"n/a")
A70: P: average outstanding balance per period (eq. 6) | B70: =IF(B65=0,0,SUMPRODUCT((COB_CA_Schedule!$H$5:$H$524)*(COB_CA_Schedule!$C$5:$C$524))/B65) | C70: Average, across this term's counted periods, of the balance outstanding at the END of each period BEFORE that period's payment is subtracted -- i.e. each period's beginning balance (interest accrues on it before the payment is applied). Per Financial Consumer Protection Framework Regulations SOR/2021-181 s.47(1).
A71: cob_amount = total_interest + fees included in COB (eq. 7) | B71: =B67+B49
A72: cob_rate_percent = (C/(T*P))*100 (eq. 6) | B72: =IF(OR(B54=0,B70=0),"n/a",ROUND(B71/(B54*B70)*100,4)) | C72: Regulatory average-outstanding-balance formula (Financial Consumer Protection Framework Regulations SOR/2021-181 ss.47-48) -- deliberately NOT spec 002's IRR/actuarial APR solve.
A74: Optional: COB_Calculator_CA_macros.bas (in this folder) adds a chart of the schedule above plus a one-click disclosure-summary PDF export -- see COB-xlsx/MANUAL.md, "COB_CA macros", for how to import it (requires saving this file as a macro-enabled .xlsm; not required to use any of the formulas on this sheet).

Sheet COB_CA_Schedule
A1: COB_CA amortization schedule (computed) -- do not edit
A2: One row per period within the CURRENT CONTRACT TERM ONLY (not the full amortization) -- bounded to 520 rows. Rows past the term's own length (COB_CA!B58) freeze at the term's own ending balance; rows past an early full payoff (rare -- only if remaining amortization is shorter than the term) read $0, same self-stabilizing technique used throughout COB_Calculator.xlsx (see docs/new-req/005).
A4: Period # | B4: Period Date | C4: Beginning Balance | D4: Interest | E4: Principal | F4: Payment | G4: Ending Balance | H4: Counted in term totals?
A5: 1 | B5: =IF(COB_CA!$B$44=12,DATE(YEAR(COB_CA!$B$22)+INT((MONTH(COB_CA!$B$22)-1+0)/12),MOD(MONTH(COB_CA!$B$22)-1+0,12)+1,1)+(DAY(COB_CA!$B$22)-1),IF(COB_CA!$B$44=24,COB_CA!$B$22+ROUND((0*365.25)/24,0),IF(COB_CA!$B$44=26,COB_CA!$B$22+0,COB_CA!$B$22+0))) | C5: =COB_CA!$B$52 | D5: =IF((A5<=COB_CA!$B$58),ROUND(C5*COB_CA!$B$45,2),0) | E5: =IF((A5<=COB_CA!$B$58),IF(AND((A5<=COB_CA!$B$58),ROUND(C5-ROUND(COB_CA!$B$59-D5,2),2)<=0),C5,ROUND(COB_CA!$B$59-D5,2)),0) | F5: =IF((A5<=COB_CA!$B$58),IF(AND((A5<=COB_CA!$B$58),ROUND(C5-ROUND(COB_CA!$B$59-D5,2),2)<=0),ROUND(D5+E5,2),COB_CA!$B$59),0) | G5: =IF((A5<=COB_CA!$B$58),IF(AND((A5<=COB_CA!$B$58),ROUND(C5-ROUND(COB_CA!$B$59-D5,2),2)<=0),0,ROUND(C5-E5,2)),C5) | H5: =(A5<=COB_CA!$B$58)
A6: 2 | B6: =IF(COB_CA!$B$44=12,DATE(YEAR(COB_CA!$B$22)+INT((MONTH(COB_CA!$B$22)-1+1)/12),MOD(MONTH(COB_CA!$B$22)-1+1,12)+1,1)+(DAY(COB_CA!$B$22)-1),IF(COB_CA!$B$44=24,COB_CA!$B$22+ROUND((1*365.25)/24,0),IF(COB_CA!$B$44=26,COB_CA!$B$22+14,COB_CA!$B$22+7))) | C6: =G5 | D6: =IF((A6<=COB_CA!$B$58),ROUND(C6*COB_CA!$B$45,2),0) | E6: =IF((A6<=COB_CA!$B$58),IF(AND((A6<=COB_CA!$B$58),ROUND(C6-ROUND(COB_CA!$B$59-D6,2),2)<=0),C6,ROUND(COB_CA!$B$59-D6,2)),0) | F6: =IF((A6<=COB_CA!$B$58),IF(AND((A6<=COB_CA!$B$58),ROUND(C6-ROUND(COB_CA!$B$59-D6,2),2)<=0),ROUND(D6+E6,2),COB_CA!$B$59),0) | G6: =IF((A6<=COB_CA!$B$58),IF(AND((A6<=COB_CA!$B$58),ROUND(C6-ROUND(COB_CA!$B$59-D6,2),2)<=0),0,ROUND(C6-E6,2)),C6) | H6: =AND(H5,C5>0,(A6<=COB_CA!$B$58))
A7: 3 | B7: =IF(COB_CA!$B$44=12,DATE(YEAR(COB_CA!$B$22)+INT((MONTH(COB_CA!$B$22)-1+2)/12),MOD(MONTH(COB_CA!$B$22)-1+2,12)+1,1)+(DAY(COB_CA!$B$22)-1),IF(COB_CA!$B$44=24,COB_CA!$B$22+ROUND((2*365.25)/24,0),IF(COB_CA!$B$44=26,COB_CA!$B$22+28,COB_CA!$B$22+14))) | C7: =G6 | D7: =IF((A7<=COB_CA!$B$58),ROUND(C7*COB_CA!$B$45,2),0) | E7: =IF((A7<=COB_CA!$B$58),IF(AND((A7<=COB_CA!$B$58),ROUND(C7-ROUND(COB_CA!$B$59-D7,2),2)<=0),C7,ROUND(COB_CA!$B$59-D7,2)),0) | F7: =IF((A7<=COB_CA!$B$58),IF(AND((A7<=COB_CA!$B$58),ROUND(C7-ROUND(COB_CA!$B$59-D7,2),2)<=0),ROUND(D7+E7,2),COB_CA!$B$59),0) | G7: =IF((A7<=COB_CA!$B$58),IF(AND((A7<=COB_CA!$B$58),ROUND(C7-ROUND(COB_CA!$B$59-D7,2),2)<=0),0,ROUND(C7-E7,2)),C7) | H7: =AND(H6,C6>0,(A7<=COB_CA!$B$58))
A8: 4 | B8: =IF(COB_CA!$B$44=12,DATE(YEAR(COB_CA!$B$22)+INT((MONTH(COB_CA!$B$22)-1+3)/12),MOD(MONTH(COB_CA!$B$22)-1+3,12)+1,1)+(DAY(COB_CA!$B$22)-1),IF(COB_CA!$B$44=24,COB_CA!$B$22+ROUND((3*365.25)/24,0),IF(COB_CA!$B$44=26,COB_CA!$B$22+42,COB_CA!$B$22+21))) | C8: =G7 | D8: =IF((A8<=COB_CA!$B$58),ROUND(C8*COB_CA!$B$45,2),0) | E8: =IF((A8<=COB_CA!$B$58),IF(AND((A8<=COB_CA!$B$58),ROUND(C8-ROUND(COB_CA!$B$59-D8,2),2)<=0),C8,ROUND(COB_CA!$B$59-D8,2)),0) | F8: =IF((A8<=COB_CA!$B$58),IF(AND((A8<=COB_CA!$B$58),ROUND(C8-ROUND(COB_CA!$B$59-D8,2),2)<=0),ROUND(D8+E8,2),COB_CA!$B$59),0) | G8: =IF((A8<=COB_CA!$B$58),IF(AND((A8<=COB_CA!$B$58),ROUND(C8-ROUND(COB_CA!$B$59-D8,2),2)<=0),0,ROUND(C8-E8,2)),C8) | H8: =AND(H7,C7>0,(A8<=COB_CA!$B$58))
A9: 5 | B9: =IF(COB_CA!$B$44=12,DATE(YEAR(COB_CA!$B$22)+INT((MONTH(COB_CA!$B$22)-1+4)/12),MOD(MONTH(COB_CA!$B$22)-1+4,12)+1,1)+(DAY(COB_CA!$B$22)-1),IF(COB_CA!$B$44=24,COB_CA!$B$22+ROUND((4*365.25)/24,0),IF(COB_CA!$B$44=26,COB_CA!$B$22+56,COB_CA!$B$22+28))) | C9: =G8 | D9: =IF((A9<=COB_CA!$B$58),ROUND(C9*COB_CA!$B$45,2),0) | E9: =IF((A9<=COB_CA!$B$58),IF(AND((A9<=COB_CA!$B$58),ROUND(C9-ROUND(COB_CA!$B$59-D9,2),2)<=0),C9,ROUND(COB_CA!$B$59-D9,2)),0) | F9: =IF((A9<=COB_CA!$B$58),IF(AND((A9<=COB_CA!$B$58),ROUND(C9-ROUND(COB_CA!$B$59-D9,2),2)<=0),ROUND(D9+E9,2),COB_CA!$B$59),0) | G9: =IF((A9<=COB_CA!$B$58),IF(AND((A9<=COB_CA!$B$58),ROUND(C9-ROUND(COB_CA!$B$59-D9,2),2)<=0),0,ROUND(C9-E9,2)),C9) | H9: =AND(H8,C8>0,(A9<=COB_CA!$B$58))
A10: 6 | B10: =IF(COB_CA!$B$44=12,DATE(YEAR(COB_CA!$B$22)+INT((MONTH(COB_CA!$B$22)-1+5)/12),MOD(MONTH(COB_CA!$B$22)-1+5,12)+1,1)+(DAY(COB_CA!$B$22)-1),IF(COB_CA!$B$44=24,COB_CA!$B$22+ROUND((5*365.25)/24,0),IF(COB_CA!$B$44=26,COB_CA!$B$22+70,COB_CA!$B$22+35))) | C10: =G9 | D10: =IF((A10<=COB_CA!$B$58),ROUND(C10*COB_CA!$B$45,2),0) | E10: =IF((A10<=COB_CA!$B$58),IF(AND((A10<=COB_CA!$B$58),ROUND(C10-ROUND(COB_CA!$B$59-D10,2),2)<=0),C10,ROUND(COB_CA!$B$59-D10,2)),0) | F10: =IF((A10<=COB_CA!$B$58),IF(AND((A10<=COB_CA!$B$58),ROUND(C10-ROUND(COB_CA!$B$59-D10,2),2)<=0),ROUND(D10+E10,2),COB_CA!$B$59),0) | G10: =IF((A10<=COB_CA!$B$58),IF(AND((A10<=COB_CA!$B$58),ROUND(C10-ROUND(COB_CA!$B$59-D10,2),2)<=0),0,ROUND(C10-E10,2)),C10) | H10: =AND(H9,C9>0,(A10<=COB_CA!$B$58))
A11: 7 | B11: =IF(COB_CA!$B$44=12,DATE(YEAR(COB_CA!$B$22)+INT((MONTH(COB_CA!$B$22)-1+6)/12),MOD(MONTH(COB_CA!$B$22)-1+6,12)+1,1)+(DAY(COB_CA!$B$22)-1),IF(COB_CA!$B$44=24,COB_CA!$B$22+ROUND((6*365.25)/24,0),IF(COB_CA!$B$44=26,COB_CA!$B$22+84,COB_CA!$B$22+42))) | C11: =G10 | D11: =IF((A11<=COB_CA!$B$58),ROUND(C11*COB_CA!$B$45,2),0) | E11: =IF((A11<=COB_CA!$B$58),IF(AND((A11<=COB_CA!$B$58),ROUND(C11-ROUND(COB_CA!$B$59-D11,2),2)<=0),C11,ROUND(COB_CA!$B$59-D11,2)),0) | F11: =IF((A11<=COB_CA!$B$58),IF(AND((A11<=COB_CA!$B$58),ROUND(C11-ROUND(COB_CA!$B$59-D11,2),2)<=0),ROUND(D11+E11,2),COB_CA!$B$59),0) | G11: =IF((A11<=COB_CA!$B$58),IF(AND((A11<=COB_CA!$B$58),ROUND(C11-ROUND(COB_CA!$B$59-D11,2),2)<=0),0,ROUND(C11-E11,2)),C11) | H11: =AND(H10,C10>0,(A11<=COB_CA!$B$58))
A12: 8 | B12: =IF(COB_CA!$B$44=12,DATE(YEAR(COB_CA!$B$22)+INT((MONTH(COB_CA!$B$22)-1+7)/12),MOD(MONTH(COB_CA!$B$22)-1+7,12)+1,1)+(DAY(COB_CA!$B$22)-1),IF(COB_CA!$B$44=24,COB_CA!$B$22+ROUND((7*365.25)/24,0),IF(COB_CA!$B$44=26,COB_CA!$B$22+98,COB_CA!$B$22+49))) | C12: =G11 | D12: =IF((A12<=COB_CA!$B$58),ROUND(C12*COB_CA!$B$45,2),0) | E12: =IF((A12<=COB_CA!$B$58),IF(AND((A12<=COB_CA!$B$58),ROUND(C12-ROUND(COB_CA!$B$59-D12,2),2)<=0),C12,ROUND(COB_CA!$B$59-D12,2)),0) | F12: =IF((A12<=COB_CA!$B$58),IF(AND((A12<=COB_CA!$B$58),ROUND(C12-ROUND(COB_CA!$B$59-D12,2),2)<=0),ROUND(D12+E12,2),COB_CA!$B$59),0) | G12: =IF((A12<=COB_CA!$B$58),IF(AND((A12<=COB_CA!$B$58),ROUND(C12-ROUND(COB_CA!$B$59-D12,2),2)<=0),0,ROUND(C12-E12,2)),C12) | H12: =AND(H11,C11>0,(A12<=COB_CA!$B$58))
A13: 9 | B13: =IF(COB_CA!$B$44=12,DATE(YEAR(COB_CA!$B$22)+INT((MONTH(COB_CA!$B$22)-1+8)/12),MOD(MONTH(COB_CA!$B$22)-1+8,12)+1,1)+(DAY(COB_CA!$B$22)-1),IF(COB_CA!$B$44=24,COB_CA!$B$22+ROUND((8*365.25)/24,0),IF(COB_CA!$B$44=26,COB_CA!$B$22+112,COB_CA!$B$22+56))) | C13: =G12 | D13: =IF((A13<=COB_CA!$B$58),ROUND(C13*COB_CA!$B$45,2),0) | E13: =IF((A13<=COB_CA!$B$58),IF(AND((A13<=COB_CA!$B$58),ROUND(C13-ROUND(COB_CA!$B$59-D13,2),2)<=0),C13,ROUND(COB_CA!$B$59-D13,2)),0) | F13: =IF((A13<=COB_CA!$B$58),IF(AND((A13<=COB_CA!$B$58),ROUND(C13-ROUND(COB_CA!$B$59-D13,2),2)<=0),ROUND(D13+E13,2),COB_CA!$B$59),0) | G13: =IF((A13<=COB_CA!$B$58),IF(AND((A13<=COB_CA!$B$58),ROUND(C13-ROUND(COB_CA!$B$59-D13,2),2)<=0),0,ROUND(C13-E13,2)),C13) | H13: =AND(H12,C12>0,(A13<=COB_CA!$B$58))
A14: 10 | B14: =IF(COB_CA!$B$44=12,DATE(YEAR(COB_CA!$B$22)+INT((MONTH(COB_CA!$B$22)-1+9)/12),MOD(MONTH(COB_CA!$B$22)-1+9,12)+1,1)+(DAY(COB_CA!$B$22)-1),IF(COB_CA!$B$44=24,COB_CA!$B$22+ROUND((9*365.25)/24,0),IF(COB_CA!$B$44=26,COB_CA!$B$22+126,COB_CA!$B$22+63))) | C14: =G13 | D14: =IF((A14<=COB_CA!$B$58),ROUND(C14*COB_CA!$B$45,2),0) | E14: =IF((A14<=COB_CA!$B$58),IF(AND((A14<=COB_CA!$B$58),ROUND(C14-ROUND(COB_CA!$B$59-D14,2),2)<=0),C14,ROUND(COB_CA!$B$59-D14,2)),0) | F14: =IF((A14<=COB_CA!$B$58),IF(AND((A14<=COB_CA!$B$58),ROUND(C14-ROUND(COB_CA!$B$59-D14,2),2)<=0),ROUND(D14+E14,2),COB_CA!$B$59),0) | G14: =IF((A14<=COB_CA!$B$58),IF(AND((A14<=COB_CA!$B$58),ROUND(C14-ROUND(COB_CA!$B$59-D14,2),2)<=0),0,ROUND(C14-E14,2)),C14) | H14: =AND(H13,C13>0,(A14<=COB_CA!$B$58))
A15: 11 | B15: =IF(COB_CA!$B$44=12,DATE(YEAR(COB_CA!$B$22)+INT((MONTH(COB_CA!$B$22)-1+10)/12),MOD(MONTH(COB_CA!$B$22)-1+10,12)+1,1)+(DAY(COB_CA!$B$22)-1),IF(COB_CA!$B$44=24,COB_CA!$B$22+ROUND((10*365.25)/24,0),IF(COB_CA!$B$44=26,COB_CA!$B$22+140,COB_CA!$B$22+70))) | C15: =G14 | D15: =IF((A15<=COB_CA!$B$58),ROUND(C15*COB_CA!$B$45,2),0) | E15: =IF((A15<=COB_CA!$B$58),IF(AND((A15<=COB_CA!$B$58),ROUND(C15-ROUND(COB_CA!$B$59-D15,2),2)<=0),C15,ROUND(COB_CA!$B$59-D15,2)),0) | F15: =IF((A15<=COB_CA!$B$58),IF(AND((A15<=COB_CA!$B$58),ROUND(C15-ROUND(COB_CA!$B$59-D15,2),2)<=0),ROUND(D15+E15,2),COB_CA!$B$59),0) | G15: =IF((A15<=COB_CA!$B$58),IF(AND((A15<=COB_CA!$B$58),ROUND(C15-ROUND(COB_CA!$B$59-D15,2),2)<=0),0,ROUND(C15-E15,2)),C15) | H15: =AND(H14,C14>0,(A15<=COB_CA!$B$58))
A16: 12 | B16: =IF(COB_CA!$B$44=12,DATE(YEAR(COB_CA!$B$22)+INT((MONTH(COB_CA!$B$22)-1+11)/12),MOD(MONTH(COB_CA!$B$22)-1+11,12)+1,1)+(DAY(COB_CA!$B$22)-1),IF(COB_CA!$B$44=24,COB_CA!$B$22+ROUND((11*365.25)/24,0),IF(COB_CA!$B$44=26,COB_CA!$B$22+154,COB_CA!$B$22+77))) | C16: =G15 | D16: =IF((A16<=COB_CA!$B$58),ROUND(C16*COB_CA!$B$45,2),0) | E16: =IF((A16<=COB_CA!$B$58),IF(AND((A16<=COB_CA!$B$58),ROUND(C16-ROUND(COB_CA!$B$59-D16,2),2)<=0),C16,ROUND(COB_CA!$B$59-D16,2)),0) | F16: =IF((A16<=COB_CA!$B$58),IF(AND((A16<=COB_CA!$B$58),ROUND(C16-ROUND(COB_CA!$B$59-D16,2),2)<=0),ROUND(D16+E16,2),COB_CA!$B$59),0) | G16: =IF((A16<=COB_CA!$B$58),IF(AND((A16<=COB_CA!$B$58),ROUND(C16-ROUND(COB_CA!$B$59-D16,2),2)<=0),0,ROUND(C16-E16,2)),C16) | H16: =AND(H15,C15>0,(A16<=COB_CA!$B$58))
A17: 13 | B17: =IF(COB_CA!$B$44=12,DATE(YEAR(COB_CA!$B$22)+INT((MONTH(COB_CA!$B$22)-1+12)/12),MOD(MONTH(COB_CA!$B$22)-1+12,12)+1,1)+(DAY(COB_CA!$B$22)-1),IF(COB_CA!$B$44=24,COB_CA!$B$22+ROUND((12*365.25)/24,0),IF(COB_CA!$B$44=26,COB_CA!$B$22+168,COB_CA!$B$22+84))) | C17: =G16 | D17: =IF((A17<=COB_CA!$B$58),ROUND(C17*COB_CA!$B$45,2),0) | E17: =IF((A17<=COB_CA!$B$58),IF(AND((A17<=COB_CA!$B$58),ROUND(C17-ROUND(COB_CA!$B$59-D17,2),2)<=0),C17,ROUND(COB_CA!$B$59-D17,2)),0) | F17: =IF((A17<=COB_CA!$B$58),IF(AND((A17<=COB_CA!$B$58),ROUND(C17-ROUND(COB_CA!$B$59-D17,2),2)<=0),ROUND(D17+E17,2),COB_CA!$B$59),0) | G17: =IF((A17<=COB_CA!$B$58),IF(AND((A17<=COB_CA!$B$58),ROUND(C17-ROUND(COB_CA!$B$59-D17,2),2)<=0),0,ROUND(C17-E17,2)),C17) | H17: =AND(H16,C16>0,(A17<=COB_CA!$B$58))
A18: 14 | B18: =IF(COB_CA!$B$44=12,DATE(YEAR(COB_CA!$B$22)+INT((MONTH(COB_CA!$B$22)-1+13)/12),MOD(MONTH(COB_CA!$B$22)-1+13,12)+1,1)+(DAY(COB_CA!$B$22)-1),IF(COB_CA!$B$44=24,COB_CA!$B$22+ROUND((13*365.25)/24,0),IF(COB_CA!$B$44=26,COB_CA!$B$22+182,COB_CA!$B$22+91))) | C18: =G17 | D18: =IF((A18<=COB_CA!$B$58),ROUND(C18*COB_CA!$B$45,2),0) | E18: =IF((A18<=COB_CA!$B$58),IF(AND((A18<=COB_CA!$B$58),ROUND(C18-ROUND(COB_CA!$B$59-D18,2),2)<=0),C18,ROUND(COB_CA!$B$59-D18,2)),0) | F18: =IF((A18<=COB_CA!$B$58),IF(AND((A18<=COB_CA!$B$58),ROUND(C18-ROUND(COB_CA!$B$59-D18,2),2)<=0),ROUND(D18+E18,2),COB_CA!$B$59),0) | G18: =IF((A18<=COB_CA!$B$58),IF(AND((A18<=COB_CA!$B$58),ROUND(C18-ROUND(COB_CA!$B$59-D18,2),2)<=0),0,ROUND(C18-E18,2)),C18) | H18: =AND(H17,C17>0,(A18<=COB_CA!$B$58))
A19: 15 | B19: =IF(COB_CA!$B$44=12,DATE(YEAR(COB_CA!$B$22)+INT((MONTH(COB_CA!$B$22)-1+14)/12),MOD(MONTH(COB_CA!$B$22)-1+14,12)+1,1)+(DAY(COB_CA!$B$22)-1),IF(COB_CA!$B$44=24,COB_CA!$B$22+ROUND((14*365.25)/24,0),IF(COB_CA!$B$44=26,COB_CA!$B$22+196,COB_CA!$B$22+98))) | C19: =G18 | D19: =IF((A19<=COB_CA!$B$58),ROUND(C19*COB_CA!$B$45,2),0) | E19: =IF((A19<=COB_CA!$B$58),IF(AND((A19<=COB_CA!$B$58),ROUND(C19-ROUND(COB_CA!$B$59-D19,2),2)<=0),C19,ROUND(COB_CA!$B$59-D19,2)),0) | F19: =IF((A19<=COB_CA!$B$58),IF(AND((A19<=COB_CA!$B$58),ROUND(C19-ROUND(COB_CA!$B$59-D19,2),2)<=0),ROUND(D19+E19,2),COB_CA!$B$59),0) | G19: =IF((A19<=COB_CA!$B$58),IF(AND((A19<=COB_CA!$B$58),ROUND(C19-ROUND(COB_CA!$B$59-D19,2),2)<=0),0,ROUND(C19-E19,2)),C19) | H19: =AND(H18,C18>0,(A19<=COB_CA!$B$58))
A20: 16 | B20: =IF(COB_CA!$B$44=12,DATE(YEAR(COB_CA!$B$22)+INT((MONTH(COB_CA!$B$22)-1+15)/12),MOD(MONTH(COB_CA!$B$22)-1+15,12)+1,1)+(DAY(COB_CA!$B$22)-1),IF(COB_CA!$B$44=24,COB_CA!$B$22+ROUND((15*365.25)/24,0),IF(COB_CA!$B$44=26,COB_CA!$B$22+210,COB_CA!$B$22+105))) | C20: =G19 | D20: =IF((A20<=COB_CA!$B$58),ROUND(C20*COB_CA!$B$45,2),0) | E20: =IF((A20<=COB_CA!$B$58),IF(AND((A20<=COB_CA!$B$58),ROUND(C20-ROUND(COB_CA!$B$59-D20,2),2)<=0),C20,ROUND(COB_CA!$B$59-D20,2)),0) | F20: =IF((A20<=COB_CA!$B$58),IF(AND((A20<=COB_CA!$B$58),ROUND(C20-ROUND(COB_CA!$B$59-D20,2),2)<=0),ROUND(D20+E20,2),COB_CA!$B$59),0) | G20: =IF((A20<=COB_CA!$B$58),IF(AND((A20<=COB_CA!$B$58),ROUND(C20-ROUND(COB_CA!$B$59-D20,2),2)<=0),0,ROUND(C20-E20,2)),C20) | H20: =AND(H19,C19>0,(A20<=COB_CA!$B$58))
A21: 17 | B21: =IF(COB_CA!$B$44=12,DATE(YEAR(COB_CA!$B$22)+INT((MONTH(COB_CA!$B$22)-1+16)/12),MOD(MONTH(COB_CA!$B$22)-1+16,12)+1,1)+(DAY(COB_CA!$B$22)-1),IF(COB_CA!$B$44=24,COB_CA!$B$22+ROUND((16*365.25)/24,0),IF(COB_CA!$B$44=26,COB_CA!$B$22+224,COB_CA!$B$22+112))) | C21: =G20 | D21: =IF((A21<=COB_CA!$B$58),ROUND(C21*COB_CA!$B$45,2),0) | E21: =IF((A21<=COB_CA!$B$58),IF(AND((A21<=COB_CA!$B$58),ROUND(C21-ROUND(COB_CA!$B$59-D21,2),2)<=0),C21,ROUND(COB_CA!$B$59-D21,2)),0) | F21: =IF((A21<=COB_CA!$B$58),IF(AND((A21<=COB_CA!$B$58),ROUND(C21-ROUND(COB_CA!$B$59-D21,2),2)<=0),ROUND(D21+E21,2),COB_CA!$B$59),0) | G21: =IF((A21<=COB_CA!$B$58),IF(AND((A21<=COB_CA!$B$58),ROUND(C21-ROUND(COB_CA!$B$59-D21,2),2)<=0),0,ROUND(C21-E21,2)),C21) | H21: =AND(H20,C20>0,(A21<=COB_CA!$B$58))
A22: 18 | B22: =IF(COB_CA!$B$44=12,DATE(YEAR(COB_CA!$B$22)+INT((MONTH(COB_CA!$B$22)-1+17)/12),MOD(MONTH(COB_CA!$B$22)-1+17,12)+1,1)+(DAY(COB_CA!$B$22)-1),IF(COB_CA!$B$44=24,COB_CA!$B$22+ROUND((17*365.25)/24,0),IF(COB_CA!$B$44=26,COB_CA!$B$22+238,COB_CA!$B$22+119))) | C22: =G21 | D22: =IF((A22<=COB_CA!$B$58),ROUND(C22*COB_CA!$B$45,2),0) | E22: =IF((A22<=COB_CA!$B$58),IF(AND((A22<=COB_CA!$B$58),ROUND(C22-ROUND(COB_CA!$B$59-D22,2),2)<=0),C22,ROUND(COB_CA!$B$59-D22,2)),0) | F22: =IF((A22<=COB_CA!$B$58),IF(AND((A22<=COB_CA!$B$58),ROUND(C22-ROUND(COB_CA!$B$59-D22,2),2)<=0),ROUND(D22+E22,2),COB_CA!$B$59),0) | G22: =IF((A22<=COB_CA!$B$58),IF(AND((A22<=COB_CA!$B$58),ROUND(C22-ROUND(COB_CA!$B$59-D22,2),2)<=0),0,ROUND(C22-E22,2)),C22) | H22: =AND(H21,C21>0,(A22<=COB_CA!$B$58))
A23: 19 | B23: =IF(COB_CA!$B$44=12,DATE(YEAR(COB_CA!$B$22)+INT((MONTH(COB_CA!$B$22)-1+18)/12),MOD(MONTH(COB_CA!$B$22)-1+18,12)+1,1)+(DAY(COB_CA!$B$22)-1),IF(COB_CA!$B$44=24,COB_CA!$B$22+ROUND((18*365.25)/24,0),IF(COB_CA!$B$44=26,COB_CA!$B$22+252,COB_CA!$B$22+126))) | C23: =G22 | D23: =IF((A23<=COB_CA!$B$58),ROUND(C23*COB_CA!$B$45,2),0) | E23: =IF((A23<=COB_CA!$B$58),IF(AND((A23<=COB_CA!$B$58),ROUND(C23-ROUND(COB_CA!$B$59-D23,2),2)<=0),C23,ROUND(COB_CA!$B$59-D23,2)),0) | F23: =IF((A23<=COB_CA!$B$58),IF(AND((A23<=COB_CA!$B$58),ROUND(C23-ROUND(COB_CA!$B$59-D23,2),2)<=0),ROUND(D23+E23,2),COB_CA!$B$59),0) | G23: =IF((A23<=COB_CA!$B$58),IF(AND((A23<=COB_CA!$B$58),ROUND(C23-ROUND(COB_CA!$B$59-D23,2),2)<=0),0,ROUND(C23-E23,2)),C23) | H23: =AND(H22,C22>0,(A23<=COB_CA!$B$58))
A24: 20 | B24: =IF(COB_CA!$B$44=12,DATE(YEAR(COB_CA!$B$22)+INT((MONTH(COB_CA!$B$22)-1+19)/12),MOD(MONTH(COB_CA!$B$22)-1+19,12)+1,1)+(DAY(COB_CA!$B$22)-1),IF(COB_CA!$B$44=24,COB_CA!$B$22+ROUND((19*365.25)/24,0),IF(COB_CA!$B$44=26,COB_CA!$B$22+266,COB_CA!$B$22+133))) | C24: =G23 | D24: =IF((A24<=COB_CA!$B$58),ROUND(C24*COB_CA!$B$45,2),0) | E24: =IF((A24<=COB_CA!$B$58),IF(AND((A24<=COB_CA!$B$58),ROUND(C24-ROUND(COB_CA!$B$59-D24,2),2)<=0),C24,ROUND(COB_CA!$B$59-D24,2)),0) | F24: =IF((A24<=COB_CA!$B$58),IF(AND((A24<=COB_CA!$B$58),ROUND(C24-ROUND(COB_CA!$B$59-D24,2),2)<=0),ROUND(D24+E24,2),COB_CA!$B$59),0) | G24: =IF((A24<=COB_CA!$B$58),IF(AND((A24<=COB_CA!$B$58),ROUND(C24-ROUND(COB_CA!$B$59-D24,2),2)<=0),0,ROUND(C24-E24,2)),C24) | H24: =AND(H23,C23>0,(A24<=COB_CA!$B$58))
A25: 21 | B25: =IF(COB_CA!$B$44=12,DATE(YEAR(COB_CA!$B$22)+INT((MONTH(COB_CA!$B$22)-1+20)/12),MOD(MONTH(COB_CA!$B$22)-1+20,12)+1,1)+(DAY(COB_CA!$B$22)-1),IF(COB_CA!$B$44=24,COB_CA!$B$22+ROUND((20*365.25)/24,0),IF(COB_CA!$B$44=26,COB_CA!$B$22+280,COB_CA!$B$22+140))) | C25: =G24 | D25: =IF((A25<=COB_CA!$B$58),ROUND(C25*COB_CA!$B$45,2),0) | E25: =IF((A25<=COB_CA!$B$58),IF(AND((A25<=COB_CA!$B$58),ROUND(C25-ROUND(COB_CA!$B$59-D25,2),2)<=0),C25,ROUND(COB_CA!$B$59-D25,2)),0) | F25: =IF((A25<=COB_CA!$B$58),IF(AND((A25<=COB_CA!$B$58),ROUND(C25-ROUND(COB_CA!$B$59-D25,2),2)<=0),ROUND(D25+E25,2),COB_CA!$B$59),0) | G25: =IF((A25<=COB_CA!$B$58),IF(AND((A25<=COB_CA!$B$58),ROUND(C25-ROUND(COB_CA!$B$59-D25,2),2)<=0),0,ROUND(C25-E25,2)),C25) | H25: =AND(H24,C24>0,(A25<=COB_CA!$B$58))
A26: 22 | B26: =IF(COB_CA!$B$44=12,DATE(YEAR(COB_CA!$B$22)+INT((MONTH(COB_CA!$B$22)-1+21)/12),MOD(MONTH(COB_CA!$B$22)-1+21,12)+1,1)+(DAY(COB_CA!$B$22)-1),IF(COB_CA!$B$44=24,COB_CA!$B$22+ROUND((21*365.25)/24,0),IF(COB_CA!$B$44=26,COB_CA!$B$22+294,COB_CA!$B$22+147))) | C26: =G25 | D26: =IF((A26<=COB_CA!$B$58),ROUND(C26*COB_CA!$B$45,2),0) | E26: =IF((A26<=COB_CA!$B$58),IF(AND((A26<=COB_CA!$B$58),ROUND(C26-ROUND(COB_CA!$B$59-D26,2),2)<=0),C26,ROUND(COB_CA!$B$59-D26,2)),0) | F26: =IF((A26<=COB_CA!$B$58),IF(AND((A26<=COB_CA!$B$58),ROUND(C26-ROUND(COB_CA!$B$59-D26,2),2)<=0),ROUND(D26+E26,2),COB_CA!$B$59),0) | G26: =IF((A26<=COB_CA!$B$58),IF(AND((A26<=COB_CA!$B$58),ROUND(C26-ROUND(COB_CA!$B$59-D26,2),2)<=0),0,ROUND(C26-E26,2)),C26) | H26: =AND(H25,C25>0,(A26<=COB_CA!$B$58))
A27: 23 | B27: =IF(COB_CA!$B$44=12,DATE(YEAR(COB_CA!$B$22)+INT((MONTH(COB_CA!$B$22)-1+22)/12),MOD(MONTH(COB_CA!$B$22)-1+22,12)+1,1)+(DAY(COB_CA!$B$22)-1),IF(COB_CA!$B$44=24,COB_CA!$B$22+ROUND((22*365.25)/24,0),IF(COB_CA!$B$44=26,COB_CA!$B$22+308,COB_CA!$B$22+154))) | C27: =G26 | D27: =IF((A27<=COB_CA!$B$58),ROUND(C27*COB_CA!$B$45,2),0) | E27: =IF((A27<=COB_CA!$B$58),IF(AND((A27<=COB_CA!$B$58),ROUND(C27-ROUND(COB_CA!$B$59-D27,2),2)<=0),C27,ROUND(COB_CA!$B$59-D27,2)),0) | F27: =IF((A27<=COB_CA!$B$58),IF(AND((A27<=COB_CA!$B$58),ROUND(C27-ROUND(COB_CA!$B$59-D27,2),2)<=0),ROUND(D27+E27,2),COB_CA!$B$59),0) | G27: =IF((A27<=COB_CA!$B$58),IF(AND((A27<=COB_CA!$B$58),ROUND(C27-ROUND(COB_CA!$B$59-D27,2),2)<=0),0,ROUND(C27-E27,2)),C27) | H27: =AND(H26,C26>0,(A27<=COB_CA!$B$58))
A28: 24 | B28: =IF(COB_CA!$B$44=12,DATE(YEAR(COB_CA!$B$22)+INT((MONTH(COB_CA!$B$22)-1+23)/12),MOD(MONTH(COB_CA!$B$22)-1+23,12)+1,1)+(DAY(COB_CA!$B$22)-1),IF(COB_CA!$B$44=24,COB_CA!$B$22+ROUND((23*365.25)/24,0),IF(COB_CA!$B$44=26,COB_CA!$B$22+322,COB_CA!$B$22+161))) | C28: =G27 | D28: =IF((A28<=COB_CA!$B$58),ROUND(C28*COB_CA!$B$45,2),0) | E28: =IF((A28<=COB_CA!$B$58),IF(AND((A28<=COB_CA!$B$58),ROUND(C28-ROUND(COB_CA!$B$59-D28,2),2)<=0),C28,ROUND(COB_CA!$B$59-D28,2)),0) | F28: =IF((A28<=COB_CA!$B$58),IF(AND((A28<=COB_CA!$B$58),ROUND(C28-ROUND(COB_CA!$B$59-D28,2),2)<=0),ROUND(D28+E28,2),COB_CA!$B$59),0) | G28: =IF((A28<=COB_CA!$B$58),IF(AND((A28<=COB_CA!$B$58),ROUND(C28-ROUND(COB_CA!$B$59-D28,2),2)<=0),0,ROUND(C28-E28,2)),C28) | H28: =AND(H27,C27>0,(A28<=COB_CA!$B$58))
A29: 25 | B29: =IF(COB_CA!$B$44=12,DATE(YEAR(COB_CA!$B$22)+INT((MONTH(COB_CA!$B$22)-1+24)/12),MOD(MONTH(COB_CA!$B$22)-1+24,12)+1,1)+(DAY(COB_CA!$B$22)-1),IF(COB_CA!$B$44=24,COB_CA!$B$22+ROUND((24*365.25)/24,0),IF(COB_CA!$B$44=26,COB_CA!$B$22+336,COB_CA!$B$22+168))) | C29: =G28 | D29: =IF((A29<=COB_CA!$B$58),ROUND(C29*COB_CA!$B$45,2),0) | E29: =IF((A29<=COB_CA!$B$58),IF(AND((A29<=COB_CA!$B$58),ROUND(C29-ROUND(COB_CA!$B$59-D29,2),2)<=0),C29,ROUND(COB_CA!$B$59-D29,2)),0) | F29: =IF((A29<=COB_CA!$B$58),IF(AND((A29<=COB_CA!$B$58),ROUND(C29-ROUND(COB_CA!$B$59-D29,2),2)<=0),ROUND(D29+E29,2),COB_CA!$B$59),0) | G29: =IF((A29<=COB_CA!$B$58),IF(AND((A29<=COB_CA!$B$58),ROUND(C29-ROUND(COB_CA!$B$59-D29,2),2)<=0),0,ROUND(C29-E29,2)),C29) | H29: =AND(H28,C28>0,(A29<=COB_CA!$B$58))
A30: 26 | B30: =IF(COB_CA!$B$44=12,DATE(YEAR(COB_CA!$B$22)+INT((MONTH(COB_CA!$B$22)-1+25)/12),MOD(MONTH(COB_CA!$B$22)-1+25,12)+1,1)+(DAY(COB_CA!$B$22)-1),IF(COB_CA!$B$44=24,COB_CA!$B$22+ROUND((25*365.25)/24,0),IF(COB_CA!$B$44=26,COB_CA!$B$22+350,COB_CA!$B$22+175))) | C30: =G29 | D30: =IF((A30<=COB_CA!$B$58),ROUND(C30*COB_CA!$B$45,2),0) | E30: =IF((A30<=COB_CA!$B$58),IF(AND((A30<=COB_CA!$B$58),ROUND(C30-ROUND(COB_CA!$B$59-D30,2),2)<=0),C30,ROUND(COB_CA!$B$59-D30,2)),0) | F30: =IF((A30<=COB_CA!$B$58),IF(AND((A30<=COB_CA!$B$58),ROUND(C30-ROUND(COB_CA!$B$59-D30,2),2)<=0),ROUND(D30+E30,2),COB_CA!$B$59),0) | G30: =IF((A30<=COB_CA!$B$58),IF(AND((A30<=COB_CA!$B$58),ROUND(C30-ROUND(COB_CA!$B$59-D30,2),2)<=0),0,ROUND(C30-E30,2)),C30) | H30: =AND(H29,C29>0,(A30<=COB_CA!$B$58))
A31: 27 | B31: =IF(COB_CA!$B$44=12,DATE(YEAR(COB_CA!$B$22)+INT((MONTH(COB_CA!$B$22)-1+26)/12),MOD(MONTH(COB_CA!$B$22)-1+26,12)+1,1)+(DAY(COB_CA!$B$22)-1),IF(COB_CA!$B$44=24,COB_CA!$B$22+ROUND((26*365.25)/24,0),IF(COB_CA!$B$44=26,COB_CA!$B$22+364,COB_CA!$B$22+182))) | C31: =G30 | D31: =IF((A31<=COB_CA!$B$58),ROUND(C31*COB_CA!$B$45,2),0) | E31: =IF((A31<=COB_CA!$B$58),IF(AND((A31<=COB_CA!$B$58),ROUND(C31-ROUND(COB_CA!$B$59-D31,2),2)<=0),C31,ROUND(COB_CA!$B$59-D31,2)),0) | F31: =IF((A31<=COB_CA!$B$58),IF(AND((A31<=COB_CA!$B$58),ROUND(C31-ROUND(COB_CA!$B$59-D31,2),2)<=0),ROUND(D31+E31,2),COB_CA!$B$59),0) | G31: =IF((A31<=COB_CA!$B$58),IF(AND((A31<=COB_CA!$B$58),ROUND(C31-ROUND(COB_CA!$B$59-D31,2),2)<=0),0,ROUND(C31-E31,2)),C31) | H31: =AND(H30,C30>0,(A31<=COB_CA!$B$58))
A32: 28 | B32: =IF(COB_CA!$B$44=12,DATE(YEAR(COB_CA!$B$22)+INT((MONTH(COB_CA!$B$22)-1+27)/12),MOD(MONTH(COB_CA!$B$22)-1+27,12)+1,1)+(DAY(COB_CA!$B$22)-1),IF(COB_CA!$B$44=24,COB_CA!$B$22+ROUND((27*365.25)/24,0),IF(COB_CA!$B$44=26,COB_CA!$B$22+378,COB_CA!$B$22+189))) | C32: =G31 | D32: =IF((A32<=COB_CA!$B$58),ROUND(C32*COB_CA!$B$45,2),0) | E32: =IF((A32<=COB_CA!$B$58),IF(AND((A32<=COB_CA!$B$58),ROUND(C32-ROUND(COB_CA!$B$59-D32,2),2)<=0),C32,ROUND(COB_CA!$B$59-D32,2)),0) | F32: =IF((A32<=COB_CA!$B$58),IF(AND((A32<=COB_CA!$B$58),ROUND(C32-ROUND(COB_CA!$B$59-D32,2),2)<=0),ROUND(D32+E32,2),COB_CA!$B$59),0) | G32: =IF((A32<=COB_CA!$B$58),IF(AND((A32<=COB_CA!$B$58),ROUND(C32-ROUND(COB_CA!$B$59-D32,2),2)<=0),0,ROUND(C32-E32,2)),C32) | H32: =AND(H31,C31>0,(A32<=COB_CA!$B$58))
A33: 29 | B33: =IF(COB_CA!$B$44=12,DATE(YEAR(COB_CA!$B$22)+INT((MONTH(COB_CA!$B$22)-1+28)/12),MOD(MONTH(COB_CA!$B$22)-1+28,12)+1,1)+(DAY(COB_CA!$B$22)-1),IF(COB_CA!$B$44=24,COB_CA!$B$22+ROUND((28*365.25)/24,0),IF(COB_CA!$B$44=26,COB_CA!$B$22+392,COB_CA!$B$22+196))) | C33: =G32 | D33: =IF((A33<=COB_CA!$B$58),ROUND(C33*COB_CA!$B$45,2),0) | E33: =IF((A33<=COB_CA!$B$58),IF(AND((A33<=COB_CA!$B$58),ROUND(C33-ROUND(COB_CA!$B$59-D33,2),2)<=0),C33,ROUND(COB_CA!$B$59-D33,2)),0) | F33: =IF((A33<=COB_CA!$B$58),IF(AND((A33<=COB_CA!$B$58),ROUND(C33-ROUND(COB_CA!$B$59-D33,2),2)<=0),ROUND(D33+E33,2),COB_CA!$B$59),0) | G33: =IF((A33<=COB_CA!$B$58),IF(AND((A33<=COB_CA!$B$58),ROUND(C33-ROUND(COB_CA!$B$59-D33,2),2)<=0),0,ROUND(C33-E33,2)),C33) | H33: =AND(H32,C32>0,(A33<=COB_CA!$B$58))
A34: 30 | B34: =IF(COB_CA!$B$44=12,DATE(YEAR(COB_CA!$B$22)+INT((MONTH(COB_CA!$B$22)-1+29)/12),MOD(MONTH(COB_CA!$B$22)-1+29,12)+1,1)+(DAY(COB_CA!$B$22)-1),IF(COB_CA!$B$44=24,COB_CA!$B$22+ROUND((29*365.25)/24,0),IF(COB_CA!$B$44=26,COB_CA!$B$22+406,COB_CA!$B$22+203))) | C34: =G33 | D34: =IF((A34<=COB_CA!$B$58),ROUND(C34*COB_CA!$B$45,2),0) | E34: =IF((A34<=COB_CA!$B$58),IF(AND((A34<=COB_CA!$B$58),ROUND(C34-ROUND(COB_CA!$B$59-D34,2),2)<=0),C34,ROUND(COB_CA!$B$59-D34,2)),0) | F34: =IF((A34<=COB_CA!$B$58),IF(AND((A34<=COB_CA!$B$58),ROUND(C34-ROUND(COB_CA!$B$59-D34,2),2)<=0),ROUND(D34+E34,2),COB_CA!$B$59),0) | G34: =IF((A34<=COB_CA!$B$58),IF(AND((A34<=COB_CA!$B$58),ROUND(C34-ROUND(COB_CA!$B$59-D34,2),2)<=0),0,ROUND(C34-E34,2)),C34) | H34: =AND(H33,C33>0,(A34<=COB_CA!$B$58))
A35: 31 | B35: =IF(COB_CA!$B$44=12,DATE(YEAR(COB_CA!$B$22)+INT((MONTH(COB_CA!$B$22)-1+30)/12),MOD(MONTH(COB_CA!$B$22)-1+30,12)+1,1)+(DAY(COB_CA!$B$22)-1),IF(COB_CA!$B$44=24,COB_CA!$B$22+ROUND((30*365.25)/24,0),IF(COB_CA!$B$44=26,COB_CA!$B$22+420,COB_CA!$B$22+210))) | C35: =G34 | D35: =IF((A35<=COB_CA!$B$58),ROUND(C35*COB_CA!$B$45,2),0) | E35: =IF((A35<=COB_CA!$B$58),IF(AND((A35<=COB_CA!$B$58),ROUND(C35-ROUND(COB_CA!$B$59-D35,2),2)<=0),C35,ROUND(COB_CA!$B$59-D35,2)),0) | F35: =IF((A35<=COB_CA!$B$58),IF(AND((A35<=COB_CA!$B$58),ROUND(C35-ROUND(COB_CA!$B$59-D35,2),2)<=0),ROUND(D35+E35,2),COB_CA!$B$59),0) | G35: =IF((A35<=COB_CA!$B$58),IF(AND((A35<=COB_CA!$B$58),ROUND(C35-ROUND(COB_CA!$B$59-D35,2),2)<=0),0,ROUND(C35-E35,2)),C35) | H35: =AND(H34,C34>0,(A35<=COB_CA!$B$58))
A36: 32 | B36: =IF(COB_CA!$B$44=12,DATE(YEAR(COB_CA!$B$22)+INT((MONTH(COB_CA!$B$22)-1+31)/12),MOD(MONTH(COB_CA!$B$22)-1+31,12)+1,1)+(DAY(COB_CA!$B$22)-1),IF(COB_CA!$B$44=24,COB_CA!$B$22+ROUND((31*365.25)/24,0),IF(COB_CA!$B$44=26,COB_CA!$B$22+434,COB_CA!$B$22+217))) | C36: =G35 | D36: =IF((A36<=COB_CA!$B$58),ROUND(C36*COB_CA!$B$45,2),0) | E36: =IF((A36<=COB_CA!$B$58),IF(AND((A36<=COB_CA!$B$58),ROUND(C36-ROUND(COB_CA!$B$59-D36,2),2)<=0),C36,ROUND(COB_CA!$B$59-D36,2)),0) | F36: =IF((A36<=COB_CA!$B$58),IF(AND((A36<=COB_CA!$B$58),ROUND(C36-ROUND(COB_CA!$B$59-D36,2),2)<=0),ROUND(D36+E36,2),COB_CA!$B$59),0) | G36: =IF((A36<=COB_CA!$B$58),IF(AND((A36<=COB_CA!$B$58),ROUND(C36-ROUND(COB_CA!$B$59-D36,2),2)<=0),0,ROUND(C36-E36,2)),C36) | H36: =AND(H35,C35>0,(A36<=COB_CA!$B$58))
A37: 33 | B37: =IF(COB_CA!$B$44=12,DATE(YEAR(COB_CA!$B$22)+INT((MONTH(COB_CA!$B$22)-1+32)/12),MOD(MONTH(COB_CA!$B$22)-1+32,12)+1,1)+(DAY(COB_CA!$B$22)-1),IF(COB_CA!$B$44=24,COB_CA!$B$22+ROUND((32*365.25)/24,0),IF(COB_CA!$B$44=26,COB_CA!$B$22+448,COB_CA!$B$22+224))) | C37: =G36 | D37: =IF((A37<=COB_CA!$B$58),ROUND(C37*COB_CA!$B$45,2),0) | E37: =IF((A37<=COB_CA!$B$58),IF(AND((A37<=COB_CA!$B$58),ROUND(C37-ROUND(COB_CA!$B$59-D37,2),2)<=0),C37,ROUND(COB_CA!$B$59-D37,2)),0) | F37: =IF((A37<=COB_CA!$B$58),IF(AND((A37<=COB_CA!$B$58),ROUND(C37-ROUND(COB_CA!$B$59-D37,2),2)<=0),ROUND(D37+E37,2),COB_CA!$B$59),0) | G37: =IF((A37<=COB_CA!$B$58),IF(AND((A37<=COB_CA!$B$58),ROUND(C37-ROUND(COB_CA!$B$59-D37,2),2)<=0),0,ROUND(C37-E37,2)),C37) | H37: =AND(H36,C36>0,(A37<=COB_CA!$B$58))
A38: 34 | B38: =IF(COB_CA!$B$44=12,DATE(YEAR(COB_CA!$B$22)+INT((MONTH(COB_CA!$B$22)-1+33)/12),MOD(MONTH(COB_CA!$B$22)-1+33,12)+1,1)+(DAY(COB_CA!$B$22)-1),IF(COB_CA!$B$44=24,COB_CA!$B$22+ROUND((33*365.25)/24,0),IF(COB_CA!$B$44=26,COB_CA!$B$22+462,COB_CA!$B$22+231))) | C38: =G37 | D38: =IF((A38<=COB_CA!$B$58),ROUND(C38*COB_CA!$B$45,2),0) | E38: =IF((A38<=COB_CA!$B$58),IF(AND((A38<=COB_CA!$B$58),ROUND(C38-ROUND(COB_CA!$B$59-D38,2),2)<=0),C38,ROUND(COB_CA!$B$59-D38,2)),0) | F38: =IF((A38<=COB_CA!$B$58),IF(AND((A38<=COB_CA!$B$58),ROUND(C38-ROUND(COB_CA!$B$59-D38,2),2)<=0),ROUND(D38+E38,2),COB_CA!$B$59),0) | G38: =IF((A38<=COB_CA!$B$58),IF(AND((A38<=COB_CA!$B$58),ROUND(C38-ROUND(COB_CA!$B$59-D38,2),2)<=0),0,ROUND(C38-E38,2)),C38) | H38: =AND(H37,C37>0,(A38<=COB_CA!$B$58))
A39: 35 | B39: =IF(COB_CA!$B$44=12,DATE(YEAR(COB_CA!$B$22)+INT((MONTH(COB_CA!$B$22)-1+34)/12),MOD(MONTH(COB_CA!$B$22)-1+34,12)+1,1)+(DAY(COB_CA!$B$22)-1),IF(COB_CA!$B$44=24,COB_CA!$B$22+ROUND((34*365.25)/24,0),IF(COB_CA!$B$44=26,COB_CA!$B$22+476,COB_CA!$B$22+238))) | C39: =G38 | D39: =IF((A39<=COB_CA!$B$58),ROUND(C39*COB_CA!$B$45,2),0) | E39: =IF((A39<=COB_CA!$B$58),IF(AND((A39<=COB_CA!$B$58),ROUND(C39-ROUND(COB_CA!$B$59-D39,2),2)<=0),C39,ROUND(COB_CA!$B$59-D39,2)),0) | F39: =IF((A39<=COB_CA!$B$58),IF(AND((A39<=COB_CA!$B$58),ROUND(C39-ROUND(COB_CA!$B$59-D39,2),2)<=0),ROUND(D39+E39,2),COB_CA!$B$59),0) | G39: =IF((A39<=COB_CA!$B$58),IF(AND((A39<=COB_CA!$B$58),ROUND(C39-ROUND(COB_CA!$B$59-D39,2),2)<=0),0,ROUND(C39-E39,2)),C39) | H39: =AND(H38,C38>0,(A39<=COB_CA!$B$58))
A40: 36 | B40: =IF(COB_CA!$B$44=12,DATE(YEAR(COB_CA!$B$22)+INT((MONTH(COB_CA!$B$22)-1+35)/12),MOD(MONTH(COB_CA!$B$22)-1+35,12)+1,1)+(DAY(COB_CA!$B$22)-1),IF(COB_CA!$B$44=24,COB_CA!$B$22+ROUND((35*365.25)/24,0),IF(COB_CA!$B$44=26,COB_CA!$B$22+490,COB_CA!$B$22+245))) | C40: =G39 | D40: =IF((A40<=COB_CA!$B$58),ROUND(C40*COB_CA!$B$45,2),0) | E40: =IF((A40<=COB_CA!$B$58),IF(AND((A40<=COB_CA!$B$58),ROUND(C40-ROUND(COB_CA!$B$59-D40,2),2)<=0),C40,ROUND(COB_CA!$B$59-D40,2)),0) | F40: =IF((A40<=COB_CA!$B$58),IF(AND((A40<=COB_CA!$B$58),ROUND(C40-ROUND(COB_CA!$B$59-D40,2),2)<=0),ROUND(D40+E40,2),COB_CA!$B$59),0) | G40: =IF((A40<=COB_CA!$B$58),IF(AND((A40<=COB_CA!$B$58),ROUND(C40-ROUND(COB_CA!$B$59-D40,2),2)<=0),0,ROUND(C40-E40,2)),C40) | H40: =AND(H39,C39>0,(A40<=COB_CA!$B$58))
A41: 37 | B41: =IF(COB_CA!$B$44=12,DATE(YEAR(COB_CA!$B$22)+INT((MONTH(COB_CA!$B$22)-1+36)/12),MOD(MONTH(COB_CA!$B$22)-1+36,12)+1,1)+(DAY(COB_CA!$B$22)-1),IF(COB_CA!$B$44=24,COB_CA!$B$22+ROUND((36*365.25)/24,0),IF(COB_CA!$B$44=26,COB_CA!$B$22+504,COB_CA!$B$22+252))) | C41: =G40 | D41: =IF((A41<=COB_CA!$B$58),ROUND(C41*COB_CA!$B$45,2),0) | E41: =IF((A41<=COB_CA!$B$58),IF(AND((A41<=COB_CA!$B$58),ROUND(C41-ROUND(COB_CA!$B$59-D41,2),2)<=0),C41,ROUND(COB_CA!$B$59-D41,2)),0) | F41: =IF((A41<=COB_CA!$B$58),IF(AND((A41<=COB_CA!$B$58),ROUND(C41-ROUND(COB_CA!$B$59-D41,2),2)<=0),ROUND(D41+E41,2),COB_CA!$B$59),0) | G41: =IF((A41<=COB_CA!$B$58),IF(AND((A41<=COB_CA!$B$58),ROUND(C41-ROUND(COB_CA!$B$59-D41,2),2)<=0),0,ROUND(C41-E41,2)),C41) | H41: =AND(H40,C40>0,(A41<=COB_CA!$B$58))
A42: 38 | B42: =IF(COB_CA!$B$44=12,DATE(YEAR(COB_CA!$B$22)+INT((MONTH(COB_CA!$B$22)-1+37)/12),MOD(MONTH(COB_CA!$B$22)-1+37,12)+1,1)+(DAY(COB_CA!$B$22)-1),IF(COB_CA!$B$44=24,COB_CA!$B$22+ROUND((37*365.25)/24,0),IF(COB_CA!$B$44=26,COB_CA!$B$22+518,COB_CA!$B$22+259))) | C42: =G41 | D42: =IF((A42<=COB_CA!$B$58),ROUND(C42*COB_CA!$B$45,2),0) | E42: =IF((A42<=COB_CA!$B$58),IF(AND((A42<=COB_CA!$B$58),ROUND(C42-ROUND(COB_CA!$B$59-D42,2),2)<=0),C42,ROUND(COB_CA!$B$59-D42,2)),0) | F42: =IF((A42<=COB_CA!$B$58),IF(AND((A42<=COB_CA!$B$58),ROUND(C42-ROUND(COB_CA!$B$59-D42,2),2)<=0),ROUND(D42+E42,2),COB_CA!$B$59),0) | G42: =IF((A42<=COB_CA!$B$58),IF(AND((A42<=COB_CA!$B$58),ROUND(C42-ROUND(COB_CA!$B$59-D42,2),2)<=0),0,ROUND(C42-E42,2)),C42) | H42: =AND(H41,C41>0,(A42<=COB_CA!$B$58))
A43: 39 | B43: =IF(COB_CA!$B$44=12,DATE(YEAR(COB_CA!$B$22)+INT((MONTH(COB_CA!$B$22)-1+38)/12),MOD(MONTH(COB_CA!$B$22)-1+38,12)+1,1)+(DAY(COB_CA!$B$22)-1),IF(COB_CA!$B$44=24,COB_CA!$B$22+ROUND((38*365.25)/24,0),IF(COB_CA!$B$44=26,COB_CA!$B$22+532,COB_CA!$B$22+266))) | C43: =G42 | D43: =IF((A43<=COB_CA!$B$58),ROUND(C43*COB_CA!$B$45,2),0) | E43: =IF((A43<=COB_CA!$B$58),IF(AND((A43<=COB_CA!$B$58),ROUND(C43-ROUND(COB_CA!$B$59-D43,2),2)<=0),C43,ROUND(COB_CA!$B$59-D43,2)),0) | F43: =IF((A43<=COB_CA!$B$58),IF(AND((A43<=COB_CA!$B$58),ROUND(C43-ROUND(COB_CA!$B$59-D43,2),2)<=0),ROUND(D43+E43,2),COB_CA!$B$59),0) | G43: =IF((A43<=COB_CA!$B$58),IF(AND((A43<=COB_CA!$B$58),ROUND(C43-ROUND(COB_CA!$B$59-D43,2),2)<=0),0,ROUND(C43-E43,2)),C43) | H43: =AND(H42,C42>0,(A43<=COB_CA!$B$58))
A44: 40 | B44: =IF(COB_CA!$B$44=12,DATE(YEAR(COB_CA!$B$22)+INT((MONTH(COB_CA!$B$22)-1+39)/12),MOD(MONTH(COB_CA!$B$22)-1+39,12)+1,1)+(DAY(COB_CA!$B$22)-1),IF(COB_CA!$B$44=24,COB_CA!$B$22+ROUND((39*365.25)/24,0),IF(COB_CA!$B$44=26,COB_CA!$B$22+546,COB_CA!$B$22+273))) | C44: =G43 | D44: =IF((A44<=COB_CA!$B$58),ROUND(C44*COB_CA!$B$45,2),0) | E44: =IF((A44<=COB_CA!$B$58),IF(AND((A44<=COB_CA!$B$58),ROUND(C44-ROUND(COB_CA!$B$59-D44,2),2)<=0),C44,ROUND(COB_CA!$B$59-D44,2)),0) | F44: =IF((A44<=COB_CA!$B$58),IF(AND((A44<=COB_CA!$B$58),ROUND(C44-ROUND(COB_CA!$B$59-D44,2),2)<=0),ROUND(D44+E44,2),COB_CA!$B$59),0) | G44: =IF((A44<=COB_CA!$B$58),IF(AND((A44<=COB_CA!$B$58),ROUND(C44-ROUND(COB_CA!$B$59-D44,2),2)<=0),0,ROUND(C44-E44,2)),C44) | H44: =AND(H43,C43>0,(A44<=COB_CA!$B$58))
A45: 41 | B45: =IF(COB_CA!$B$44=12,DATE(YEAR(COB_CA!$B$22)+INT((MONTH(COB_CA!$B$22)-1+40)/12),MOD(MONTH(COB_CA!$B$22)-1+40,12)+1,1)+(DAY(COB_CA!$B$22)-1),IF(COB_CA!$B$44=24,COB_CA!$B$22+ROUND((40*365.25)/24,0),IF(COB_CA!$B$44=26,COB_CA!$B$22+560,COB_CA!$B$22+280))) | C45: =G44 | D45: =IF((A45<=COB_CA!$B$58),ROUND(C45*COB_CA!$B$45,2),0) | E45: =IF((A45<=COB_CA!$B$58),IF(AND((A45<=COB_CA!$B$58),ROUND(C45-ROUND(COB_CA!$B$59-D45,2),2)<=0),C45,ROUND(COB_CA!$B$59-D45,2)),0) | F45: =IF((A45<=COB_CA!$B$58),IF(AND((A45<=COB_CA!$B$58),ROUND(C45-ROUND(COB_CA!$B$59-D45,2),2)<=0),ROUND(D45+E45,2),COB_CA!$B$59),0) | G45: =IF((A45<=COB_CA!$B$58),IF(AND((A45<=COB_CA!$B$58),ROUND(C45-ROUND(COB_CA!$B$59-D45,2),2)<=0),0,ROUND(C45-E45,2)),C45) | H45: =AND(H44,C44>0,(A45<=COB_CA!$B$58))
A46: 42 | B46: =IF(COB_CA!$B$44=12,DATE(YEAR(COB_CA!$B$22)+INT((MONTH(COB_CA!$B$22)-1+41)/12),MOD(MONTH(COB_CA!$B$22)-1+41,12)+1,1)+(DAY(COB_CA!$B$22)-1),IF(COB_CA!$B$44=24,COB_CA!$B$22+ROUND((41*365.25)/24,0),IF(COB_CA!$B$44=26,COB_CA!$B$22+574,COB_CA!$B$22+287))) | C46: =G45 | D46: =IF((A46<=COB_CA!$B$58),ROUND(C46*COB_CA!$B$45,2),0) | E46: =IF((A46<=COB_CA!$B$58),IF(AND((A46<=COB_CA!$B$58),ROUND(C46-ROUND(COB_CA!$B$59-D46,2),2)<=0),C46,ROUND(COB_CA!$B$59-D46,2)),0) | F46: =IF((A46<=COB_CA!$B$58),IF(AND((A46<=COB_CA!$B$58),ROUND(C46-ROUND(COB_CA!$B$59-D46,2),2)<=0),ROUND(D46+E46,2),COB_CA!$B$59),0) | G46: =IF((A46<=COB_CA!$B$58),IF(AND((A46<=COB_CA!$B$58),ROUND(C46-ROUND(COB_CA!$B$59-D46,2),2)<=0),0,ROUND(C46-E46,2)),C46) | H46: =AND(H45,C45>0,(A46<=COB_CA!$B$58))
A47: 43 | B47: =IF(COB_CA!$B$44=12,DATE(YEAR(COB_CA!$B$22)+INT((MONTH(COB_CA!$B$22)-1+42)/12),MOD(MONTH(COB_CA!$B$22)-1+42,12)+1,1)+(DAY(COB_CA!$B$22)-1),IF(COB_CA!$B$44=24,COB_CA!$B$22+ROUND((42*365.25)/24,0),IF(COB_CA!$B$44=26,COB_CA!$B$22+588,COB_CA!$B$22+294))) | C47: =G46 | D47: =IF((A47<=COB_CA!$B$58),ROUND(C47*COB_CA!$B$45,2),0) | E47: =IF((A47<=COB_CA!$B$58),IF(AND((A47<=COB_CA!$B$58),ROUND(C47-ROUND(COB_CA!$B$59-D47,2),2)<=0),C47,ROUND(COB_CA!$B$59-D47,2)),0) | F47: =IF((A47<=COB_CA!$B$58),IF(AND((A47<=COB_CA!$B$58),ROUND(C47-ROUND(COB_CA!$B$59-D47,2),2)<=0),ROUND(D47+E47,2),COB_CA!$B$59),0) | G47: =IF((A47<=COB_CA!$B$58),IF(AND((A47<=COB_CA!$B$58),ROUND(C47-ROUND(COB_CA!$B$59-D47,2),2)<=0),0,ROUND(C47-E47,2)),C47) | H47: =AND(H46,C46>0,(A47<=COB_CA!$B$58))
A48: 44 | B48: =IF(COB_CA!$B$44=12,DATE(YEAR(COB_CA!$B$22)+INT((MONTH(COB_CA!$B$22)-1+43)/12),MOD(MONTH(COB_CA!$B$22)-1+43,12)+1,1)+(DAY(COB_CA!$B$22)-1),IF(COB_CA!$B$44=24,COB_CA!$B$22+ROUND((43*365.25)/24,0),IF(COB_CA!$B$44=26,COB_CA!$B$22+602,COB_CA!$B$22+301))) | C48: =G47 | D48: =IF((A48<=COB_CA!$B$58),ROUND(C48*COB_CA!$B$45,2),0) | E48: =IF((A48<=COB_CA!$B$58),IF(AND((A48<=COB_CA!$B$58),ROUND(C48-ROUND(COB_CA!$B$59-D48,2),2)<=0),C48,ROUND(COB_CA!$B$59-D48,2)),0) | F48: =IF((A48<=COB_CA!$B$58),IF(AND((A48<=COB_CA!$B$58),ROUND(C48-ROUND(COB_CA!$B$59-D48,2),2)<=0),ROUND(D48+E48,2),COB_CA!$B$59),0) | G48: =IF((A48<=COB_CA!$B$58),IF(AND((A48<=COB_CA!$B$58),ROUND(C48-ROUND(COB_CA!$B$59-D48,2),2)<=0),0,ROUND(C48-E48,2)),C48) | H48: =AND(H47,C47>0,(A48<=COB_CA!$B$58))
A49: 45 | B49: =IF(COB_CA!$B$44=12,DATE(YEAR(COB_CA!$B$22)+INT((MONTH(COB_CA!$B$22)-1+44)/12),MOD(MONTH(COB_CA!$B$22)-1+44,12)+1,1)+(DAY(COB_CA!$B$22)-1),IF(COB_CA!$B$44=24,COB_CA!$B$22+ROUND((44*365.25)/24,0),IF(COB_CA!$B$44=26,COB_CA!$B$22+616,COB_CA!$B$22+308))) | C49: =G48 | D49: =IF((A49<=COB_CA!$B$58),ROUND(C49*COB_CA!$B$45,2),0) | E49: =IF((A49<=COB_CA!$B$58),IF(AND((A49<=COB_CA!$B$58),ROUND(C49-ROUND(COB_CA!$B$59-D49,2),2)<=0),C49,ROUND(COB_CA!$B$59-D49,2)),0) | F49: =IF((A49<=COB_CA!$B$58),IF(AND((A49<=COB_CA!$B$58),ROUND(C49-ROUND(COB_CA!$B$59-D49,2),2)<=0),ROUND(D49+E49,2),COB_CA!$B$59),0) | G49: =IF((A49<=COB_CA!$B$58),IF(AND((A49<=COB_CA!$B$58),ROUND(C49-ROUND(COB_CA!$B$59-D49,2),2)<=0),0,ROUND(C49-E49,2)),C49) | H49: =AND(H48,C48>0,(A49<=COB_CA!$B$58))
A50: 46 | B50: =IF(COB_CA!$B$44=12,DATE(YEAR(COB_CA!$B$22)+INT((MONTH(COB_CA!$B$22)-1+45)/12),MOD(MONTH(COB_CA!$B$22)-1+45,12)+1,1)+(DAY(COB_CA!$B$22)-1),IF(COB_CA!$B$44=24,COB_CA!$B$22+ROUND((45*365.25)/24,0),IF(COB_CA!$B$44=26,COB_CA!$B$22+630,COB_CA!$B$22+315))) | C50: =G49 | D50: =IF((A50<=COB_CA!$B$58),ROUND(C50*COB_CA!$B$45,2),0) | E50: =IF((A50<=COB_CA!$B$58),IF(AND((A50<=COB_CA!$B$58),ROUND(C50-ROUND(COB_CA!$B$59-D50,2),2)<=0),C50,ROUND(COB_CA!$B$59-D50,2)),0) | F50: =IF((A50<=COB_CA!$B$58),IF(AND((A50<=COB_CA!$B$58),ROUND(C50-ROUND(COB_CA!$B$59-D50,2),2)<=0),ROUND(D50+E50,2),COB_CA!$B$59),0) | G50: =IF((A50<=COB_CA!$B$58),IF(AND((A50<=COB_CA!$B$58),ROUND(C50-ROUND(COB_CA!$B$59-D50,2),2)<=0),0,ROUND(C50-E50,2)),C50) | H50: =AND(H49,C49>0,(A50<=COB_CA!$B$58))
A51: 47 | B51: =IF(COB_CA!$B$44=12,DATE(YEAR(COB_CA!$B$22)+INT((MONTH(COB_CA!$B$22)-1+46)/12),MOD(MONTH(COB_CA!$B$22)-1+46,12)+1,1)+(DAY(COB_CA!$B$22)-1),IF(COB_CA!$B$44=24,COB_CA!$B$22+ROUND((46*365.25)/24,0),IF(COB_CA!$B$44=26,COB_CA!$B$22+644,COB_CA!$B$22+322))) | C51: =G50 | D51: =IF((A51<=COB_CA!$B$58),ROUND(C51*COB_CA!$B$45,2),0) | E51: =IF((A51<=COB_CA!$B$58),IF(AND((A51<=COB_CA!$B$58),ROUND(C51-ROUND(COB_CA!$B$59-D51,2),2)<=0),C51,ROUND(COB_CA!$B$59-D51,2)),0) | F51: =IF((A51<=COB_CA!$B$58),IF(AND((A51<=COB_CA!$B$58),ROUND(C51-ROUND(COB_CA!$B$59-D51,2),2)<=0),ROUND(D51+E51,2),COB_CA!$B$59),0) | G51: =IF((A51<=COB_CA!$B$58),IF(AND((A51<=COB_CA!$B$58),ROUND(C51-ROUND(COB_CA!$B$59-D51,2),2)<=0),0,ROUND(C51-E51,2)),C51) | H51: =AND(H50,C50>0,(A51<=COB_CA!$B$58))
A52: 48 | B52: =IF(COB_CA!$B$44=12,DATE(YEAR(COB_CA!$B$22)+INT((MONTH(COB_CA!$B$22)-1+47)/12),MOD(MONTH(COB_CA!$B$22)-1+47,12)+1,1)+(DAY(COB_CA!$B$22)-1),IF(COB_CA!$B$44=24,COB_CA!$B$22+ROUND((47*365.25)/24,0),IF(COB_CA!$B$44=26,COB_CA!$B$22+658,COB_CA!$B$22+329))) | C52: =G51 | D52: =IF((A52<=COB_CA!$B$58),ROUND(C52*COB_CA!$B$45,2),0) | E52: =IF((A52<=COB_CA!$B$58),IF(AND((A52<=COB_CA!$B$58),ROUND(C52-ROUND(COB_CA!$B$59-D52,2),2)<=0),C52,ROUND(COB_CA!$B$59-D52,2)),0) | F52: =IF((A52<=COB_CA!$B$58),IF(AND((A52<=COB_CA!$B$58),ROUND(C52-ROUND(COB_CA!$B$59-D52,2),2)<=0),ROUND(D52+E52,2),COB_CA!$B$59),0) | G52: =IF((A52<=COB_CA!$B$58),IF(AND((A52<=COB_CA!$B$58),ROUND(C52-ROUND(COB_CA!$B$59-D52,2),2)<=0),0,ROUND(C52-E52,2)),C52) | H52: =AND(H51,C51>0,(A52<=COB_CA!$B$58))
A53: 49 | B53: =IF(COB_CA!$B$44=12,DATE(YEAR(COB_CA!$B$22)+INT((MONTH(COB_CA!$B$22)-1+48)/12),MOD(MONTH(COB_CA!$B$22)-1+48,12)+1,1)+(DAY(COB_CA!$B$22)-1),IF(COB_CA!$B$44=24,COB_CA!$B$22+ROUND((48*365.25)/24,0),IF(COB_CA!$B$44=26,COB_CA!$B$22+672,COB_CA!$B$22+336))) | C53: =G52 | D53: =IF((A53<=COB_CA!$B$58),ROUND(C53*COB_CA!$B$45,2),0) | E53: =IF((A53<=COB_CA!$B$58),IF(AND((A53<=COB_CA!$B$58),ROUND(C53-ROUND(COB_CA!$B$59-D53,2),2)<=0),C53,ROUND(COB_CA!$B$59-D53,2)),0) | F53: =IF((A53<=COB_CA!$B$58),IF(AND((A53<=COB_CA!$B$58),ROUND(C53-ROUND(COB_CA!$B$59-D53,2),2)<=0),ROUND(D53+E53,2),COB_CA!$B$59),0) | G53: =IF((A53<=COB_CA!$B$58),IF(AND((A53<=COB_CA!$B$58),ROUND(C53-ROUND(COB_CA!$B$59-D53,2),2)<=0),0,ROUND(C53-E53,2)),C53) | H53: =AND(H52,C52>0,(A53<=COB_CA!$B$58))
A54: 50 | B54: =IF(COB_CA!$B$44=12,DATE(YEAR(COB_CA!$B$22)+INT((MONTH(COB_CA!$B$22)-1+49)/12),MOD(MONTH(COB_CA!$B$22)-1+49,12)+1,1)+(DAY(COB_CA!$B$22)-1),IF(COB_CA!$B$44=24,COB_CA!$B$22+ROUND((49*365.25)/24,0),IF(COB_CA!$B$44=26,COB_CA!$B$22+686,COB_CA!$B$22+343))) | C54: =G53 | D54: =IF((A54<=COB_CA!$B$58),ROUND(C54*COB_CA!$B$45,2),0) | E54: =IF((A54<=COB_CA!$B$58),IF(AND((A54<=COB_CA!$B$58),ROUND(C54-ROUND(COB_CA!$B$59-D54,2),2)<=0),C54,ROUND(COB_CA!$B$59-D54,2)),0) | F54: =IF((A54<=COB_CA!$B$58),IF(AND((A54<=COB_CA!$B$58),ROUND(C54-ROUND(COB_CA!$B$59-D54,2),2)<=0),ROUND(D54+E54,2),COB_CA!$B$59),0) | G54: =IF((A54<=COB_CA!$B$58),IF(AND((A54<=COB_CA!$B$58),ROUND(C54-ROUND(COB_CA!$B$59-D54,2),2)<=0),0,ROUND(C54-E54,2)),C54) | H54: =AND(H53,C53>0,(A54<=COB_CA!$B$58))
A55: 51 | B55: =IF(COB_CA!$B$44=12,DATE(YEAR(COB_CA!$B$22)+INT((MONTH(COB_CA!$B$22)-1+50)/12),MOD(MONTH(COB_CA!$B$22)-1+50,12)+1,1)+(DAY(COB_CA!$B$22)-1),IF(COB_CA!$B$44=24,COB_CA!$B$22+ROUND((50*365.25)/24,0),IF(COB_CA!$B$44=26,COB_CA!$B$22+700,COB_CA!$B$22+350))) | C55: =G54 | D55: =IF((A55<=COB_CA!$B$58),ROUND(C55*COB_CA!$B$45,2),0) | E55: =IF((A55<=COB_CA!$B$58),IF(AND((A55<=COB_CA!$B$58),ROUND(C55-ROUND(COB_CA!$B$59-D55,2),2)<=0),C55,ROUND(COB_CA!$B$59-D55,2)),0) | F55: =IF((A55<=COB_CA!$B$58),IF(AND((A55<=COB_CA!$B$58),ROUND(C55-ROUND(COB_CA!$B$59-D55,2),2)<=0),ROUND(D55+E55,2),COB_CA!$B$59),0) | G55: =IF((A55<=COB_CA!$B$58),IF(AND((A55<=COB_CA!$B$58),ROUND(C55-ROUND(COB_CA!$B$59-D55,2),2)<=0),0,ROUND(C55-E55,2)),C55) | H55: =AND(H54,C54>0,(A55<=COB_CA!$B$58))
A56: 52 | B56: =IF(COB_CA!$B$44=12,DATE(YEAR(COB_CA!$B$22)+INT((MONTH(COB_CA!$B$22)-1+51)/12),MOD(MONTH(COB_CA!$B$22)-1+51,12)+1,1)+(DAY(COB_CA!$B$22)-1),IF(COB_CA!$B$44=24,COB_CA!$B$22+ROUND((51*365.25)/24,0),IF(COB_CA!$B$44=26,COB_CA!$B$22+714,COB_CA!$B$22+357))) | C56: =G55 | D56: =IF((A56<=COB_CA!$B$58),ROUND(C56*COB_CA!$B$45,2),0) | E56: =IF((A56<=COB_CA!$B$58),IF(AND((A56<=COB_CA!$B$58),ROUND(C56-ROUND(COB_CA!$B$59-D56,2),2)<=0),C56,ROUND(COB_CA!$B$59-D56,2)),0) | F56: =IF((A56<=COB_CA!$B$58),IF(AND((A56<=COB_CA!$B$58),ROUND(C56-ROUND(COB_CA!$B$59-D56,2),2)<=0),ROUND(D56+E56,2),COB_CA!$B$59),0) | G56: =IF((A56<=COB_CA!$B$58),IF(AND((A56<=COB_CA!$B$58),ROUND(C56-ROUND(COB_CA!$B$59-D56,2),2)<=0),0,ROUND(C56-E56,2)),C56) | H56: =AND(H55,C55>0,(A56<=COB_CA!$B$58))
A57: 53 | B57: =IF(COB_CA!$B$44=12,DATE(YEAR(COB_CA!$B$22)+INT((MONTH(COB_CA!$B$22)-1+52)/12),MOD(MONTH(COB_CA!$B$22)-1+52,12)+1,1)+(DAY(COB_CA!$B$22)-1),IF(COB_CA!$B$44=24,COB_CA!$B$22+ROUND((52*365.25)/24,0),IF(COB_CA!$B$44=26,COB_CA!$B$22+728,COB_CA!$B$22+364))) | C57: =G56 | D57: =IF((A57<=COB_CA!$B$58),ROUND(C57*COB_CA!$B$45,2),0) | E57: =IF((A57<=COB_CA!$B$58),IF(AND((A57<=COB_CA!$B$58),ROUND(C57-ROUND(COB_CA!$B$59-D57,2),2)<=0),C57,ROUND(COB_CA!$B$59-D57,2)),0) | F57: =IF((A57<=COB_CA!$B$58),IF(AND((A57<=COB_CA!$B$58),ROUND(C57-ROUND(COB_CA!$B$59-D57,2),2)<=0),ROUND(D57+E57,2),COB_CA!$B$59),0) | G57: =IF((A57<=COB_CA!$B$58),IF(AND((A57<=COB_CA!$B$58),ROUND(C57-ROUND(COB_CA!$B$59-D57,2),2)<=0),0,ROUND(C57-E57,2)),C57) | H57: =AND(H56,C56>0,(A57<=COB_CA!$B$58))
A58: 54 | B58: =IF(COB_CA!$B$44=12,DATE(YEAR(COB_CA!$B$22)+INT((MONTH(COB_CA!$B$22)-1+53)/12),MOD(MONTH(COB_CA!$B$22)-1+53,12)+1,1)+(DAY(COB_CA!$B$22)-1),IF(COB_CA!$B$44=24,COB_CA!$B$22+ROUND((53*365.25)/24,0),IF(COB_CA!$B$44=26,COB_CA!$B$22+742,COB_CA!$B$22+371))) | C58: =G57 | D58: =IF((A58<=COB_CA!$B$58),ROUND(C58*COB_CA!$B$45,2),0) | E58: =IF((A58<=COB_CA!$B$58),IF(AND((A58<=COB_CA!$B$58),ROUND(C58-ROUND(COB_CA!$B$59-D58,2),2)<=0),C58,ROUND(COB_CA!$B$59-D58,2)),0) | F58: =IF((A58<=COB_CA!$B$58),IF(AND((A58<=COB_CA!$B$58),ROUND(C58-ROUND(COB_CA!$B$59-D58,2),2)<=0),ROUND(D58+E58,2),COB_CA!$B$59),0) | G58: =IF((A58<=COB_CA!$B$58),IF(AND((A58<=COB_CA!$B$58),ROUND(C58-ROUND(COB_CA!$B$59-D58,2),2)<=0),0,ROUND(C58-E58,2)),C58) | H58: =AND(H57,C57>0,(A58<=COB_CA!$B$58))
A59: 55 | B59: =IF(COB_CA!$B$44=12,DATE(YEAR(COB_CA!$B$22)+INT((MONTH(COB_CA!$B$22)-1+54)/12),MOD(MONTH(COB_CA!$B$22)-1+54,12)+1,1)+(DAY(COB_CA!$B$22)-1),IF(COB_CA!$B$44=24,COB_CA!$B$22+ROUND((54*365.25)/24,0),IF(COB_CA!$B$44=26,COB_CA!$B$22+756,COB_CA!$B$22+378))) | C59: =G58 | D59: =IF((A59<=COB_CA!$B$58),ROUND(C59*COB_CA!$B$45,2),0) | E59: =IF((A59<=COB_CA!$B$58),IF(AND((A59<=COB_CA!$B$58),ROUND(C59-ROUND(COB_CA!$B$59-D59,2),2)<=0),C59,ROUND(COB_CA!$B$59-D59,2)),0) | F59: =IF((A59<=COB_CA!$B$58),IF(AND((A59<=COB_CA!$B$58),ROUND(C59-ROUND(COB_CA!$B$59-D59,2),2)<=0),ROUND(D59+E59,2),COB_CA!$B$59),0) | G59: =IF((A59<=COB_CA!$B$58),IF(AND((A59<=COB_CA!$B$58),ROUND(C59-ROUND(COB_CA!$B$59-D59,2),2)<=0),0,ROUND(C59-E59,2)),C59) | H59: =AND(H58,C58>0,(A59<=COB_CA!$B$58))
A60: 56 | B60: =IF(COB_CA!$B$44=12,DATE(YEAR(COB_CA!$B$22)+INT((MONTH(COB_CA!$B$22)-1+55)/12),MOD(MONTH(COB_CA!$B$22)-1+55,12)+1,1)+(DAY(COB_CA!$B$22)-1),IF(COB_CA!$B$44=24,COB_CA!$B$22+ROUND((55*365.25)/24,0),IF(COB_CA!$B$44=26,COB_CA!$B$22+770,COB_CA!$B$22+385))) | C60: =G59 | D60: =IF((A60<=COB_CA!$B$58),ROUND(C60*COB_CA!$B$45,2),0) | E60: =IF((A60<=COB_CA!$B$58),IF(AND((A60<=COB_CA!$B$58),ROUND(C60-ROUND(COB_CA!$B$59-D60,2),2)<=0),C60,ROUND(COB_CA!$B$59-D60,2)),0) | F60: =IF((A60<=COB_CA!$B$58),IF(AND((A60<=COB_CA!$B$58),ROUND(C60-ROUND(COB_CA!$B$59-D60,2),2)<=0),ROUND(D60+E60,2),COB_CA!$B$59),0) | G60: =IF((A60<=COB_CA!$B$58),IF(AND((A60<=COB_CA!$B$58),ROUND(C60-ROUND(COB_CA!$B$59-D60,2),2)<=0),0,ROUND(C60-E60,2)),C60) | H60: =AND(H59,C59>0,(A60<=COB_CA!$B$58))
A61: 57 | B61: =IF(COB_CA!$B$44=12,DATE(YEAR(COB_CA!$B$22)+INT((MONTH(COB_CA!$B$22)-1+56)/12),MOD(MONTH(COB_CA!$B$22)-1+56,12)+1,1)+(DAY(COB_CA!$B$22)-1),IF(COB_CA!$B$44=24,COB_CA!$B$22+ROUND((56*365.25)/24,0),IF(COB_CA!$B$44=26,COB_CA!$B$22+784,COB_CA!$B$22+392))) | C61: =G60 | D61: =IF((A61<=COB_CA!$B$58),ROUND(C61*COB_CA!$B$45,2),0) | E61: =IF((A61<=COB_CA!$B$58),IF(AND((A61<=COB_CA!$B$58),ROUND(C61-ROUND(COB_CA!$B$59-D61,2),2)<=0),C61,ROUND(COB_CA!$B$59-D61,2)),0) | F61: =IF((A61<=COB_CA!$B$58),IF(AND((A61<=COB_CA!$B$58),ROUND(C61-ROUND(COB_CA!$B$59-D61,2),2)<=0),ROUND(D61+E61,2),COB_CA!$B$59),0) | G61: =IF((A61<=COB_CA!$B$58),IF(AND((A61<=COB_CA!$B$58),ROUND(C61-ROUND(COB_CA!$B$59-D61,2),2)<=0),0,ROUND(C61-E61,2)),C61) | H61: =AND(H60,C60>0,(A61<=COB_CA!$B$58))
A62: 58 | B62: =IF(COB_CA!$B$44=12,DATE(YEAR(COB_CA!$B$22)+INT((MONTH(COB_CA!$B$22)-1+57)/12),MOD(MONTH(COB_CA!$B$22)-1+57,12)+1,1)+(DAY(COB_CA!$B$22)-1),IF(COB_CA!$B$44=24,COB_CA!$B$22+ROUND((57*365.25)/24,0),IF(COB_CA!$B$44=26,COB_CA!$B$22+798,COB_CA!$B$22+399))) | C62: =G61 | D62: =IF((A62<=COB_CA!$B$58),ROUND(C62*COB_CA!$B$45,2),0) | E62: =IF((A62<=COB_CA!$B$58),IF(AND((A62<=COB_CA!$B$58),ROUND(C62-ROUND(COB_CA!$B$59-D62,2),2)<=0),C62,ROUND(COB_CA!$B$59-D62,2)),0) | F62: =IF((A62<=COB_CA!$B$58),IF(AND((A62<=COB_CA!$B$58),ROUND(C62-ROUND(COB_CA!$B$59-D62,2),2)<=0),ROUND(D62+E62,2),COB_CA!$B$59),0) | G62: =IF((A62<=COB_CA!$B$58),IF(AND((A62<=COB_CA!$B$58),ROUND(C62-ROUND(COB_CA!$B$59-D62,2),2)<=0),0,ROUND(C62-E62,2)),C62) | H62: =AND(H61,C61>0,(A62<=COB_CA!$B$58))
A63: 59 | B63: =IF(COB_CA!$B$44=12,DATE(YEAR(COB_CA!$B$22)+INT((MONTH(COB_CA!$B$22)-1+58)/12),MOD(MONTH(COB_CA!$B$22)-1+58,12)+1,1)+(DAY(COB_CA!$B$22)-1),IF(COB_CA!$B$44=24,COB_CA!$B$22+ROUND((58*365.25)/24,0),IF(COB_CA!$B$44=26,COB_CA!$B$22+812,COB_CA!$B$22+406))) | C63: =G62 | D63: =IF((A63<=COB_CA!$B$58),ROUND(C63*COB_CA!$B$45,2),0) | E63: =IF((A63<=COB_CA!$B$58),IF(AND((A63<=COB_CA!$B$58),ROUND(C63-ROUND(COB_CA!$B$59-D63,2),2)<=0),C63,ROUND(COB_CA!$B$59-D63,2)),0) | F63: =IF((A63<=COB_CA!$B$58),IF(AND((A63<=COB_CA!$B$58),ROUND(C63-ROUND(COB_CA!$B$59-D63,2),2)<=0),ROUND(D63+E63,2),COB_CA!$B$59),0) | G63: =IF((A63<=COB_CA!$B$58),IF(AND((A63<=COB_CA!$B$58),ROUND(C63-ROUND(COB_CA!$B$59-D63,2),2)<=0),0,ROUND(C63-E63,2)),C63) | H63: =AND(H62,C62>0,(A63<=COB_CA!$B$58))
A64: 60 | B64: =IF(COB_CA!$B$44=12,DATE(YEAR(COB_CA!$B$22)+INT((MONTH(COB_CA!$B$22)-1+59)/12),MOD(MONTH(COB_CA!$B$22)-1+59,12)+1,1)+(DAY(COB_CA!$B$22)-1),IF(COB_CA!$B$44=24,COB_CA!$B$22+ROUND((59*365.25)/24,0),IF(COB_CA!$B$44=26,COB_CA!$B$22+826,COB_CA!$B$22+413))) | C64: =G63 | D64: =IF((A64<=COB_CA!$B$58),ROUND(C64*COB_CA!$B$45,2),0) | E64: =IF((A64<=COB_CA!$B$58),IF(AND((A64<=COB_CA!$B$58),ROUND(C64-ROUND(COB_CA!$B$59-D64,2),2)<=0),C64,ROUND(COB_CA!$B$59-D64,2)),0) | F64: =IF((A64<=COB_CA!$B$58),IF(AND((A64<=COB_CA!$B$58),ROUND(C64-ROUND(COB_CA!$B$59-D64,2),2)<=0),ROUND(D64+E64,2),COB_CA!$B$59),0) | G64: =IF((A64<=COB_CA!$B$58),IF(AND((A64<=COB_CA!$B$58),ROUND(C64-ROUND(COB_CA!$B$59-D64,2),2)<=0),0,ROUND(C64-E64,2)),C64) | H64: =AND(H63,C63>0,(A64<=COB_CA!$B$58))
A65: 61 | B65: =IF(COB_CA!$B$44=12,DATE(YEAR(COB_CA!$B$22)+INT((MONTH(COB_CA!$B$22)-1+60)/12),MOD(MONTH(COB_CA!$B$22)-1+60,12)+1,1)+(DAY(COB_CA!$B$22)-1),IF(COB_CA!$B$44=24,COB_CA!$B$22+ROUND((60*365.25)/24,0),IF(COB_CA!$B$44=26,COB_CA!$B$22+840,COB_CA!$B$22+420))) | C65: =G64 | D65: =IF((A65<=COB_CA!$B$58),ROUND(C65*COB_CA!$B$45,2),0) | E65: =IF((A65<=COB_CA!$B$58),IF(AND((A65<=COB_CA!$B$58),ROUND(C65-ROUND(COB_CA!$B$59-D65,2),2)<=0),C65,ROUND(COB_CA!$B$59-D65,2)),0) | F65: =IF((A65<=COB_CA!$B$58),IF(AND((A65<=COB_CA!$B$58),ROUND(C65-ROUND(COB_CA!$B$59-D65,2),2)<=0),ROUND(D65+E65,2),COB_CA!$B$59),0) | G65: =IF((A65<=COB_CA!$B$58),IF(AND((A65<=COB_CA!$B$58),ROUND(C65-ROUND(COB_CA!$B$59-D65,2),2)<=0),0,ROUND(C65-E65,2)),C65) | H65: =AND(H64,C64>0,(A65<=COB_CA!$B$58))
A66: 62 | B66: =IF(COB_CA!$B$44=12,DATE(YEAR(COB_CA!$B$22)+INT((MONTH(COB_CA!$B$22)-1+61)/12),MOD(MONTH(COB_CA!$B$22)-1+61,12)+1,1)+(DAY(COB_CA!$B$22)-1),IF(COB_CA!$B$44=24,COB_CA!$B$22+ROUND((61*365.25)/24,0),IF(COB_CA!$B$44=26,COB_CA!$B$22+854,COB_CA!$B$22+427))) | C66: =G65 | D66: =IF((A66<=COB_CA!$B$58),ROUND(C66*COB_CA!$B$45,2),0) | E66: =IF((A66<=COB_CA!$B$58),IF(AND((A66<=COB_CA!$B$58),ROUND(C66-ROUND(COB_CA!$B$59-D66,2),2)<=0),C66,ROUND(COB_CA!$B$59-D66,2)),0) | F66: =IF((A66<=COB_CA!$B$58),IF(AND((A66<=COB_CA!$B$58),ROUND(C66-ROUND(COB_CA!$B$59-D66,2),2)<=0),ROUND(D66+E66,2),COB_CA!$B$59),0) | G66: =IF((A66<=COB_CA!$B$58),IF(AND((A66<=COB_CA!$B$58),ROUND(C66-ROUND(COB_CA!$B$59-D66,2),2)<=0),0,ROUND(C66-E66,2)),C66) | H66: =AND(H65,C65>0,(A66<=COB_CA!$B$58))
A67: 63 | B67: =IF(COB_CA!$B$44=12,DATE(YEAR(COB_CA!$B$22)+INT((MONTH(COB_CA!$B$22)-1+62)/12),MOD(MONTH(COB_CA!$B$22)-1+62,12)+1,1)+(DAY(COB_CA!$B$22)-1),IF(COB_CA!$B$44=24,COB_CA!$B$22+ROUND((62*365.25)/24,0),IF(COB_CA!$B$44=26,COB_CA!$B$22+868,COB_CA!$B$22+434))) | C67: =G66 | D67: =IF((A67<=COB_CA!$B$58),ROUND(C67*COB_CA!$B$45,2),0) | E67: =IF((A67<=COB_CA!$B$58),IF(AND((A67<=COB_CA!$B$58),ROUND(C67-ROUND(COB_CA!$B$59-D67,2),2)<=0),C67,ROUND(COB_CA!$B$59-D67,2)),0) | F67: =IF((A67<=COB_CA!$B$58),IF(AND((A67<=COB_CA!$B$58),ROUND(C67-ROUND(COB_CA!$B$59-D67,2),2)<=0),ROUND(D67+E67,2),COB_CA!$B$59),0) | G67: =IF((A67<=COB_CA!$B$58),IF(AND((A67<=COB_CA!$B$58),ROUND(C67-ROUND(COB_CA!$B$59-D67,2),2)<=0),0,ROUND(C67-E67,2)),C67) | H67: =AND(H66,C66>0,(A67<=COB_CA!$B$58))
A68: 64 | B68: =IF(COB_CA!$B$44=12,DATE(YEAR(COB_CA!$B$22)+INT((MONTH(COB_CA!$B$22)-1+63)/12),MOD(MONTH(COB_CA!$B$22)-1+63,12)+1,1)+(DAY(COB_CA!$B$22)-1),IF(COB_CA!$B$44=24,COB_CA!$B$22+ROUND((63*365.25)/24,0),IF(COB_CA!$B$44=26,COB_CA!$B$22+882,COB_CA!$B$22+441))) | C68: =G67 | D68: =IF((A68<=COB_CA!$B$58),ROUND(C68*COB_CA!$B$45,2),0) | E68: =IF((A68<=COB_CA!$B$58),IF(AND((A68<=COB_CA!$B$58),ROUND(C68-ROUND(COB_CA!$B$59-D68,2),2)<=0),C68,ROUND(COB_CA!$B$59-D68,2)),0) | F68: =IF((A68<=COB_CA!$B$58),IF(AND((A68<=COB_CA!$B$58),ROUND(C68-ROUND(COB_CA!$B$59-D68,2),2)<=0),ROUND(D68+E68,2),COB_CA!$B$59),0) | G68: =IF((A68<=COB_CA!$B$58),IF(AND((A68<=COB_CA!$B$58),ROUND(C68-ROUND(COB_CA!$B$59-D68,2),2)<=0),0,ROUND(C68-E68,2)),C68) | H68: =AND(H67,C67>0,(A68<=COB_CA!$B$58))
A69: 65 | B69: =IF(COB_CA!$B$44=12,DATE(YEAR(COB_CA!$B$22)+INT((MONTH(COB_CA!$B$22)-1+64)/12),MOD(MONTH(COB_CA!$B$22)-1+64,12)+1,1)+(DAY(COB_CA!$B$22)-1),IF(COB_CA!$B$44=24,COB_CA!$B$22+ROUND((64*365.25)/24,0),IF(COB_CA!$B$44=26,COB_CA!$B$22+896,COB_CA!$B$22+448))) | C69: =G68 | D69: =IF((A69<=COB_CA!$B$58),ROUND(C69*COB_CA!$B$45,2),0) | E69: =IF((A69<=COB_CA!$B$58),IF(AND((A69<=COB_CA!$B$58),ROUND(C69-ROUND(COB_CA!$B$59-D69,2),2)<=0),C69,ROUND(COB_CA!$B$59-D69,2)),0) | F69: =IF((A69<=COB_CA!$B$58),IF(AND((A69<=COB_CA!$B$58),ROUND(C69-ROUND(COB_CA!$B$59-D69,2),2)<=0),ROUND(D69+E69,2),COB_CA!$B$59),0) | G69: =IF((A69<=COB_CA!$B$58),IF(AND((A69<=COB_CA!$B$58),ROUND(C69-ROUND(COB_CA!$B$59-D69,2),2)<=0),0,ROUND(C69-E69,2)),C69) | H69: =AND(H68,C68>0,(A69<=COB_CA!$B$58))
A70: 66 | B70: =IF(COB_CA!$B$44=12,DATE(YEAR(COB_CA!$B$22)+INT((MONTH(COB_CA!$B$22)-1+65)/12),MOD(MONTH(COB_CA!$B$22)-1+65,12)+1,1)+(DAY(COB_CA!$B$22)-1),IF(COB_CA!$B$44=24,COB_CA!$B$22+ROUND((65*365.25)/24,0),IF(COB_CA!$B$44=26,COB_CA!$B$22+910,COB_CA!$B$22+455))) | C70: =G69 | D70: =IF((A70<=COB_CA!$B$58),ROUND(C70*COB_CA!$B$45,2),0) | E70: =IF((A70<=COB_CA!$B$58),IF(AND((A70<=COB_CA!$B$58),ROUND(C70-ROUND(COB_CA!$B$59-D70,2),2)<=0),C70,ROUND(COB_CA!$B$59-D70,2)),0) | F70: =IF((A70<=COB_CA!$B$58),IF(AND((A70<=COB_CA!$B$58),ROUND(C70-ROUND(COB_CA!$B$59-D70,2),2)<=0),ROUND(D70+E70,2),COB_CA!$B$59),0) | G70: =IF((A70<=COB_CA!$B$58),IF(AND((A70<=COB_CA!$B$58),ROUND(C70-ROUND(COB_CA!$B$59-D70,2),2)<=0),0,ROUND(C70-E70,2)),C70) | H70: =AND(H69,C69>0,(A70<=COB_CA!$B$58))
A71: 67 | B71: =IF(COB_CA!$B$44=12,DATE(YEAR(COB_CA!$B$22)+INT((MONTH(COB_CA!$B$22)-1+66)/12),MOD(MONTH(COB_CA!$B$22)-1+66,12)+1,1)+(DAY(COB_CA!$B$22)-1),IF(COB_CA!$B$44=24,COB_CA!$B$22+ROUND((66*365.25)/24,0),IF(COB_CA!$B$44=26,COB_CA!$B$22+924,COB_CA!$B$22+462))) | C71: =G70 | D71: =IF((A71<=COB_CA!$B$58),ROUND(C71*COB_CA!$B$45,2),0) | E71: =IF((A71<=COB_CA!$B$58),IF(AND((A71<=COB_CA!$B$58),ROUND(C71-ROUND(COB_CA!$B$59-D71,2),2)<=0),C71,ROUND(COB_CA!$B$59-D71,2)),0) | F71: =IF((A71<=COB_CA!$B$58),IF(AND((A71<=COB_CA!$B$58),ROUND(C71-ROUND(COB_CA!$B$59-D71,2),2)<=0),ROUND(D71+E71,2),COB_CA!$B$59),0) | G71: =IF((A71<=COB_CA!$B$58),IF(AND((A71<=COB_CA!$B$58),ROUND(C71-ROUND(COB_CA!$B$59-D71,2),2)<=0),0,ROUND(C71-E71,2)),C71) | H71: =AND(H70,C70>0,(A71<=COB_CA!$B$58))
A72: 68 | B72: =IF(COB_CA!$B$44=12,DATE(YEAR(COB_CA!$B$22)+INT((MONTH(COB_CA!$B$22)-1+67)/12),MOD(MONTH(COB_CA!$B$22)-1+67,12)+1,1)+(DAY(COB_CA!$B$22)-1),IF(COB_CA!$B$44=24,COB_CA!$B$22+ROUND((67*365.25)/24,0),IF(COB_CA!$B$44=26,COB_CA!$B$22+938,COB_CA!$B$22+469))) | C72: =G71 | D72: =IF((A72<=COB_CA!$B$58),ROUND(C72*COB_CA!$B$45,2),0) | E72: =IF((A72<=COB_CA!$B$58),IF(AND((A72<=COB_CA!$B$58),ROUND(C72-ROUND(COB_CA!$B$59-D72,2),2)<=0),C72,ROUND(COB_CA!$B$59-D72,2)),0) | F72: =IF((A72<=COB_CA!$B$58),IF(AND((A72<=COB_CA!$B$58),ROUND(C72-ROUND(COB_CA!$B$59-D72,2),2)<=0),ROUND(D72+E72,2),COB_CA!$B$59),0) | G72: =IF((A72<=COB_CA!$B$58),IF(AND((A72<=COB_CA!$B$58),ROUND(C72-ROUND(COB_CA!$B$59-D72,2),2)<=0),0,ROUND(C72-E72,2)),C72) | H72: =AND(H71,C71>0,(A72<=COB_CA!$B$58))
A73: 69 | B73: =IF(COB_CA!$B$44=12,DATE(YEAR(COB_CA!$B$22)+INT((MONTH(COB_CA!$B$22)-1+68)/12),MOD(MONTH(COB_CA!$B$22)-1+68,12)+1,1)+(DAY(COB_CA!$B$22)-1),IF(COB_CA!$B$44=24,COB_CA!$B$22+ROUND((68*365.25)/24,0),IF(COB_CA!$B$44=26,COB_CA!$B$22+952,COB_CA!$B$22+476))) | C73: =G72 | D73: =IF((A73<=COB_CA!$B$58),ROUND(C73*COB_CA!$B$45,2),0) | E73: =IF((A73<=COB_CA!$B$58),IF(AND((A73<=COB_CA!$B$58),ROUND(C73-ROUND(COB_CA!$B$59-D73,2),2)<=0),C73,ROUND(COB_CA!$B$59-D73,2)),0) | F73: =IF((A73<=COB_CA!$B$58),IF(AND((A73<=COB_CA!$B$58),ROUND(C73-ROUND(COB_CA!$B$59-D73,2),2)<=0),ROUND(D73+E73,2),COB_CA!$B$59),0) | G73: =IF((A73<=COB_CA!$B$58),IF(AND((A73<=COB_CA!$B$58),ROUND(C73-ROUND(COB_CA!$B$59-D73,2),2)<=0),0,ROUND(C73-E73,2)),C73) | H73: =AND(H72,C72>0,(A73<=COB_CA!$B$58))
A74: 70 | B74: =IF(COB_CA!$B$44=12,DATE(YEAR(COB_CA!$B$22)+INT((MONTH(COB_CA!$B$22)-1+69)/12),MOD(MONTH(COB_CA!$B$22)-1+69,12)+1,1)+(DAY(COB_CA!$B$22)-1),IF(COB_CA!$B$44=24,COB_CA!$B$22+ROUND((69*365.25)/24,0),IF(COB_CA!$B$44=26,COB_CA!$B$22+966,COB_CA!$B$22+483))) | C74: =G73 | D74: =IF((A74<=COB_CA!$B$58),ROUND(C74*COB_CA!$B$45,2),0) | E74: =IF((A74<=COB_CA!$B$58),IF(AND((A74<=COB_CA!$B$58),ROUND(C74-ROUND(COB_CA!$B$59-D74,2),2)<=0),C74,ROUND(COB_CA!$B$59-D74,2)),0) | F74: =IF((A74<=COB_CA!$B$58),IF(AND((A74<=COB_CA!$B$58),ROUND(C74-ROUND(COB_CA!$B$59-D74,2),2)<=0),ROUND(D74+E74,2),COB_CA!$B$59),0) | G74: =IF((A74<=COB_CA!$B$58),IF(AND((A74<=COB_CA!$B$58),ROUND(C74-ROUND(COB_CA!$B$59-D74,2),2)<=0),0,ROUND(C74-E74,2)),C74) | H74: =AND(H73,C73>0,(A74<=COB_CA!$B$58))
A75: 71 | B75: =IF(COB_CA!$B$44=12,DATE(YEAR(COB_CA!$B$22)+INT((MONTH(COB_CA!$B$22)-1+70)/12),MOD(MONTH(COB_CA!$B$22)-1+70,12)+1,1)+(DAY(COB_CA!$B$22)-1),IF(COB_CA!$B$44=24,COB_CA!$B$22+ROUND((70*365.25)/24,0),IF(COB_CA!$B$44=26,COB_CA!$B$22+980,COB_CA!$B$22+490))) | C75: =G74 | D75: =IF((A75<=COB_CA!$B$58),ROUND(C75*COB_CA!$B$45,2),0) | E75: =IF((A75<=COB_CA!$B$58),IF(AND((A75<=COB_CA!$B$58),ROUND(C75-ROUND(COB_CA!$B$59-D75,2),2)<=0),C75,ROUND(COB_CA!$B$59-D75,2)),0) | F75: =IF((A75<=COB_CA!$B$58),IF(AND((A75<=COB_CA!$B$58),ROUND(C75-ROUND(COB_CA!$B$59-D75,2),2)<=0),ROUND(D75+E75,2),COB_CA!$B$59),0) | G75: =IF((A75<=COB_CA!$B$58),IF(AND((A75<=COB_CA!$B$58),ROUND(C75-ROUND(COB_CA!$B$59-D75,2),2)<=0),0,ROUND(C75-E75,2)),C75) | H75: =AND(H74,C74>0,(A75<=COB_CA!$B$58))
A76: 72 | B76: =IF(COB_CA!$B$44=12,DATE(YEAR(COB_CA!$B$22)+INT((MONTH(COB_CA!$B$22)-1+71)/12),MOD(MONTH(COB_CA!$B$22)-1+71,12)+1,1)+(DAY(COB_CA!$B$22)-1),IF(COB_CA!$B$44=24,COB_CA!$B$22+ROUND((71*365.25)/24,0),IF(COB_CA!$B$44=26,COB_CA!$B$22+994,COB_CA!$B$22+497))) | C76: =G75 | D76: =IF((A76<=COB_CA!$B$58),ROUND(C76*COB_CA!$B$45,2),0) | E76: =IF((A76<=COB_CA!$B$58),IF(AND((A76<=COB_CA!$B$58),ROUND(C76-ROUND(COB_CA!$B$59-D76,2),2)<=0),C76,ROUND(COB_CA!$B$59-D76,2)),0) | F76: =IF((A76<=COB_CA!$B$58),IF(AND((A76<=COB_CA!$B$58),ROUND(C76-ROUND(COB_CA!$B$59-D76,2),2)<=0),ROUND(D76+E76,2),COB_CA!$B$59),0) | G76: =IF((A76<=COB_CA!$B$58),IF(AND((A76<=COB_CA!$B$58),ROUND(C76-ROUND(COB_CA!$B$59-D76,2),2)<=0),0,ROUND(C76-E76,2)),C76) | H76: =AND(H75,C75>0,(A76<=COB_CA!$B$58))
A77: 73 | B77: =IF(COB_CA!$B$44=12,DATE(YEAR(COB_CA!$B$22)+INT((MONTH(COB_CA!$B$22)-1+72)/12),MOD(MONTH(COB_CA!$B$22)-1+72,12)+1,1)+(DAY(COB_CA!$B$22)-1),IF(COB_CA!$B$44=24,COB_CA!$B$22+ROUND((72*365.25)/24,0),IF(COB_CA!$B$44=26,COB_CA!$B$22+1008,COB_CA!$B$22+504))) | C77: =G76 | D77: =IF((A77<=COB_CA!$B$58),ROUND(C77*COB_CA!$B$45,2),0) | E77: =IF((A77<=COB_CA!$B$58),IF(AND((A77<=COB_CA!$B$58),ROUND(C77-ROUND(COB_CA!$B$59-D77,2),2)<=0),C77,ROUND(COB_CA!$B$59-D77,2)),0) | F77: =IF((A77<=COB_CA!$B$58),IF(AND((A77<=COB_CA!$B$58),ROUND(C77-ROUND(COB_CA!$B$59-D77,2),2)<=0),ROUND(D77+E77,2),COB_CA!$B$59),0) | G77: =IF((A77<=COB_CA!$B$58),IF(AND((A77<=COB_CA!$B$58),ROUND(C77-ROUND(COB_CA!$B$59-D77,2),2)<=0),0,ROUND(C77-E77,2)),C77) | H77: =AND(H76,C76>0,(A77<=COB_CA!$B$58))
A78: 74 | B78: =IF(COB_CA!$B$44=12,DATE(YEAR(COB_CA!$B$22)+INT((MONTH(COB_CA!$B$22)-1+73)/12),MOD(MONTH(COB_CA!$B$22)-1+73,12)+1,1)+(DAY(COB_CA!$B$22)-1),IF(COB_CA!$B$44=24,COB_CA!$B$22+ROUND((73*365.25)/24,0),IF(COB_CA!$B$44=26,COB_CA!$B$22+1022,COB_CA!$B$22+511))) | C78: =G77 | D78: =IF((A78<=COB_CA!$B$58),ROUND(C78*COB_CA!$B$45,2),0) | E78: =IF((A78<=COB_CA!$B$58),IF(AND((A78<=COB_CA!$B$58),ROUND(C78-ROUND(COB_CA!$B$59-D78,2),2)<=0),C78,ROUND(COB_CA!$B$59-D78,2)),0) | F78: =IF((A78<=COB_CA!$B$58),IF(AND((A78<=COB_CA!$B$58),ROUND(C78-ROUND(COB_CA!$B$59-D78,2),2)<=0),ROUND(D78+E78,2),COB_CA!$B$59),0) | G78: =IF((A78<=COB_CA!$B$58),IF(AND((A78<=COB_CA!$B$58),ROUND(C78-ROUND(COB_CA!$B$59-D78,2),2)<=0),0,ROUND(C78-E78,2)),C78) | H78: =AND(H77,C77>0,(A78<=COB_CA!$B$58))
A79: 75 | B79: =IF(COB_CA!$B$44=12,DATE(YEAR(COB_CA!$B$22)+INT((MONTH(COB_CA!$B$22)-1+74)/12),MOD(MONTH(COB_CA!$B$22)-1+74,12)+1,1)+(DAY(COB_CA!$B$22)-1),IF(COB_CA!$B$44=24,COB_CA!$B$22+ROUND((74*365.25)/24,0),IF(COB_CA!$B$44=26,COB_CA!$B$22+1036,COB_CA!$B$22+518))) | C79: =G78 | D79: =IF((A79<=COB_CA!$B$58),ROUND(C79*COB_CA!$B$45,2),0) | E79: =IF((A79<=COB_CA!$B$58),IF(AND((A79<=COB_CA!$B$58),ROUND(C79-ROUND(COB_CA!$B$59-D79,2),2)<=0),C79,ROUND(COB_CA!$B$59-D79,2)),0) | F79: =IF((A79<=COB_CA!$B$58),IF(AND((A79<=COB_CA!$B$58),ROUND(C79-ROUND(COB_CA!$B$59-D79,2),2)<=0),ROUND(D79+E79,2),COB_CA!$B$59),0) | G79: =IF((A79<=COB_CA!$B$58),IF(AND((A79<=COB_CA!$B$58),ROUND(C79-ROUND(COB_CA!$B$59-D79,2),2)<=0),0,ROUND(C79-E79,2)),C79) | H79: =AND(H78,C78>0,(A79<=COB_CA!$B$58))
A80: 76 | B80: =IF(COB_CA!$B$44=12,DATE(YEAR(COB_CA!$B$22)+INT((MONTH(COB_CA!$B$22)-1+75)/12),MOD(MONTH(COB_CA!$B$22)-1+75,12)+1,1)+(DAY(COB_CA!$B$22)-1),IF(COB_CA!$B$44=24,COB_CA!$B$22+ROUND((75*365.25)/24,0),IF(COB_CA!$B$44=26,COB_CA!$B$22+1050,COB_CA!$B$22+525))) | C80: =G79 | D80: =IF((A80<=COB_CA!$B$58),ROUND(C80*COB_CA!$B$45,2),0) | E80: =IF((A80<=COB_CA!$B$58),IF(AND((A80<=COB_CA!$B$58),ROUND(C80-ROUND(COB_CA!$B$59-D80,2),2)<=0),C80,ROUND(COB_CA!$B$59-D80,2)),0) | F80: =IF((A80<=COB_CA!$B$58),IF(AND((A80<=COB_CA!$B$58),ROUND(C80-ROUND(COB_CA!$B$59-D80,2),2)<=0),ROUND(D80+E80,2),COB_CA!$B$59),0) | G80: =IF((A80<=COB_CA!$B$58),IF(AND((A80<=COB_CA!$B$58),ROUND(C80-ROUND(COB_CA!$B$59-D80,2),2)<=0),0,ROUND(C80-E80,2)),C80) | H80: =AND(H79,C79>0,(A80<=COB_CA!$B$58))
A81: 77 | B81: =IF(COB_CA!$B$44=12,DATE(YEAR(COB_CA!$B$22)+INT((MONTH(COB_CA!$B$22)-1+76)/12),MOD(MONTH(COB_CA!$B$22)-1+76,12)+1,1)+(DAY(COB_CA!$B$22)-1),IF(COB_CA!$B$44=24,COB_CA!$B$22+ROUND((76*365.25)/24,0),IF(COB_CA!$B$44=26,COB_CA!$B$22+1064,COB_CA!$B$22+532))) | C81: =G80 | D81: =IF((A81<=COB_CA!$B$58),ROUND(C81*COB_CA!$B$45,2),0) | E81: =IF((A81<=COB_CA!$B$58),IF(AND((A81<=COB_CA!$B$58),ROUND(C81-ROUND(COB_CA!$B$59-D81,2),2)<=0),C81,ROUND(COB_CA!$B$59-D81,2)),0) | F81: =IF((A81<=COB_CA!$B$58),IF(AND((A81<=COB_CA!$B$58),ROUND(C81-ROUND(COB_CA!$B$59-D81,2),2)<=0),ROUND(D81+E81,2),COB_CA!$B$59),0) | G81: =IF((A81<=COB_CA!$B$58),IF(AND((A81<=COB_CA!$B$58),ROUND(C81-ROUND(COB_CA!$B$59-D81,2),2)<=0),0,ROUND(C81-E81,2)),C81) | H81: =AND(H80,C80>0,(A81<=COB_CA!$B$58))
A82: 78 | B82: =IF(COB_CA!$B$44=12,DATE(YEAR(COB_CA!$B$22)+INT((MONTH(COB_CA!$B$22)-1+77)/12),MOD(MONTH(COB_CA!$B$22)-1+77,12)+1,1)+(DAY(COB_CA!$B$22)-1),IF(COB_CA!$B$44=24,COB_CA!$B$22+ROUND((77*365.25)/24,0),IF(COB_CA!$B$44=26,COB_CA!$B$22+1078,COB_CA!$B$22+539))) | C82: =G81 | D82: =IF((A82<=COB_CA!$B$58),ROUND(C82*COB_CA!$B$45,2),0) | E82: =IF((A82<=COB_CA!$B$58),IF(AND((A82<=COB_CA!$B$58),ROUND(C82-ROUND(COB_CA!$B$59-D82,2),2)<=0),C82,ROUND(COB_CA!$B$59-D82,2)),0) | F82: =IF((A82<=COB_CA!$B$58),IF(AND((A82<=COB_CA!$B$58),ROUND(C82-ROUND(COB_CA!$B$59-D82,2),2)<=0),ROUND(D82+E82,2),COB_CA!$B$59),0) | G82: =IF((A82<=COB_CA!$B$58),IF(AND((A82<=COB_CA!$B$58),ROUND(C82-ROUND(COB_CA!$B$59-D82,2),2)<=0),0,ROUND(C82-E82,2)),C82) | H82: =AND(H81,C81>0,(A82<=COB_CA!$B$58))
A83: 79 | B83: =IF(COB_CA!$B$44=12,DATE(YEAR(COB_CA!$B$22)+INT((MONTH(COB_CA!$B$22)-1+78)/12),MOD(MONTH(COB_CA!$B$22)-1+78,12)+1,1)+(DAY(COB_CA!$B$22)-1),IF(COB_CA!$B$44=24,COB_CA!$B$22+ROUND((78*365.25)/24,0),IF(COB_CA!$B$44=26,COB_CA!$B$22+1092,COB_CA!$B$22+546))) | C83: =G82 | D83: =IF((A83<=COB_CA!$B$58),ROUND(C83*COB_CA!$B$45,2),0) | E83: =IF((A83<=COB_CA!$B$58),IF(AND((A83<=COB_CA!$B$58),ROUND(C83-ROUND(COB_CA!$B$59-D83,2),2)<=0),C83,ROUND(COB_CA!$B$59-D83,2)),0) | F83: =IF((A83<=COB_CA!$B$58),IF(AND((A83<=COB_CA!$B$58),ROUND(C83-ROUND(COB_CA!$B$59-D83,2),2)<=0),ROUND(D83+E83,2),COB_CA!$B$59),0) | G83: =IF((A83<=COB_CA!$B$58),IF(AND((A83<=COB_CA!$B$58),ROUND(C83-ROUND(COB_CA!$B$59-D83,2),2)<=0),0,ROUND(C83-E83,2)),C83) | H83: =AND(H82,C82>0,(A83<=COB_CA!$B$58))
A84: 80 | B84: =IF(COB_CA!$B$44=12,DATE(YEAR(COB_CA!$B$22)+INT((MONTH(COB_CA!$B$22)-1+79)/12),MOD(MONTH(COB_CA!$B$22)-1+79,12)+1,1)+(DAY(COB_CA!$B$22)-1),IF(COB_CA!$B$44=24,COB_CA!$B$22+ROUND((79*365.25)/24,0),IF(COB_CA!$B$44=26,COB_CA!$B$22+1106,COB_CA!$B$22+553))) | C84: =G83 | D84: =IF((A84<=COB_CA!$B$58),ROUND(C84*COB_CA!$B$45,2),0) | E84: =IF((A84<=COB_CA!$B$58),IF(AND((A84<=COB_CA!$B$58),ROUND(C84-ROUND(COB_CA!$B$59-D84,2),2)<=0),C84,ROUND(COB_CA!$B$59-D84,2)),0) | F84: =IF((A84<=COB_CA!$B$58),IF(AND((A84<=COB_CA!$B$58),ROUND(C84-ROUND(COB_CA!$B$59-D84,2),2)<=0),ROUND(D84+E84,2),COB_CA!$B$59),0) | G84: =IF((A84<=COB_CA!$B$58),IF(AND((A84<=COB_CA!$B$58),ROUND(C84-ROUND(COB_CA!$B$59-D84,2),2)<=0),0,ROUND(C84-E84,2)),C84) | H84: =AND(H83,C83>0,(A84<=COB_CA!$B$58))
A85: 81 | B85: =IF(COB_CA!$B$44=12,DATE(YEAR(COB_CA!$B$22)+INT((MONTH(COB_CA!$B$22)-1+80)/12),MOD(MONTH(COB_CA!$B$22)-1+80,12)+1,1)+(DAY(COB_CA!$B$22)-1),IF(COB_CA!$B$44=24,COB_CA!$B$22+ROUND((80*365.25)/24,0),IF(COB_CA!$B$44=26,COB_CA!$B$22+1120,COB_CA!$B$22+560))) | C85: =G84 | D85: =IF((A85<=COB_CA!$B$58),ROUND(C85*COB_CA!$B$45,2),0) | E85: =IF((A85<=COB_CA!$B$58),IF(AND((A85<=COB_CA!$B$58),ROUND(C85-ROUND(COB_CA!$B$59-D85,2),2)<=0),C85,ROUND(COB_CA!$B$59-D85,2)),0) | F85: =IF((A85<=COB_CA!$B$58),IF(AND((A85<=COB_CA!$B$58),ROUND(C85-ROUND(COB_CA!$B$59-D85,2),2)<=0),ROUND(D85+E85,2),COB_CA!$B$59),0) | G85: =IF((A85<=COB_CA!$B$58),IF(AND((A85<=COB_CA!$B$58),ROUND(C85-ROUND(COB_CA!$B$59-D85,2),2)<=0),0,ROUND(C85-E85,2)),C85) | H85: =AND(H84,C84>0,(A85<=COB_CA!$B$58))
A86: 82 | B86: =IF(COB_CA!$B$44=12,DATE(YEAR(COB_CA!$B$22)+INT((MONTH(COB_CA!$B$22)-1+81)/12),MOD(MONTH(COB_CA!$B$22)-1+81,12)+1,1)+(DAY(COB_CA!$B$22)-1),IF(COB_CA!$B$44=24,COB_CA!$B$22+ROUND((81*365.25)/24,0),IF(COB_CA!$B$44=26,COB_CA!$B$22+1134,COB_CA!$B$22+567))) | C86: =G85 | D86: =IF((A86<=COB_CA!$B$58),ROUND(C86*COB_CA!$B$45,2),0) | E86: =IF((A86<=COB_CA!$B$58),IF(AND((A86<=COB_CA!$B$58),ROUND(C86-ROUND(COB_CA!$B$59-D86,2),2)<=0),C86,ROUND(COB_CA!$B$59-D86,2)),0) | F86: =IF((A86<=COB_CA!$B$58),IF(AND((A86<=COB_CA!$B$58),ROUND(C86-ROUND(COB_CA!$B$59-D86,2),2)<=0),ROUND(D86+E86,2),COB_CA!$B$59),0) | G86: =IF((A86<=COB_CA!$B$58),IF(AND((A86<=COB_CA!$B$58),ROUND(C86-ROUND(COB_CA!$B$59-D86,2),2)<=0),0,ROUND(C86-E86,2)),C86) | H86: =AND(H85,C85>0,(A86<=COB_CA!$B$58))
A87: 83 | B87: =IF(COB_CA!$B$44=12,DATE(YEAR(COB_CA!$B$22)+INT((MONTH(COB_CA!$B$22)-1+82)/12),MOD(MONTH(COB_CA!$B$22)-1+82,12)+1,1)+(DAY(COB_CA!$B$22)-1),IF(COB_CA!$B$44=24,COB_CA!$B$22+ROUND((82*365.25)/24,0),IF(COB_CA!$B$44=26,COB_CA!$B$22+1148,COB_CA!$B$22+574))) | C87: =G86 | D87: =IF((A87<=COB_CA!$B$58),ROUND(C87*COB_CA!$B$45,2),0) | E87: =IF((A87<=COB_CA!$B$58),IF(AND((A87<=COB_CA!$B$58),ROUND(C87-ROUND(COB_CA!$B$59-D87,2),2)<=0),C87,ROUND(COB_CA!$B$59-D87,2)),0) | F87: =IF((A87<=COB_CA!$B$58),IF(AND((A87<=COB_CA!$B$58),ROUND(C87-ROUND(COB_CA!$B$59-D87,2),2)<=0),ROUND(D87+E87,2),COB_CA!$B$59),0) | G87: =IF((A87<=COB_CA!$B$58),IF(AND((A87<=COB_CA!$B$58),ROUND(C87-ROUND(COB_CA!$B$59-D87,2),2)<=0),0,ROUND(C87-E87,2)),C87) | H87: =AND(H86,C86>0,(A87<=COB_CA!$B$58))
A88: 84 | B88: =IF(COB_CA!$B$44=12,DATE(YEAR(COB_CA!$B$22)+INT((MONTH(COB_CA!$B$22)-1+83)/12),MOD(MONTH(COB_CA!$B$22)-1+83,12)+1,1)+(DAY(COB_CA!$B$22)-1),IF(COB_CA!$B$44=24,COB_CA!$B$22+ROUND((83*365.25)/24,0),IF(COB_CA!$B$44=26,COB_CA!$B$22+1162,COB_CA!$B$22+581))) | C88: =G87 | D88: =IF((A88<=COB_CA!$B$58),ROUND(C88*COB_CA!$B$45,2),0) | E88: =IF((A88<=COB_CA!$B$58),IF(AND((A88<=COB_CA!$B$58),ROUND(C88-ROUND(COB_CA!$B$59-D88,2),2)<=0),C88,ROUND(COB_CA!$B$59-D88,2)),0) | F88: =IF((A88<=COB_CA!$B$58),IF(AND((A88<=COB_CA!$B$58),ROUND(C88-ROUND(COB_CA!$B$59-D88,2),2)<=0),ROUND(D88+E88,2),COB_CA!$B$59),0) | G88: =IF((A88<=COB_CA!$B$58),IF(AND((A88<=COB_CA!$B$58),ROUND(C88-ROUND(COB_CA!$B$59-D88,2),2)<=0),0,ROUND(C88-E88,2)),C88) | H88: =AND(H87,C87>0,(A88<=COB_CA!$B$58))
A89: 85 | B89: =IF(COB_CA!$B$44=12,DATE(YEAR(COB_CA!$B$22)+INT((MONTH(COB_CA!$B$22)-1+84)/12),MOD(MONTH(COB_CA!$B$22)-1+84,12)+1,1)+(DAY(COB_CA!$B$22)-1),IF(COB_CA!$B$44=24,COB_CA!$B$22+ROUND((84*365.25)/24,0),IF(COB_CA!$B$44=26,COB_CA!$B$22+1176,COB_CA!$B$22+588))) | C89: =G88 | D89: =IF((A89<=COB_CA!$B$58),ROUND(C89*COB_CA!$B$45,2),0) | E89: =IF((A89<=COB_CA!$B$58),IF(AND((A89<=COB_CA!$B$58),ROUND(C89-ROUND(COB_CA!$B$59-D89,2),2)<=0),C89,ROUND(COB_CA!$B$59-D89,2)),0) | F89: =IF((A89<=COB_CA!$B$58),IF(AND((A89<=COB_CA!$B$58),ROUND(C89-ROUND(COB_CA!$B$59-D89,2),2)<=0),ROUND(D89+E89,2),COB_CA!$B$59),0) | G89: =IF((A89<=COB_CA!$B$58),IF(AND((A89<=COB_CA!$B$58),ROUND(C89-ROUND(COB_CA!$B$59-D89,2),2)<=0),0,ROUND(C89-E89,2)),C89) | H89: =AND(H88,C88>0,(A89<=COB_CA!$B$58))
A90: 86 | B90: =IF(COB_CA!$B$44=12,DATE(YEAR(COB_CA!$B$22)+INT((MONTH(COB_CA!$B$22)-1+85)/12),MOD(MONTH(COB_CA!$B$22)-1+85,12)+1,1)+(DAY(COB_CA!$B$22)-1),IF(COB_CA!$B$44=24,COB_CA!$B$22+ROUND((85*365.25)/24,0),IF(COB_CA!$B$44=26,COB_CA!$B$22+1190,COB_CA!$B$22+595))) | C90: =G89 | D90: =IF((A90<=COB_CA!$B$58),ROUND(C90*COB_CA!$B$45,2),0) | E90: =IF((A90<=COB_CA!$B$58),IF(AND((A90<=COB_CA!$B$58),ROUND(C90-ROUND(COB_CA!$B$59-D90,2),2)<=0),C90,ROUND(COB_CA!$B$59-D90,2)),0) | F90: =IF((A90<=COB_CA!$B$58),IF(AND((A90<=COB_CA!$B$58),ROUND(C90-ROUND(COB_CA!$B$59-D90,2),2)<=0),ROUND(D90+E90,2),COB_CA!$B$59),0) | G90: =IF((A90<=COB_CA!$B$58),IF(AND((A90<=COB_CA!$B$58),ROUND(C90-ROUND(COB_CA!$B$59-D90,2),2)<=0),0,ROUND(C90-E90,2)),C90) | H90: =AND(H89,C89>0,(A90<=COB_CA!$B$58))
A91: 87 | B91: =IF(COB_CA!$B$44=12,DATE(YEAR(COB_CA!$B$22)+INT((MONTH(COB_CA!$B$22)-1+86)/12),MOD(MONTH(COB_CA!$B$22)-1+86,12)+1,1)+(DAY(COB_CA!$B$22)-1),IF(COB_CA!$B$44=24,COB_CA!$B$22+ROUND((86*365.25)/24,0),IF(COB_CA!$B$44=26,COB_CA!$B$22+1204,COB_CA!$B$22+602))) | C91: =G90 | D91: =IF((A91<=COB_CA!$B$58),ROUND(C91*COB_CA!$B$45,2),0) | E91: =IF((A91<=COB_CA!$B$58),IF(AND((A91<=COB_CA!$B$58),ROUND(C91-ROUND(COB_CA!$B$59-D91,2),2)<=0),C91,ROUND(COB_CA!$B$59-D91,2)),0) | F91: =IF((A91<=COB_CA!$B$58),IF(AND((A91<=COB_CA!$B$58),ROUND(C91-ROUND(COB_CA!$B$59-D91,2),2)<=0),ROUND(D91+E91,2),COB_CA!$B$59),0) | G91: =IF((A91<=COB_CA!$B$58),IF(AND((A91<=COB_CA!$B$58),ROUND(C91-ROUND(COB_CA!$B$59-D91,2),2)<=0),0,ROUND(C91-E91,2)),C91) | H91: =AND(H90,C90>0,(A91<=COB_CA!$B$58))
A92: 88 | B92: =IF(COB_CA!$B$44=12,DATE(YEAR(COB_CA!$B$22)+INT((MONTH(COB_CA!$B$22)-1+87)/12),MOD(MONTH(COB_CA!$B$22)-1+87,12)+1,1)+(DAY(COB_CA!$B$22)-1),IF(COB_CA!$B$44=24,COB_CA!$B$22+ROUND((87*365.25)/24,0),IF(COB_CA!$B$44=26,COB_CA!$B$22+1218,COB_CA!$B$22+609))) | C92: =G91 | D92: =IF((A92<=COB_CA!$B$58),ROUND(C92*COB_CA!$B$45,2),0) | E92: =IF((A92<=COB_CA!$B$58),IF(AND((A92<=COB_CA!$B$58),ROUND(C92-ROUND(COB_CA!$B$59-D92,2),2)<=0),C92,ROUND(COB_CA!$B$59-D92,2)),0) | F92: =IF((A92<=COB_CA!$B$58),IF(AND((A92<=COB_CA!$B$58),ROUND(C92-ROUND(COB_CA!$B$59-D92,2),2)<=0),ROUND(D92+E92,2),COB_CA!$B$59),0) | G92: =IF((A92<=COB_CA!$B$58),IF(AND((A92<=COB_CA!$B$58),ROUND(C92-ROUND(COB_CA!$B$59-D92,2),2)<=0),0,ROUND(C92-E92,2)),C92) | H92: =AND(H91,C91>0,(A92<=COB_CA!$B$58))
A93: 89 | B93: =IF(COB_CA!$B$44=12,DATE(YEAR(COB_CA!$B$22)+INT((MONTH(COB_CA!$B$22)-1+88)/12),MOD(MONTH(COB_CA!$B$22)-1+88,12)+1,1)+(DAY(COB_CA!$B$22)-1),IF(COB_CA!$B$44=24,COB_CA!$B$22+ROUND((88*365.25)/24,0),IF(COB_CA!$B$44=26,COB_CA!$B$22+1232,COB_CA!$B$22+616))) | C93: =G92 | D93: =IF((A93<=COB_CA!$B$58),ROUND(C93*COB_CA!$B$45,2),0) | E93: =IF((A93<=COB_CA!$B$58),IF(AND((A93<=COB_CA!$B$58),ROUND(C93-ROUND(COB_CA!$B$59-D93,2),2)<=0),C93,ROUND(COB_CA!$B$59-D93,2)),0) | F93: =IF((A93<=COB_CA!$B$58),IF(AND((A93<=COB_CA!$B$58),ROUND(C93-ROUND(COB_CA!$B$59-D93,2),2)<=0),ROUND(D93+E93,2),COB_CA!$B$59),0) | G93: =IF((A93<=COB_CA!$B$58),IF(AND((A93<=COB_CA!$B$58),ROUND(C93-ROUND(COB_CA!$B$59-D93,2),2)<=0),0,ROUND(C93-E93,2)),C93) | H93: =AND(H92,C92>0,(A93<=COB_CA!$B$58))
A94: 90 | B94: =IF(COB_CA!$B$44=12,DATE(YEAR(COB_CA!$B$22)+INT((MONTH(COB_CA!$B$22)-1+89)/12),MOD(MONTH(COB_CA!$B$22)-1+89,12)+1,1)+(DAY(COB_CA!$B$22)-1),IF(COB_CA!$B$44=24,COB_CA!$B$22+ROUND((89*365.25)/24,0),IF(COB_CA!$B$44=26,COB_CA!$B$22+1246,COB_CA!$B$22+623))) | C94: =G93 | D94: =IF((A94<=COB_CA!$B$58),ROUND(C94*COB_CA!$B$45,2),0) | E94: =IF((A94<=COB_CA!$B$58),IF(AND((A94<=COB_CA!$B$58),ROUND(C94-ROUND(COB_CA!$B$59-D94,2),2)<=0),C94,ROUND(COB_CA!$B$59-D94,2)),0) | F94: =IF((A94<=COB_CA!$B$58),IF(AND((A94<=COB_CA!$B$58),ROUND(C94-ROUND(COB_CA!$B$59-D94,2),2)<=0),ROUND(D94+E94,2),COB_CA!$B$59),0) | G94: =IF((A94<=COB_CA!$B$58),IF(AND((A94<=COB_CA!$B$58),ROUND(C94-ROUND(COB_CA!$B$59-D94,2),2)<=0),0,ROUND(C94-E94,2)),C94) | H94: =AND(H93,C93>0,(A94<=COB_CA!$B$58))
A95: 91 | B95: =IF(COB_CA!$B$44=12,DATE(YEAR(COB_CA!$B$22)+INT((MONTH(COB_CA!$B$22)-1+90)/12),MOD(MONTH(COB_CA!$B$22)-1+90,12)+1,1)+(DAY(COB_CA!$B$22)-1),IF(COB_CA!$B$44=24,COB_CA!$B$22+ROUND((90*365.25)/24,0),IF(COB_CA!$B$44=26,COB_CA!$B$22+1260,COB_CA!$B$22+630))) | C95: =G94 | D95: =IF((A95<=COB_CA!$B$58),ROUND(C95*COB_CA!$B$45,2),0) | E95: =IF((A95<=COB_CA!$B$58),IF(AND((A95<=COB_CA!$B$58),ROUND(C95-ROUND(COB_CA!$B$59-D95,2),2)<=0),C95,ROUND(COB_CA!$B$59-D95,2)),0) | F95: =IF((A95<=COB_CA!$B$58),IF(AND((A95<=COB_CA!$B$58),ROUND(C95-ROUND(COB_CA!$B$59-D95,2),2)<=0),ROUND(D95+E95,2),COB_CA!$B$59),0) | G95: =IF((A95<=COB_CA!$B$58),IF(AND((A95<=COB_CA!$B$58),ROUND(C95-ROUND(COB_CA!$B$59-D95,2),2)<=0),0,ROUND(C95-E95,2)),C95) | H95: =AND(H94,C94>0,(A95<=COB_CA!$B$58))
A96: 92 | B96: =IF(COB_CA!$B$44=12,DATE(YEAR(COB_CA!$B$22)+INT((MONTH(COB_CA!$B$22)-1+91)/12),MOD(MONTH(COB_CA!$B$22)-1+91,12)+1,1)+(DAY(COB_CA!$B$22)-1),IF(COB_CA!$B$44=24,COB_CA!$B$22+ROUND((91*365.25)/24,0),IF(COB_CA!$B$44=26,COB_CA!$B$22+1274,COB_CA!$B$22+637))) | C96: =G95 | D96: =IF((A96<=COB_CA!$B$58),ROUND(C96*COB_CA!$B$45,2),0) | E96: =IF((A96<=COB_CA!$B$58),IF(AND((A96<=COB_CA!$B$58),ROUND(C96-ROUND(COB_CA!$B$59-D96,2),2)<=0),C96,ROUND(COB_CA!$B$59-D96,2)),0) | F96: =IF((A96<=COB_CA!$B$58),IF(AND((A96<=COB_CA!$B$58),ROUND(C96-ROUND(COB_CA!$B$59-D96,2),2)<=0),ROUND(D96+E96,2),COB_CA!$B$59),0) | G96: =IF((A96<=COB_CA!$B$58),IF(AND((A96<=COB_CA!$B$58),ROUND(C96-ROUND(COB_CA!$B$59-D96,2),2)<=0),0,ROUND(C96-E96,2)),C96) | H96: =AND(H95,C95>0,(A96<=COB_CA!$B$58))
A97: 93 | B97: =IF(COB_CA!$B$44=12,DATE(YEAR(COB_CA!$B$22)+INT((MONTH(COB_CA!$B$22)-1+92)/12),MOD(MONTH(COB_CA!$B$22)-1+92,12)+1,1)+(DAY(COB_CA!$B$22)-1),IF(COB_CA!$B$44=24,COB_CA!$B$22+ROUND((92*365.25)/24,0),IF(COB_CA!$B$44=26,COB_CA!$B$22+1288,COB_CA!$B$22+644))) | C97: =G96 | D97: =IF((A97<=COB_CA!$B$58),ROUND(C97*COB_CA!$B$45,2),0) | E97: =IF((A97<=COB_CA!$B$58),IF(AND((A97<=COB_CA!$B$58),ROUND(C97-ROUND(COB_CA!$B$59-D97,2),2)<=0),C97,ROUND(COB_CA!$B$59-D97,2)),0) | F97: =IF((A97<=COB_CA!$B$58),IF(AND((A97<=COB_CA!$B$58),ROUND(C97-ROUND(COB_CA!$B$59-D97,2),2)<=0),ROUND(D97+E97,2),COB_CA!$B$59),0) | G97: =IF((A97<=COB_CA!$B$58),IF(AND((A97<=COB_CA!$B$58),ROUND(C97-ROUND(COB_CA!$B$59-D97,2),2)<=0),0,ROUND(C97-E97,2)),C97) | H97: =AND(H96,C96>0,(A97<=COB_CA!$B$58))
A98: 94 | B98: =IF(COB_CA!$B$44=12,DATE(YEAR(COB_CA!$B$22)+INT((MONTH(COB_CA!$B$22)-1+93)/12),MOD(MONTH(COB_CA!$B$22)-1+93,12)+1,1)+(DAY(COB_CA!$B$22)-1),IF(COB_CA!$B$44=24,COB_CA!$B$22+ROUND((93*365.25)/24,0),IF(COB_CA!$B$44=26,COB_CA!$B$22+1302,COB_CA!$B$22+651))) | C98: =G97 | D98: =IF((A98<=COB_CA!$B$58),ROUND(C98*COB_CA!$B$45,2),0) | E98: =IF((A98<=COB_CA!$B$58),IF(AND((A98<=COB_CA!$B$58),ROUND(C98-ROUND(COB_CA!$B$59-D98,2),2)<=0),C98,ROUND(COB_CA!$B$59-D98,2)),0) | F98: =IF((A98<=COB_CA!$B$58),IF(AND((A98<=COB_CA!$B$58),ROUND(C98-ROUND(COB_CA!$B$59-D98,2),2)<=0),ROUND(D98+E98,2),COB_CA!$B$59),0) | G98: =IF((A98<=COB_CA!$B$58),IF(AND((A98<=COB_CA!$B$58),ROUND(C98-ROUND(COB_CA!$B$59-D98,2),2)<=0),0,ROUND(C98-E98,2)),C98) | H98: =AND(H97,C97>0,(A98<=COB_CA!$B$58))
A99: 95 | B99: =IF(COB_CA!$B$44=12,DATE(YEAR(COB_CA!$B$22)+INT((MONTH(COB_CA!$B$22)-1+94)/12),MOD(MONTH(COB_CA!$B$22)-1+94,12)+1,1)+(DAY(COB_CA!$B$22)-1),IF(COB_CA!$B$44=24,COB_CA!$B$22+ROUND((94*365.25)/24,0),IF(COB_CA!$B$44=26,COB_CA!$B$22+1316,COB_CA!$B$22+658))) | C99: =G98 | D99: =IF((A99<=COB_CA!$B$58),ROUND(C99*COB_CA!$B$45,2),0) | E99: =IF((A99<=COB_CA!$B$58),IF(AND((A99<=COB_CA!$B$58),ROUND(C99-ROUND(COB_CA!$B$59-D99,2),2)<=0),C99,ROUND(COB_CA!$B$59-D99,2)),0) | F99: =IF((A99<=COB_CA!$B$58),IF(AND((A99<=COB_CA!$B$58),ROUND(C99-ROUND(COB_CA!$B$59-D99,2),2)<=0),ROUND(D99+E99,2),COB_CA!$B$59),0) | G99: =IF((A99<=COB_CA!$B$58),IF(AND((A99<=COB_CA!$B$58),ROUND(C99-ROUND(COB_CA!$B$59-D99,2),2)<=0),0,ROUND(C99-E99,2)),C99) | H99: =AND(H98,C98>0,(A99<=COB_CA!$B$58))
A100: 96 | B100: =IF(COB_CA!$B$44=12,DATE(YEAR(COB_CA!$B$22)+INT((MONTH(COB_CA!$B$22)-1+95)/12),MOD(MONTH(COB_CA!$B$22)-1+95,12)+1,1)+(DAY(COB_CA!$B$22)-1),IF(COB_CA!$B$44=24,COB_CA!$B$22+ROUND((95*365.25)/24,0),IF(COB_CA!$B$44=26,COB_CA!$B$22+1330,COB_CA!$B$22+665))) | C100: =G99 | D100: =IF((A100<=COB_CA!$B$58),ROUND(C100*COB_CA!$B$45,2),0) | E100: =IF((A100<=COB_CA!$B$58),IF(AND((A100<=COB_CA!$B$58),ROUND(C100-ROUND(COB_CA!$B$59-D100,2),2)<=0),C100,ROUND(COB_CA!$B$59-D100,2)),0) | F100: =IF((A100<=COB_CA!$B$58),IF(AND((A100<=COB_CA!$B$58),ROUND(C100-ROUND(COB_CA!$B$59-D100,2),2)<=0),ROUND(D100+E100,2),COB_CA!$B$59),0) | G100: =IF((A100<=COB_CA!$B$58),IF(AND((A100<=COB_CA!$B$58),ROUND(C100-ROUND(COB_CA!$B$59-D100,2),2)<=0),0,ROUND(C100-E100,2)),C100) | H100: =AND(H99,C99>0,(A100<=COB_CA!$B$58))
A101: 97 | B101: =IF(COB_CA!$B$44=12,DATE(YEAR(COB_CA!$B$22)+INT((MONTH(COB_CA!$B$22)-1+96)/12),MOD(MONTH(COB_CA!$B$22)-1+96,12)+1,1)+(DAY(COB_CA!$B$22)-1),IF(COB_CA!$B$44=24,COB_CA!$B$22+ROUND((96*365.25)/24,0),IF(COB_CA!$B$44=26,COB_CA!$B$22+1344,COB_CA!$B$22+672))) | C101: =G100 | D101: =IF((A101<=COB_CA!$B$58),ROUND(C101*COB_CA!$B$45,2),0) | E101: =IF((A101<=COB_CA!$B$58),IF(AND((A101<=COB_CA!$B$58),ROUND(C101-ROUND(COB_CA!$B$59-D101,2),2)<=0),C101,ROUND(COB_CA!$B$59-D101,2)),0) | F101: =IF((A101<=COB_CA!$B$58),IF(AND((A101<=COB_CA!$B$58),ROUND(C101-ROUND(COB_CA!$B$59-D101,2),2)<=0),ROUND(D101+E101,2),COB_CA!$B$59),0) | G101: =IF((A101<=COB_CA!$B$58),IF(AND((A101<=COB_CA!$B$58),ROUND(C101-ROUND(COB_CA!$B$59-D101,2),2)<=0),0,ROUND(C101-E101,2)),C101) | H101: =AND(H100,C100>0,(A101<=COB_CA!$B$58))
...
